Workbook

Sheet README
A1: How this tracker works
A3: Add a task | B3: Tasks sheet, any empty row: Goal, Task, Assigned to, Status, Start (a Monday), Weeks. That's all.
A4: It then appears | B4: on the person's sheet, on its goal's sheet, on Gantt and in Dashboard. Those sheets are automatic: don't type in them.
A5: Per person | B5: One tab per person (GS-SLAM owner, Isaac Sim owner, Sensors owner, ...): their tasks and Gantt bars.
A6: Per goal | B6: One tab per goal (G1 Digital twin, G2 SCooP, Testbed, Dual-Link comm, Semantic comm).
A7: Gantt | B7: All tasks. The timeline start (Gantt!C3) sets every sheet's timeline.
A8: People | B8: Put real names in People. Then Ctrl+H in Tasks: replace each placeholder (e.g. 'GS-SLAM owner') with the name, and rename the tab.
A9: New person | B9: Add the name in People; duplicate any person tab and change its C2 to =People!A<row of the name>.
A10: Colours | B10: Bars by Status: grey Not Started, yellow In Progress, orange Partially Completed, red Blocked, green Complete; dark blue = milestone. Red End date = overdue.
A11: ID (optional) | B11: An ID without '.' shows as a bold parent row; IDs containing '-M' are milestones. New tasks can leave ID empty.
A12: Google Sheets | B12: Upload to Drive, open, File > Save as Google Sheets, share as Editor. Use only that copy.
A13: Limits | B13: Each person/goal tab lists up to 120 tasks; Tasks has room for 400 rows (Gantt shows all of them).
A15: Own file per person | B15: In Google Sheets: put names (and emails) in People, then Extensions > Apps Script, paste split_per_person.gs, run setupPersonFiles.
B16: Each person gets 'Tasks - <name>' to edit; this file's Tasks then imports everyone's rows and stays the shared overview.
B17: After that, add or edit tasks in the person's file (you own every file, so you can add tasks for anyone).

Sheet Tasks
A1: Tasks
A2: Add a task on any empty row: Goal, Task, Assigned to, Status, Start (a Monday), Weeks. It appears on that person's sheet, its goal's sheet and the Gantt by itself.
A3: ID | B3: Goal | C3: Task | D3: Assigned to | E3: Status | F3: Start | G3: Weeks | H3: End | I3: Notes | J3: key person | K3: key goal | L3: key all
A4: TB-1 | B4: Shared SCooP testbed | C4: Hardware inventory & specs | D4: Sensors & platform owner | E4: Not Started | F4: 46307 | G4: 2 | H4: =IF(OR($F4="",$G4=""),"",$F4+7*$G4-3) -> 46318 | J4: =IF(OR($C4="",$D4=""),"",$D4&"|"&COUNTIFS($D$4:$D4,$D4,$C$4:$C4,"?*")) -> Sensors & platform owner|1 | K4: =IF(OR($C4="",$B4=""),"",$B4&"|"&COUNTIFS($B$4:$B4,$B4,$C$4:$C4,"?*")) -> Shared SCooP testbed|1 | L4: =IF($C4="","","ALL|"&COUNTIF($C$4:$C4,"?*")) -> ALL|1
A5: TB-2 | B5: Shared SCooP testbed | C5: Sensor calibration (all units) | D5: Sensors & platform owner | E5: In Progress | F5: 46195 | G5: 2 | H5: =IF(OR($F5="",$G5=""),"",$F5+7*$G5-3) -> 46206 | J5: =IF(OR($C5="",$D5=""),"",$D5&"|"&COUNTIFS($D$4:$D5,$D5,$C$4:$C5,"?*")) -> Sensors & platform owner|2 | K5: =IF(OR($C5="",$B5=""),"",$B5&"|"&COUNTIFS($B$4:$B5,$B5,$C$4:$C5,"?*")) -> Shared SCooP testbed|2 | L5: =IF($C5="","","ALL|"&COUNTIF($C$4:$C5,"?*")) -> ALL|2
A6: TB-2.1 | B6: Shared SCooP testbed | C6: Sensor Calibration (LiDAR-Camera, LiDAR-IMU, Camera-Radar, Intrinsics, Realsense-Zed, Mobile-Infra Extrinsics) | D6: Sensors & platform owner | E6: In Progress | F6: 46195 | G6: 2 | H6: =IF(OR($F6="",$G6=""),"",$F6+7*$G6-3) -> 46206 | J6: =IF(OR($C6="",$D6=""),"",$D6&"|"&COUNTIFS($D$4:$D6,$D6,$C$4:$C6,"?*")) -> Sensors & platform owner|3 | K6: =IF(OR($C6="",$B6=""),"",$B6&"|"&COUNTIFS($B$4:$B6,$B6,$C$4:$C6,"?*")) -> Shared SCooP testbed|3 | L6: =IF($C6="","","ALL|"&COUNTIF($C$4:$C6,"?*")) -> ALL|3
A7: TB-2.2 | B7: Shared SCooP testbed | C7: Calibration: LiDAR - Camera | D7: Sensors & platform owner | H7: =IF(OR($F7="",$G7=""),"",$F7+7*$G7-3) | J7: =IF(OR($C7="",$D7=""),"",$D7&"|"&COUNTIFS($D$4:$D7,$D7,$C$4:$C7,"?*")) -> Sensors & platform owner|4 | K7: =IF(OR($C7="",$B7=""),"",$B7&"|"&COUNTIFS($B$4:$B7,$B7,$C$4:$C7,"?*")) -> Shared SCooP testbed|4 | L7: =IF($C7="","","ALL|"&COUNTIF($C$4:$C7,"?*")) -> ALL|4
A8: TB-2.3 | B8: Shared SCooP testbed | C8: Calibration: LiDAR - IMU | D8: Sensors & platform owner | H8: =IF(OR($F8="",$G8=""),"",$F8+7*$G8-3) | J8: =IF(OR($C8="",$D8=""),"",$D8&"|"&COUNTIFS($D$4:$D8,$D8,$C$4:$C8,"?*")) -> Sensors & platform owner|5 | K8: =IF(OR($C8="",$B8=""),"",$B8&"|"&COUNTIFS($B$4:$B8,$B8,$C$4:$C8,"?*")) -> Shared SCooP testbed|5 | L8: =IF($C8="","","ALL|"&COUNTIF($C$4:$C8,"?*")) -> ALL|5
A9: TB-2.4 | B9: Shared SCooP testbed | C9: Calibration: RealSense - ZED | D9: Sensors & platform owner | H9: =IF(OR($F9="",$G9=""),"",$F9+7*$G9-3) | J9: =IF(OR($C9="",$D9=""),"",$D9&"|"&COUNTIFS($D$4:$D9,$D9,$C$4:$C9,"?*")) -> Sensors & platform owner|6 | K9: =IF(OR($C9="",$B9=""),"",$B9&"|"&COUNTIFS($B$4:$B9,$B9,$C$4:$C9,"?*")) -> Shared SCooP testbed|6 | L9: =IF($C9="","","ALL|"&COUNTIF($C$4:$C9,"?*")) -> ALL|6
A10: TB-2.5 | B10: Shared SCooP testbed | C10: Calibration: ZED - Arducam | D10: Sensors & platform owner | H10: =IF(OR($F10="",$G10=""),"",$F10+7*$G10-3) | J10: =IF(OR($C10="",$D10=""),"",$D10&"|"&COUNTIFS($D$4:$D10,$D10,$C$4:$C10,"?*")) -> Sensors & platform owner|7 | K10: =IF(OR($C10="",$B10=""),"",$B10&"|"&COUNTIFS($B$4:$B10,$B10,$C$4:$C10,"?*")) -> Shared SCooP testbed|7 | L10: =IF($C10="","","ALL|"&COUNTIF($C$4:$C10,"?*")) -> ALL|7
A11: TB-2.6 | B11: Shared SCooP testbed | C11: Calibration: Radars - ZED | D11: Sensors & platform owner | H11: =IF(OR($F11="",$G11=""),"",$F11+7*$G11-3) | J11: =IF(OR($C11="",$D11=""),"",$D11&"|"&COUNTIFS($D$4:$D11,$D11,$C$4:$C11,"?*")) -> Sensors & platform owner|8 | K11: =IF(OR($C11="",$B11=""),"",$B11&"|"&COUNTIFS($B$4:$B11,$B11,$C$4:$C11,"?*")) -> Shared SCooP testbed|8 | L11: =IF($C11="","","ALL|"&COUNTIF($C$4:$C11,"?*")) -> ALL|8
A12: TB-3 | B12: Shared SCooP testbed | C12: Time sync & TF chain | D12: Sensors & platform owner | E12: In Progress | F12: 46202 | G12: 1 | H12: =IF(OR($F12="",$G12=""),"",$F12+7*$G12-3) -> 46206 | J12: =IF(OR($C12="",$D12=""),"",$D12&"|"&COUNTIFS($D$4:$D12,$D12,$C$4:$C12,"?*")) -> Sensors & platform owner|9 | K12: =IF(OR($C12="",$B12=""),"",$B12&"|"&COUNTIFS($B$4:$B12,$B12,$C$4:$C12,"?*")) -> Shared SCooP testbed|9 | L12: =IF($C12="","","ALL|"&COUNTIF($C$4:$C12,"?*")) -> ALL|9
A13: TB-4 | B13: Shared SCooP testbed | C13: Wi-Fi & comms logging | D13: Sensors & platform owner | E13: In Progress | F13: 46307 | G13: 2 | H13: =IF(OR($F13="",$G13=""),"",$F13+7*$G13-3) -> 46318 | J13: =IF(OR($C13="",$D13=""),"",$D13&"|"&COUNTIFS($D$4:$D13,$D13,$C$4:$C13,"?*")) -> Sensors & platform owner|10 | K13: =IF(OR($C13="",$B13=""),"",$B13&"|"&COUNTIFS($B$4:$B13,$B13,$C$4:$C13,"?*")) -> Shared SCooP testbed|10 | L13: =IF($C13="","","ALL|"&COUNTIF($C$4:$C13,"?*")) -> ALL|10
A14: TB-5 | B14: Shared SCooP testbed | C14: Recording tooling fixes | D14: Sensors & platform owner | E14: Not Started | F14: 46307 | G14: 2 | H14: =IF(OR($F14="",$G14=""),"",$F14+7*$G14-3) -> 46318 | J14: =IF(OR($C14="",$D14=""),"",$D14&"|"&COUNTIFS($D$4:$D14,$D14,$C$4:$C14,"?*")) -> Sensors & platform owner|11 | K14: =IF(OR($C14="",$B14=""),"",$B14&"|"&COUNTIFS($B$4:$B14,$B14,$C$4:$C14,"?*")) -> Shared SCooP testbed|11 | L14: =IF($C14="","","ALL|"&COUNTIF($C$4:$C14,"?*")) -> ALL|11
A15: G2-DS-1 | B15: G2 SCooP dataset & paper | C15: Recording campaign | D15: SCooP owner | E15: Partially Completed | F15: 46314 | G15: 6 | H15: =IF(OR($F15="",$G15=""),"",$F15+7*$G15-3) -> 46353 | I15: Only Cameras and LiDAR mainly for calibration accuracy validation | J15: =IF(OR($C15="",$D15=""),"",$D15&"|"&COUNTIFS($D$4:$D15,$D15,$C$4:$C15,"?*")) -> SCooP owner|1 | K15: =IF(OR($C15="",$B15=""),"",$B15&"|"&COUNTIFS($B$4:$B15,$B15,$C$4:$C15,"?*")) -> G2 SCooP dataset & paper|1 | L15: =IF($C15="","","ALL|"&COUNTIF($C$4:$C15,"?*")) -> ALL|12
A16: G2-DS-1.1 | B16: G2 SCooP dataset & paper | C16: Indoor Trajectory Sessions | D16: SCooP owner | E16: Partially Completed | F16: 46202 | G16: 1 | H16: =IF(OR($F16="",$G16=""),"",$F16+7*$G16-3) -> 46206 | I16: 2 different datasets → detect change (in validation) | J16: =IF(OR($C16="",$D16=""),"",$D16&"|"&COUNTIFS($D$4:$D16,$D16,$C$4:$C16,"?*")) -> SCooP owner|2 | K16: =IF(OR($C16="",$B16=""),"",$B16&"|"&COUNTIFS($B$4:$B16,$B16,$C$4:$C16,"?*")) -> G2 SCooP dataset & paper|2 | L16: =IF($C16="","","ALL|"&COUNTIF($C$4:$C16,"?*")) -> ALL|13
A17: G2-DS-1.2 | B17: G2 SCooP dataset & paper | C17: Outdoor Trajectory Sessions | D17: SCooP owner | E17: Not Started | H17: =IF(OR($F17="",$G17=""),"",$F17+7*$G17-3) | J17: =IF(OR($C17="",$D17=""),"",$D17&"|"&COUNTIFS($D$4:$D17,$D17,$C$4:$C17,"?*")) -> SCooP owner|3 | K17: =IF(OR($C17="",$B17=""),"",$B17&"|"&COUNTIFS($B$4:$B17,$B17,$C$4:$C17,"?*")) -> G2 SCooP dataset & paper|3 | L17: =IF($C17="","","ALL|"&COUNTIF($C$4:$C17,"?*")) -> ALL|14
A18: G2-DS-1.3 | B18: G2 SCooP dataset & paper | C18: Record sites 2 and 3 | D18: SCooP owner | E18: Not Started | F18: 46321 | G18: 4 | H18: =IF(OR($F18="",$G18=""),"",$F18+7*$G18-3) -> 46346 | J18: =IF(OR($C18="",$D18=""),"",$D18&"|"&COUNTIFS($D$4:$D18,$D18,$C$4:$C18,"?*")) -> SCooP owner|4 | K18: =IF(OR($C18="",$B18=""),"",$B18&"|"&COUNTIFS($B$4:$B18,$B18,$C$4:$C18,"?*")) -> G2 SCooP dataset & paper|4 | L18: =IF($C18="","","ALL|"&COUNTIF($C$4:$C18,"?*")) -> ALL|15
A19: G2-DS-1.4 | B19: G2 SCooP dataset & paper | C19: Calibration rosbag | D19: SCooP owner | F19: 46314 | G19: 1 | H19: =IF(OR($F19="",$G19=""),"",$F19+7*$G19-3) -> 46318 | J19: =IF(OR($C19="",$D19=""),"",$D19&"|"&COUNTIFS($D$4:$D19,$D19,$C$4:$C19,"?*")) -> SCooP owner|5 | K19: =IF(OR($C19="",$B19=""),"",$B19&"|"&COUNTIFS($B$4:$B19,$B19,$C$4:$C19,"?*")) -> G2 SCooP dataset & paper|5 | L19: =IF($C19="","","ALL|"&COUNTIF($C$4:$C19,"?*")) -> ALL|16
A20: G2-DS-1.5 | B20: G2 SCooP dataset & paper | C20: Short test recordings | D20: SCooP owner | F20: 46314 | G20: 1 | H20: =IF(OR($F20="",$G20=""),"",$F20+7*$G20-3) -> 46318 | J20: =IF(OR($C20="",$D20=""),"",$D20&"|"&COUNTIFS($D$4:$D20,$D20,$C$4:$C20,"?*")) -> SCooP owner|6 | K20: =IF(OR($C20="",$B20=""),"",$B20&"|"&COUNTIFS($B$4:$B20,$B20,$C$4:$C20,"?*")) -> G2 SCooP dataset & paper|6 | L20: =IF($C20="","","ALL|"&COUNTIF($C$4:$C20,"?*")) -> ALL|17
A21: G2-DS-2 | B21: G2 SCooP dataset & paper | C21: Per-pass processing | D21: SCooP owner | E21: In Progress | F21: 46307 | G21: 10 | H21: =IF(OR($F21="",$G21=""),"",$F21+7*$G21-3) -> 46374 | I21: rerun per new pass | J21: =IF(OR($C21="",$D21=""),"",$D21&"|"&COUNTIFS($D$4:$D21,$D21,$C$4:$C21,"?*")) -> SCooP owner|7 | K21: =IF(OR($C21="",$B21=""),"",$B21&"|"&COUNTIFS($B$4:$B21,$B21,$C$4:$C21,"?*")) -> G2 SCooP dataset & paper|7 | L21: =IF($C21="","","ALL|"&COUNTIF($C$4:$C21,"?*")) -> ALL|18
A22: G2-DS-2.1 | B22: G2 SCooP dataset & paper | C22: Merging Sensor Data | D22: SCooP owner | E22: In Progress | F22: 46202 | G22: 1 | H22: =IF(OR($F22="",$G22=""),"",$F22+7*$G22-3) -> 46206 | J22: =IF(OR($C22="",$D22=""),"",$D22&"|"&COUNTIFS($D$4:$D22,$D22,$C$4:$C22,"?*")) -> SCooP owner|8 | K22: =IF(OR($C22="",$B22=""),"",$B22&"|"&COUNTIFS($B$4:$B22,$B22,$C$4:$C22,"?*")) -> G2 SCooP dataset & paper|8 | L22: =IF($C22="","","ALL|"&COUNTIF($C$4:$C22,"?*")) -> ALL|19
A23: G2-DS-2.2 | B23: G2 SCooP dataset & paper | C23: Timestamp Alignment Post-Processing | D23: SCooP owner | E23: Not Started | F23: 46202 | G23: 1 | H23: =IF(OR($F23="",$G23=""),"",$F23+7*$G23-3) -> 46206 | J23: =IF(OR($C23="",$D23=""),"",$D23&"|"&COUNTIFS($D$4:$D23,$D23,$C$4:$C23,"?*")) -> SCooP owner|9 | K23: =IF(OR($C23="",$B23=""),"",$B23&"|"&COUNTIFS($B$4:$B23,$B23,$C$4:$C23,"?*")) -> G2 SCooP dataset & paper|9 | L23: =IF($C23="","","ALL|"&COUNTIF($C$4:$C23,"?*")) -> ALL|20
A24: G2-DS-3 | B24: G2 SCooP dataset & paper | C24: Reference maps & board networks per site | D24: SCooP owner | E24: In Progress | F24: 46307 | G24: 8 | H24: =IF(OR($F24="",$G24=""),"",$F24+7*$G24-3) -> 46360 | J24: =IF(OR($C24="",$D24=""),"",$D24&"|"&COUNTIFS($D$4:$D24,$D24,$C$4:$C24,"?*")) -> SCooP owner|10 | K24: =IF(OR($C24="",$B24=""),"",$B24&"|"&COUNTIFS($B$4:$B24,$B24,$C$4:$C24,"?*")) -> G2 SCooP dataset & paper|10 | L24: =IF($C24="","","ALL|"&COUNTIF($C$4:$C24,"?*")) -> ALL|21
A25: G2-DS-3.1 | B25: G2 SCooP dataset & paper | C25: Localization and Mapping | D25: SCooP owner | E25: Not Started | F25: 46202 | G25: 1 | H25: =IF(OR($F25="",$G25=""),"",$F25+7*$G25-3) -> 46206 | J25: =IF(OR($C25="",$D25=""),"",$D25&"|"&COUNTIFS($D$4:$D25,$D25,$C$4:$C25,"?*")) -> SCooP owner|11 | K25: =IF(OR($C25="",$B25=""),"",$B25&"|"&COUNTIFS($B$4:$B25,$B25,$C$4:$C25,"?*")) -> G2 SCooP dataset & paper|11 | L25: =IF($C25="","","ALL|"&COUNTIF($C$4:$C25,"?*")) -> ALL|22
A26: G2-DS-3.2 | B26: G2 SCooP dataset & paper | C26: Mesh Conversion | D26: SCooP owner | E26: Not Started | F26: 46209 | G26: 2 | H26: =IF(OR($F26="",$G26=""),"",$F26+7*$G26-3) -> 46220 | I26: Varying object resolution → zoom in, zoom out | J26: =IF(OR($C26="",$D26=""),"",$D26&"|"&COUNTIFS($D$4:$D26,$D26,$C$4:$C26,"?*")) -> SCooP owner|12 | K26: =IF(OR($C26="",$B26=""),"",$B26&"|"&COUNTIFS($B$4:$B26,$B26,$C$4:$C26,"?*")) -> G2 SCooP dataset & paper|12 | L26: =IF($C26="","","ALL|"&COUNTIF($C$4:$C26,"?*")) -> ALL|23
A27: G2-DS-4 | B27: G2 SCooP dataset & paper | C27: Reference poses (map stages 03-10) | D27: SCooP owner | E27: In Progress | F27: 46307 | G27: 6 | H27: =IF(OR($F27="",$G27=""),"",$F27+7*$G27-3) -> 46346 | J27: =IF(OR($C27="",$D27=""),"",$D27&"|"&COUNTIFS($D$4:$D27,$D27,$C$4:$C27,"?*")) -> SCooP owner|13 | K27: =IF(OR($C27="",$B27=""),"",$B27&"|"&COUNTIFS($B$4:$B27,$B27,$C$4:$C27,"?*")) -> G2 SCooP dataset & paper|13 | L27: =IF($C27="","","ALL|"&COUNTIF($C$4:$C27,"?*")) -> ALL|24
A28: G2-DS-5 | B28: G2 SCooP dataset & paper | C28: Ground-truth validation | D28: SCooP owner | E28: Not Started | F28: 46342 | G28: 3 | H28: =IF(OR($F28="",$G28=""),"",$F28+7*$G28-3) -> 46360 | J28: =IF(OR($C28="",$D28=""),"",$D28&"|"&COUNTIFS($D$4:$D28,$D28,$C$4:$C28,"?*")) -> SCooP owner|14 | K28: =IF(OR($C28="",$B28=""),"",$B28&"|"&COUNTIFS($B$4:$B28,$B28,$C$4:$C28,"?*")) -> G2 SCooP dataset & paper|14 | L28: =IF($C28="","","ALL|"&COUNTIF($C$4:$C28,"?*")) -> ALL|25
A29: G2-DS-6 | B29: G2 SCooP dataset & paper | C29: Annotations | D29: SCooP owner | E29: Not Started | F29: 46335 | G29: 7 | H29: =IF(OR($F29="",$G29=""),"",$F29+7*$G29-3) -> 46381 | J29: =IF(OR($C29="",$D29=""),"",$D29&"|"&COUNTIFS($D$4:$D29,$D29,$C$4:$C29,"?*")) -> SCooP owner|15 | K29: =IF(OR($C29="",$B29=""),"",$B29&"|"&COUNTIFS($B$4:$B29,$B29,$C$4:$C29,"?*")) -> G2 SCooP dataset & paper|15 | L29: =IF($C29="","","ALL|"&COUNTIF($C$4:$C29,"?*")) -> ALL|26
A30: G2-DS-6.1 | B30: G2 SCooP dataset & paper | C30: Label QA (Coverage & Class Balance) | D30: SCooP owner | E30: Not Started | H30: =IF(OR($F30="",$G30=""),"",$F30+7*$G30-3) | J30: =IF(OR($C30="",$D30=""),"",$D30&"|"&COUNTIFS($D$4:$D30,$D30,$C$4:$C30,"?*")) -> SCooP owner|16 | K30: =IF(OR($C30="",$B30=""),"",$B30&"|"&COUNTIFS($B$4:$B30,$B30,$C$4:$C30,"?*")) -> G2 SCooP dataset & paper|16 | L30: =IF($C30="","","ALL|"&COUNTIF($C$4:$C30,"?*")) -> ALL|27
A31: G2-DS-7 | B31: G2 SCooP dataset & paper | C31: Collaboration geometry & comm ground truth | D31: SCooP owner | E31: Not Started | F31: 46349 | G31: 5 | H31: =IF(OR($F31="",$G31=""),"",$F31+7*$G31-3) -> 46381 | J31: =IF(OR($C31="",$D31=""),"",$D31&"|"&COUNTIFS($D$4:$D31,$D31,$C$4:$C31,"?*")) -> SCooP owner|17 | K31: =IF(OR($C31="",$B31=""),"",$B31&"|"&COUNTIFS($B$4:$B31,$B31,$C$4:$C31,"?*")) -> G2 SCooP dataset & paper|17 | L31: =IF($C31="","","ALL|"&COUNTIF($C$4:$C31,"?*")) -> ALL|28
A32: G2-DS-8 | B32: G2 SCooP dataset & paper | C32: Release | D32: SCooP owner | E32: Not Started | F32: 46384 | G32: 5 | H32: =IF(OR($F32="",$G32=""),"",$F32+7*$G32-3) -> 46416 | J32: =IF(OR($C32="",$D32=""),"",$D32&"|"&COUNTIFS($D$4:$D32,$D32,$C$4:$C32,"?*")) -> SCooP owner|18 | K32: =IF(OR($C32="",$B32=""),"",$B32&"|"&COUNTIFS($B$4:$B32,$B32,$C$4:$C32,"?*")) -> G2 SCooP dataset & paper|18 | L32: =IF($C32="","","ALL|"&COUNTIF($C$4:$C32,"?*")) -> ALL|29
A33: G2-DS-8.1 | B33: G2 SCooP dataset & paper | C33: Dataset Packaging & Documentation | D33: SCooP owner | E33: Not Started | H33: =IF(OR($F33="",$G33=""),"",$F33+7*$G33-3) | J33: =IF(OR($C33="",$D33=""),"",$D33&"|"&COUNTIFS($D$4:$D33,$D33,$C$4:$C33,"?*")) -> SCooP owner|19 | K33: =IF(OR($C33="",$B33=""),"",$B33&"|"&COUNTIFS($B$4:$B33,$B33,$C$4:$C33,"?*")) -> G2 SCooP dataset & paper|19 | L33: =IF($C33="","","ALL|"&COUNTIF($C$4:$C33,"?*")) -> ALL|30
A34: G2-DS-8.2 | B34: G2 SCooP dataset & paper | C34: Devkit | D34: SCooP owner | E34: Not Started | F34: 46384 | G34: 4 | H34: =IF(OR($F34="",$G34=""),"",$F34+7*$G34-3) -> 46409 | J34: =IF(OR($C34="",$D34=""),"",$D34&"|"&COUNTIFS($D$4:$D34,$D34,$C$4:$C34,"?*")) -> SCooP owner|20 | K34: =IF(OR($C34="",$B34=""),"",$B34&"|"&COUNTIFS($B$4:$B34,$B34,$C$4:$C34,"?*")) -> G2 SCooP dataset & paper|20 | L34: =IF($C34="","","ALL|"&COUNTIF($C$4:$C34,"?*")) -> ALL|31
A35: G2-DS-8.3 | B35: G2 SCooP dataset & paper | C35: License, DOI, hosting | D35: SCooP owner | E35: Not Started | F35: 46398 | G35: 2 | H35: =IF(OR($F35="",$G35=""),"",$F35+7*$G35-3) -> 46409 | J35: =IF(OR($C35="",$D35=""),"",$D35&"|"&COUNTIFS($D$4:$D35,$D35,$C$4:$C35,"?*")) -> SCooP owner|21 | K35: =IF(OR($C35="",$B35=""),"",$B35&"|"&COUNTIFS($B$4:$B35,$B35,$C$4:$C35,"?*")) -> G2 SCooP dataset & paper|21 | L35: =IF($C35="","","ALL|"&COUNTIF($C$4:$C35,"?*")) -> ALL|32
A36: G2-BP-A | B36: G2 SCooP dataset & paper | C36: Ground-truth numbers (RESULTS_PLAN A0) | D36: SCooP owner | E36: Not Started | F36: 46314 | G36: 3 | H36: =IF(OR($F36="",$G36=""),"",$F36+7*$G36-3) -> 46332 | J36: =IF(OR($C36="",$D36=""),"",$D36&"|"&COUNTIFS($D$4:$D36,$D36,$C$4:$C36,"?*")) -> SCooP owner|22 | K36: =IF(OR($C36="",$B36=""),"",$B36&"|"&COUNTIFS($B$4:$B36,$B36,$C$4:$C36,"?*")) -> G2 SCooP dataset & paper|22 | L36: =IF($C36="","","ALL|"&COUNTIF($C$4:$C36,"?*")) -> ALL|33
A37: G2-BP-B | B37: G2 SCooP dataset & paper | C37: Inventory & statistics tables (B) | D37: SCooP owner | E37: Not Started | F37: 46342 | G37: 3 | H37: =IF(OR($F37="",$G37=""),"",$F37+7*$G37-3) -> 46360 | J37: =IF(OR($C37="",$D37=""),"",$D37&"|"&COUNTIFS($D$4:$D37,$D37,$C$4:$C37,"?*")) -> SCooP owner|23 | K37: =IF(OR($C37="",$B37=""),"",$B37&"|"&COUNTIFS($B$4:$B37,$B37,$C$4:$C37,"?*")) -> G2 SCooP dataset & paper|23 | L37: =IF($C37="","","ALL|"&COUNTIF($C$4:$C37,"?*")) -> ALL|34
A38: G2-BP-C | B38: G2 SCooP dataset & paper | C38: Geometry validation (C) | D38: SCooP owner | E38: Not Started | F38: 46363 | G38: 3 | H38: =IF(OR($F38="",$G38=""),"",$F38+7*$G38-3) -> 46381 | J38: =IF(OR($C38="",$D38=""),"",$D38&"|"&COUNTIFS($D$4:$D38,$D38,$C$4:$C38,"?*")) -> SCooP owner|24 | K38: =IF(OR($C38="",$B38=""),"",$B38&"|"&COUNTIFS($B$4:$B38,$B38,$C$4:$C38,"?*")) -> G2 SCooP dataset & paper|24 | L38: =IF($C38="","","ALL|"&COUNTIF($C$4:$C38,"?*")) -> ALL|35
A39: G2-BP-D | B39: G2 SCooP dataset & paper | C39: T2 collaborative perception under 3 channels (D) | D39: SCooP owner | E39: Not Started | F39: 46363 | G39: 5 | H39: =IF(OR($F39="",$G39=""),"",$F39+7*$G39-3) -> 46395 | J39: =IF(OR($C39="",$D39=""),"",$D39&"|"&COUNTIFS($D$4:$D39,$D39,$C$4:$C39,"?*")) -> SCooP owner|25 | K39: =IF(OR($C39="",$B39=""),"",$B39&"|"&COUNTIFS($B$4:$B39,$B39,$C$4:$C39,"?*")) -> G2 SCooP dataset & paper|25 | L39: =IF($C39="","","ALL|"&COUNTIF($C$4:$C39,"?*")) -> ALL|36
A40: G2-BP-E | B40: G2 SCooP dataset & paper | C40: T1 collaborative SLAM (E) | D40: SCooP owner | E40: Not Started | F40: 46363 | G40: 5 | H40: =IF(OR($F40="",$G40=""),"",$F40+7*$G40-3) -> 46395 | J40: =IF(OR($C40="",$D40=""),"",$D40&"|"&COUNTIFS($D$4:$D40,$D40,$C$4:$C40,"?*")) -> SCooP owner|26 | K40: =IF(OR($C40="",$B40=""),"",$B40&"|"&COUNTIFS($B$4:$B40,$B40,$C$4:$C40,"?*")) -> G2 SCooP dataset & paper|26 | L40: =IF($C40="","","ALL|"&COUNTIF($C$4:$C40,"?*")) -> ALL|37
A41: G2-BP-F | B41: G2 SCooP dataset & paper | C41: Q2 regression (F) | D41: SCooP owner | E41: Not Started | F41: 46398 | G41: 2 | H41: =IF(OR($F41="",$G41=""),"",$F41+7*$G41-3) -> 46409 | J41: =IF(OR($C41="",$D41=""),"",$D41&"|"&COUNTIFS($D$4:$D41,$D41,$C$4:$C41,"?*")) -> SCooP owner|27 | K41: =IF(OR($C41="",$B41=""),"",$B41&"|"&COUNTIFS($B$4:$B41,$B41,$C$4:$C41,"?*")) -> G2 SCooP dataset & paper|27 | L41: =IF($C41="","","ALL|"&COUNTIF($C$4:$C41,"?*")) -> ALL|38
A42: G2-BP-G | B42: G2 SCooP dataset & paper | C42: Write-up (G) | D42: SCooP owner | E42: Not Started | F42: 46398 | G42: 4 | H42: =IF(OR($F42="",$G42=""),"",$F42+7*$G42-3) -> 46423 | J42: =IF(OR($C42="",$D42=""),"",$D42&"|"&COUNTIFS($D$4:$D42,$D42,$C$4:$C42,"?*")) -> SCooP owner|28 | K42: =IF(OR($C42="",$B42=""),"",$B42&"|"&COUNTIFS($B$4:$B42,$B42,$C$4:$C42,"?*")) -> G2 SCooP dataset & paper|28 | L42: =IF($C42="","","ALL|"&COUNTIF($C$4:$C42,"?*")) -> ALL|39
A43: G2-M1 | B43: G2 SCooP dataset & paper | C43: Paper submitted (IJRR) | D43: SCooP owner | E43: Not Started | F43: 46426 | G43: 1 | H43: =IF(OR($F43="",$G43=""),"",$F43+7*$G43-3) -> 46430 | J43: =IF(OR($C43="",$D43=""),"",$D43&"|"&COUNTIFS($D$4:$D43,$D43,$C$4:$C43,"?*")) -> SCooP owner|29 | K43: =IF(OR($C43="",$B43=""),"",$B43&"|"&COUNTIFS($B$4:$B43,$B43,$C$4:$C43,"?*")) -> G2 SCooP dataset & paper|29 | L43: =IF($C43="","","ALL|"&COUNTIF($C$4:$C43,"?*")) -> ALL|40
A44: G1-SP-1 | B44: G1 ED305 live digital twin | C44: Sensor rig & TF tree per robot | D44: Sensors & platform owner | E44: Not Started | F44: 46307 | G44: 2 | H44: =IF(OR($F44="",$G44=""),"",$F44+7*$G44-3) -> 46318 | J44: =IF(OR($C44="",$D44=""),"",$D44&"|"&COUNTIFS($D$4:$D44,$D44,$C$4:$C44,"?*")) -> Sensors & platform owner|12 | K44: =IF(OR($C44="",$B44=""),"",$B44&"|"&COUNTIFS($B$4:$B44,$B44,$C$4:$C44,"?*")) -> G1 ED305 live digital twin|1 | L44: =IF($C44="","","ALL|"&COUNTIF($C$4:$C44,"?*")) -> ALL|41
A45: G1-SP-2 | B45: G1 ED305 live digital twin | C45: Odometry: front end + fusion filter | D45: Sensors & platform owner | E45: Not Started | F45: 46314 | G45: 4 | H45: =IF(OR($F45="",$G45=""),"",$F45+7*$G45-3) -> 46339 | J45: =IF(OR($C45="",$D45=""),"",$D45&"|"&COUNTIFS($D$4:$D45,$D45,$C$4:$C45,"?*")) -> Sensors & platform owner|13 | K45: =IF(OR($C45="",$B45=""),"",$B45&"|"&COUNTIFS($B$4:$B45,$B45,$C$4:$C45,"?*")) -> G1 ED305 live digital twin|2 | L45: =IF($C45="","","ALL|"&COUNTIF($C$4:$C45,"?*")) -> ALL|42
... A58: G1-SD-1 | B58: G1 ED305 live digital twin | C58: Object asset library | D58: Scene detection owner | E58: Not Started | F58: 46307 | G58: 3 | H58: =IF(OR($F58="",$G58=""),"",$F58+7*$G58-3) -> 46325 | J58: =IF(OR($C58="",$D58=""),"",$D58&"|"&COUNTIFS($D$4:$D58,$D58,$C$4:$C58,"?*")) -> Scene detection owner|1 | K58: =IF(OR($C58="",$B58=""),"",$B58&"|"&COUNTIFS($B$4:$B58,$B58,$C$4:$C58,"?*")) -> G1 ED305 live digital twin|15 | L58: =IF($C58="","","ALL|"&COUNTIF($C$4:$C58,"?*")) -> ALL|55
A59: G1-SD-2 | B59: G1 ED305 live digital twin | C59: Object retrieval from G* | D59: Scene detection owner | E59: Not Started | F59: 46328 | G59: 4 | H59: =IF(OR($F59="",$G59=""),"",$F59+7*$G59-3) -> 46353 | I59: Split up the metric map into objects | J59: =IF(OR($C59="",$D59=""),"",$D59&"|"&COUNTIFS($D$4:$D59,$D59,$C$4:$C59,"?*")) -> Scene detection owner|2 | K59: =IF(OR($C59="",$B59=""),"",$B59&"|"&COUNTIFS($B$4:$B59,$B59,$C$4:$C59,"?*")) -> G1 ED305 live digital twin|16 | L59: =IF($C59="","","ALL|"&COUNTIF($C$4:$C59,"?*")) -> ALL|56
A60: G1-SD-2.1 | B60: G1 ED305 live digital twin | C60: Object Detection & Instance Identification (RGB / RGBD / LiDAR / Radar) | D60: Scene detection owner | E60: Not Started | F60: 46209 | G60: 2 | H60: =IF(OR($F60="",$G60=""),"",$F60+7*$G60-3) -> 46220 | J60: =IF(OR($C60="",$D60=""),"",$D60&"|"&COUNTIFS($D$4:$D60,$D60,$C$4:$C60,"?*")) -> Scene detection owner|3 | K60: =IF(OR($C60="",$B60=""),"",$B60&"|"&COUNTIFS($B$4:$B60,$B60,$C$4:$C60,"?*")) -> G1 ED305 live digital twin|17 | L60: =IF($C60="","","ALL|"&COUNTIF($C$4:$C60,"?*")) -> ALL|57
A61: G1-SD-2.2 | B61: G1 ED305 live digital twin | C61: Radar + Panoptic Fusion Tracking | D61: Scene detection owner | E61: Not Started | F61: 46209 | G61: 2 | H61: =IF(OR($F61="",$G61=""),"",$F61+7*$G61-3) -> 46220 | J61: =IF(OR($C61="",$D61=""),"",$D61&"|"&COUNTIFS($D$4:$D61,$D61,$C$4:$C61,"?*")) -> Scene detection owner|4 | K61: =IF(OR($C61="",$B61=""),"",$B61&"|"&COUNTIFS($B$4:$B61,$B61,$C$4:$C61,"?*")) -> G1 ED305 live digital twin|18 | L61: =IF($C61="","","ALL|"&COUNTIF($C$4:$C61,"?*")) -> ALL|58
A62: G1-SD-3 | B62: G1 ED305 live digital twin | C62: Decomposition: segments & materials | D62: Scene detection owner | E62: Not Started | F62: 46335 | G62: 4 | H62: =IF(OR($F62="",$G62=""),"",$F62+7*$G62-3) -> 46360 | J62: =IF(OR($C62="",$D62=""),"",$D62&"|"&COUNTIFS($D$4:$D62,$D62,$C$4:$C62,"?*")) -> Scene detection owner|5 | K62: =IF(OR($C62="",$B62=""),"",$B62&"|"&COUNTIFS($B$4:$B62,$B62,$C$4:$C62,"?*")) -> G1 ED305 live digital twin|19 | L62: =IF($C62="","","ALL|"&COUNTIF($C$4:$C62,"?*")) -> ALL|59
A63: G1-SD-4 | B63: G1 ED305 live digital twin | C63: Change detection | D63: Scene detection owner | E63: Not Started | F63: 46356 | G63: 4 | H63: =IF(OR($F63="",$G63=""),"",$F63+7*$G63-3) -> 46381 | J63: =IF(OR($C63="",$D63=""),"",$D63&"|"&COUNTIFS($D$4:$D63,$D63,$C$4:$C63,"?*")) -> Scene detection owner|6 | K63: =IF(OR($C63="",$B63=""),"",$B63&"|"&COUNTIFS($B$4:$B63,$B63,$C$4:$C63,"?*")) -> G1 ED305 live digital twin|20 | L63: =IF($C63="","","ALL|"&COUNTIF($C$4:$C63,"?*")) -> ALL|60
A64: G1-SD-4.1 | B64: G1 ED305 live digital twin | C64: Change Detection (Object Moved / Appeared / Disappeared) | D64: Scene detection owner | E64: Not Started | F64: 46223 | G64: 1 | H64: =IF(OR($F64="",$G64=""),"",$F64+7*$G64-3) -> 46227 | J64: =IF(OR($C64="",$D64=""),"",$D64&"|"&COUNTIFS($D$4:$D64,$D64,$C$4:$C64,"?*")) -> Scene detection owner|7 | K64: =IF(OR($C64="",$B64=""),"",$B64&"|"&COUNTIFS($B$4:$B64,$B64,$C$4:$C64,"?*")) -> G1 ED305 live digital twin|21 | L64: =IF($C64="","","ALL|"&COUNTIF($C$4:$C64,"?*")) -> ALL|61
A65: G1-SD-5 | B65: G1 ED305 live digital twin | C65: Maintenance with change history | D65: Scene detection owner | E65: Not Started | F65: 46370 | G65: 3 | H65: =IF(OR($F65="",$G65=""),"",$F65+7*$G65-3) -> 46388 | J65: =IF(OR($C65="",$D65=""),"",$D65&"|"&COUNTIFS($D$4:$D65,$D65,$C$4:$C65,"?*")) -> Scene detection owner|8 | K65: =IF(OR($C65="",$B65=""),"",$B65&"|"&COUNTIFS($B$4:$B65,$B65,$C$4:$C65,"?*")) -> G1 ED305 live digital twin|22 | L65: =IF($C65="","","ALL|"&COUNTIF($C$4:$C65,"?*")) -> ALL|62
A66: G1-SD-5.1 | B66: G1 ED305 live digital twin | C66: Scene Graph & Map Update on Change (with Change History) | D66: Scene detection owner | E66: Not Started | F66: 46223 | G66: 2 | H66: =IF(OR($F66="",$G66=""),"",$F66+7*$G66-3) -> 46234 | J66: =IF(OR($C66="",$D66=""),"",$D66&"|"&COUNTIFS($D$4:$D66,$D66,$C$4:$C66,"?*")) -> Scene detection owner|9 | K66: =IF(OR($C66="",$B66=""),"",$B66&"|"&COUNTIFS($B$4:$B66,$B66,$C$4:$C66,"?*")) -> G1 ED305 live digital twin|23 | L66: =IF($C66="","","ALL|"&COUNTIF($C$4:$C66,"?*")) -> ALL|63
A67: G1-SD-6 | B67: G1 ED305 live digital twin | C67: USD edits to Isaac | D67: Scene detection owner | E67: Not Started | F67: 46370 | G67: 3 | H67: =IF(OR($F67="",$G67=""),"",$F67+7*$G67-3) -> 46388 | J67: =IF(OR($C67="",$D67=""),"",$D67&"|"&COUNTIFS($D$4:$D67,$D67,$C$4:$C67,"?*")) -> Scene detection owner|10 | K67: =IF(OR($C67="",$B67=""),"",$B67&"|"&COUNTIFS($B$4:$B67,$B67,$C$4:$C67,"?*")) -> G1 ED305 live digital twin|24 | L67: =IF($C67="","","ALL|"&COUNTIF($C$4:$C67,"?*")) -> ALL|64
A68: G1-SD-7 | B68: G1 ED305 live digital twin | C68: Live targets from the ED305 cameras | D68: Scene detection owner | E68: Not Started | F68: 46349 | G68: 4 | H68: =IF(OR($F68="",$G68=""),"",$F68+7*$G68-3) -> 46374 | J68: =IF(OR($C68="",$D68=""),"",$D68&"|"&COUNTIFS($D$4:$D68,$D68,$C$4:$C68,"?*")) -> Scene detection owner|11 | K68: =IF(OR($C68="",$B68=""),"",$B68&"|"&COUNTIFS($B$4:$B68,$B68,$C$4:$C68,"?*")) -> G1 ED305 live digital twin|25 | L68: =IF($C68="","","ALL|"&COUNTIF($C$4:$C68,"?*")) -> ALL|65
A69: G1-IS-1 | B69: G1 ED305 live digital twin | C69: ED305 USD stage in the room frame | D69: Isaac Sim owner | E69: Not Started | F69: 46307 | G69: 3 | H69: =IF(OR($F69="",$G69=""),"",$F69+7*$G69-3) -> 46325 | J69: =IF(OR($C69="",$D69=""),"",$D69&"|"&COUNTIFS($D$4:$D69,$D69,$C$4:$C69,"?*")) -> Isaac Sim owner|1 | K69: =IF(OR($C69="",$B69=""),"",$B69&"|"&COUNTIFS($B$4:$B69,$B69,$C$4:$C69,"?*")) -> G1 ED305 live digital twin|26 | L69: =IF($C69="","","ALL|"&COUNTIF($C$4:$C69,"?*")) -> ALL|66
A70: G1-IS-2 | B70: G1 ED305 live digital twin | C70: Robot + antenna prims, live pose | D70: Isaac Sim owner | E70: Not Started | F70: 46321 | G70: 3 | H70: =IF(OR($F70="",$G70=""),"",$F70+7*$G70-3) -> 46339 | J70: =IF(OR($C70="",$D70=""),"",$D70&"|"&COUNTIFS($D$4:$D70,$D70,$C$4:$C70,"?*")) -> Isaac Sim owner|2 | K70: =IF(OR($C70="",$B70=""),"",$B70&"|"&COUNTIFS($B$4:$B70,$B70,$C$4:$C70,"?*")) -> G1 ED305 live digital twin|27 | L70: =IF($C70="","","ALL|"&COUNTIF($C$4:$C70,"?*")) -> ALL|67
A71: G1-IS-3 | B71: G1 ED305 live digital twin | C71: Gaussian layer | D71: Isaac Sim owner | E71: Not Started | F71: 46335 | G71: 3 | H71: =IF(OR($F71="",$G71=""),"",$F71+7*$G71-3) -> 46353 | J71: =IF(OR($C71="",$D71=""),"",$D71&"|"&COUNTIFS($D$4:$D71,$D71,$C$4:$C71,"?*")) -> Isaac Sim owner|3 | K71: =IF(OR($C71="",$B71=""),"",$B71&"|"&COUNTIFS($B$4:$B71,$B71,$C$4:$C71,"?*")) -> G1 ED305 live digital twin|28 | L71: =IF($C71="","","ALL|"&COUNTIF($C$4:$C71,"?*")) -> ALL|68
... A114: SC-2.2 | B114: Semantic Communication | C114: Realistic Channel Model | D114: Semantic comm owner | E114: Not Started | F114: 46216 | G114: 1 | H114: =IF(OR($F114="",$G114=""),"",$F114+7*$G114-3) -> 46220 | J114: =IF(OR($C114="",$D114=""),"",$D114&"|"&COUNTIFS($D$4:$D114,$D114,$C$4:$C114,"?*")) -> Semantic comm owner|6 | K114: =IF(OR($C114="",$B114=""),"",$B114&"|"&COUNTIFS($B$4:$B114,$B114,$C$4:$C114,"?*")) -> Semantic Communication|6 | L114: =IF($C114="","","ALL|"&COUNTIF($C$4:$C114,"?*")) -> ALL|111
A115: SC-3 | B115: Semantic Communication | C115: Dynamic Bandwidth Management | D115: Semantic comm owner | E115: Not Started | H115: =IF(OR($F115="",$G115=""),"",$F115+7*$G115-3) | J115: =IF(OR($C115="",$D115=""),"",$D115&"|"&COUNTIFS($D$4:$D115,$D115,$C$4:$C115,"?*")) -> Semantic comm owner|7 | K115: =IF(OR($C115="",$B115=""),"",$B115&"|"&COUNTIFS($B$4:$B115,$B115,$C$4:$C115,"?*")) -> Semantic Communication|7 | L115: =IF($C115="","","ALL|"&COUNTIF($C$4:$C115,"?*")) -> ALL|112
A116: SC-3.1 | B116: Semantic Communication | C116: Semantic Allocation | D116: Semantic comm owner | E116: Not Started | H116: =IF(OR($F116="",$G116=""),"",$F116+7*$G116-3) | J116: =IF(OR($C116="",$D116=""),"",$D116&"|"&COUNTIFS($D$4:$D116,$D116,$C$4:$C116,"?*")) -> Semantic comm owner|8 | K116: =IF(OR($C116="",$B116=""),"",$B116&"|"&COUNTIFS($B$4:$B116,$B116,$C$4:$C116,"?*")) -> Semantic Communication|8 | L116: =IF($C116="","","ALL|"&COUNTIF($C$4:$C116,"?*")) -> ALL|113
A117: SC-3.2 | B117: Semantic Communication | C117: Physical Constraint Bounds | D117: Semantic comm owner | E117: Not Started | H117: =IF(OR($F117="",$G117=""),"",$F117+7*$G117-3) | J117: =IF(OR($C117="",$D117=""),"",$D117&"|"&COUNTIFS($D$4:$D117,$D117,$C$4:$C117,"?*")) -> Semantic comm owner|9 | K117: =IF(OR($C117="",$B117=""),"",$B117&"|"&COUNTIFS($B$4:$B117,$B117,$C$4:$C117,"?*")) -> Semantic Communication|9 | L117: =IF($C117="","","ALL|"&COUNTIF($C$4:$C117,"?*")) -> ALL|114
A118: SC-3.3 | B118: Semantic Communication | C118: Per-Modality Truncation | D118: Semantic comm owner | E118: Not Started | H118: =IF(OR($F118="",$G118=""),"",$F118+7*$G118-3) | J118: =IF(OR($C118="",$D118=""),"",$D118&"|"&COUNTIFS($D$4:$D118,$D118,$C$4:$C118,"?*")) -> Semantic comm owner|10 | K118: =IF(OR($C118="",$B118=""),"",$B118&"|"&COUNTIFS($B$4:$B118,$B118,$C$4:$C118,"?*")) -> Semantic Communication|10 | L118: =IF($C118="","","ALL|"&COUNTIF($C$4:$C118,"?*")) -> ALL|115
A119: SC-3.4 | B119: Semantic Communication | C119: Cost-Aware Feedback Loop | D119: Semantic comm owner | E119: Not Started | H119: =IF(OR($F119="",$G119=""),"",$F119+7*$G119-3) | J119: =IF(OR($C119="",$D119=""),"",$D119&"|"&COUNTIFS($D$4:$D119,$D119,$C$4:$C119,"?*")) -> Semantic comm owner|11 | K119: =IF(OR($C119="",$B119=""),"",$B119&"|"&COUNTIFS($B$4:$B119,$B119,$C$4:$C119,"?*")) -> Semantic Communication|11 | L119: =IF($C119="","","ALL|"&COUNTIF($C$4:$C119,"?*")) -> ALL|116
A120: SC-4 | B120: Semantic Communication | C120: Multi-Task Transmission | D120: Semantic comm owner | E120: Not Started | H120: =IF(OR($F120="",$G120=""),"",$F120+7*$G120-3) | J120: =IF(OR($C120="",$D120=""),"",$D120&"|"&COUNTIFS($D$4:$D120,$D120,$C$4:$C120,"?*")) -> Semantic comm owner|12 | K120: =IF(OR($C120="",$B120=""),"",$B120&"|"&COUNTIFS($B$4:$B120,$B120,$C$4:$C120,"?*")) -> Semantic Communication|12 | L120: =IF($C120="","","ALL|"&COUNTIF($C$4:$C120,"?*")) -> ALL|117
A121: SC-5 | B121: Semantic Communication | C121: Train & Evaluate on Dataset | D121: Semantic comm owner | E121: Not Started | H121: =IF(OR($F121="",$G121=""),"",$F121+7*$G121-3) | J121: =IF(OR($C121="",$D121=""),"",$D121&"|"&COUNTIFS($D$4:$D121,$D121,$C$4:$C121,"?*")) -> Semantic comm owner|13 | K121: =IF(OR($C121="",$B121=""),"",$B121&"|"&COUNTIFS($B$4:$B121,$B121,$C$4:$C121,"?*")) -> Semantic Communication|13 | L121: =IF($C121="","","ALL|"&COUNTIF($C$4:$C121,"?*")) -> ALL|118
A122: SC-6 | B122: Semantic Communication | C122: Integrate with Dual-Link | D122: Semantic comm owner | E122: Not Started | H122: =IF(OR($F122="",$G122=""),"",$F122+7*$G122-3) | J122: =IF(OR($C122="",$D122=""),"",$D122&"|"&COUNTIFS($D$4:$D122,$D122,$C$4:$C122,"?*")) -> Semantic comm owner|14 | K122: =IF(OR($C122="",$B122=""),"",$B122&"|"&COUNTIFS($B$4:$B122,$B122,$C$4:$C122,"?*")) -> Semantic Communication|14 | L122: =IF($C122="","","ALL|"&COUNTIF($C$4:$C122,"?*")) -> ALL|119
H123: =IF(OR($F123="",$G123=""),"",$F123+7*$G123-3) | J123: =IF(OR($C123="",$D123=""),"",$D123&"|"&COUNTIFS($D$4:$D123,$D123,$C$4:$C123,"?*")) | K123: =IF(OR($C123="",$B123=""),"",$B123&"|"&COUNTIFS($B$4:$B123,$B123,$C$4:$C123,"?*")) | L123: =IF($C123="","","ALL|"&COUNTIF($C$4:$C123,"?*"))
H124: =IF(OR($F124="",$G124=""),"",$F124+7*$G124-3) | J124: =IF(OR($C124="",$D124=""),"",$D124&"|"&COUNTIFS($D$4:$D124,$D124,$C$4:$C124,"?*")) | K124: =IF(OR($C124="",$B124=""),"",$B124&"|"&COUNTIFS($B$4:$B124,$B124,$C$4:$C124,"?*")) | L124: =IF($C124="","","ALL|"&COUNTIF($C$4:$C124,"?*"))
H125: =IF(OR($F125="",$G125=""),"",$F125+7*$G125-3) | J125: =IF(OR($C125="",$D125=""),"",$D125&"|"&COUNTIFS($D$4:$D125,$D125,$C$4:$C125,"?*")) | K125: =IF(OR($C125="",$B125=""),"",$B125&"|"&COUNTIFS($B$4:$B125,$B125,$C$4:$C125,"?*")) | L125: =IF($C125="","","ALL|"&COUNTIF($C$4:$C125,"?*"))
H126: =IF(OR($F126="",$G126=""),"",$F126+7*$G126-3) | J126: =IF(OR($C126="",$D126=""),"",$D126&"|"&COUNTIFS($D$4:$D126,$D126,$C$4:$C126,"?*")) | K126: =IF(OR($C126="",$B126=""),"",$B126&"|"&COUNTIFS($B$4:$B126,$B126,$C$4:$C126,"?*")) | L126: =IF($C126="","","ALL|"&COUNTIF($C$4:$C126,"?*"))
H127: =IF(OR($F127="",$G127=""),"",$F127+7*$G127-3) | J127: =IF(OR($C127="",$D127=""),"",$D127&"|"&COUNTIFS($D$4:$D127,$D127,$C$4:$C127,"?*")) | K127: =IF(OR($C127="",$B127=""),"",$B127&"|"&COUNTIFS($B$4:$B127,$B127,$C$4:$C127,"?*")) | L127: =IF($C127="","","ALL|"&COUNTIF($C$4:$C127,"?*"))
H128: =IF(OR($F128="",$G128=""),"",$F128+7*$G128-3) | J128: =IF(OR($C128="",$D128=""),"",$D128&"|"&COUNTIFS($D$4:$D128,$D128,$C$4:$C128,"?*")) | K128: =IF(OR($C128="",$B128=""),"",$B128&"|"&COUNTIFS($B$4:$B128,$B128,$C$4:$C128,"?*")) | L128: =IF($C128="","","ALL|"&COUNTIF($C$4:$C128,"?*"))
H129: =IF(OR($F129="",$G129=""),"",$F129+7*$G129-3) | J129: =IF(OR($C129="",$D129=""),"",$D129&"|"&COUNTIFS($D$4:$D129,$D129,$C$4:$C129,"?*")) | K129: =IF(OR($C129="",$B129=""),"",$B129&"|"&COUNTIFS($B$4:$B129,$B129,$C$4:$C129,"?*")) | L129: =IF($C129="","","ALL|"&COUNTIF($C$4:$C129,"?*"))
H130: =IF(OR($F130="",$G130=""),"",$F130+7*$G130-3) | J130: =IF(OR($C130="",$D130=""),"",$D130&"|"&COUNTIFS($D$4:$D130,$D130,$C$4:$C130,"?*")) | K130: =IF(OR($C130="",$B130=""),"",$B130&"|"&COUNTIFS($B$4:$B130,$B130,$C$4:$C130,"?*")) | L130: =IF($C130="","","ALL|"&COUNTIF($C$4:$C130,"?*"))
H131: =IF(OR($F131="",$G131=""),"",$F131+7*$G131-3) | J131: =IF(OR($C131="",$D131=""),"",$D131&"|"&COUNTIFS($D$4:$D131,$D131,$C$4:$C131,"?*")) | K131: =IF(OR($C131="",$B131=""),"",$B131&"|"&COUNTIFS($B$4:$B131,$B131,$C$4:$C131,"?*")) | L131: =IF($C131="","","ALL|"&COUNTIF($C$4:$C131,"?*"))
H132: =IF(OR($F132="",$G132=""),"",$F132+7*$G132-3) | J132: =IF(OR($C132="",$D132=""),"",$D132&"|"&COUNTIFS($D$4:$D132,$D132,$C$4:$C132,"?*")) | K132: =IF(OR($C132="",$B132=""),"",$B132&"|"&COUNTIFS($B$4:$B132,$B132,$C$4:$C132,"?*")) | L132: =IF($C132="","","ALL|"&COUNTIF($C$4:$C132,"?*"))
H133: =IF(OR($F133="",$G133=""),"",$F133+7*$G133-3) | J133: =IF(OR($C133="",$D133=""),"",$D133&"|"&COUNTIFS($D$4:$D133,$D133,$C$4:$C133,"?*")) | K133: =IF(OR($C133="",$B133=""),"",$B133&"|"&COUNTIFS($B$4:$B133,$B133,$C$4:$C133,"?*")) | L133: =IF($C133="","","ALL|"&COUNTIF($C$4:$C133,"?*"))
H134: =IF(OR($F134="",$G134=""),"",$F134+7*$G134-3) | J134: =IF(OR($C134="",$D134=""),"",$D134&"|"&COUNTIFS($D$4:$D134,$D134,$C$4:$C134,"?*")) | K134: =IF(OR($C134="",$B134=""),"",$B134&"|"&COUNTIFS($B$4:$B134,$B134,$C$4:$C134,"?*")) | L134: =IF($C134="","","ALL|"&COUNTIF($C$4:$C134,"?*"))
... H403: =IF(OR($F403="",$G403=""),"",$F403+7*$G403-3) | J403: =IF(OR($C403="",$D403=""),"",$D403&"|"&COUNTIFS($D$4:$D403,$D403,$C$4:$C403,"?*")) | K403: =IF(OR($C403="",$B403=""),"",$B403&"|"&COUNTIFS($B$4:$B403,$B403,$C$4:$C403,"?*")) | L403: =IF($C403="","","ALL|"&COUNTIF($C$4:$C403,"?*"))

Sheet Dashboard
A1: Dashboard
A2: Counts from Tasks. Nothing to edit.
A4: Goal | B4: Not Started | C4: In Progress | D4: Blocked | E4: Complete | F4: Partially Completed | G4: No status | H4: Total | I4: Overdue
A5: G1 ED305 live digital twin | B5: =COUNTIFS(Tasks!$B$4:$B$403,$A5,Tasks!$C$4:$C$403,"?*",Tasks!$E$4:$E$403,"Not Started") -> 41 | C5: =COUNTIFS(Tasks!$B$4:$B$403,$A5,Tasks!$C$4:$C$403,"?*",Tasks!$E$4:$E$403,"In Progress") -> 1 | D5: =COUNTIFS(Tasks!$B$4:$B$403,$A5,Tasks!$C$4:$C$403,"?*",Tasks!$E$4:$E$403,"Blocked") -> 1 | E5: =COUNTIFS(Tasks!$B$4:$B$403,$A5,Tasks!$C$4:$C$403,"?*",Tasks!$E$4:$E$403,"Complete") -> 0 | F5: =COUNTIFS(Tasks!$B$4:$B$403,$A5,Tasks!$C$4:$C$403,"?*",Tasks!$E$4:$E$403,"Partially Completed") -> 0 | G5: =COUNTIFS(Tasks!$B$4:$B$403,$A5,Tasks!$C$4:$C$403,"?*",Tasks!$E$4:$E$403,"") -> 0 | H5: =SUM(B5:G5) -> 43 | I5: =COUNTIFS(Tasks!$B$4:$B$403,$A5,Tasks!$C$4:$C$403,"?*",Tasks!$H$4:$H$403,"<"&TODAY(),Tasks!$E$4:$E$403,"<>Complete") -> 6
A6: G2 SCooP dataset & paper | B6: =COUNTIFS(Tasks!$B$4:$B$403,$A6,Tasks!$C$4:$C$403,"?*",Tasks!$E$4:$E$403,"Not Started") -> 21 | C6: =COUNTIFS(Tasks!$B$4:$B$403,$A6,Tasks!$C$4:$C$403,"?*",Tasks!$E$4:$E$403,"In Progress") -> 4 | D6: =COUNTIFS(Tasks!$B$4:$B$403,$A6,Tasks!$C$4:$C$403,"?*",Tasks!$E$4:$E$403,"Blocked") -> 0 | E6: =COUNTIFS(Tasks!$B$4:$B$403,$A6,Tasks!$C$4:$C$403,"?*",Tasks!$E$4:$E$403,"Complete") -> 0 | F6: =COUNTIFS(Tasks!$B$4:$B$403,$A6,Tasks!$C$4:$C$403,"?*",Tasks!$E$4:$E$403,"Partially Completed") -> 2 | G6: =COUNTIFS(Tasks!$B$4:$B$403,$A6,Tasks!$C$4:$C$403,"?*",Tasks!$E$4:$E$403,"") -> 2 | H6: =SUM(B6:G6) -> 29 | I6: =COUNTIFS(Tasks!$B$4:$B$403,$A6,Tasks!$C$4:$C$403,"?*",Tasks!$H$4:$H$403,"<"&TODAY(),Tasks!$E$4:$E$403,"<>Complete") -> 5
A7: Shared SCooP testbed | B7: =COUNTIFS(Tasks!$B$4:$B$403,$A7,Tasks!$C$4:$C$403,"?*",Tasks!$E$4:$E$403,"Not Started") -> 2 | C7: =COUNTIFS(Tasks!$B$4:$B$403,$A7,Tasks!$C$4:$C$403,"?*",Tasks!$E$4:$E$403,"In Progress") -> 4 | D7: =COUNTIFS(Tasks!$B$4:$B$403,$A7,Tasks!$C$4:$C$403,"?*",Tasks!$E$4:$E$403,"Blocked") -> 0 | E7: =COUNTIFS(Tasks!$B$4:$B$403,$A7,Tasks!$C$4:$C$403,"?*",Tasks!$E$4:$E$403,"Complete") -> 0 | F7: =COUNTIFS(Tasks!$B$4:$B$403,$A7,Tasks!$C$4:$C$403,"?*",Tasks!$E$4:$E$403,"Partially Completed") -> 0 | G7: =COUNTIFS(Tasks!$B$4:$B$403,$A7,Tasks!$C$4:$C$403,"?*",Tasks!$E$4:$E$403,"") -> 5 | H7: =SUM(B7:G7) -> 11 | I7: =COUNTIFS(Tasks!$B$4:$B$403,$A7,Tasks!$C$4:$C$403,"?*",Tasks!$H$4:$H$403,"<"&TODAY(),Tasks!$E$4:$E$403,"<>Complete") -> 3
A8: Dual-Link Communication | B8: =COUNTIFS(Tasks!$B$4:$B$403,$A8,Tasks!$C$4:$C$403,"?*",Tasks!$E$4:$E$403,"Not Started") -> 13 | C8: =COUNTIFS(Tasks!$B$4:$B$403,$A8,Tasks!$C$4:$C$403,"?*",Tasks!$E$4:$E$403,"In Progress") -> 2 | D8: =COUNTIFS(Tasks!$B$4:$B$403,$A8,Tasks!$C$4:$C$403,"?*",Tasks!$E$4:$E$403,"Blocked") -> 0 | E8: =COUNTIFS(Tasks!$B$4:$B$403,$A8,Tasks!$C$4:$C$403,"?*",Tasks!$E$4:$E$403,"Complete") -> 0 | F8: =COUNTIFS(Tasks!$B$4:$B$403,$A8,Tasks!$C$4:$C$403,"?*",Tasks!$E$4:$E$403,"Partially Completed") -> 7 | G8: =COUNTIFS(Tasks!$B$4:$B$403,$A8,Tasks!$C$4:$C$403,"?*",Tasks!$E$4:$E$403,"") -> 0 | H8: =SUM(B8:G8) -> 22 | I8: =COUNTIFS(Tasks!$B$4:$B$403,$A8,Tasks!$C$4:$C$403,"?*",Tasks!$H$4:$H$403,"<"&TODAY(),Tasks!$E$4:$E$403,"<>Complete") -> 22
A9: Semantic Communication | B9: =COUNTIFS(Tasks!$B$4:$B$403,$A9,Tasks!$C$4:$C$403,"?*",Tasks!$E$4:$E$403,"Not Started") -> 14 | C9: =COUNTIFS(Tasks!$B$4:$B$403,$A9,Tasks!$C$4:$C$403,"?*",Tasks!$E$4:$E$403,"In Progress") -> 0 | D9: =COUNTIFS(Tasks!$B$4:$B$403,$A9,Tasks!$C$4:$C$403,"?*",Tasks!$E$4:$E$403,"Blocked") -> 0 | E9: =COUNTIFS(Tasks!$B$4:$B$403,$A9,Tasks!$C$4:$C$403,"?*",Tasks!$E$4:$E$403,"Complete") -> 0 | F9: =COUNTIFS(Tasks!$B$4:$B$403,$A9,Tasks!$C$4:$C$403,"?*",Tasks!$E$4:$E$403,"Partially Completed") -> 0 | G9: =COUNTIFS(Tasks!$B$4:$B$403,$A9,Tasks!$C$4:$C$403,"?*",Tasks!$E$4:$E$403,"") -> 0 | H9: =SUM(B9:G9) -> 14 | I9: =COUNTIFS(Tasks!$B$4:$B$403,$A9,Tasks!$C$4:$C$403,"?*",Tasks!$H$4:$H$403,"<"&TODAY(),Tasks!$E$4:$E$403,"<>Complete") -> 6
A10: Total | B10: =SUM(B5:B9) -> 91 | C10: =SUM(C5:C9) -> 11 | D10: =SUM(D5:D9) -> 1 | E10: =SUM(E5:E9) -> 0 | F10: =SUM(F5:F9) -> 9 | G10: =SUM(G5:G9) -> 7 | H10: =SUM(H5:H9) -> 119 | I10: =SUM(I5:I9) -> 42
A13: Person | B13: Not Started | C13: In Progress | D13: Blocked | E13: Complete | F13: Partially Completed | G13: No status | H13: Total | I13: Overdue
A14: =People!$A$4 -> GS-SLAM owner | B14: =COUNTIFS(Tasks!$D$4:$D$403,$A14,Tasks!$C$4:$C$403,"?*",Tasks!$E$4:$E$403,"Not Started") -> 8 | C14: =COUNTIFS(Tasks!$D$4:$D$403,$A14,Tasks!$C$4:$C$403,"?*",Tasks!$E$4:$E$403,"In Progress") -> 0 | D14: =COUNTIFS(Tasks!$D$4:$D$403,$A14,Tasks!$C$4:$C$403,"?*",Tasks!$E$4:$E$403,"Blocked") -> 0 | E14: =COUNTIFS(Tasks!$D$4:$D$403,$A14,Tasks!$C$4:$C$403,"?*",Tasks!$E$4:$E$403,"Complete") -> 0 | F14: =COUNTIFS(Tasks!$D$4:$D$403,$A14,Tasks!$C$4:$C$403,"?*",Tasks!$E$4:$E$403,"Partially Completed") -> 0 | G14: =COUNTIFS(Tasks!$D$4:$D$403,$A14,Tasks!$C$4:$C$403,"?*",Tasks!$E$4:$E$403,"") -> 0 | H14: =SUM(B14:G14) -> 8 | I14: =COUNTIFS(Tasks!$D$4:$D$403,$A14,Tasks!$C$4:$C$403,"?*",Tasks!$H$4:$H$403,"<"&TODAY(),Tasks!$E$4:$E$403,"<>Complete") -> 2
A15: =People!$A$5 -> Isaac Sim owner | B15: =COUNTIFS(Tasks!$D$4:$D$403,$A15,Tasks!$C$4:$C$403,"?*",Tasks!$E$4:$E$403,"Not Started") -> 8 | C15: =COUNTIFS(Tasks!$D$4:$D$403,$A15,Tasks!$C$4:$C$403,"?*",Tasks!$E$4:$E$403,"In Progress") -> 0 | D15: =COUNTIFS(Tasks!$D$4:$D$403,$A15,Tasks!$C$4:$C$403,"?*",Tasks!$E$4:$E$403,"Blocked") -> 0 | E15: =COUNTIFS(Tasks!$D$4:$D$403,$A15,Tasks!$C$4:$C$403,"?*",Tasks!$E$4:$E$403,"Complete") -> 0 | F15: =COUNTIFS(Tasks!$D$4:$D$403,$A15,Tasks!$C$4:$C$403,"?*",Tasks!$E$4:$E$403,"Partially Completed") -> 0 | G15: =COUNTIFS(Tasks!$D$4:$D$403,$A15,Tasks!$C$4:$C$403,"?*",Tasks!$E$4:$E$403,"") -> 0 | H15: =SUM(B15:G15) -> 8 | I15: =COUNTIFS(Tasks!$D$4:$D$403,$A15,Tasks!$C$4:$C$403,"?*",Tasks!$H$4:$H$403,"<"&TODAY(),Tasks!$E$4:$E$403,"<>Complete") -> 0
A16: =People!$A$6 -> Sensors & platform owner | B16: =COUNTIFS(Tasks!$D$4:$D$403,$A16,Tasks!$C$4:$C$403,"?*",Tasks!$E$4:$E$403,"Not Started") -> 6 | C16: =COUNTIFS(Tasks!$D$4:$D$403,$A16,Tasks!$C$4:$C$403,"?*",Tasks!$E$4:$E$403,"In Progress") -> 5 | D16: =COUNTIFS(Tasks!$D$4:$D$403,$A16,Tasks!$C$4:$C$403,"?*",Tasks!$E$4:$E$403,"Blocked") -> 1 | E16: =COUNTIFS(Tasks!$D$4:$D$403,$A16,Tasks!$C$4:$C$403,"?*",Tasks!$E$4:$E$403,"Complete") -> 0 | F16: =COUNTIFS(Tasks!$D$4:$D$403,$A16,Tasks!$C$4:$C$403,"?*",Tasks!$E$4:$E$403,"Partially Completed") -> 0 | G16: =COUNTIFS(Tasks!$D$4:$D$403,$A16,Tasks!$C$4:$C$403,"?*",Tasks!$E$4:$E$403,"") -> 5 | H16: =SUM(B16:G16) -> 17 | I16: =COUNTIFS(Tasks!$D$4:$D$403,$A16,Tasks!$C$4:$C$403,"?*",Tasks!$H$4:$H$403,"<"&TODAY(),Tasks!$E$4:$E$403,"<>Complete") -> 3
A17: =People!$A$7 -> Scene detection owner | B17: =COUNTIFS(Tasks!$D$4:$D$403,$A17,Tasks!$C$4:$C$403,"?*",Tasks!$E$4:$E$403,"Not Started") -> 11 | C17: =COUNTIFS(Tasks!$D$4:$D$403,$A17,Tasks!$C$4:$C$403,"?*",Tasks!$E$4:$E$403,"In Progress") -> 0 | D17: =COUNTIFS(Tasks!$D$4:$D$403,$A17,Tasks!$C$4:$C$403,"?*",Tasks!$E$4:$E$403,"Blocked") -> 0 | E17: =COUNTIFS(Tasks!$D$4:$D$403,$A17,Tasks!$C$4:$C$403,"?*",Tasks!$E$4:$E$403,"Complete") -> 0 | F17: =COUNTIFS(Tasks!$D$4:$D$403,$A17,Tasks!$C$4:$C$403,"?*",Tasks!$E$4:$E$403,"Partially Completed") -> 0 | G17: =COUNTIFS(Tasks!$D$4:$D$403,$A17,Tasks!$C$4:$C$403,"?*",Tasks!$E$4:$E$403,"") -> 0 | H17: =SUM(B17:G17) -> 11 | I17: =COUNTIFS(Tasks!$D$4:$D$403,$A17,Tasks!$C$4:$C$403,"?*",Tasks!$H$4:$H$403,"<"&TODAY(),Tasks!$E$4:$E$403,"<>Complete") -> 4
A18: =People!$A$8 -> Sionna RT owner | B18: =COUNTIFS(Tasks!$D$4:$D$403,$A18,Tasks!$C$4:$C$403,"?*",Tasks!$E$4:$E$403,"Not Started") -> 4 | C18: =COUNTIFS(Tasks!$D$4:$D$403,$A18,Tasks!$C$4:$C$403,"?*",Tasks!$E$4:$E$403,"In Progress") -> 0 | D18: =COUNTIFS(Tasks!$D$4:$D$403,$A18,Tasks!$C$4:$C$403,"?*",Tasks!$E$4:$E$403,"Blocked") -> 0 | E18: =COUNTIFS(Tasks!$D$4:$D$403,$A18,Tasks!$C$4:$C$403,"?*",Tasks!$E$4:$E$403,"Complete") -> 0 | F18: =COUNTIFS(Tasks!$D$4:$D$403,$A18,Tasks!$C$4:$C$403,"?*",Tasks!$E$4:$E$403,"Partially Completed") -> 0 | G18: =COUNTIFS(Tasks!$D$4:$D$403,$A18,Tasks!$C$4:$C$403,"?*",Tasks!$E$4:$E$403,"") -> 0 | H18: =SUM(B18:G18) -> 4 | I18: =COUNTIFS(Tasks!$D$4:$D$403,$A18,Tasks!$C$4:$C$403,"?*",Tasks!$H$4:$H$403,"<"&TODAY(),Tasks!$E$4:$E$403,"<>Complete") -> 0
A19: =People!$A$9 -> SCooP owner | B19: =COUNTIFS(Tasks!$D$4:$D$403,$A19,Tasks!$C$4:$C$403,"?*",Tasks!$E$4:$E$403,"Not Started") -> 21 | C19: =COUNTIFS(Tasks!$D$4:$D$403,$A19,Tasks!$C$4:$C$403,"?*",Tasks!$E$4:$E$403,"In Progress") -> 4 | D19: =COUNTIFS(Tasks!$D$4:$D$403,$A19,Tasks!$C$4:$C$403,"?*",Tasks!$E$4:$E$403,"Blocked") -> 0 | E19: =COUNTIFS(Tasks!$D$4:$D$403,$A19,Tasks!$C$4:$C$403,"?*",Tasks!$E$4:$E$403,"Complete") -> 0 | F19: =COUNTIFS(Tasks!$D$4:$D$403,$A19,Tasks!$C$4:$C$403,"?*",Tasks!$E$4:$E$403,"Partially Completed") -> 2 | G19: =COUNTIFS(Tasks!$D$4:$D$403,$A19,Tasks!$C$4:$C$403,"?*",Tasks!$E$4:$E$403,"") -> 2 | H19: =SUM(B19:G19) -> 29 | I19: =COUNTIFS(Tasks!$D$4:$D$403,$A19,Tasks!$C$4:$C$403,"?*",Tasks!$H$4:$H$403,"<"&TODAY(),Tasks!$E$4:$E$403,"<>Complete") -> 5
A20: =People!$A$10 -> Dual-link owner | B20: =COUNTIFS(Tasks!$D$4:$D$403,$A20,Tasks!$C$4:$C$403,"?*",Tasks!$E$4:$E$403,"Not Started") -> 13 | C20: =COUNTIFS(Tasks!$D$4:$D$403,$A20,Tasks!$C$4:$C$403,"?*",Tasks!$E$4:$E$403,"In Progress") -> 2 | D20: =COUNTIFS(Tasks!$D$4:$D$403,$A20,Tasks!$C$4:$C$403,"?*",Tasks!$E$4:$E$403,"Blocked") -> 0 | E20: =COUNTIFS(Tasks!$D$4:$D$403,$A20,Tasks!$C$4:$C$403,"?*",Tasks!$E$4:$E$403,"Complete") -> 0 | F20: =COUNTIFS(Tasks!$D$4:$D$403,$A20,Tasks!$C$4:$C$403,"?*",Tasks!$E$4:$E$403,"Partially Completed") -> 7 | G20: =COUNTIFS(Tasks!$D$4:$D$403,$A20,Tasks!$C$4:$C$403,"?*",Tasks!$E$4:$E$403,"") -> 0 | H20: =SUM(B20:G20) -> 22 | I20: =COUNTIFS(Tasks!$D$4:$D$403,$A20,Tasks!$C$4:$C$403,"?*",Tasks!$H$4:$H$403,"<"&TODAY(),Tasks!$E$4:$E$403,"<>Complete") -> 22
A21: =People!$A$11 -> Semantic comm owner | B21: =COUNTIFS(Tasks!$D$4:$D$403,$A21,Tasks!$C$4:$C$403,"?*",Tasks!$E$4:$E$403,"Not Started") -> 14 | C21: =COUNTIFS(Tasks!$D$4:$D$403,$A21,Tasks!$C$4:$C$403,"?*",Tasks!$E$4:$E$403,"In Progress") -> 0 | D21: =COUNTIFS(Tasks!$D$4:$D$403,$A21,Tasks!$C$4:$C$403,"?*",Tasks!$E$4:$E$403,"Blocked") -> 0 | E21: =COUNTIFS(Tasks!$D$4:$D$403,$A21,Tasks!$C$4:$C$403,"?*",Tasks!$E$4:$E$403,"Complete") -> 0 | F21: =COUNTIFS(Tasks!$D$4:$D$403,$A21,Tasks!$C$4:$C$403,"?*",Tasks!$E$4:$E$403,"Partially Completed") -> 0 | G21: =COUNTIFS(Tasks!$D$4:$D$403,$A21,Tasks!$C$4:$C$403,"?*",Tasks!$E$4:$E$403,"") -> 0 | H21: =SUM(B21:G21) -> 14 | I21: =COUNTIFS(Tasks!$D$4:$D$403,$A21,Tasks!$C$4:$C$403,"?*",Tasks!$H$4:$H$403,"<"&TODAY(),Tasks!$E$4:$E$403,"<>Complete") -> 6
A22: =People!$A$12 -> Team | B22: =COUNTIFS(Tasks!$D$4:$D$403,$A22,Tasks!$C$4:$C$403,"?*",Tasks!$E$4:$E$403,"Not Started") -> 6 | C22: =COUNTIFS(Tasks!$D$4:$D$403,$A22,Tasks!$C$4:$C$403,"?*",Tasks!$E$4:$E$403,"In Progress") -> 0 | D22: =COUNTIFS(Tasks!$D$4:$D$403,$A22,Tasks!$C$4:$C$403,"?*",Tasks!$E$4:$E$403,"Blocked") -> 0 | E22: =COUNTIFS(Tasks!$D$4:$D$403,$A22,Tasks!$C$4:$C$403,"?*",Tasks!$E$4:$E$403,"Complete") -> 0 | F22: =COUNTIFS(Tasks!$D$4:$D$403,$A22,Tasks!$C$4:$C$403,"?*",Tasks!$E$4:$E$403,"Partially Completed") -> 0 | G22: =COUNTIFS(Tasks!$D$4:$D$403,$A22,Tasks!$C$4:$C$403,"?*",Tasks!$E$4:$E$403,"") -> 0 | H22: =SUM(B22:G22) -> 6 | I22: =COUNTIFS(Tasks!$D$4:$D$403,$A22,Tasks!$C$4:$C$403,"?*",Tasks!$H$4:$H$403,"<"&TODAY(),Tasks!$E$4:$E$403,"<>Complete") -> 0
A23: Total | B23: =SUM(B14:B22) -> 91 | C23: =SUM(C14:C22) -> 11 | D23: =SUM(D14:D22) -> 1 | E23: =SUM(E14:E22) -> 0 | F23: =SUM(F14:F22) -> 9 | G23: =SUM(G14:G22) -> 7 | H23: =SUM(H14:H22) -> 119 | I23: =SUM(I14:I22) -> 42

Sheet Gantt
B1: Gantt: all tasks
C2: ALL | E2: =COUNTIF(Tasks!$C$4:$C$403,"?*")&" tasks · "&COUNTIFS(Tasks!$H$4:$H$403,"<"&TODAY(),Tasks!$E$4:$E$403,"<>Complete")&" overdue" -> 119 tasks · 42 overdue
B3: Gantt starts (Monday): | C3: 46195
A4: Tasks row | B4: ID | C4: Task | D4: Assigned to | E4: Status | F4: Start | G4: End | H4: =$C$3+7*0 -> 46195 | I4: =$C$3+7*1 -> 46202 | J4: =$C$3+7*2 -> 46209 | K4: =$C$3+7*3 -> 46216 | L4: =$C$3+7*4 -> 46223 | M4: =$C$3+7*5 -> 46230 | N4: =$C$3+7*6 -> 46237 | O4: =$C$3+7*7 -> 46244 | P4: =$C$3+7*8 -> 46251 | Q4: =$C$3+7*9 -> 46258 | R4: =$C$3+7*10 -> 46265 | S4: =$C$3+7*11 -> 46272 | T4: =$C$3+7*12 -> 46279 | U4: =$C$3+7*13 -> 46286 | V4: =$C$3+7*14 -> 46293 | W4: =$C$3+7*15 -> 46300 | X4: =$C$3+7*16 -> 46307 | Y4: =$C$3+7*17 -> 46314 | Z4: =$C$3+7*18 -> 46321 | AA4: =$C$3+7*19 -> 46328 | AB4: =$C$3+7*20 -> 46335 | AC4: =$C$3+7*21 -> 46342 | AD4: =$C$3+7*22 -> 46349 | AE4: =$C$3+7*23 -> 46356 | AF4: =$C$3+7*24 -> 46363 | AG4: =$C$3+7*25 -> 46370 | AH4: =$C$3+7*26 -> 46377 | AI4: =$C$3+7*27 -> 46384 | AJ4: =$C$3+7*28 -> 46391 | AK4: =$C$3+7*29 -> 46398 | AL4: =$C$3+7*30 -> 46405 | AM4: =$C$3+7*31 -> 46412 | AN4: =$C$3+7*32 -> 46419 | AO4: =$C$3+7*33 -> 46426 | AP4: =$C$3+7*34 -> 46433 | AQ4: =$C$3+7*35 -> 46440 | AR4: =$C$3+7*36 -> 46447 | AS4: =$C$3+7*37 -> 46454 | AT4: =$C$3+7*38 -> 46461 | AU4: =$C$3+7*39 -> 46468 | AV4: =$C$3+7*40 -> 46475 | AW4: =$C$3+7*41 -> 46482 | AX4: =$C$3+7*42 -> 46489 | AY4: =$C$3+7*43 -> 46496 | BB4: Legend
A5: =IFERROR(MATCH($C$2&"|"&(ROW()-4),Tasks!$L$4:$L$403,0)+3,"") -> 4 | B5: =IF($A5="","",IF(INDEX(Tasks!$A:$A,$A5)="","",INDEX(Tasks!$A:$A,$A5))) -> TB-1 | C5: =IF($A5="","",IF(ISERROR(FIND(".",INDEX(Tasks!$A:$A,$A5))),""," ")&INDEX(Tasks!$C:$C,$A5)) -> Hardware inventory & specs | D5: =IF($A5="","",IF(INDEX(Tasks!$D:$D,$A5)="","",INDEX(Tasks!$D:$D,$A5))) -> Sensors & platform owner | E5: =IF($A5="","",IF(INDEX(Tasks!$E:$E,$A5)="","",INDEX(Tasks!$E:$E,$A5))) -> Not Started | F5: =IF($A5="","",IF(INDEX(Tasks!$F:$F,$A5)="","",INDEX(Tasks!$F:$F,$A5))) -> 46307 | G5: =IF($A5="","",IF(INDEX(Tasks!$H:$H,$A5)="","",INDEX(Tasks!$H:$H,$A5))) -> 46318 | BB5: Complete
A6: =IFERROR(MATCH($C$2&"|"&(ROW()-4),Tasks!$L$4:$L$403,0)+3,"") -> 5 | B6: =IF($A6="","",IF(INDEX(Tasks!$A:$A,$A6)="","",INDEX(Tasks!$A:$A,$A6))) -> TB-2 | C6: =IF($A6="","",IF(ISERROR(FIND(".",INDEX(Tasks!$A:$A,$A6))),""," ")&INDEX(Tasks!$C:$C,$A6)) -> Sensor calibration (all units) | D6: =IF($A6="","",IF(INDEX(Tasks!$D:$D,$A6)="","",INDEX(Tasks!$D:$D,$A6))) -> Sensors & platform owner | E6: =IF($A6="","",IF(INDEX(Tasks!$E:$E,$A6)="","",INDEX(Tasks!$E:$E,$A6))) -> In Progress | F6: =IF($A6="","",IF(INDEX(Tasks!$F:$F,$A6)="","",INDEX(Tasks!$F:$F,$A6))) -> 46195 | G6: =IF($A6="","",IF(INDEX(Tasks!$H:$H,$A6)="","",INDEX(Tasks!$H:$H,$A6))) -> 46206 | BB6: In Progress
A7: =IFERROR(MATCH($C$2&"|"&(ROW()-4),Tasks!$L$4:$L$403,0)+3,"") -> 6 | B7: =IF($A7="","",IF(INDEX(Tasks!$A:$A,$A7)="","",INDEX(Tasks!$A:$A,$A7))) -> TB-2.1 | C7: =IF($A7="","",IF(ISERROR(FIND(".",INDEX(Tasks!$A:$A,$A7))),""," ")&INDEX(Tasks!$C:$C,$A7)) -> Sensor Calibration (LiDAR-Camera, LiDAR-IMU, Camera-Radar, Intrinsics, Realsense-Zed, Mobile-Infra Extrinsics) | D7: =IF($A7="","",IF(INDEX(Tasks!$D:$D,$A7)="","",INDEX(Tasks!$D:$D,$A7))) -> Sensors & platform owner | E7: =IF($A7="","",IF(INDEX(Tasks!$E:$E,$A7)="","",INDEX(Tasks!$E:$E,$A7))) -> In Progress | F7: =IF($A7="","",IF(INDEX(Tasks!$F:$F,$A7)="","",INDEX(Tasks!$F:$F,$A7))) -> 46195 | G7: =IF($A7="","",IF(INDEX(Tasks!$H:$H,$A7)="","",INDEX(Tasks!$H:$H,$A7))) -> 46206 | BB7: Partially Completed
A8: =IFERROR(MATCH($C$2&"|"&(ROW()-4),Tasks!$L$4:$L$403,0)+3,"") -> 7 | B8: =IF($A8="","",IF(INDEX(Tasks!$A:$A,$A8)="","",INDEX(Tasks!$A:$A,$A8))) -> TB-2.2 | C8: =IF($A8="","",IF(ISERROR(FIND(".",INDEX(Tasks!$A:$A,$A8))),""," ")&INDEX(Tasks!$C:$C,$A8)) -> Calibration: LiDAR - Camera | D8: =IF($A8="","",IF(INDEX(Tasks!$D:$D,$A8)="","",INDEX(Tasks!$D:$D,$A8))) -> Sensors & platform owner | E8: =IF($A8="","",IF(INDEX(Tasks!$E:$E,$A8)="","",INDEX(Tasks!$E:$E,$A8))) | F8: =IF($A8="","",IF(INDEX(Tasks!$F:$F,$A8)="","",INDEX(Tasks!$F:$F,$A8))) | G8: =IF($A8="","",IF(INDEX(Tasks!$H:$H,$A8)="","",INDEX(Tasks!$H:$H,$A8))) | BB8: Blocked
A9: =IFERROR(MATCH($C$2&"|"&(ROW()-4),Tasks!$L$4:$L$403,0)+3,"") -> 8 | B9: =IF($A9="","",IF(INDEX(Tasks!$A:$A,$A9)="","",INDEX(Tasks!$A:$A,$A9))) -> TB-2.3 | C9: =IF($A9="","",IF(ISERROR(FIND(".",INDEX(Tasks!$A:$A,$A9))),""," ")&INDEX(Tasks!$C:$C,$A9)) -> Calibration: LiDAR - IMU | D9: =IF($A9="","",IF(INDEX(Tasks!$D:$D,$A9)="","",INDEX(Tasks!$D:$D,$A9))) -> Sensors & platform owner | E9: =IF($A9="","",IF(INDEX(Tasks!$E:$E,$A9)="","",INDEX(Tasks!$E:$E,$A9))) | F9: =IF($A9="","",IF(INDEX(Tasks!$F:$F,$A9)="","",INDEX(Tasks!$F:$F,$A9))) | G9: =IF($A9="","",IF(INDEX(Tasks!$H:$H,$A9)="","",INDEX(Tasks!$H:$H,$A9))) | BB9: Not Started
A10: =IFERROR(MATCH($C$2&"|"&(ROW()-4),Tasks!$L$4:$L$403,0)+3,"") -> 9 | B10: =IF($A10="","",IF(INDEX(Tasks!$A:$A,$A10)="","",INDEX(Tasks!$A:$A,$A10))) -> TB-2.4 | C10: =IF($A10="","",IF(ISERROR(FIND(".",INDEX(Tasks!$A:$A,$A10))),""," ")&INDEX(Tasks!$C:$C,$A10)) -> Calibration: RealSense - ZED | D10: =IF($A10="","",IF(INDEX(Tasks!$D:$D,$A10)="","",INDEX(Tasks!$D:$D,$A10))) -> Sensors & platform owner | E10: =IF($A10="","",IF(INDEX(Tasks!$E:$E,$A10)="","",INDEX(Tasks!$E:$E,$A10))) | F10: =IF($A10="","",IF(INDEX(Tasks!$F:$F,$A10)="","",INDEX(Tasks!$F:$F,$A10))) | G10: =IF($A10="","",IF(INDEX(Tasks!$H:$H,$A10)="","",INDEX(Tasks!$H:$H,$A10))) | BB10: Milestone
A11: =IFERROR(MATCH($C$2&"|"&(ROW()-4),Tasks!$L$4:$L$403,0)+3,"") -> 10 | B11: =IF($A11="","",IF(INDEX(Tasks!$A:$A,$A11)="","",INDEX(Tasks!$A:$A,$A11))) -> TB-2.5 | C11: =IF($A11="","",IF(ISERROR(FIND(".",INDEX(Tasks!$A:$A,$A11))),""," ")&INDEX(Tasks!$C:$C,$A11)) -> Calibration: ZED - Arducam | D11: =IF($A11="","",IF(INDEX(Tasks!$D:$D,$A11)="","",INDEX(Tasks!$D:$D,$A11))) -> Sensors & platform owner | E11: =IF($A11="","",IF(INDEX(Tasks!$E:$E,$A11)="","",INDEX(Tasks!$E:$E,$A11))) | F11: =IF($A11="","",IF(INDEX(Tasks!$F:$F,$A11)="","",INDEX(Tasks!$F:$F,$A11))) | G11: =IF($A11="","",IF(INDEX(Tasks!$H:$H,$A11)="","",INDEX(Tasks!$H:$H,$A11))) | BB11: Today's week
A12: =IFERROR(MATCH($C$2&"|"&(ROW()-4),Tasks!$L$4:$L$403,0)+3,"") -> 11 | B12: =IF($A12="","",IF(INDEX(Tasks!$A:$A,$A12)="","",INDEX(Tasks!$A:$A,$A12))) -> TB-2.6 | C12: =IF($A12="","",IF(ISERROR(FIND(".",INDEX(Tasks!$A:$A,$A12))),""," ")&INDEX(Tasks!$C:$C,$A12)) -> Calibration: Radars - ZED | D12: =IF($A12="","",IF(INDEX(Tasks!$D:$D,$A12)="","",INDEX(Tasks!$D:$D,$A12))) -> Sensors & platform owner | E12: =IF($A12="","",IF(INDEX(Tasks!$E:$E,$A12)="","",INDEX(Tasks!$E:$E,$A12))) | F12: =IF($A12="","",IF(INDEX(Tasks!$F:$F,$A12)="","",INDEX(Tasks!$F:$F,$A12))) | G12: =IF($A12="","",IF(INDEX(Tasks!$H:$H,$A12)="","",INDEX(Tasks!$H:$H,$A12)))
A13: =IFERROR(MATCH($C$2&"|"&(ROW()-4),Tasks!$L$4:$L$403,0)+3,"") -> 12 | B13: =IF($A13="","",IF(INDEX(Tasks!$A:$A,$A13)="","",INDEX(Tasks!$A:$A,$A13))) -> TB-3 | C13: =IF($A13="","",IF(ISERROR(FIND(".",INDEX(Tasks!$A:$A,$A13))),""," ")&INDEX(Tasks!$C:$C,$A13)) -> Time sync & TF chain | D13: =IF($A13="","",IF(INDEX(Tasks!$D:$D,$A13)="","",INDEX(Tasks!$D:$D,$A13))) -> Sensors & platform owner | E13: =IF($A13="","",IF(INDEX(Tasks!$E:$E,$A13)="","",INDEX(Tasks!$E:$E,$A13))) -> In Progress | F13: =IF($A13="","",IF(INDEX(Tasks!$F:$F,$A13)="","",INDEX(Tasks!$F:$F,$A13))) -> 46202 | G13: =IF($A13="","",IF(INDEX(Tasks!$H:$H,$A13)="","",INDEX(Tasks!$H:$H,$A13))) -> 46206 | BB13: Red End = overdue
A14: =IFERROR(MATCH($C$2&"|"&(ROW()-4),Tasks!$L$4:$L$403,0)+3,"") -> 13 | B14: =IF($A14="","",IF(INDEX(Tasks!$A:$A,$A14)="","",INDEX(Tasks!$A:$A,$A14))) -> TB-4 | C14: =IF($A14="","",IF(ISERROR(FIND(".",INDEX(Tasks!$A:$A,$A14))),""," ")&INDEX(Tasks!$C:$C,$A14)) -> Wi-Fi & comms logging | D14: =IF($A14="","",IF(INDEX(Tasks!$D:$D,$A14)="","",INDEX(Tasks!$D:$D,$A14))) -> Sensors & platform owner | E14: =IF($A14="","",IF(INDEX(Tasks!$E:$E,$A14)="","",INDEX(Tasks!$E:$E,$A14))) -> In Progress | F14: =IF($A14="","",IF(INDEX(Tasks!$F:$F,$A14)="","",INDEX(Tasks!$F:$F,$A14))) -> 46307 | G14: =IF($A14="","",IF(INDEX(Tasks!$H:$H,$A14)="","",INDEX(Tasks!$H:$H,$A14))) -> 46318
A15: =IFERROR(MATCH($C$2&"|"&(ROW()-4),Tasks!$L$4:$L$403,0)+3,"") -> 14 | B15: =IF($A15="","",IF(INDEX(Tasks!$A:$A,$A15)="","",INDEX(Tasks!$A:$A,$A15))) -> TB-5 | C15: =IF($A15="","",IF(ISERROR(FIND(".",INDEX(Tasks!$A:$A,$A15))),""," ")&INDEX(Tasks!$C:$C,$A15)) -> Recording tooling fixes | D15: =IF($A15="","",IF(INDEX(Tasks!$D:$D,$A15)="","",INDEX(Tasks!$D:$D,$A15))) -> Sensors & platform owner | E15: =IF($A15="","",IF(INDEX(Tasks!$E:$E,$A15)="","",INDEX(Tasks!$E:$E,$A15))) -> Not Started | F15: =IF($A15="","",IF(INDEX(Tasks!$F:$F,$A15)="","",INDEX(Tasks!$F:$F,$A15))) -> 46307 | G15: =IF($A15="","",IF(INDEX(Tasks!$H:$H,$A15)="","",INDEX(Tasks!$H:$H,$A15))) -> 46318
A16: =IFERROR(MATCH($C$2&"|"&(ROW()-4),Tasks!$L$4:$L$403,0)+3,"") -> 15 | B16: =IF($A16="","",IF(INDEX(Tasks!$A:$A,$A16)="","",INDEX(Tasks!$A:$A,$A16))) -> G2-DS-1 | C16: =IF($A16="","",IF(ISERROR(FIND(".",INDEX(Tasks!$A:$A,$A16))),""," ")&INDEX(Tasks!$C:$C,$A16)) -> Recording campaign | D16: =IF($A16="","",IF(INDEX(Tasks!$D:$D,$A16)="","",INDEX(Tasks!$D:$D,$A16))) -> SCooP owner | E16: =IF($A16="","",IF(INDEX(Tasks!$E:$E,$A16)="","",INDEX(Tasks!$E:$E,$A16))) -> Partially Completed | F16: =IF($A16="","",IF(INDEX(Tasks!$F:$F,$A16)="","",INDEX(Tasks!$F:$F,$A16))) -> 46314 | G16: =IF($A16="","",IF(INDEX(Tasks!$H:$H,$A16)="","",INDEX(Tasks!$H:$H,$A16))) -> 46353
A17: =IFERROR(MATCH($C$2&"|"&(ROW()-4),Tasks!$L$4:$L$403,0)+3,"") -> 16 | B17: =IF($A17="","",IF(INDEX(Tasks!$A:$A,$A17)="","",INDEX(Tasks!$A:$A,$A17))) -> G2-DS-1.1 | C17: =IF($A17="","",IF(ISERROR(FIND(".",INDEX(Tasks!$A:$A,$A17))),""," ")&INDEX(Tasks!$C:$C,$A17)) -> Indoor Trajectory Sessions | D17: =IF($A17="","",IF(INDEX(Tasks!$D:$D,$A17)="","",INDEX(Tasks!$D:$D,$A17))) -> SCooP owner | E17: =IF($A17="","",IF(INDEX(Tasks!$E:$E,$A17)="","",INDEX(Tasks!$E:$E,$A17))) -> Partially Completed | F17: =IF($A17="","",IF(INDEX(Tasks!$F:$F,$A17)="","",INDEX(Tasks!$F:$F,$A17))) -> 46202 | G17: =IF($A17="","",IF(INDEX(Tasks!$H:$H,$A17)="","",INDEX(Tasks!$H:$H,$A17))) -> 46206
A18: =IFERROR(MATCH($C$2&"|"&(ROW()-4),Tasks!$L$4:$L$403,0)+3,"") -> 17 | B18: =IF($A18="","",IF(INDEX(Tasks!$A:$A,$A18)="","",INDEX(Tasks!$A:$A,$A18))) -> G2-DS-1.2 | C18: =IF($A18="","",IF(ISERROR(FIND(".",INDEX(Tasks!$A:$A,$A18))),""," ")&INDEX(Tasks!$C:$C,$A18)) -> Outdoor Trajectory Sessions | D18: =IF($A18="","",IF(INDEX(Tasks!$D:$D,$A18)="","",INDEX(Tasks!$D:$D,$A18))) -> SCooP owner | E18: =IF($A18="","",IF(INDEX(Tasks!$E:$E,$A18)="","",INDEX(Tasks!$E:$E,$A18))) -> Not Started | F18: =IF($A18="","",IF(INDEX(Tasks!$F:$F,$A18)="","",INDEX(Tasks!$F:$F,$A18))) | G18: =IF($A18="","",IF(INDEX(Tasks!$H:$H,$A18)="","",INDEX(Tasks!$H:$H,$A18)))
A19: =IFERROR(MATCH($C$2&"|"&(ROW()-4),Tasks!$L$4:$L$403,0)+3,"") -> 18 | B19: =IF($A19="","",IF(INDEX(Tasks!$A:$A,$A19)="","",INDEX(Tasks!$A:$A,$A19))) -> G2-DS-1.3 | C19: =IF($A19="","",IF(ISERROR(FIND(".",INDEX(Tasks!$A:$A,$A19))),""," ")&INDEX(Tasks!$C:$C,$A19)) -> Record sites 2 and 3 | D19: =IF($A19="","",IF(INDEX(Tasks!$D:$D,$A19)="","",INDEX(Tasks!$D:$D,$A19))) -> SCooP owner | E19: =IF($A19="","",IF(INDEX(Tasks!$E:$E,$A19)="","",INDEX(Tasks!$E:$E,$A19))) -> Not Started | F19: =IF($A19="","",IF(INDEX(Tasks!$F:$F,$A19)="","",INDEX(Tasks!$F:$F,$A19))) -> 46321 | G19: =IF($A19="","",IF(INDEX(Tasks!$H:$H,$A19)="","",INDEX(Tasks!$H:$H,$A19))) -> 46346
A20: =IFERROR(MATCH($C$2&"|"&(ROW()-4),Tasks!$L$4:$L$403,0)+3,"") -> 19 | B20: =IF($A20="","",IF(INDEX(Tasks!$A:$A,$A20)="","",INDEX(Tasks!$A:$A,$A20))) -> G2-DS-1.4 | C20: =IF($A20="","",IF(ISERROR(FIND(".",INDEX(Tasks!$A:$A,$A20))),""," ")&INDEX(Tasks!$C:$C,$A20)) -> Calibration rosbag | D20: =IF($A20="","",IF(INDEX(Tasks!$D:$D,$A20)="","",INDEX(Tasks!$D:$D,$A20))) -> SCooP owner | E20: =IF($A20="","",IF(INDEX(Tasks!$E:$E,$A20)="","",INDEX(Tasks!$E:$E,$A20))) | F20: =IF($A20="","",IF(INDEX(Tasks!$F:$F,$A20)="","",INDEX(Tasks!$F:$F,$A20))) -> 46314 | G20: =IF($A20="","",IF(INDEX(Tasks!$H:$H,$A20)="","",INDEX(Tasks!$H:$H,$A20))) -> 46318
A21: =IFERROR(MATCH($C$2&"|"&(ROW()-4),Tasks!$L$4:$L$403,0)+3,"") -> 20 | B21: =IF($A21="","",IF(INDEX(Tasks!$A:$A,$A21)="","",INDEX(Tasks!$A:$A,$A21))) -> G2-DS-1.5 | C21: =IF($A21="","",IF(ISERROR(FIND(".",INDEX(Tasks!$A:$A,$A21))),""," ")&INDEX(Tasks!$C:$C,$A21)) -> Short test recordings | D21: =IF($A21="","",IF(INDEX(Tasks!$D:$D,$A21)="","",INDEX(Tasks!$D:$D,$A21))) -> SCooP owner | E21: =IF($A21="","",IF(INDEX(Tasks!$E:$E,$A21)="","",INDEX(Tasks!$E:$E,$A21))) | F21: =IF($A21="","",IF(INDEX(Tasks!$F:$F,$A21)="","",INDEX(Tasks!$F:$F,$A21))) -> 46314 | G21: =IF($A21="","",IF(INDEX(Tasks!$H:$H,$A21)="","",INDEX(Tasks!$H:$H,$A21))) -> 46318
A22: =IFERROR(MATCH($C$2&"|"&(ROW()-4),Tasks!$L$4:$L$403,0)+3,"") -> 21 | B22: =IF($A22="","",IF(INDEX(Tasks!$A:$A,$A22)="","",INDEX(Tasks!$A:$A,$A22))) -> G2-DS-2 | C22: =IF($A22="","",IF(ISERROR(FIND(".",INDEX(Tasks!$A:$A,$A22))),""," ")&INDEX(Tasks!$C:$C,$A22)) -> Per-pass processing | D22: =IF($A22="","",IF(INDEX(Tasks!$D:$D,$A22)="","",INDEX(Tasks!$D:$D,$A22))) -> SCooP owner | E22: =IF($A22="","",IF(INDEX(Tasks!$E:$E,$A22)="","",INDEX(Tasks!$E:$E,$A22))) -> In Progress | F22: =IF($A22="","",IF(INDEX(Tasks!$F:$F,$A22)="","",INDEX(Tasks!$F:$F,$A22))) -> 46307 | G22: =IF($A22="","",IF(INDEX(Tasks!$H:$H,$A22)="","",INDEX(Tasks!$H:$H,$A22))) -> 46374
A23: =IFERROR(MATCH($C$2&"|"&(ROW()-4),Tasks!$L$4:$L$403,0)+3,"") -> 22 | B23: =IF($A23="","",IF(INDEX(Tasks!$A:$A,$A23)="","",INDEX(Tasks!$A:$A,$A23))) -> G2-DS-2.1 | C23: =IF($A23="","",IF(ISERROR(FIND(".",INDEX(Tasks!$A:$A,$A23))),""," ")&INDEX(Tasks!$C:$C,$A23)) -> Merging Sensor Data | D23: =IF($A23="","",IF(INDEX(Tasks!$D:$D,$A23)="","",INDEX(Tasks!$D:$D,$A23))) -> SCooP owner | E23: =IF($A23="","",IF(INDEX(Tasks!$E:$E,$A23)="","",INDEX(Tasks!$E:$E,$A23))) -> In Progress | F23: =IF($A23="","",IF(INDEX(Tasks!$F:$F,$A23)="","",INDEX(Tasks!$F:$F,$A23))) -> 46202 | G23: =IF($A23="","",IF(INDEX(Tasks!$H:$H,$A23)="","",INDEX(Tasks!$H:$H,$A23))) -> 46206
A24: =IFERROR(MATCH($C$2&"|"&(ROW()-4),Tasks!$L$4:$L$403,0)+3,"") -> 23 | B24: =IF($A24="","",IF(INDEX(Tasks!$A:$A,$A24)="","",INDEX(Tasks!$A:$A,$A24))) -> G2-DS-2.2 | C24: =IF($A24="","",IF(ISERROR(FIND(".",INDEX(Tasks!$A:$A,$A24))),""," ")&INDEX(Tasks!$C:$C,$A24)) -> Timestamp Alignment Post-Processing | D24: =IF($A24="","",IF(INDEX(Tasks!$D:$D,$A24)="","",INDEX(Tasks!$D:$D,$A24))) -> SCooP owner | E24: =IF($A24="","",IF(INDEX(Tasks!$E:$E,$A24)="","",INDEX(Tasks!$E:$E,$A24))) -> Not Started | F24: =IF($A24="","",IF(INDEX(Tasks!$F:$F,$A24)="","",INDEX(Tasks!$F:$F,$A24))) -> 46202 | G24: =IF($A24="","",IF(INDEX(Tasks!$H:$H,$A24)="","",INDEX(Tasks!$H:$H,$A24))) -> 46206
A25: =IFERROR(MATCH($C$2&"|"&(ROW()-4),Tasks!$L$4:$L$403,0)+3,"") -> 24 | B25: =IF($A25="","",IF(INDEX(Tasks!$A:$A,$A25)="","",INDEX(Tasks!$A:$A,$A25))) -> G2-DS-3 | C25: =IF($A25="","",IF(ISERROR(FIND(".",INDEX(Tasks!$A:$A,$A25))),""," ")&INDEX(Tasks!$C:$C,$A25)) -> Reference maps & board networks per site | D25: =IF($A25="","",IF(INDEX(Tasks!$D:$D,$A25)="","",INDEX(Tasks!$D:$D,$A25))) -> SCooP owner | E25: =IF($A25="","",IF(INDEX(Tasks!$E:$E,$A25)="","",INDEX(Tasks!$E:$E,$A25))) -> In Progress | F25: =IF($A25="","",IF(INDEX(Tasks!$F:$F,$A25)="","",INDEX(Tasks!$F:$F,$A25))) -> 46307 | G25: =IF($A25="","",IF(INDEX(Tasks!$H:$H,$A25)="","",INDEX(Tasks!$H:$H,$A25))) -> 46360
... A404: =IFERROR(MATCH($C$2&"|"&(ROW()-4),Tasks!$L$4:$L$403,0)+3,"") | B404: =IF($A404="","",IF(INDEX(Tasks!$A:$A,$A404)="","",INDEX(Tasks!$A:$A,$A404))) | C404: =IF($A404="","",IF(ISERROR(FIND(".",INDEX(Tasks!$A:$A,$A404))),""," ")&INDEX(Tasks!$C:$C,$A404)) | D404: =IF($A404="","",IF(INDEX(Tasks!$D:$D,$A404)="","",INDEX(Tasks!$D:$D,$A404))) | E404: =IF($A404="","",IF(INDEX(Tasks!$E:$E,$A404)="","",INDEX(Tasks!$E:$E,$A404))) | F404: =IF($A404="","",IF(INDEX(Tasks!$F:$F,$A404)="","",INDEX(Tasks!$F:$F,$A404))) | G404: =IF($A404="","",IF(INDEX(Tasks!$H:$H,$A404)="","",INDEX(Tasks!$H:$H,$A404)))

Sheet G1 Digital twin
B1: Goal: G1 ED305 live digital twin
B2: Goal: | C2: G1 ED305 live digital twin | E2: =COUNTIFS(Tasks!$B$4:$B$403,$C$2,Tasks!$C$4:$C$403,"?*")&" tasks · "&COUNTIFS(Tasks!$B$4:$B$403,$C$2,Tasks!$C$4:$C$403,"?*",Tasks!$E$4:$E$403,"In Progress")&" in progress · "&COUNTIFS(Tasks!$B$4:$B$403,$C$2,Tasks!$C$4:$C$403,"?*",Tasks!$E$4:$E$403,"Blocked")&" blocked · "&COUNTIFS(Tasks!$B$4:$B$403,$C$2,Tasks!$C$4:$C$403,"?*",Tasks!$H$4:$H$403,"<"&TODAY(),Tasks!$E$4:$E$403,"<>Complete")&" overdue" -> 43 tasks · 1 in progress · 1 blocked · 6 overdue
A4: Tasks row | B4: ID | C4: Task | D4: Assigned to | E4: Status | F4: Start | G4: End | H4: =Gantt!$C$3+7*0 -> 46195 | I4: =Gantt!$C$3+7*1 -> 46202 | J4: =Gantt!$C$3+7*2 -> 46209 | K4: =Gantt!$C$3+7*3 -> 46216 | L4: =Gantt!$C$3+7*4 -> 46223 | M4: =Gantt!$C$3+7*5 -> 46230 | N4: =Gantt!$C$3+7*6 -> 46237 | O4: =Gantt!$C$3+7*7 -> 46244 | P4: =Gantt!$C$3+7*8 -> 46251 | Q4: =Gantt!$C$3+7*9 -> 46258 | R4: =Gantt!$C$3+7*10 -> 46265 | S4: =Gantt!$C$3+7*11 -> 46272 | T4: =Gantt!$C$3+7*12 -> 46279 | U4: =Gantt!$C$3+7*13 -> 46286 | V4: =Gantt!$C$3+7*14 -> 46293 | W4: =Gantt!$C$3+7*15 -> 46300 | X4: =Gantt!$C$3+7*16 -> 46307 | Y4: =Gantt!$C$3+7*17 -> 46314 | Z4: =Gantt!$C$3+7*18 -> 46321 | AA4: =Gantt!$C$3+7*19 -> 46328 | AB4: =Gantt!$C$3+7*20 -> 46335 | AC4: =Gantt!$C$3+7*21 -> 46342 | AD4: =Gantt!$C$3+7*22 -> 46349 | AE4: =Gantt!$C$3+7*23 -> 46356 | AF4: =Gantt!$C$3+7*24 -> 46363 | AG4: =Gantt!$C$3+7*25 -> 46370 | AH4: =Gantt!$C$3+7*26 -> 46377 | AI4: =Gantt!$C$3+7*27 -> 46384 | AJ4: =Gantt!$C$3+7*28 -> 46391 | AK4: =Gantt!$C$3+7*29 -> 46398 | AL4: =Gantt!$C$3+7*30 -> 46405 | AM4: =Gantt!$C$3+7*31 -> 46412 | AN4: =Gantt!$C$3+7*32 -> 46419 | AO4: =Gantt!$C$3+7*33 -> 46426 | AP4: =Gantt!$C$3+7*34 -> 46433 | AQ4: =Gantt!$C$3+7*35 -> 46440 | AR4: =Gantt!$C$3+7*36 -> 46447 | AS4: =Gantt!$C$3+7*37 -> 46454 | AT4: =Gantt!$C$3+7*38 -> 46461 | AU4: =Gantt!$C$3+7*39 -> 46468 | AV4: =Gantt!$C$3+7*40 -> 46475 | AW4: =Gantt!$C$3+7*41 -> 46482 | AX4: =Gantt!$C$3+7*42 -> 46489 | AY4: =Gantt!$C$3+7*43 -> 46496 | BB4: Legend
A5: =IFERROR(MATCH($C$2&"|"&(ROW()-4),Tasks!$K$4:$K$403,0)+3,"") -> 44 | B5: =IF($A5="","",IF(INDEX(Tasks!$A:$A,$A5)="","",INDEX(Tasks!$A:$A,$A5))) -> G1-SP-1 | C5: =IF($A5="","",IF(ISERROR(FIND(".",INDEX(Tasks!$A:$A,$A5))),""," ")&INDEX(Tasks!$C:$C,$A5)) -> Sensor rig & TF tree per robot | D5: =IF($A5="","",IF(INDEX(Tasks!$D:$D,$A5)="","",INDEX(Tasks!$D:$D,$A5))) -> Sensors & platform owner | E5: =IF($A5="","",IF(INDEX(Tasks!$E:$E,$A5)="","",INDEX(Tasks!$E:$E,$A5))) -> Not Started | F5: =IF($A5="","",IF(INDEX(Tasks!$F:$F,$A5)="","",INDEX(Tasks!$F:$F,$A5))) -> 46307 | G5: =IF($A5="","",IF(INDEX(Tasks!$H:$H,$A5)="","",INDEX(Tasks!$H:$H,$A5))) -> 46318 | BB5: Complete
A6: =IFERROR(MATCH($C$2&"|"&(ROW()-4),Tasks!$K$4:$K$403,0)+3,"") -> 45 | B6: =IF($A6="","",IF(INDEX(Tasks!$A:$A,$A6)="","",INDEX(Tasks!$A:$A,$A6))) -> G1-SP-2 | C6: =IF($A6="","",IF(ISERROR(FIND(".",INDEX(Tasks!$A:$A,$A6))),""," ")&INDEX(Tasks!$C:$C,$A6)) -> Odometry: front end + fusion filter | D6: =IF($A6="","",IF(INDEX(Tasks!$D:$D,$A6)="","",INDEX(Tasks!$D:$D,$A6))) -> Sensors & platform owner | E6: =IF($A6="","",IF(INDEX(Tasks!$E:$E,$A6)="","",INDEX(Tasks!$E:$E,$A6))) -> Not Started | F6: =IF($A6="","",IF(INDEX(Tasks!$F:$F,$A6)="","",INDEX(Tasks!$F:$F,$A6))) -> 46314 | G6: =IF($A6="","",IF(INDEX(Tasks!$H:$H,$A6)="","",INDEX(Tasks!$H:$H,$A6))) -> 46339 | BB6: In Progress
A7: =IFERROR(MATCH($C$2&"|"&(ROW()-4),Tasks!$K$4:$K$403,0)+3,"") -> 46 | B7: =IF($A7="","",IF(INDEX(Tasks!$A:$A,$A7)="","",INDEX(Tasks!$A:$A,$A7))) -> G1-SP-3 | C7: =IF($A7="","",IF(ISERROR(FIND(".",INDEX(Tasks!$A:$A,$A7))),""," ")&INDEX(Tasks!$C:$C,$A7)) -> ED305 camera calibration in the room frame | D7: =IF($A7="","",IF(INDEX(Tasks!$D:$D,$A7)="","",INDEX(Tasks!$D:$D,$A7))) -> Sensors & platform owner | E7: =IF($A7="","",IF(INDEX(Tasks!$E:$E,$A7)="","",INDEX(Tasks!$E:$E,$A7))) -> Blocked | F7: =IF($A7="","",IF(INDEX(Tasks!$F:$F,$A7)="","",INDEX(Tasks!$F:$F,$A7))) -> 46307 | G7: =IF($A7="","",IF(INDEX(Tasks!$H:$H,$A7)="","",INDEX(Tasks!$H:$H,$A7))) -> 46318 | BB7: Partially Completed
A8: =IFERROR(MATCH($C$2&"|"&(ROW()-4),Tasks!$K$4:$K$403,0)+3,"") -> 47 | B8: =IF($A8="","",IF(INDEX(Tasks!$A:$A,$A8)="","",INDEX(Tasks!$A:$A,$A8))) -> G1-SP-4 | C8: =IF($A8="","",IF(ISERROR(FIND(".",INDEX(Tasks!$A:$A,$A8))),""," ")&INDEX(Tasks!$C:$C,$A8)) -> ED305 coverage & camera placement | D8: =IF($A8="","",IF(INDEX(Tasks!$D:$D,$A8)="","",INDEX(Tasks!$D:$D,$A8))) -> Sensors & platform owner | E8: =IF($A8="","",IF(INDEX(Tasks!$E:$E,$A8)="","",INDEX(Tasks!$E:$E,$A8))) -> In Progress | F8: =IF($A8="","",IF(INDEX(Tasks!$F:$F,$A8)="","",INDEX(Tasks!$F:$F,$A8))) -> 46321 | G8: =IF($A8="","",IF(INDEX(Tasks!$H:$H,$A8)="","",INDEX(Tasks!$H:$H,$A8))) -> 46339 | BB8: Blocked
A9: =IFERROR(MATCH($C$2&"|"&(ROW()-4),Tasks!$K$4:$K$403,0)+3,"") -> 48 | B9: =IF($A9="","",IF(INDEX(Tasks!$A:$A,$A9)="","",INDEX(Tasks!$A:$A,$A9))) -> G1-SP-5 | C9: =IF($A9="","",IF(ISERROR(FIND(".",INDEX(Tasks!$A:$A,$A9))),""," ")&INDEX(Tasks!$C:$C,$A9)) -> Printed pan-tilt heads | D9: =IF($A9="","",IF(INDEX(Tasks!$D:$D,$A9)="","",INDEX(Tasks!$D:$D,$A9))) -> Sensors & platform owner | E9: =IF($A9="","",IF(INDEX(Tasks!$E:$E,$A9)="","",INDEX(Tasks!$E:$E,$A9))) -> Not Started | F9: =IF($A9="","",IF(INDEX(Tasks!$F:$F,$A9)="","",INDEX(Tasks!$F:$F,$A9))) -> 46314 | G9: =IF($A9="","",IF(INDEX(Tasks!$H:$H,$A9)="","",INDEX(Tasks!$H:$H,$A9))) -> 46332 | BB9: Not Started
A10: =IFERROR(MATCH($C$2&"|"&(ROW()-4),Tasks!$K$4:$K$403,0)+3,"") -> 49 | B10: =IF($A10="","",IF(INDEX(Tasks!$A:$A,$A10)="","",INDEX(Tasks!$A:$A,$A10))) -> G1-SP-6 | C10: =IF($A10="","",IF(ISERROR(FIND(".",INDEX(Tasks!$A:$A,$A10))),""," ")&INDEX(Tasks!$C:$C,$A10)) -> ED305 camera time sync | D10: =IF($A10="","",IF(INDEX(Tasks!$D:$D,$A10)="","",INDEX(Tasks!$D:$D,$A10))) -> Sensors & platform owner | E10: =IF($A10="","",IF(INDEX(Tasks!$E:$E,$A10)="","",INDEX(Tasks!$E:$E,$A10))) -> Not Started | F10: =IF($A10="","",IF(INDEX(Tasks!$F:$F,$A10)="","",INDEX(Tasks!$F:$F,$A10))) -> 46321 | G10: =IF($A10="","",IF(INDEX(Tasks!$H:$H,$A10)="","",INDEX(Tasks!$H:$H,$A10))) -> 46332 | BB10: Milestone
A11: =IFERROR(MATCH($C$2&"|"&(ROW()-4),Tasks!$K$4:$K$403,0)+3,"") -> 50 | B11: =IF($A11="","",IF(INDEX(Tasks!$A:$A,$A11)="","",INDEX(Tasks!$A:$A,$A11))) -> G1-GS-1 | C11: =IF($A11="","",IF(ISERROR(FIND(".",INDEX(Tasks!$A:$A,$A11))),""," ")&INDEX(Tasks!$C:$C,$A11)) -> Metric prior | D11: =IF($A11="","",IF(INDEX(Tasks!$D:$D,$A11)="","",INDEX(Tasks!$D:$D,$A11))) -> GS-SLAM owner | E11: =IF($A11="","",IF(INDEX(Tasks!$E:$E,$A11)="","",INDEX(Tasks!$E:$E,$A11))) -> Not Started | F11: =IF($A11="","",IF(INDEX(Tasks!$F:$F,$A11)="","",INDEX(Tasks!$F:$F,$A11))) -> 46307 | G11: =IF($A11="","",IF(INDEX(Tasks!$H:$H,$A11)="","",INDEX(Tasks!$H:$H,$A11))) -> 46318 | BB11: Today's week
A12: =IFERROR(MATCH($C$2&"|"&(ROW()-4),Tasks!$K$4:$K$403,0)+3,"") -> 51 | B12: =IF($A12="","",IF(INDEX(Tasks!$A:$A,$A12)="","",INDEX(Tasks!$A:$A,$A12))) -> G1-GS-2 | C12: =IF($A12="","",IF(ISERROR(FIND(".",INDEX(Tasks!$A:$A,$A12))),""," ")&INDEX(Tasks!$C:$C,$A12)) -> Tracking + keyframe gate | D12: =IF($A12="","",IF(INDEX(Tasks!$D:$D,$A12)="","",INDEX(Tasks!$D:$D,$A12))) -> GS-SLAM owner | E12: =IF($A12="","",IF(INDEX(Tasks!$E:$E,$A12)="","",INDEX(Tasks!$E:$E,$A12))) -> Not Started | F12: =IF($A12="","",IF(INDEX(Tasks!$F:$F,$A12)="","",INDEX(Tasks!$F:$F,$A12))) -> 46314 | G12: =IF($A12="","",IF(INDEX(Tasks!$H:$H,$A12)="","",INDEX(Tasks!$H:$H,$A12))) -> 46339
A13: =IFERROR(MATCH($C$2&"|"&(ROW()-4),Tasks!$K$4:$K$403,0)+3,"") -> 52 | B13: =IF($A13="","",IF(INDEX(Tasks!$A:$A,$A13)="","",INDEX(Tasks!$A:$A,$A13))) -> G1-GS-3 | C13: =IF($A13="","",IF(ISERROR(FIND(".",INDEX(Tasks!$A:$A,$A13))),""," ")&INDEX(Tasks!$C:$C,$A13)) -> Mapping + loop closure | D13: =IF($A13="","",IF(INDEX(Tasks!$D:$D,$A13)="","",INDEX(Tasks!$D:$D,$A13))) -> GS-SLAM owner | E13: =IF($A13="","",IF(INDEX(Tasks!$E:$E,$A13)="","",INDEX(Tasks!$E:$E,$A13))) -> Not Started | F13: =IF($A13="","",IF(INDEX(Tasks!$F:$F,$A13)="","",INDEX(Tasks!$F:$F,$A13))) -> 46328 | G13: =IF($A13="","",IF(INDEX(Tasks!$H:$H,$A13)="","",INDEX(Tasks!$H:$H,$A13))) -> 46353 | BB13: Red End = overdue
A14: =IFERROR(MATCH($C$2&"|"&(ROW()-4),Tasks!$K$4:$K$403,0)+3,"") -> 53 | B14: =IF($A14="","",IF(INDEX(Tasks!$A:$A,$A14)="","",INDEX(Tasks!$A:$A,$A14))) -> G1-GS-3.1 | C14: =IF($A14="","",IF(ISERROR(FIND(".",INDEX(Tasks!$A:$A,$A14))),""," ")&INDEX(Tasks!$C:$C,$A14)) -> Dynamic-Object Filter (Pre-Registration) | D14: =IF($A14="","",IF(INDEX(Tasks!$D:$D,$A14)="","",INDEX(Tasks!$D:$D,$A14))) -> GS-SLAM owner | E14: =IF($A14="","",IF(INDEX(Tasks!$E:$E,$A14)="","",INDEX(Tasks!$E:$E,$A14))) -> Not Started | F14: =IF($A14="","",IF(INDEX(Tasks!$F:$F,$A14)="","",INDEX(Tasks!$F:$F,$A14))) -> 46202 | G14: =IF($A14="","",IF(INDEX(Tasks!$H:$H,$A14)="","",INDEX(Tasks!$H:$H,$A14))) -> 46206
A15: =IFERROR(MATCH($C$2&"|"&(ROW()-4),Tasks!$K$4:$K$403,0)+3,"") -> 54 | B15: =IF($A15="","",IF(INDEX(Tasks!$A:$A,$A15)="","",INDEX(Tasks!$A:$A,$A15))) -> G1-GS-3.2 | C15: =IF($A15="","",IF(ISERROR(FIND(".",INDEX(Tasks!$A:$A,$A15))),""," ")&INDEX(Tasks!$C:$C,$A15)) -> Static Point Cloud Registration | D15: =IF($A15="","",IF(INDEX(Tasks!$D:$D,$A15)="","",INDEX(Tasks!$D:$D,$A15))) -> GS-SLAM owner | E15: =IF($A15="","",IF(INDEX(Tasks!$E:$E,$A15)="","",INDEX(Tasks!$E:$E,$A15))) -> Not Started | F15: =IF($A15="","",IF(INDEX(Tasks!$F:$F,$A15)="","",INDEX(Tasks!$F:$F,$A15))) -> 46202 | G15: =IF($A15="","",IF(INDEX(Tasks!$H:$H,$A15)="","",INDEX(Tasks!$H:$H,$A15))) -> 46206
A16: =IFERROR(MATCH($C$2&"|"&(ROW()-4),Tasks!$K$4:$K$403,0)+3,"") -> 55 | B16: =IF($A16="","",IF(INDEX(Tasks!$A:$A,$A16)="","",INDEX(Tasks!$A:$A,$A16))) -> G1-GS-4 | C16: =IF($A16="","",IF(ISERROR(FIND(".",INDEX(Tasks!$A:$A,$A16))),""," ")&INDEX(Tasks!$C:$C,$A16)) -> Real-time budget | D16: =IF($A16="","",IF(INDEX(Tasks!$D:$D,$A16)="","",INDEX(Tasks!$D:$D,$A16))) -> GS-SLAM owner | E16: =IF($A16="","",IF(INDEX(Tasks!$E:$E,$A16)="","",INDEX(Tasks!$E:$E,$A16))) -> Not Started | F16: =IF($A16="","",IF(INDEX(Tasks!$F:$F,$A16)="","",INDEX(Tasks!$F:$F,$A16))) -> 46349 | G16: =IF($A16="","",IF(INDEX(Tasks!$H:$H,$A16)="","",INDEX(Tasks!$H:$H,$A16))) -> 46360
A17: =IFERROR(MATCH($C$2&"|"&(ROW()-4),Tasks!$K$4:$K$403,0)+3,"") -> 56 | B17: =IF($A17="","",IF(INDEX(Tasks!$A:$A,$A17)="","",INDEX(Tasks!$A:$A,$A17))) -> G1-GS-5 | C17: =IF($A17="","",IF(ISERROR(FIND(".",INDEX(Tasks!$A:$A,$A17))),""," ")&INDEX(Tasks!$C:$C,$A17)) -> Map fusion (multi-robot) | D17: =IF($A17="","",IF(INDEX(Tasks!$D:$D,$A17)="","",INDEX(Tasks!$D:$D,$A17))) -> GS-SLAM owner | E17: =IF($A17="","",IF(INDEX(Tasks!$E:$E,$A17)="","",INDEX(Tasks!$E:$E,$A17))) -> Not Started | F17: =IF($A17="","",IF(INDEX(Tasks!$F:$F,$A17)="","",INDEX(Tasks!$F:$F,$A17))) -> 46356 | G17: =IF($A17="","",IF(INDEX(Tasks!$H:$H,$A17)="","",INDEX(Tasks!$H:$H,$A17))) -> 46381
A18: =IFERROR(MATCH($C$2&"|"&(ROW()-4),Tasks!$K$4:$K$403,0)+3,"") -> 57 | B18: =IF($A18="","",IF(INDEX(Tasks!$A:$A,$A18)="","",INDEX(Tasks!$A:$A,$A18))) -> G1-GS-6 | C18: =IF($A18="","",IF(ISERROR(FIND(".",INDEX(Tasks!$A:$A,$A18))),""," ")&INDEX(Tasks!$C:$C,$A18)) -> Evaluation | D18: =IF($A18="","",IF(INDEX(Tasks!$D:$D,$A18)="","",INDEX(Tasks!$D:$D,$A18))) -> GS-SLAM owner | E18: =IF($A18="","",IF(INDEX(Tasks!$E:$E,$A18)="","",INDEX(Tasks!$E:$E,$A18))) -> Not Started | F18: =IF($A18="","",IF(INDEX(Tasks!$F:$F,$A18)="","",INDEX(Tasks!$F:$F,$A18))) -> 46377 | G18: =IF($A18="","",IF(INDEX(Tasks!$H:$H,$A18)="","",INDEX(Tasks!$H:$H,$A18))) -> 46388
A19: =IFERROR(MATCH($C$2&"|"&(ROW()-4),Tasks!$K$4:$K$403,0)+3,"") -> 58 | B19: =IF($A19="","",IF(INDEX(Tasks!$A:$A,$A19)="","",INDEX(Tasks!$A:$A,$A19))) -> G1-SD-1 | C19: =IF($A19="","",IF(ISERROR(FIND(".",INDEX(Tasks!$A:$A,$A19))),""," ")&INDEX(Tasks!$C:$C,$A19)) -> Object asset library | D19: =IF($A19="","",IF(INDEX(Tasks!$D:$D,$A19)="","",INDEX(Tasks!$D:$D,$A19))) -> Scene detection owner | E19: =IF($A19="","",IF(INDEX(Tasks!$E:$E,$A19)="","",INDEX(Tasks!$E:$E,$A19))) -> Not Started | F19: =IF($A19="","",IF(INDEX(Tasks!$F:$F,$A19)="","",INDEX(Tasks!$F:$F,$A19))) -> 46307 | G19: =IF($A19="","",IF(INDEX(Tasks!$H:$H,$A19)="","",INDEX(Tasks!$H:$H,$A19))) -> 46325
A20: =IFERROR(MATCH($C$2&"|"&(ROW()-4),Tasks!$K$4:$K$403,0)+3,"") -> 59 | B20: =IF($A20="","",IF(INDEX(Tasks!$A:$A,$A20)="","",INDEX(Tasks!$A:$A,$A20))) -> G1-SD-2 | C20: =IF($A20="","",IF(ISERROR(FIND(".",INDEX(Tasks!$A:$A,$A20))),""," ")&INDEX(Tasks!$C:$C,$A20)) -> Object retrieval from G* | D20: =IF($A20="","",IF(INDEX(Tasks!$D:$D,$A20)="","",INDEX(Tasks!$D:$D,$A20))) -> Scene detection owner | E20: =IF($A20="","",IF(INDEX(Tasks!$E:$E,$A20)="","",INDEX(Tasks!$E:$E,$A20))) -> Not Started | F20: =IF($A20="","",IF(INDEX(Tasks!$F:$F,$A20)="","",INDEX(Tasks!$F:$F,$A20))) -> 46328 | G20: =IF($A20="","",IF(INDEX(Tasks!$H:$H,$A20)="","",INDEX(Tasks!$H:$H,$A20))) -> 46353
A21: =IFERROR(MATCH($C$2&"|"&(ROW()-4),Tasks!$K$4:$K$403,0)+3,"") -> 60 | B21: =IF($A21="","",IF(INDEX(Tasks!$A:$A,$A21)="","",INDEX(Tasks!$A:$A,$A21))) -> G1-SD-2.1 | C21: =IF($A21="","",IF(ISERROR(FIND(".",INDEX(Tasks!$A:$A,$A21))),""," ")&INDEX(Tasks!$C:$C,$A21)) -> Object Detection & Instance Identification (RGB / RGBD / LiDAR / Radar) | D21: =IF($A21="","",IF(INDEX(Tasks!$D:$D,$A21)="","",INDEX(Tasks!$D:$D,$A21))) -> Scene detection owner | E21: =IF($A21="","",IF(INDEX(Tasks!$E:$E,$A21)="","",INDEX(Tasks!$E:$E,$A21))) -> Not Started | F21: =IF($A21="","",IF(INDEX(Tasks!$F:$F,$A21)="","",INDEX(Tasks!$F:$F,$A21))) -> 46209 | G21: =IF($A21="","",IF(INDEX(Tasks!$H:$H,$A21)="","",INDEX(Tasks!$H:$H,$A21))) -> 46220
A22: =IFERROR(MATCH($C$2&"|"&(ROW()-4),Tasks!$K$4:$K$403,0)+3,"") -> 61 | B22: =IF($A22="","",IF(INDEX(Tasks!$A:$A,$A22)="","",INDEX(Tasks!$A:$A,$A22))) -> G1-SD-2.2 | C22: =IF($A22="","",IF(ISERROR(FIND(".",INDEX(Tasks!$A:$A,$A22))),""," ")&INDEX(Tasks!$C:$C,$A22)) -> Radar + Panoptic Fusion Tracking | D22: =IF($A22="","",IF(INDEX(Tasks!$D:$D,$A22)="","",INDEX(Tasks!$D:$D,$A22))) -> Scene detection owner | E22: =IF($A22="","",IF(INDEX(Tasks!$E:$E,$A22)="","",INDEX(Tasks!$E:$E,$A22))) -> Not Started | F22: =IF($A22="","",IF(INDEX(Tasks!$F:$F,$A22)="","",INDEX(Tasks!$F:$F,$A22))) -> 46209 | G22: =IF($A22="","",IF(INDEX(Tasks!$H:$H,$A22)="","",INDEX(Tasks!$H:$H,$A22))) -> 46220
A23: =IFERROR(MATCH($C$2&"|"&(ROW()-4),Tasks!$K$4:$K$403,0)+3,"") -> 62 | B23: =IF($A23="","",IF(INDEX(Tasks!$A:$A,$A23)="","",INDEX(Tasks!$A:$A,$A23))) -> G1-SD-3 | C23: =IF($A23="","",IF(ISERROR(FIND(".",INDEX(Tasks!$A:$A,$A23))),""," ")&INDEX(Tasks!$C:$C,$A23)) -> Decomposition: segments & materials | D23: =IF($A23="","",IF(INDEX(Tasks!$D:$D,$A23)="","",INDEX(Tasks!$D:$D,$A23))) -> Scene detection owner | E23: =IF($A23="","",IF(INDEX(Tasks!$E:$E,$A23)="","",INDEX(Tasks!$E:$E,$A23))) -> Not Started | F23: =IF($A23="","",IF(INDEX(Tasks!$F:$F,$A23)="","",INDEX(Tasks!$F:$F,$A23))) -> 46335 | G23: =IF($A23="","",IF(INDEX(Tasks!$H:$H,$A23)="","",INDEX(Tasks!$H:$H,$A23))) -> 46360
A24: =IFERROR(MATCH($C$2&"|"&(ROW()-4),Tasks!$K$4:$K$403,0)+3,"") -> 63 | B24: =IF($A24="","",IF(INDEX(Tasks!$A:$A,$A24)="","",INDEX(Tasks!$A:$A,$A24))) -> G1-SD-4 | C24: =IF($A24="","",IF(ISERROR(FIND(".",INDEX(Tasks!$A:$A,$A24))),""," ")&INDEX(Tasks!$C:$C,$A24)) -> Change detection | D24: =IF($A24="","",IF(INDEX(Tasks!$D:$D,$A24)="","",INDEX(Tasks!$D:$D,$A24))) -> Scene detection owner | E24: =IF($A24="","",IF(INDEX(Tasks!$E:$E,$A24)="","",INDEX(Tasks!$E:$E,$A24))) -> Not Started | F24: =IF($A24="","",IF(INDEX(Tasks!$F:$F,$A24)="","",INDEX(Tasks!$F:$F,$A24))) -> 46356 | G24: =IF($A24="","",IF(INDEX(Tasks!$H:$H,$A24)="","",INDEX(Tasks!$H:$H,$A24))) -> 46381
A25: =IFERROR(MATCH($C$2&"|"&(ROW()-4),Tasks!$K$4:$K$403,0)+3,"") -> 64 | B25: =IF($A25="","",IF(INDEX(Tasks!$A:$A,$A25)="","",INDEX(Tasks!$A:$A,$A25))) -> G1-SD-4.1 | C25: =IF($A25="","",IF(ISERROR(FIND(".",INDEX(Tasks!$A:$A,$A25))),""," ")&INDEX(Tasks!$C:$C,$A25)) -> Change Detection (Object Moved / Appeared / Disappeared) | D25: =IF($A25="","",IF(INDEX(Tasks!$D:$D,$A25)="","",INDEX(Tasks!$D:$D,$A25))) -> Scene detection owner | E25: =IF($A25="","",IF(INDEX(Tasks!$E:$E,$A25)="","",INDEX(Tasks!$E:$E,$A25))) -> Not Started | F25: =IF($A25="","",IF(INDEX(Tasks!$F:$F,$A25)="","",INDEX(Tasks!$F:$F,$A25))) -> 46223 | G25: =IF($A25="","",IF(INDEX(Tasks!$H:$H,$A25)="","",INDEX(Tasks!$H:$H,$A25))) -> 46227
... A124: =IFERROR(MATCH($C$2&"|"&(ROW()-4),Tasks!$K$4:$K$403,0)+3,"") | B124: =IF($A124="","",IF(INDEX(Tasks!$A:$A,$A124)="","",INDEX(Tasks!$A:$A,$A124))) | C124: =IF($A124="","",IF(ISERROR(FIND(".",INDEX(Tasks!$A:$A,$A124))),""," ")&INDEX(Tasks!$C:$C,$A124)) | D124: =IF($A124="","",IF(INDEX(Tasks!$D:$D,$A124)="","",INDEX(Tasks!$D:$D,$A124))) | E124: =IF($A124="","",IF(INDEX(Tasks!$E:$E,$A124)="","",INDEX(Tasks!$E:$E,$A124))) | F124: =IF($A124="","",IF(INDEX(Tasks!$F:$F,$A124)="","",INDEX(Tasks!$F:$F,$A124))) | G124: =IF($A124="","",IF(INDEX(Tasks!$H:$H,$A124)="","",INDEX(Tasks!$H:$H,$A124)))

Sheet G2 SCooP
B1: Goal: G2 SCooP dataset & paper
B2: Goal: | C2: G2 SCooP dataset & paper | E2: =COUNTIFS(Tasks!$B$4:$B$403,$C$2,Tasks!$C$4:$C$403,"?*")&" tasks · "&COUNTIFS(Tasks!$B$4:$B$403,$C$2,Tasks!$C$4:$C$403,"?*",Tasks!$E$4:$E$403,"In Progress")&" in progress · "&COUNTIFS(Tasks!$B$4:$B$403,$C$2,Tasks!$C$4:$C$403,"?*",Tasks!$E$4:$E$403,"Blocked")&" blocked · "&COUNTIFS(Tasks!$B$4:$B$403,$C$2,Tasks!$C$4:$C$403,"?*",Tasks!$H$4:$H$403,"<"&TODAY(),Tasks!$E$4:$E$403,"<>Complete")&" overdue" -> 29 tasks · 4 in progress · 0 blocked · 5 overdue
A4: Tasks row | B4: ID | C4: Task | D4: Assigned to | E4: Status | F4: Start | G4: End | H4: =Gantt!$C$3+7*0 -> 46195 | I4: =Gantt!$C$3+7*1 -> 46202 | J4: =Gantt!$C$3+7*2 -> 46209 | K4: =Gantt!$C$3+7*3 -> 46216 | L4: =Gantt!$C$3+7*4 -> 46223 | M4: =Gantt!$C$3+7*5 -> 46230 | N4: =Gantt!$C$3+7*6 -> 46237 | O4: =Gantt!$C$3+7*7 -> 46244 | P4: =Gantt!$C$3+7*8 -> 46251 | Q4: =Gantt!$C$3+7*9 -> 46258 | R4: =Gantt!$C$3+7*10 -> 46265 | S4: =Gantt!$C$3+7*11 -> 46272 | T4: =Gantt!$C$3+7*12 -> 46279 | U4: =Gantt!$C$3+7*13 -> 46286 | V4: =Gantt!$C$3+7*14 -> 46293 | W4: =Gantt!$C$3+7*15 -> 46300 | X4: =Gantt!$C$3+7*16 -> 46307 | Y4: =Gantt!$C$3+7*17 -> 46314 | Z4: =Gantt!$C$3+7*18 -> 46321 | AA4: =Gantt!$C$3+7*19 -> 46328 | AB4: =Gantt!$C$3+7*20 -> 46335 | AC4: =Gantt!$C$3+7*21 -> 46342 | AD4: =Gantt!$C$3+7*22 -> 46349 | AE4: =Gantt!$C$3+7*23 -> 46356 | AF4: =Gantt!$C$3+7*24 -> 46363 | AG4: =Gantt!$C$3+7*25 -> 46370 | AH4: =Gantt!$C$3+7*26 -> 46377 | AI4: =Gantt!$C$3+7*27 -> 46384 | AJ4: =Gantt!$C$3+7*28 -> 46391 | AK4: =Gantt!$C$3+7*29 -> 46398 | AL4: =Gantt!$C$3+7*30 -> 46405 | AM4: =Gantt!$C$3+7*31 -> 46412 | AN4: =Gantt!$C$3+7*32 -> 46419 | AO4: =Gantt!$C$3+7*33 -> 46426 | AP4: =Gantt!$C$3+7*34 -> 46433 | AQ4: =Gantt!$C$3+7*35 -> 46440 | AR4: =Gantt!$C$3+7*36 -> 46447 | AS4: =Gantt!$C$3+7*37 -> 46454 | AT4: =Gantt!$C$3+7*38 -> 46461 | AU4: =Gantt!$C$3+7*39 -> 46468 | AV4: =Gantt!$C$3+7*40 -> 46475 | AW4: =Gantt!$C$3+7*41 -> 46482 | AX4: =Gantt!$C$3+7*42 -> 46489 | AY4: =Gantt!$C$3+7*43 -> 46496 | BB4: Legend
A5: =IFERROR(MATCH($C$2&"|"&(ROW()-4),Tasks!$K$4:$K$403,0)+3,"") -> 15 | B5: =IF($A5="","",IF(INDEX(Tasks!$A:$A,$A5)="","",INDEX(Tasks!$A:$A,$A5))) -> G2-DS-1 | C5: =IF($A5="","",IF(ISERROR(FIND(".",INDEX(Tasks!$A:$A,$A5))),""," ")&INDEX(Tasks!$C:$C,$A5)) -> Recording campaign | D5: =IF($A5="","",IF(INDEX(Tasks!$D:$D,$A5)="","",INDEX(Tasks!$D:$D,$A5))) -> SCooP owner | E5: =IF($A5="","",IF(INDEX(Tasks!$E:$E,$A5)="","",INDEX(Tasks!$E:$E,$A5))) -> Partially Completed | F5: =IF($A5="","",IF(INDEX(Tasks!$F:$F,$A5)="","",INDEX(Tasks!$F:$F,$A5))) -> 46314 | G5: =IF($A5="","",IF(INDEX(Tasks!$H:$H,$A5)="","",INDEX(Tasks!$H:$H,$A5))) -> 46353 | BB5: Complete
A6: =IFERROR(MATCH($C$2&"|"&(ROW()-4),Tasks!$K$4:$K$403,0)+3,"") -> 16 | B6: =IF($A6="","",IF(INDEX(Tasks!$A:$A,$A6)="","",INDEX(Tasks!$A:$A,$A6))) -> G2-DS-1.1 | C6: =IF($A6="","",IF(ISERROR(FIND(".",INDEX(Tasks!$A:$A,$A6))),""," ")&INDEX(Tasks!$C:$C,$A6)) -> Indoor Trajectory Sessions | D6: =IF($A6="","",IF(INDEX(Tasks!$D:$D,$A6)="","",INDEX(Tasks!$D:$D,$A6))) -> SCooP owner | E6: =IF($A6="","",IF(INDEX(Tasks!$E:$E,$A6)="","",INDEX(Tasks!$E:$E,$A6))) -> Partially Completed | F6: =IF($A6="","",IF(INDEX(Tasks!$F:$F,$A6)="","",INDEX(Tasks!$F:$F,$A6))) -> 46202 | G6: =IF($A6="","",IF(INDEX(Tasks!$H:$H,$A6)="","",INDEX(Tasks!$H:$H,$A6))) -> 46206 | BB6: In Progress
A7: =IFERROR(MATCH($C$2&"|"&(ROW()-4),Tasks!$K$4:$K$403,0)+3,"") -> 17 | B7: =IF($A7="","",IF(INDEX(Tasks!$A:$A,$A7)="","",INDEX(Tasks!$A:$A,$A7))) -> G2-DS-1.2 | C7: =IF($A7="","",IF(ISERROR(FIND(".",INDEX(Tasks!$A:$A,$A7))),""," ")&INDEX(Tasks!$C:$C,$A7)) -> Outdoor Trajectory Sessions | D7: =IF($A7="","",IF(INDEX(Tasks!$D:$D,$A7)="","",INDEX(Tasks!$D:$D,$A7))) -> SCooP owner | E7: =IF($A7="","",IF(INDEX(Tasks!$E:$E,$A7)="","",INDEX(Tasks!$E:$E,$A7))) -> Not Started | F7: =IF($A7="","",IF(INDEX(Tasks!$F:$F,$A7)="","",INDEX(Tasks!$F:$F,$A7))) | G7: =IF($A7="","",IF(INDEX(Tasks!$H:$H,$A7)="","",INDEX(Tasks!$H:$H,$A7))) | BB7: Partially Completed
A8: =IFERROR(MATCH($C$2&"|"&(ROW()-4),Tasks!$K$4:$K$403,0)+3,"") -> 18 | B8: =IF($A8="","",IF(INDEX(Tasks!$A:$A,$A8)="","",INDEX(Tasks!$A:$A,$A8))) -> G2-DS-1.3 | C8: =IF($A8="","",IF(ISERROR(FIND(".",INDEX(Tasks!$A:$A,$A8))),""," ")&INDEX(Tasks!$C:$C,$A8)) -> Record sites 2 and 3 | D8: =IF($A8="","",IF(INDEX(Tasks!$D:$D,$A8)="","",INDEX(Tasks!$D:$D,$A8))) -> SCooP owner | E8: =IF($A8="","",IF(INDEX(Tasks!$E:$E,$A8)="","",INDEX(Tasks!$E:$E,$A8))) -> Not Started | F8: =IF($A8="","",IF(INDEX(Tasks!$F:$F,$A8)="","",INDEX(Tasks!$F:$F,$A8))) -> 46321 | G8: =IF($A8="","",IF(INDEX(Tasks!$H:$H,$A8)="","",INDEX(Tasks!$H:$H,$A8))) -> 46346 | BB8: Blocked
A9: =IFERROR(MATCH($C$2&"|"&(ROW()-4),Tasks!$K$4:$K$403,0)+3,"") -> 19 | B9: =IF($A9="","",IF(INDEX(Tasks!$A:$A,$A9)="","",INDEX(Tasks!$A:$A,$A9))) -> G2-DS-1.4 | C9: =IF($A9="","",IF(ISERROR(FIND(".",INDEX(Tasks!$A:$A,$A9))),""," ")&INDEX(Tasks!$C:$C,$A9)) -> Calibration rosbag | D9: =IF($A9="","",IF(INDEX(Tasks!$D:$D,$A9)="","",INDEX(Tasks!$D:$D,$A9))) -> SCooP owner | E9: =IF($A9="","",IF(INDEX(Tasks!$E:$E,$A9)="","",INDEX(Tasks!$E:$E,$A9))) | F9: =IF($A9="","",IF(INDEX(Tasks!$F:$F,$A9)="","",INDEX(Tasks!$F:$F,$A9))) -> 46314 | G9: =IF($A9="","",IF(INDEX(Tasks!$H:$H,$A9)="","",INDEX(Tasks!$H:$H,$A9))) -> 46318 | BB9: Not Started
A10: =IFERROR(MATCH($C$2&"|"&(ROW()-4),Tasks!$K$4:$K$403,0)+3,"") -> 20 | B10: =IF($A10="","",IF(INDEX(Tasks!$A:$A,$A10)="","",INDEX(Tasks!$A:$A,$A10))) -> G2-DS-1.5 | C10: =IF($A10="","",IF(ISERROR(FIND(".",INDEX(Tasks!$A:$A,$A10))),""," ")&INDEX(Tasks!$C:$C,$A10)) -> Short test recordings | D10: =IF($A10="","",IF(INDEX(Tasks!$D:$D,$A10)="","",INDEX(Tasks!$D:$D,$A10))) -> SCooP owner | E10: =IF($A10="","",IF(INDEX(Tasks!$E:$E,$A10)="","",INDEX(Tasks!$E:$E,$A10))) | F10: =IF($A10="","",IF(INDEX(Tasks!$F:$F,$A10)="","",INDEX(Tasks!$F:$F,$A10))) -> 46314 | G10: =IF($A10="","",IF(INDEX(Tasks!$H:$H,$A10)="","",INDEX(Tasks!$H:$H,$A10))) -> 46318 | BB10: Milestone
A11: =IFERROR(MATCH($C$2&"|"&(ROW()-4),Tasks!$K$4:$K$403,0)+3,"") -> 21 | B11: =IF($A11="","",IF(INDEX(Tasks!$A:$A,$A11)="","",INDEX(Tasks!$A:$A,$A11))) -> G2-DS-2 | C11: =IF($A11="","",IF(ISERROR(FIND(".",INDEX(Tasks!$A:$A,$A11))),""," ")&INDEX(Tasks!$C:$C,$A11)) -> Per-pass processing | D11: =IF($A11="","",IF(INDEX(Tasks!$D:$D,$A11)="","",INDEX(Tasks!$D:$D,$A11))) -> SCooP owner | E11: =IF($A11="","",IF(INDEX(Tasks!$E:$E,$A11)="","",INDEX(Tasks!$E:$E,$A11))) -> In Progress | F11: =IF($A11="","",IF(INDEX(Tasks!$F:$F,$A11)="","",INDEX(Tasks!$F:$F,$A11))) -> 46307 | G11: =IF($A11="","",IF(INDEX(Tasks!$H:$H,$A11)="","",INDEX(Tasks!$H:$H,$A11))) -> 46374 | BB11: Today's week
A12: =IFERROR(MATCH($C$2&"|"&(ROW()-4),Tasks!$K$4:$K$403,0)+3,"") -> 22 | B12: =IF($A12="","",IF(INDEX(Tasks!$A:$A,$A12)="","",INDEX(Tasks!$A:$A,$A12))) -> G2-DS-2.1 | C12: =IF($A12="","",IF(ISERROR(FIND(".",INDEX(Tasks!$A:$A,$A12))),""," ")&INDEX(Tasks!$C:$C,$A12)) -> Merging Sensor Data | D12: =IF($A12="","",IF(INDEX(Tasks!$D:$D,$A12)="","",INDEX(Tasks!$D:$D,$A12))) -> SCooP owner | E12: =IF($A12="","",IF(INDEX(Tasks!$E:$E,$A12)="","",INDEX(Tasks!$E:$E,$A12))) -> In Progress | F12: =IF($A12="","",IF(INDEX(Tasks!$F:$F,$A12)="","",INDEX(Tasks!$F:$F,$A12))) -> 46202 | G12: =IF($A12="","",IF(INDEX(Tasks!$H:$H,$A12)="","",INDEX(Tasks!$H:$H,$A12))) -> 46206
A13: =IFERROR(MATCH($C$2&"|"&(ROW()-4),Tasks!$K$4:$K$403,0)+3,"") -> 23 | B13: =IF($A13="","",IF(INDEX(Tasks!$A:$A,$A13)="","",INDEX(Tasks!$A:$A,$A13))) -> G2-DS-2.2 | C13: =IF($A13="","",IF(ISERROR(FIND(".",INDEX(Tasks!$A:$A,$A13))),""," ")&INDEX(Tasks!$C:$C,$A13)) -> Timestamp Alignment Post-Processing | D13: =IF($A13="","",IF(INDEX(Tasks!$D:$D,$A13)="","",INDEX(Tasks!$D:$D,$A13))) -> SCooP owner | E13: =IF($A13="","",IF(INDEX(Tasks!$E:$E,$A13)="","",INDEX(Tasks!$E:$E,$A13))) -> Not Started | F13: =IF($A13="","",IF(INDEX(Tasks!$F:$F,$A13)="","",INDEX(Tasks!$F:$F,$A13))) -> 46202 | G13: =IF($A13="","",IF(INDEX(Tasks!$H:$H,$A13)="","",INDEX(Tasks!$H:$H,$A13))) -> 46206 | BB13: Red End = overdue
A14: =IFERROR(MATCH($C$2&"|"&(ROW()-4),Tasks!$K$4:$K$403,0)+3,"") -> 24 | B14: =IF($A14="","",IF(INDEX(Tasks!$A:$A,$A14)="","",INDEX(Tasks!$A:$A,$A14))) -> G2-DS-3 | C14: =IF($A14="","",IF(ISERROR(FIND(".",INDEX(Tasks!$A:$A,$A14))),""," ")&INDEX(Tasks!$C:$C,$A14)) -> Reference maps & board networks per site | D14: =IF($A14="","",IF(INDEX(Tasks!$D:$D,$A14)="","",INDEX(Tasks!$D:$D,$A14))) -> SCooP owner | E14: =IF($A14="","",IF(INDEX(Tasks!$E:$E,$A14)="","",INDEX(Tasks!$E:$E,$A14))) -> In Progress | F14: =IF($A14="","",IF(INDEX(Tasks!$F:$F,$A14)="","",INDEX(Tasks!$F:$F,$A14))) -> 46307 | G14: =IF($A14="","",IF(INDEX(Tasks!$H:$H,$A14)="","",INDEX(Tasks!$H:$H,$A14))) -> 46360
A15: =IFERROR(MATCH($C$2&"|"&(ROW()-4),Tasks!$K$4:$K$403,0)+3,"") -> 25 | B15: =IF($A15="","",IF(INDEX(Tasks!$A:$A,$A15)="","",INDEX(Tasks!$A:$A,$A15))) -> G2-DS-3.1 | C15: =IF($A15="","",IF(ISERROR(FIND(".",INDEX(Tasks!$A:$A,$A15))),""," ")&INDEX(Tasks!$C:$C,$A15)) -> Localization and Mapping | D15: =IF($A15="","",IF(INDEX(Tasks!$D:$D,$A15)="","",INDEX(Tasks!$D:$D,$A15))) -> SCooP owner | E15: =IF($A15="","",IF(INDEX(Tasks!$E:$E,$A15)="","",INDEX(Tasks!$E:$E,$A15))) -> Not Started | F15: =IF($A15="","",IF(INDEX(Tasks!$F:$F,$A15)="","",INDEX(Tasks!$F:$F,$A15))) -> 46202 | G15: =IF($A15="","",IF(INDEX(Tasks!$H:$H,$A15)="","",INDEX(Tasks!$H:$H,$A15))) -> 46206
A16: =IFERROR(MATCH($C$2&"|"&(ROW()-4),Tasks!$K$4:$K$403,0)+3,"") -> 26 | B16: =IF($A16="","",IF(INDEX(Tasks!$A:$A,$A16)="","",INDEX(Tasks!$A:$A,$A16))) -> G2-DS-3.2 | C16: =IF($A16="","",IF(ISERROR(FIND(".",INDEX(Tasks!$A:$A,$A16))),""," ")&INDEX(Tasks!$C:$C,$A16)) -> Mesh Conversion | D16: =IF($A16="","",IF(INDEX(Tasks!$D:$D,$A16)="","",INDEX(Tasks!$D:$D,$A16))) -> SCooP owner | E16: =IF($A16="","",IF(INDEX(Tasks!$E:$E,$A16)="","",INDEX(Tasks!$E:$E,$A16))) -> Not Started | F16: =IF($A16="","",IF(INDEX(Tasks!$F:$F,$A16)="","",INDEX(Tasks!$F:$F,$A16))) -> 46209 | G16: =IF($A16="","",IF(INDEX(Tasks!$H:$H,$A16)="","",INDEX(Tasks!$H:$H,$A16))) -> 46220
A17: =IFERROR(MATCH($C$2&"|"&(ROW()-4),Tasks!$K$4:$K$403,0)+3,"") -> 27 | B17: =IF($A17="","",IF(INDEX(Tasks!$A:$A,$A17)="","",INDEX(Tasks!$A:$A,$A17))) -> G2-DS-4 | C17: =IF($A17="","",IF(ISERROR(FIND(".",INDEX(Tasks!$A:$A,$A17))),""," ")&INDEX(Tasks!$C:$C,$A17)) -> Reference poses (map stages 03-10) | D17: =IF($A17="","",IF(INDEX(Tasks!$D:$D,$A17)="","",INDEX(Tasks!$D:$D,$A17))) -> SCooP owner | E17: =IF($A17="","",IF(INDEX(Tasks!$E:$E,$A17)="","",INDEX(Tasks!$E:$E,$A17))) -> In Progress | F17: =IF($A17="","",IF(INDEX(Tasks!$F:$F,$A17)="","",INDEX(Tasks!$F:$F,$A17))) -> 46307 | G17: =IF($A17="","",IF(INDEX(Tasks!$H:$H,$A17)="","",INDEX(Tasks!$H:$H,$A17))) -> 46346
A18: =IFERROR(MATCH($C$2&"|"&(ROW()-4),Tasks!$K$4:$K$403,0)+3,"") -> 28 | B18: =IF($A18="","",IF(INDEX(Tasks!$A:$A,$A18)="","",INDEX(Tasks!$A:$A,$A18))) -> G2-DS-5 | C18: =IF($A18="","",IF(ISERROR(FIND(".",INDEX(Tasks!$A:$A,$A18))),""," ")&INDEX(Tasks!$C:$C,$A18)) -> Ground-truth validation | D18: =IF($A18="","",IF(INDEX(Tasks!$D:$D,$A18)="","",INDEX(Tasks!$D:$D,$A18))) -> SCooP owner | E18: =IF($A18="","",IF(INDEX(Tasks!$E:$E,$A18)="","",INDEX(Tasks!$E:$E,$A18))) -> Not Started | F18: =IF($A18="","",IF(INDEX(Tasks!$F:$F,$A18)="","",INDEX(Tasks!$F:$F,$A18))) -> 46342 | G18: =IF($A18="","",IF(INDEX(Tasks!$H:$H,$A18)="","",INDEX(Tasks!$H:$H,$A18))) -> 46360
A19: =IFERROR(MATCH($C$2&"|"&(ROW()-4),Tasks!$K$4:$K$403,0)+3,"") -> 29 | B19: =IF($A19="","",IF(INDEX(Tasks!$A:$A,$A19)="","",INDEX(Tasks!$A:$A,$A19))) -> G2-DS-6 | C19: =IF($A19="","",IF(ISERROR(FIND(".",INDEX(Tasks!$A:$A,$A19))),""," ")&INDEX(Tasks!$C:$C,$A19)) -> Annotations | D19: =IF($A19="","",IF(INDEX(Tasks!$D:$D,$A19)="","",INDEX(Tasks!$D:$D,$A19))) -> SCooP owner | E19: =IF($A19="","",IF(INDEX(Tasks!$E:$E,$A19)="","",INDEX(Tasks!$E:$E,$A19))) -> Not Started | F19: =IF($A19="","",IF(INDEX(Tasks!$F:$F,$A19)="","",INDEX(Tasks!$F:$F,$A19))) -> 46335 | G19: =IF($A19="","",IF(INDEX(Tasks!$H:$H,$A19)="","",INDEX(Tasks!$H:$H,$A19))) -> 46381
A20: =IFERROR(MATCH($C$2&"|"&(ROW()-4),Tasks!$K$4:$K$403,0)+3,"") -> 30 | B20: =IF($A20="","",IF(INDEX(Tasks!$A:$A,$A20)="","",INDEX(Tasks!$A:$A,$A20))) -> G2-DS-6.1 | C20: =IF($A20="","",IF(ISERROR(FIND(".",INDEX(Tasks!$A:$A,$A20))),""," ")&INDEX(Tasks!$C:$C,$A20)) -> Label QA (Coverage & Class Balance) | D20: =IF($A20="","",IF(INDEX(Tasks!$D:$D,$A20)="","",INDEX(Tasks!$D:$D,$A20))) -> SCooP owner | E20: =IF($A20="","",IF(INDEX(Tasks!$E:$E,$A20)="","",INDEX(Tasks!$E:$E,$A20))) -> Not Started | F20: =IF($A20="","",IF(INDEX(Tasks!$F:$F,$A20)="","",INDEX(Tasks!$F:$F,$A20))) | G20: =IF($A20="","",IF(INDEX(Tasks!$H:$H,$A20)="","",INDEX(Tasks!$H:$H,$A20)))
A21: =IFERROR(MATCH($C$2&"|"&(ROW()-4),Tasks!$K$4:$K$403,0)+3,"") -> 31 | B21: =IF($A21="","",IF(INDEX(Tasks!$A:$A,$A21)="","",INDEX(Tasks!$A:$A,$A21))) -> G2-DS-7 | C21: =IF($A21="","",IF(ISERROR(FIND(".",INDEX(Tasks!$A:$A,$A21))),""," ")&INDEX(Tasks!$C:$C,$A21)) -> Collaboration geometry & comm ground truth | D21: =IF($A21="","",IF(INDEX(Tasks!$D:$D,$A21)="","",INDEX(Tasks!$D:$D,$A21))) -> SCooP owner | E21: =IF($A21="","",IF(INDEX(Tasks!$E:$E,$A21)="","",INDEX(Tasks!$E:$E,$A21))) -> Not Started | F21: =IF($A21="","",IF(INDEX(Tasks!$F:$F,$A21)="","",INDEX(Tasks!$F:$F,$A21))) -> 46349 | G21: =IF($A21="","",IF(INDEX(Tasks!$H:$H,$A21)="","",INDEX(Tasks!$H:$H,$A21))) -> 46381
A22: =IFERROR(MATCH($C$2&"|"&(ROW()-4),Tasks!$K$4:$K$403,0)+3,"") -> 32 | B22: =IF($A22="","",IF(INDEX(Tasks!$A:$A,$A22)="","",INDEX(Tasks!$A:$A,$A22))) -> G2-DS-8 | C22: =IF($A22="","",IF(ISERROR(FIND(".",INDEX(Tasks!$A:$A,$A22))),""," ")&INDEX(Tasks!$C:$C,$A22)) -> Release | D22: =IF($A22="","",IF(INDEX(Tasks!$D:$D,$A22)="","",INDEX(Tasks!$D:$D,$A22))) -> SCooP owner | E22: =IF($A22="","",IF(INDEX(Tasks!$E:$E,$A22)="","",INDEX(Tasks!$E:$E,$A22))) -> Not Started | F22: =IF($A22="","",IF(INDEX(Tasks!$F:$F,$A22)="","",INDEX(Tasks!$F:$F,$A22))) -> 46384 | G22: =IF($A22="","",IF(INDEX(Tasks!$H:$H,$A22)="","",INDEX(Tasks!$H:$H,$A22))) -> 46416
A23: =IFERROR(MATCH($C$2&"|"&(ROW()-4),Tasks!$K$4:$K$403,0)+3,"") -> 33 | B23: =IF($A23="","",IF(INDEX(Tasks!$A:$A,$A23)="","",INDEX(Tasks!$A:$A,$A23))) -> G2-DS-8.1 | C23: =IF($A23="","",IF(ISERROR(FIND(".",INDEX(Tasks!$A:$A,$A23))),""," ")&INDEX(Tasks!$C:$C,$A23)) -> Dataset Packaging & Documentation | D23: =IF($A23="","",IF(INDEX(Tasks!$D:$D,$A23)="","",INDEX(Tasks!$D:$D,$A23))) -> SCooP owner | E23: =IF($A23="","",IF(INDEX(Tasks!$E:$E,$A23)="","",INDEX(Tasks!$E:$E,$A23))) -> Not Started | F23: =IF($A23="","",IF(INDEX(Tasks!$F:$F,$A23)="","",INDEX(Tasks!$F:$F,$A23))) | G23: =IF($A23="","",IF(INDEX(Tasks!$H:$H,$A23)="","",INDEX(Tasks!$H:$H,$A23)))
A24: =IFERROR(MATCH($C$2&"|"&(ROW()-4),Tasks!$K$4:$K$403,0)+3,"") -> 34 | B24: =IF($A24="","",IF(INDEX(Tasks!$A:$A,$A24)="","",INDEX(Tasks!$A:$A,$A24))) -> G2-DS-8.2 | C24: =IF($A24="","",IF(ISERROR(FIND(".",INDEX(Tasks!$A:$A,$A24))),""," ")&INDEX(Tasks!$C:$C,$A24)) -> Devkit | D24: =IF($A24="","",IF(INDEX(Tasks!$D:$D,$A24)="","",INDEX(Tasks!$D:$D,$A24))) -> SCooP owner | E24: =IF($A24="","",IF(INDEX(Tasks!$E:$E,$A24)="","",INDEX(Tasks!$E:$E,$A24))) -> Not Started | F24: =IF($A24="","",IF(INDEX(Tasks!$F:$F,$A24)="","",INDEX(Tasks!$F:$F,$A24))) -> 46384 | G24: =IF($A24="","",IF(INDEX(Tasks!$H:$H,$A24)="","",INDEX(Tasks!$H:$H,$A24))) -> 46409
A25: =IFERROR(MATCH($C$2&"|"&(ROW()-4),Tasks!$K$4:$K$403,0)+3,"") -> 35 | B25: =IF($A25="","",IF(INDEX(Tasks!$A:$A,$A25)="","",INDEX(Tasks!$A:$A,$A25))) -> G2-DS-8.3 | C25: =IF($A25="","",IF(ISERROR(FIND(".",INDEX(Tasks!$A:$A,$A25))),""," ")&INDEX(Tasks!$C:$C,$A25)) -> License, DOI, hosting | D25: =IF($A25="","",IF(INDEX(Tasks!$D:$D,$A25)="","",INDEX(Tasks!$D:$D,$A25))) -> SCooP owner | E25: =IF($A25="","",IF(INDEX(Tasks!$E:$E,$A25)="","",INDEX(Tasks!$E:$E,$A25))) -> Not Started | F25: =IF($A25="","",IF(INDEX(Tasks!$F:$F,$A25)="","",INDEX(Tasks!$F:$F,$A25))) -> 46398 | G25: =IF($A25="","",IF(INDEX(Tasks!$H:$H,$A25)="","",INDEX(Tasks!$H:$H,$A25))) -> 46409
... A124: =IFERROR(MATCH($C$2&"|"&(ROW()-4),Tasks!$K$4:$K$403,0)+3,"") | B124: =IF($A124="","",IF(INDEX(Tasks!$A:$A,$A124)="","",INDEX(Tasks!$A:$A,$A124))) | C124: =IF($A124="","",IF(ISERROR(FIND(".",INDEX(Tasks!$A:$A,$A124))),""," ")&INDEX(Tasks!$C:$C,$A124)) | D124: =IF($A124="","",IF(INDEX(Tasks!$D:$D,$A124)="","",INDEX(Tasks!$D:$D,$A124))) | E124: =IF($A124="","",IF(INDEX(Tasks!$E:$E,$A124)="","",INDEX(Tasks!$E:$E,$A124))) | F124: =IF($A124="","",IF(INDEX(Tasks!$F:$F,$A124)="","",INDEX(Tasks!$F:$F,$A124))) | G124: =IF($A124="","",IF(INDEX(Tasks!$H:$H,$A124)="","",INDEX(Tasks!$H:$H,$A124)))

Sheet Testbed
B1: Goal: Shared SCooP testbed
B2: Goal: | C2: Shared SCooP testbed | E2: =COUNTIFS(Tasks!$B$4:$B$403,$C$2,Tasks!$C$4:$C$403,"?*")&" tasks · "&COUNTIFS(Tasks!$B$4:$B$403,$C$2,Tasks!$C$4:$C$403,"?*",Tasks!$E$4:$E$403,"In Progress")&" in progress · "&COUNTIFS(Tasks!$B$4:$B$403,$C$2,Tasks!$C$4:$C$403,"?*",Tasks!$E$4:$E$403,"Blocked")&" blocked · "&COUNTIFS(Tasks!$B$4:$B$403,$C$2,Tasks!$C$4:$C$403,"?*",Tasks!$H$4:$H$403,"<"&TODAY(),Tasks!$E$4:$E$403,"<>Complete")&" overdue" -> 11 tasks · 4 in progress · 0 blocked · 3 overdue
A4: Tasks row | B4: ID | C4: Task | D4: Assigned to | E4: Status | F4: Start | G4: End | H4: =Gantt!$C$3+7*0 -> 46195 | I4: =Gantt!$C$3+7*1 -> 46202 | J4: =Gantt!$C$3+7*2 -> 46209 | K4: =Gantt!$C$3+7*3 -> 46216 | L4: =Gantt!$C$3+7*4 -> 46223 | M4: =Gantt!$C$3+7*5 -> 46230 | N4: =Gantt!$C$3+7*6 -> 46237 | O4: =Gantt!$C$3+7*7 -> 46244 | P4: =Gantt!$C$3+7*8 -> 46251 | Q4: =Gantt!$C$3+7*9 -> 46258 | R4: =Gantt!$C$3+7*10 -> 46265 | S4: =Gantt!$C$3+7*11 -> 46272 | T4: =Gantt!$C$3+7*12 -> 46279 | U4: =Gantt!$C$3+7*13 -> 46286 | V4: =Gantt!$C$3+7*14 -> 46293 | W4: =Gantt!$C$3+7*15 -> 46300 | X4: =Gantt!$C$3+7*16 -> 46307 | Y4: =Gantt!$C$3+7*17 -> 46314 | Z4: =Gantt!$C$3+7*18 -> 46321 | AA4: =Gantt!$C$3+7*19 -> 46328 | AB4: =Gantt!$C$3+7*20 -> 46335 | AC4: =Gantt!$C$3+7*21 -> 46342 | AD4: =Gantt!$C$3+7*22 -> 46349 | AE4: =Gantt!$C$3+7*23 -> 46356 | AF4: =Gantt!$C$3+7*24 -> 46363 | AG4: =Gantt!$C$3+7*25 -> 46370 | AH4: =Gantt!$C$3+7*26 -> 46377 | AI4: =Gantt!$C$3+7*27 -> 46384 | AJ4: =Gantt!$C$3+7*28 -> 46391 | AK4: =Gantt!$C$3+7*29 -> 46398 | AL4: =Gantt!$C$3+7*30 -> 46405 | AM4: =Gantt!$C$3+7*31 -> 46412 | AN4: =Gantt!$C$3+7*32 -> 46419 | AO4: =Gantt!$C$3+7*33 -> 46426 | AP4: =Gantt!$C$3+7*34 -> 46433 | AQ4: =Gantt!$C$3+7*35 -> 46440 | AR4: =Gantt!$C$3+7*36 -> 46447 | AS4: =Gantt!$C$3+7*37 -> 46454 | AT4: =Gantt!$C$3+7*38 -> 46461 | AU4: =Gantt!$C$3+7*39 -> 46468 | AV4: =Gantt!$C$3+7*40 -> 46475 | AW4: =Gantt!$C$3+7*41 -> 46482 | AX4: =Gantt!$C$3+7*42 -> 46489 | AY4: =Gantt!$C$3+7*43 -> 46496 | BB4: Legend
A5: =IFERROR(MATCH($C$2&"|"&(ROW()-4),Tasks!$K$4:$K$403,0)+3,"") -> 4 | B5: =IF($A5="","",IF(INDEX(Tasks!$A:$A,$A5)="","",INDEX(Tasks!$A:$A,$A5))) -> TB-1 | C5: =IF($A5="","",IF(ISERROR(FIND(".",INDEX(Tasks!$A:$A,$A5))),""," ")&INDEX(Tasks!$C:$C,$A5)) -> Hardware inventory & specs | D5: =IF($A5="","",IF(INDEX(Tasks!$D:$D,$A5)="","",INDEX(Tasks!$D:$D,$A5))) -> Sensors & platform owner | E5: =IF($A5="","",IF(INDEX(Tasks!$E:$E,$A5)="","",INDEX(Tasks!$E:$E,$A5))) -> Not Started | F5: =IF($A5="","",IF(INDEX(Tasks!$F:$F,$A5)="","",INDEX(Tasks!$F:$F,$A5))) -> 46307 | G5: =IF($A5="","",IF(INDEX(Tasks!$H:$H,$A5)="","",INDEX(Tasks!$H:$H,$A5))) -> 46318 | BB5: Complete
A6: =IFERROR(MATCH($C$2&"|"&(ROW()-4),Tasks!$K$4:$K$403,0)+3,"") -> 5 | B6: =IF($A6="","",IF(INDEX(Tasks!$A:$A,$A6)="","",INDEX(Tasks!$A:$A,$A6))) -> TB-2 | C6: =IF($A6="","",IF(ISERROR(FIND(".",INDEX(Tasks!$A:$A,$A6))),""," ")&INDEX(Tasks!$C:$C,$A6)) -> Sensor calibration (all units) | D6: =IF($A6="","",IF(INDEX(Tasks!$D:$D,$A6)="","",INDEX(Tasks!$D:$D,$A6))) -> Sensors & platform owner | E6: =IF($A6="","",IF(INDEX(Tasks!$E:$E,$A6)="","",INDEX(Tasks!$E:$E,$A6))) -> In Progress | F6: =IF($A6="","",IF(INDEX(Tasks!$F:$F,$A6)="","",INDEX(Tasks!$F:$F,$A6))) -> 46195 | G6: =IF($A6="","",IF(INDEX(Tasks!$H:$H,$A6)="","",INDEX(Tasks!$H:$H,$A6))) -> 46206 | BB6: In Progress
A7: =IFERROR(MATCH($C$2&"|"&(ROW()-4),Tasks!$K$4:$K$403,0)+3,"") -> 6 | B7: =IF($A7="","",IF(INDEX(Tasks!$A:$A,$A7)="","",INDEX(Tasks!$A:$A,$A7))) -> TB-2.1 | C7: =IF($A7="","",IF(ISERROR(FIND(".",INDEX(Tasks!$A:$A,$A7))),""," ")&INDEX(Tasks!$C:$C,$A7)) -> Sensor Calibration (LiDAR-Camera, LiDAR-IMU, Camera-Radar, Intrinsics, Realsense-Zed, Mobile-Infra Extrinsics) | D7: =IF($A7="","",IF(INDEX(Tasks!$D:$D,$A7)="","",INDEX(Tasks!$D:$D,$A7))) -> Sensors & platform owner | E7: =IF($A7="","",IF(INDEX(Tasks!$E:$E,$A7)="","",INDEX(Tasks!$E:$E,$A7))) -> In Progress | F7: =IF($A7="","",IF(INDEX(Tasks!$F:$F,$A7)="","",INDEX(Tasks!$F:$F,$A7))) -> 46195 | G7: =IF($A7="","",IF(INDEX(Tasks!$H:$H,$A7)="","",INDEX(Tasks!$H:$H,$A7))) -> 46206 | BB7: Partially Completed
A8: =IFERROR(MATCH($C$2&"|"&(ROW()-4),Tasks!$K$4:$K$403,0)+3,"") -> 7 | B8: =IF($A8="","",IF(INDEX(Tasks!$A:$A,$A8)="","",INDEX(Tasks!$A:$A,$A8))) -> TB-2.2 | C8: =IF($A8="","",IF(ISERROR(FIND(".",INDEX(Tasks!$A:$A,$A8))),""," ")&INDEX(Tasks!$C:$C,$A8)) -> Calibration: LiDAR - Camera | D8: =IF($A8="","",IF(INDEX(Tasks!$D:$D,$A8)="","",INDEX(Tasks!$D:$D,$A8))) -> Sensors & platform owner | E8: =IF($A8="","",IF(INDEX(Tasks!$E:$E,$A8)="","",INDEX(Tasks!$E:$E,$A8))) | F8: =IF($A8="","",IF(INDEX(Tasks!$F:$F,$A8)="","",INDEX(Tasks!$F:$F,$A8))) | G8: =IF($A8="","",IF(INDEX(Tasks!$H:$H,$A8)="","",INDEX(Tasks!$H:$H,$A8))) | BB8: Blocked
A9: =IFERROR(MATCH($C$2&"|"&(ROW()-4),Tasks!$K$4:$K$403,0)+3,"") -> 8 | B9: =IF($A9="","",IF(INDEX(Tasks!$A:$A,$A9)="","",INDEX(Tasks!$A:$A,$A9))) -> TB-2.3 | C9: =IF($A9="","",IF(ISERROR(FIND(".",INDEX(Tasks!$A:$A,$A9))),""," ")&INDEX(Tasks!$C:$C,$A9)) -> Calibration: LiDAR - IMU | D9: =IF($A9="","",IF(INDEX(Tasks!$D:$D,$A9)="","",INDEX(Tasks!$D:$D,$A9))) -> Sensors & platform owner | E9: =IF($A9="","",IF(INDEX(Tasks!$E:$E,$A9)="","",INDEX(Tasks!$E:$E,$A9))) | F9: =IF($A9="","",IF(INDEX(Tasks!$F:$F,$A9)="","",INDEX(Tasks!$F:$F,$A9))) | G9: =IF($A9="","",IF(INDEX(Tasks!$H:$H,$A9)="","",INDEX(Tasks!$H:$H,$A9))) | BB9: Not Started
A10: =IFERROR(MATCH($C$2&"|"&(ROW()-4),Tasks!$K$4:$K$403,0)+3,"") -> 9 | B10: =IF($A10="","",IF(INDEX(Tasks!$A:$A,$A10)="","",INDEX(Tasks!$A:$A,$A10))) -> TB-2.4 | C10: =IF($A10="","",IF(ISERROR(FIND(".",INDEX(Tasks!$A:$A,$A10))),""," ")&INDEX(Tasks!$C:$C,$A10)) -> Calibration: RealSense - ZED | D10: =IF($A10="","",IF(INDEX(Tasks!$D:$D,$A10)="","",INDEX(Tasks!$D:$D,$A10))) -> Sensors & platform owner | E10: =IF($A10="","",IF(INDEX(Tasks!$E:$E,$A10)="","",INDEX(Tasks!$E:$E,$A10))) | F10: =IF($A10="","",IF(INDEX(Tasks!$F:$F,$A10)="","",INDEX(Tasks!$F:$F,$A10))) | G10: =IF($A10="","",IF(INDEX(Tasks!$H:$H,$A10)="","",INDEX(Tasks!$H:$H,$A10))) | BB10: Milestone
A11: =IFERROR(MATCH($C$2&"|"&(ROW()-4),Tasks!$K$4:$K$403,0)+3,"") -> 10 | B11: =IF($A11="","",IF(INDEX(Tasks!$A:$A,$A11)="","",INDEX(Tasks!$A:$A,$A11))) -> TB-2.5 | C11: =IF($A11="","",IF(ISERROR(FIND(".",INDEX(Tasks!$A:$A,$A11))),""," ")&INDEX(Tasks!$C:$C,$A11)) -> Calibration: ZED - Arducam | D11: =IF($A11="","",IF(INDEX(Tasks!$D:$D,$A11)="","",INDEX(Tasks!$D:$D,$A11))) -> Sensors & platform owner | E11: =IF($A11="","",IF(INDEX(Tasks!$E:$E,$A11)="","",INDEX(Tasks!$E:$E,$A11))) | F11: =IF($A11="","",IF(INDEX(Tasks!$F:$F,$A11)="","",INDEX(Tasks!$F:$F,$A11))) | G11: =IF($A11="","",IF(INDEX(Tasks!$H:$H,$A11)="","",INDEX(Tasks!$H:$H,$A11))) | BB11: Today's week
A12: =IFERROR(MATCH($C$2&"|"&(ROW()-4),Tasks!$K$4:$K$403,0)+3,"") -> 11 | B12: =IF($A12="","",IF(INDEX(Tasks!$A:$A,$A12)="","",INDEX(Tasks!$A:$A,$A12))) -> TB-2.6 | C12: =IF($A12="","",IF(ISERROR(FIND(".",INDEX(Tasks!$A:$A,$A12))),""," ")&INDEX(Tasks!$C:$C,$A12)) -> Calibration: Radars - ZED | D12: =IF($A12="","",IF(INDEX(Tasks!$D:$D,$A12)="","",INDEX(Tasks!$D:$D,$A12))) -> Sensors & platform owner | E12: =IF($A12="","",IF(INDEX(Tasks!$E:$E,$A12)="","",INDEX(Tasks!$E:$E,$A12))) | F12: =IF($A12="","",IF(INDEX(Tasks!$F:$F,$A12)="","",INDEX(Tasks!$F:$F,$A12))) | G12: =IF($A12="","",IF(INDEX(Tasks!$H:$H,$A12)="","",INDEX(Tasks!$H:$H,$A12)))
A13: =IFERROR(MATCH($C$2&"|"&(ROW()-4),Tasks!$K$4:$K$403,0)+3,"") -> 12 | B13: =IF($A13="","",IF(INDEX(Tasks!$A:$A,$A13)="","",INDEX(Tasks!$A:$A,$A13))) -> TB-3 | C13: =IF($A13="","",IF(ISERROR(FIND(".",INDEX(Tasks!$A:$A,$A13))),""," ")&INDEX(Tasks!$C:$C,$A13)) -> Time sync & TF chain | D13: =IF($A13="","",IF(INDEX(Tasks!$D:$D,$A13)="","",INDEX(Tasks!$D:$D,$A13))) -> Sensors & platform owner | E13: =IF($A13="","",IF(INDEX(Tasks!$E:$E,$A13)="","",INDEX(Tasks!$E:$E,$A13))) -> In Progress | F13: =IF($A13="","",IF(INDEX(Tasks!$F:$F,$A13)="","",INDEX(Tasks!$F:$F,$A13))) -> 46202 | G13: =IF($A13="","",IF(INDEX(Tasks!$H:$H,$A13)="","",INDEX(Tasks!$H:$H,$A13))) -> 46206 | BB13: Red End = overdue
A14: =IFERROR(MATCH($C$2&"|"&(ROW()-4),Tasks!$K$4:$K$403,0)+3,"") -> 13 | B14: =IF($A14="","",IF(INDEX(Tasks!$A:$A,$A14)="","",INDEX(Tasks!$A:$A,$A14))) -> TB-4 | C14: =IF($A14="","",IF(ISERROR(FIND(".",INDEX(Tasks!$A:$A,$A14))),""," ")&INDEX(Tasks!$C:$C,$A14)) -> Wi-Fi & comms logging | D14: =IF($A14="","",IF(INDEX(Tasks!$D:$D,$A14)="","",INDEX(Tasks!$D:$D,$A14))) -> Sensors & platform owner | E14: =IF($A14="","",IF(INDEX(Tasks!$E:$E,$A14)="","",INDEX(Tasks!$E:$E,$A14))) -> In Progress | F14: =IF($A14="","",IF(INDEX(Tasks!$F:$F,$A14)="","",INDEX(Tasks!$F:$F,$A14))) -> 46307 | G14: =IF($A14="","",IF(INDEX(Tasks!$H:$H,$A14)="","",INDEX(Tasks!$H:$H,$A14))) -> 46318
A15: =IFERROR(MATCH($C$2&"|"&(ROW()-4),Tasks!$K$4:$K$403,0)+3,"") -> 14 | B15: =IF($A15="","",IF(INDEX(Tasks!$A:$A,$A15)="","",INDEX(Tasks!$A:$A,$A15))) -> TB-5 | C15: =IF($A15="","",IF(ISERROR(FIND(".",INDEX(Tasks!$A:$A,$A15))),""," ")&INDEX(Tasks!$C:$C,$A15)) -> Recording tooling fixes | D15: =IF($A15="","",IF(INDEX(Tasks!$D:$D,$A15)="","",INDEX(Tasks!$D:$D,$A15))) -> Sensors & platform owner | E15: =IF($A15="","",IF(INDEX(Tasks!$E:$E,$A15)="","",INDEX(Tasks!$E:$E,$A15))) -> Not Started | F15: =IF($A15="","",IF(INDEX(Tasks!$F:$F,$A15)="","",INDEX(Tasks!$F:$F,$A15))) -> 46307 | G15: =IF($A15="","",IF(INDEX(Tasks!$H:$H,$A15)="","",INDEX(Tasks!$H:$H,$A15))) -> 46318
A16: =IFERROR(MATCH($C$2&"|"&(ROW()-4),Tasks!$K$4:$K$403,0)+3,"") | B16: =IF($A16="","",IF(INDEX(Tasks!$A:$A,$A16)="","",INDEX(Tasks!$A:$A,$A16))) | C16: =IF($A16="","",IF(ISERROR(FIND(".",INDEX(Tasks!$A:$A,$A16))),""," ")&INDEX(Tasks!$C:$C,$A16)) | D16: =IF($A16="","",IF(INDEX(Tasks!$D:$D,$A16)="","",INDEX(Tasks!$D:$D,$A16))) | E16: =IF($A16="","",IF(INDEX(Tasks!$E:$E,$A16)="","",INDEX(Tasks!$E:$E,$A16))) | F16: =IF($A16="","",IF(INDEX(Tasks!$F:$F,$A16)="","",INDEX(Tasks!$F:$F,$A16))) | G16: =IF($A16="","",IF(INDEX(Tasks!$H:$H,$A16)="","",INDEX(Tasks!$H:$H,$A16)))
A17: =IFERROR(MATCH($C$2&"|"&(ROW()-4),Tasks!$K$4:$K$403,0)+3,"") | B17: =IF($A17="","",IF(INDEX(Tasks!$A:$A,$A17)="","",INDEX(Tasks!$A:$A,$A17))) | C17: =IF($A17="","",IF(ISERROR(FIND(".",INDEX(Tasks!$A:$A,$A17))),""," ")&INDEX(Tasks!$C:$C,$A17)) | D17: =IF($A17="","",IF(INDEX(Tasks!$D:$D,$A17)="","",INDEX(Tasks!$D:$D,$A17))) | E17: =IF($A17="","",IF(INDEX(Tasks!$E:$E,$A17)="","",INDEX(Tasks!$E:$E,$A17))) | F17: =IF($A17="","",IF(INDEX(Tasks!$F:$F,$A17)="","",INDEX(Tasks!$F:$F,$A17))) | G17: =IF($A17="","",IF(INDEX(Tasks!$H:$H,$A17)="","",INDEX(Tasks!$H:$H,$A17)))
A18: =IFERROR(MATCH($C$2&"|"&(ROW()-4),Tasks!$K$4:$K$403,0)+3,"") | B18: =IF($A18="","",IF(INDEX(Tasks!$A:$A,$A18)="","",INDEX(Tasks!$A:$A,$A18))) | C18: =IF($A18="","",IF(ISERROR(FIND(".",INDEX(Tasks!$A:$A,$A18))),""," ")&INDEX(Tasks!$C:$C,$A18)) | D18: =IF($A18="","",IF(INDEX(Tasks!$D:$D,$A18)="","",INDEX(Tasks!$D:$D,$A18))) | E18: =IF($A18="","",IF(INDEX(Tasks!$E:$E,$A18)="","",INDEX(Tasks!$E:$E,$A18))) | F18: =IF($A18="","",IF(INDEX(Tasks!$F:$F,$A18)="","",INDEX(Tasks!$F:$F,$A18))) | G18: =IF($A18="","",IF(INDEX(Tasks!$H:$H,$A18)="","",INDEX(Tasks!$H:$H,$A18)))
A19: =IFERROR(MATCH($C$2&"|"&(ROW()-4),Tasks!$K$4:$K$403,0)+3,"") | B19: =IF($A19="","",IF(INDEX(Tasks!$A:$A,$A19)="","",INDEX(Tasks!$A:$A,$A19))) | C19: =IF($A19="","",IF(ISERROR(FIND(".",INDEX(Tasks!$A:$A,$A19))),""," ")&INDEX(Tasks!$C:$C,$A19)) | D19: =IF($A19="","",IF(INDEX(Tasks!$D:$D,$A19)="","",INDEX(Tasks!$D:$D,$A19))) | E19: =IF($A19="","",IF(INDEX(Tasks!$E:$E,$A19)="","",INDEX(Tasks!$E:$E,$A19))) | F19: =IF($A19="","",IF(INDEX(Tasks!$F:$F,$A19)="","",INDEX(Tasks!$F:$F,$A19))) | G19: =IF($A19="","",IF(INDEX(Tasks!$H:$H,$A19)="","",INDEX(Tasks!$H:$H,$A19)))
A20: =IFERROR(MATCH($C$2&"|"&(ROW()-4),Tasks!$K$4:$K$403,0)+3,"") | B20: =IF($A20="","",IF(INDEX(Tasks!$A:$A,$A20)="","",INDEX(Tasks!$A:$A,$A20))) | C20: =IF($A20="","",IF(ISERROR(FIND(".",INDEX(Tasks!$A:$A,$A20))),""," ")&INDEX(Tasks!$C:$C,$A20)) | D20: =IF($A20="","",IF(INDEX(Tasks!$D:$D,$A20)="","",INDEX(Tasks!$D:$D,$A20))) | E20: =IF($A20="","",IF(INDEX(Tasks!$E:$E,$A20)="","",INDEX(Tasks!$E:$E,$A20))) | F20: =IF($A20="","",IF(INDEX(Tasks!$F:$F,$A20)="","",INDEX(Tasks!$F:$F,$A20))) | G20: =IF($A20="","",IF(INDEX(Tasks!$H:$H,$A20)="","",INDEX(Tasks!$H:$H,$A20)))
A21: =IFERROR(MATCH($C$2&"|"&(ROW()-4),Tasks!$K$4:$K$403,0)+3,"") | B21: =IF($A21="","",IF(INDEX(Tasks!$A:$A,$A21)="","",INDEX(Tasks!$A:$A,$A21))) | C21: =IF($A21="","",IF(ISERROR(FIND(".",INDEX(Tasks!$A:$A,$A21))),""," ")&INDEX(Tasks!$C:$C,$A21)) | D21: =IF($A21="","",IF(INDEX(Tasks!$D:$D,$A21)="","",INDEX(Tasks!$D:$D,$A21))) | E21: =IF($A21="","",IF(INDEX(Tasks!$E:$E,$A21)="","",INDEX(Tasks!$E:$E,$A21))) | F21: =IF($A21="","",IF(INDEX(Tasks!$F:$F,$A21)="","",INDEX(Tasks!$F:$F,$A21))) | G21: =IF($A21="","",IF(INDEX(Tasks!$H:$H,$A21)="","",INDEX(Tasks!$H:$H,$A21)))
A22: =IFERROR(MATCH($C$2&"|"&(ROW()-4),Tasks!$K$4:$K$403,0)+3,"") | B22: =IF($A22="","",IF(INDEX(Tasks!$A:$A,$A22)="","",INDEX(Tasks!$A:$A,$A22))) | C22: =IF($A22="","",IF(ISERROR(FIND(".",INDEX(Tasks!$A:$A,$A22))),""," ")&INDEX(Tasks!$C:$C,$A22)) | D22: =IF($A22="","",IF(INDEX(Tasks!$D:$D,$A22)="","",INDEX(Tasks!$D:$D,$A22))) | E22: =IF($A22="","",IF(INDEX(Tasks!$E:$E,$A22)="","",INDEX(Tasks!$E:$E,$A22))) | F22: =IF($A22="","",IF(INDEX(Tasks!$F:$F,$A22)="","",INDEX(Tasks!$F:$F,$A22))) | G22: =IF($A22="","",IF(INDEX(Tasks!$H:$H,$A22)="","",INDEX(Tasks!$H:$H,$A22)))
A23: =IFERROR(MATCH($C$2&"|"&(ROW()-4),Tasks!$K$4:$K$403,0)+3,"") | B23: =IF($A23="","",IF(INDEX(Tasks!$A:$A,$A23)="","",INDEX(Tasks!$A:$A,$A23))) | C23: =IF($A23="","",IF(ISERROR(FIND(".",INDEX(Tasks!$A:$A,$A23))),""," ")&INDEX(Tasks!$C:$C,$A23)) | D23: =IF($A23="","",IF(INDEX(Tasks!$D:$D,$A23)="","",INDEX(Tasks!$D:$D,$A23))) | E23: =IF($A23="","",IF(INDEX(Tasks!$E:$E,$A23)="","",INDEX(Tasks!$E:$E,$A23))) | F23: =IF($A23="","",IF(INDEX(Tasks!$F:$F,$A23)="","",INDEX(Tasks!$F:$F,$A23))) | G23: =IF($A23="","",IF(INDEX(Tasks!$H:$H,$A23)="","",INDEX(Tasks!$H:$H,$A23)))
A24: =IFERROR(MATCH($C$2&"|"&(ROW()-4),Tasks!$K$4:$K$403,0)+3,"") | B24: =IF($A24="","",IF(INDEX(Tasks!$A:$A,$A24)="","",INDEX(Tasks!$A:$A,$A24))) | C24: =IF($A24="","",IF(ISERROR(FIND(".",INDEX(Tasks!$A:$A,$A24))),""," ")&INDEX(Tasks!$C:$C,$A24)) | D24: =IF($A24="","",IF(INDEX(Tasks!$D:$D,$A24)="","",INDEX(Tasks!$D:$D,$A24))) | E24: =IF($A24="","",IF(INDEX(Tasks!$E:$E,$A24)="","",INDEX(Tasks!$E:$E,$A24))) | F24: =IF($A24="","",IF(INDEX(Tasks!$F:$F,$A24)="","",INDEX(Tasks!$F:$F,$A24))) | G24: =IF($A24="","",IF(INDEX(Tasks!$H:$H,$A24)="","",INDEX(Tasks!$H:$H,$A24)))
A25: =IFERROR(MATCH($C$2&"|"&(ROW()-4),Tasks!$K$4:$K$403,0)+3,"") | B25: =IF($A25="","",IF(INDEX(Tasks!$A:$A,$A25)="","",INDEX(Tasks!$A:$A,$A25))) | C25: =IF($A25="","",IF(ISERROR(FIND(".",INDEX(Tasks!$A:$A,$A25))),""," ")&INDEX(Tasks!$C:$C,$A25)) | D25: =IF($A25="","",IF(INDEX(Tasks!$D:$D,$A25)="","",INDEX(Tasks!$D:$D,$A25))) | E25: =IF($A25="","",IF(INDEX(Tasks!$E:$E,$A25)="","",INDEX(Tasks!$E:$E,$A25))) | F25: =IF($A25="","",IF(INDEX(Tasks!$F:$F,$A25)="","",INDEX(Tasks!$F:$F,$A25))) | G25: =IF($A25="","",IF(INDEX(Tasks!$H:$H,$A25)="","",INDEX(Tasks!$H:$H,$A25)))
... A124: =IFERROR(MATCH($C$2&"|"&(ROW()-4),Tasks!$K$4:$K$403,0)+3,"") | B124: =IF($A124="","",IF(INDEX(Tasks!$A:$A,$A124)="","",INDEX(Tasks!$A:$A,$A124))) | C124: =IF($A124="","",IF(ISERROR(FIND(".",INDEX(Tasks!$A:$A,$A124))),""," ")&INDEX(Tasks!$C:$C,$A124)) | D124: =IF($A124="","",IF(INDEX(Tasks!$D:$D,$A124)="","",INDEX(Tasks!$D:$D,$A124))) | E124: =IF($A124="","",IF(INDEX(Tasks!$E:$E,$A124)="","",INDEX(Tasks!$E:$E,$A124))) | F124: =IF($A124="","",IF(INDEX(Tasks!$F:$F,$A124)="","",INDEX(Tasks!$F:$F,$A124))) | G124: =IF($A124="","",IF(INDEX(Tasks!$H:$H,$A124)="","",INDEX(Tasks!$H:$H,$A124)))

Sheet Dual-Link comm
B1: Goal: Dual-Link Communication
B2: Goal: | C2: Dual-Link Communication | E2: =COUNTIFS(Tasks!$B$4:$B$403,$C$2,Tasks!$C$4:$C$403,"?*")&" tasks · "&COUNTIFS(Tasks!$B$4:$B$403,$C$2,Tasks!$C$4:$C$403,"?*",Tasks!$E$4:$E$403,"In Progress")&" in progress · "&COUNTIFS(Tasks!$B$4:$B$403,$C$2,Tasks!$C$4:$C$403,"?*",Tasks!$E$4:$E$403,"Blocked")&" blocked · "&COUNTIFS(Tasks!$B$4:$B$403,$C$2,Tasks!$C$4:$C$403,"?*",Tasks!$H$4:$H$403,"<"&TODAY(),Tasks!$E$4:$E$403,"<>Complete")&" overdue" -> 22 tasks · 2 in progress · 0 blocked · 22 overdue
A4: Tasks row | B4: ID | C4: Task | D4: Assigned to | E4: Status | F4: Start | G4: End | H4: =Gantt!$C$3+7*0 -> 46195 | I4: =Gantt!$C$3+7*1 -> 46202 | J4: =Gantt!$C$3+7*2 -> 46209 | K4: =Gantt!$C$3+7*3 -> 46216 | L4: =Gantt!$C$3+7*4 -> 46223 | M4: =Gantt!$C$3+7*5 -> 46230 | N4: =Gantt!$C$3+7*6 -> 46237 | O4: =Gantt!$C$3+7*7 -> 46244 | P4: =Gantt!$C$3+7*8 -> 46251 | Q4: =Gantt!$C$3+7*9 -> 46258 | R4: =Gantt!$C$3+7*10 -> 46265 | S4: =Gantt!$C$3+7*11 -> 46272 | T4: =Gantt!$C$3+7*12 -> 46279 | U4: =Gantt!$C$3+7*13 -> 46286 | V4: =Gantt!$C$3+7*14 -> 46293 | W4: =Gantt!$C$3+7*15 -> 46300 | X4: =Gantt!$C$3+7*16 -> 46307 | Y4: =Gantt!$C$3+7*17 -> 46314 | Z4: =Gantt!$C$3+7*18 -> 46321 | AA4: =Gantt!$C$3+7*19 -> 46328 | AB4: =Gantt!$C$3+7*20 -> 46335 | AC4: =Gantt!$C$3+7*21 -> 46342 | AD4: =Gantt!$C$3+7*22 -> 46349 | AE4: =Gantt!$C$3+7*23 -> 46356 | AF4: =Gantt!$C$3+7*24 -> 46363 | AG4: =Gantt!$C$3+7*25 -> 46370 | AH4: =Gantt!$C$3+7*26 -> 46377 | AI4: =Gantt!$C$3+7*27 -> 46384 | AJ4: =Gantt!$C$3+7*28 -> 46391 | AK4: =Gantt!$C$3+7*29 -> 46398 | AL4: =Gantt!$C$3+7*30 -> 46405 | AM4: =Gantt!$C$3+7*31 -> 46412 | AN4: =Gantt!$C$3+7*32 -> 46419 | AO4: =Gantt!$C$3+7*33 -> 46426 | AP4: =Gantt!$C$3+7*34 -> 46433 | AQ4: =Gantt!$C$3+7*35 -> 46440 | AR4: =Gantt!$C$3+7*36 -> 46447 | AS4: =Gantt!$C$3+7*37 -> 46454 | AT4: =Gantt!$C$3+7*38 -> 46461 | AU4: =Gantt!$C$3+7*39 -> 46468 | AV4: =Gantt!$C$3+7*40 -> 46475 | AW4: =Gantt!$C$3+7*41 -> 46482 | AX4: =Gantt!$C$3+7*42 -> 46489 | AY4: =Gantt!$C$3+7*43 -> 46496 | BB4: Legend
A5: =IFERROR(MATCH($C$2&"|"&(ROW()-4),Tasks!$K$4:$K$403,0)+3,"") -> 87 | B5: =IF($A5="","",IF(INDEX(Tasks!$A:$A,$A5)="","",INDEX(Tasks!$A:$A,$A5))) -> DL-1 | C5: =IF($A5="","",IF(ISERROR(FIND(".",INDEX(Tasks!$A:$A,$A5))),""," ")&INDEX(Tasks!$C:$C,$A5)) -> Define dual-link architecture | D5: =IF($A5="","",IF(INDEX(Tasks!$D:$D,$A5)="","",INDEX(Tasks!$D:$D,$A5))) -> Dual-link owner | E5: =IF($A5="","",IF(INDEX(Tasks!$E:$E,$A5)="","",INDEX(Tasks!$E:$E,$A5))) -> Partially Completed | F5: =IF($A5="","",IF(INDEX(Tasks!$F:$F,$A5)="","",INDEX(Tasks!$F:$F,$A5))) -> 46195 | G5: =IF($A5="","",IF(INDEX(Tasks!$H:$H,$A5)="","",INDEX(Tasks!$H:$H,$A5))) -> 46199 | BB5: Complete
A6: =IFERROR(MATCH($C$2&"|"&(ROW()-4),Tasks!$K$4:$K$403,0)+3,"") -> 88 | B6: =IF($A6="","",IF(INDEX(Tasks!$A:$A,$A6)="","",INDEX(Tasks!$A:$A,$A6))) -> DL-1.1 | C6: =IF($A6="","",IF(ISERROR(FIND(".",INDEX(Tasks!$A:$A,$A6))),""," ")&INDEX(Tasks!$C:$C,$A6)) -> Link Pairing Selection (WiFi + WiFi) | D6: =IF($A6="","",IF(INDEX(Tasks!$D:$D,$A6)="","",INDEX(Tasks!$D:$D,$A6))) -> Dual-link owner | E6: =IF($A6="","",IF(INDEX(Tasks!$E:$E,$A6)="","",INDEX(Tasks!$E:$E,$A6))) -> Partially Completed | F6: =IF($A6="","",IF(INDEX(Tasks!$F:$F,$A6)="","",INDEX(Tasks!$F:$F,$A6))) -> 46195 | G6: =IF($A6="","",IF(INDEX(Tasks!$H:$H,$A6)="","",INDEX(Tasks!$H:$H,$A6))) -> 46199 | BB6: In Progress
A7: =IFERROR(MATCH($C$2&"|"&(ROW()-4),Tasks!$K$4:$K$403,0)+3,"") -> 89 | B7: =IF($A7="","",IF(INDEX(Tasks!$A:$A,$A7)="","",INDEX(Tasks!$A:$A,$A7))) -> DL-1.2 | C7: =IF($A7="","",IF(ISERROR(FIND(".",INDEX(Tasks!$A:$A,$A7))),""," ")&INDEX(Tasks!$C:$C,$A7)) -> QoS-Tiered Traffic-Steering Policy | D7: =IF($A7="","",IF(INDEX(Tasks!$D:$D,$A7)="","",INDEX(Tasks!$D:$D,$A7))) -> Dual-link owner | E7: =IF($A7="","",IF(INDEX(Tasks!$E:$E,$A7)="","",INDEX(Tasks!$E:$E,$A7))) -> Partially Completed | F7: =IF($A7="","",IF(INDEX(Tasks!$F:$F,$A7)="","",INDEX(Tasks!$F:$F,$A7))) -> 46195 | G7: =IF($A7="","",IF(INDEX(Tasks!$H:$H,$A7)="","",INDEX(Tasks!$H:$H,$A7))) -> 46199 | BB7: Partially Completed
A8: =IFERROR(MATCH($C$2&"|"&(ROW()-4),Tasks!$K$4:$K$403,0)+3,"") -> 90 | B8: =IF($A8="","",IF(INDEX(Tasks!$A:$A,$A8)="","",INDEX(Tasks!$A:$A,$A8))) -> DL-2 | C8: =IF($A8="","",IF(ISERROR(FIND(".",INDEX(Tasks!$A:$A,$A8))),""," ")&INDEX(Tasks!$C:$C,$A8)) -> Build link monitor | D8: =IF($A8="","",IF(INDEX(Tasks!$D:$D,$A8)="","",INDEX(Tasks!$D:$D,$A8))) -> Dual-link owner | E8: =IF($A8="","",IF(INDEX(Tasks!$E:$E,$A8)="","",INDEX(Tasks!$E:$E,$A8))) -> Partially Completed | F8: =IF($A8="","",IF(INDEX(Tasks!$F:$F,$A8)="","",INDEX(Tasks!$F:$F,$A8))) -> 46195 | G8: =IF($A8="","",IF(INDEX(Tasks!$H:$H,$A8)="","",INDEX(Tasks!$H:$H,$A8))) -> 46199 | BB8: Blocked
A9: =IFERROR(MATCH($C$2&"|"&(ROW()-4),Tasks!$K$4:$K$403,0)+3,"") -> 91 | B9: =IF($A9="","",IF(INDEX(Tasks!$A:$A,$A9)="","",INDEX(Tasks!$A:$A,$A9))) -> DL-2.1 | C9: =IF($A9="","",IF(ISERROR(FIND(".",INDEX(Tasks!$A:$A,$A9))),""," ")&INDEX(Tasks!$C:$C,$A9)) -> PER / MTU Tracking | D9: =IF($A9="","",IF(INDEX(Tasks!$D:$D,$A9)="","",INDEX(Tasks!$D:$D,$A9))) -> Dual-link owner | E9: =IF($A9="","",IF(INDEX(Tasks!$E:$E,$A9)="","",INDEX(Tasks!$E:$E,$A9))) -> Partially Completed | F9: =IF($A9="","",IF(INDEX(Tasks!$F:$F,$A9)="","",INDEX(Tasks!$F:$F,$A9))) -> 46195 | G9: =IF($A9="","",IF(INDEX(Tasks!$H:$H,$A9)="","",INDEX(Tasks!$H:$H,$A9))) -> 46199 | BB9: Not Started
A10: =IFERROR(MATCH($C$2&"|"&(ROW()-4),Tasks!$K$4:$K$403,0)+3,"") -> 92 | B10: =IF($A10="","",IF(INDEX(Tasks!$A:$A,$A10)="","",INDEX(Tasks!$A:$A,$A10))) -> DL-2.2 | C10: =IF($A10="","",IF(ISERROR(FIND(".",INDEX(Tasks!$A:$A,$A10))),""," ")&INDEX(Tasks!$C:$C,$A10)) -> Throughput / RTT / Queue-Health Tracking | D10: =IF($A10="","",IF(INDEX(Tasks!$D:$D,$A10)="","",INDEX(Tasks!$D:$D,$A10))) -> Dual-link owner | E10: =IF($A10="","",IF(INDEX(Tasks!$E:$E,$A10)="","",INDEX(Tasks!$E:$E,$A10))) -> Partially Completed | F10: =IF($A10="","",IF(INDEX(Tasks!$F:$F,$A10)="","",INDEX(Tasks!$F:$F,$A10))) -> 46195 | G10: =IF($A10="","",IF(INDEX(Tasks!$H:$H,$A10)="","",INDEX(Tasks!$H:$H,$A10))) -> 46199 | BB10: Milestone
A11: =IFERROR(MATCH($C$2&"|"&(ROW()-4),Tasks!$K$4:$K$403,0)+3,"") -> 93 | B11: =IF($A11="","",IF(INDEX(Tasks!$A:$A,$A11)="","",INDEX(Tasks!$A:$A,$A11))) -> DL-3 | C11: =IF($A11="","",IF(ISERROR(FIND(".",INDEX(Tasks!$A:$A,$A11))),""," ")&INDEX(Tasks!$C:$C,$A11)) -> Implement link compression | D11: =IF($A11="","",IF(INDEX(Tasks!$D:$D,$A11)="","",INDEX(Tasks!$D:$D,$A11))) -> Dual-link owner | E11: =IF($A11="","",IF(INDEX(Tasks!$E:$E,$A11)="","",INDEX(Tasks!$E:$E,$A11))) -> In Progress | F11: =IF($A11="","",IF(INDEX(Tasks!$F:$F,$A11)="","",INDEX(Tasks!$F:$F,$A11))) -> 46195 | G11: =IF($A11="","",IF(INDEX(Tasks!$H:$H,$A11)="","",INDEX(Tasks!$H:$H,$A11))) -> 46199 | BB11: Today's week
A12: =IFERROR(MATCH($C$2&"|"&(ROW()-4),Tasks!$K$4:$K$403,0)+3,"") -> 94 | B12: =IF($A12="","",IF(INDEX(Tasks!$A:$A,$A12)="","",INDEX(Tasks!$A:$A,$A12))) -> DL-3.1 | C12: =IF($A12="","",IF(ISERROR(FIND(".",INDEX(Tasks!$A:$A,$A12))),""," ")&INDEX(Tasks!$C:$C,$A12)) -> Compression Module (Link-Monitor Reactive) | D12: =IF($A12="","",IF(INDEX(Tasks!$D:$D,$A12)="","",INDEX(Tasks!$D:$D,$A12))) -> Dual-link owner | E12: =IF($A12="","",IF(INDEX(Tasks!$E:$E,$A12)="","",INDEX(Tasks!$E:$E,$A12))) -> Partially Completed | F12: =IF($A12="","",IF(INDEX(Tasks!$F:$F,$A12)="","",INDEX(Tasks!$F:$F,$A12))) -> 46195 | G12: =IF($A12="","",IF(INDEX(Tasks!$H:$H,$A12)="","",INDEX(Tasks!$H:$H,$A12))) -> 46199
A13: =IFERROR(MATCH($C$2&"|"&(ROW()-4),Tasks!$K$4:$K$403,0)+3,"") -> 95 | B13: =IF($A13="","",IF(INDEX(Tasks!$A:$A,$A13)="","",INDEX(Tasks!$A:$A,$A13))) -> DL-3.2 | C13: =IF($A13="","",IF(ISERROR(FIND(".",INDEX(Tasks!$A:$A,$A13))),""," ")&INDEX(Tasks!$C:$C,$A13)) -> Compression Threshold Tuning | D13: =IF($A13="","",IF(INDEX(Tasks!$D:$D,$A13)="","",INDEX(Tasks!$D:$D,$A13))) -> Dual-link owner | E13: =IF($A13="","",IF(INDEX(Tasks!$E:$E,$A13)="","",INDEX(Tasks!$E:$E,$A13))) -> In Progress | F13: =IF($A13="","",IF(INDEX(Tasks!$F:$F,$A13)="","",INDEX(Tasks!$F:$F,$A13))) -> 46195 | G13: =IF($A13="","",IF(INDEX(Tasks!$H:$H,$A13)="","",INDEX(Tasks!$H:$H,$A13))) -> 46199 | BB13: Red End = overdue
A14: =IFERROR(MATCH($C$2&"|"&(ROW()-4),Tasks!$K$4:$K$403,0)+3,"") -> 96 | B14: =IF($A14="","",IF(INDEX(Tasks!$A:$A,$A14)="","",INDEX(Tasks!$A:$A,$A14))) -> DL-4 | C14: =IF($A14="","",IF(ISERROR(FIND(".",INDEX(Tasks!$A:$A,$A14))),""," ")&INDEX(Tasks!$C:$C,$A14)) -> Validate Switching Strategies — WiFi1 + WiFi2 | D14: =IF($A14="","",IF(INDEX(Tasks!$D:$D,$A14)="","",INDEX(Tasks!$D:$D,$A14))) -> Dual-link owner | E14: =IF($A14="","",IF(INDEX(Tasks!$E:$E,$A14)="","",INDEX(Tasks!$E:$E,$A14))) -> Not Started | F14: =IF($A14="","",IF(INDEX(Tasks!$F:$F,$A14)="","",INDEX(Tasks!$F:$F,$A14))) -> 46195 | G14: =IF($A14="","",IF(INDEX(Tasks!$H:$H,$A14)="","",INDEX(Tasks!$H:$H,$A14))) -> 46199
A15: =IFERROR(MATCH($C$2&"|"&(ROW()-4),Tasks!$K$4:$K$403,0)+3,"") -> 97 | B15: =IF($A15="","",IF(INDEX(Tasks!$A:$A,$A15)="","",INDEX(Tasks!$A:$A,$A15))) -> DL-4.1 | C15: =IF($A15="","",IF(ISERROR(FIND(".",INDEX(Tasks!$A:$A,$A15))),""," ")&INDEX(Tasks!$C:$C,$A15)) -> Single-Link Baseline | D15: =IF($A15="","",IF(INDEX(Tasks!$D:$D,$A15)="","",INDEX(Tasks!$D:$D,$A15))) -> Dual-link owner | E15: =IF($A15="","",IF(INDEX(Tasks!$E:$E,$A15)="","",INDEX(Tasks!$E:$E,$A15))) -> Not Started | F15: =IF($A15="","",IF(INDEX(Tasks!$F:$F,$A15)="","",INDEX(Tasks!$F:$F,$A15))) -> 46195 | G15: =IF($A15="","",IF(INDEX(Tasks!$H:$H,$A15)="","",INDEX(Tasks!$H:$H,$A15))) -> 46199
A16: =IFERROR(MATCH($C$2&"|"&(ROW()-4),Tasks!$K$4:$K$403,0)+3,"") -> 98 | B16: =IF($A16="","",IF(INDEX(Tasks!$A:$A,$A16)="","",INDEX(Tasks!$A:$A,$A16))) -> DL-4.2 | C16: =IF($A16="","",IF(ISERROR(FIND(".",INDEX(Tasks!$A:$A,$A16))),""," ")&INDEX(Tasks!$C:$C,$A16)) -> Full Topic Switchover | D16: =IF($A16="","",IF(INDEX(Tasks!$D:$D,$A16)="","",INDEX(Tasks!$D:$D,$A16))) -> Dual-link owner | E16: =IF($A16="","",IF(INDEX(Tasks!$E:$E,$A16)="","",INDEX(Tasks!$E:$E,$A16))) -> Not Started | F16: =IF($A16="","",IF(INDEX(Tasks!$F:$F,$A16)="","",INDEX(Tasks!$F:$F,$A16))) -> 46195 | G16: =IF($A16="","",IF(INDEX(Tasks!$H:$H,$A16)="","",INDEX(Tasks!$H:$H,$A16))) -> 46199
A17: =IFERROR(MATCH($C$2&"|"&(ROW()-4),Tasks!$K$4:$K$403,0)+3,"") -> 99 | B17: =IF($A17="","",IF(INDEX(Tasks!$A:$A,$A17)="","",INDEX(Tasks!$A:$A,$A17))) -> DL-4.3 | C17: =IF($A17="","",IF(ISERROR(FIND(".",INDEX(Tasks!$A:$A,$A17))),""," ")&INDEX(Tasks!$C:$C,$A17)) -> True Dual-Link (QoS-Tiered Per-Topic) | D17: =IF($A17="","",IF(INDEX(Tasks!$D:$D,$A17)="","",INDEX(Tasks!$D:$D,$A17))) -> Dual-link owner | E17: =IF($A17="","",IF(INDEX(Tasks!$E:$E,$A17)="","",INDEX(Tasks!$E:$E,$A17))) -> Not Started | F17: =IF($A17="","",IF(INDEX(Tasks!$F:$F,$A17)="","",INDEX(Tasks!$F:$F,$A17))) -> 46202 | G17: =IF($A17="","",IF(INDEX(Tasks!$H:$H,$A17)="","",INDEX(Tasks!$H:$H,$A17))) -> 46206
A18: =IFERROR(MATCH($C$2&"|"&(ROW()-4),Tasks!$K$4:$K$403,0)+3,"") -> 100 | B18: =IF($A18="","",IF(INDEX(Tasks!$A:$A,$A18)="","",INDEX(Tasks!$A:$A,$A18))) -> DL-5 | C18: =IF($A18="","",IF(ISERROR(FIND(".",INDEX(Tasks!$A:$A,$A18))),""," ")&INDEX(Tasks!$C:$C,$A18)) -> Extend to WiFi + 5G | D18: =IF($A18="","",IF(INDEX(Tasks!$D:$D,$A18)="","",INDEX(Tasks!$D:$D,$A18))) -> Dual-link owner | E18: =IF($A18="","",IF(INDEX(Tasks!$E:$E,$A18)="","",INDEX(Tasks!$E:$E,$A18))) -> Not Started | F18: =IF($A18="","",IF(INDEX(Tasks!$F:$F,$A18)="","",INDEX(Tasks!$F:$F,$A18))) -> 46202 | G18: =IF($A18="","",IF(INDEX(Tasks!$H:$H,$A18)="","",INDEX(Tasks!$H:$H,$A18))) -> 46213
A19: =IFERROR(MATCH($C$2&"|"&(ROW()-4),Tasks!$K$4:$K$403,0)+3,"") -> 101 | B19: =IF($A19="","",IF(INDEX(Tasks!$A:$A,$A19)="","",INDEX(Tasks!$A:$A,$A19))) -> DL-5.1 | C19: =IF($A19="","",IF(ISERROR(FIND(".",INDEX(Tasks!$A:$A,$A19))),""," ")&INDEX(Tasks!$C:$C,$A19)) -> WiFi + 5G Link Pairing & Switching Validation | D19: =IF($A19="","",IF(INDEX(Tasks!$D:$D,$A19)="","",INDEX(Tasks!$D:$D,$A19))) -> Dual-link owner | E19: =IF($A19="","",IF(INDEX(Tasks!$E:$E,$A19)="","",INDEX(Tasks!$E:$E,$A19))) -> Not Started | F19: =IF($A19="","",IF(INDEX(Tasks!$F:$F,$A19)="","",INDEX(Tasks!$F:$F,$A19))) -> 46202 | G19: =IF($A19="","",IF(INDEX(Tasks!$H:$H,$A19)="","",INDEX(Tasks!$H:$H,$A19))) -> 46206
A20: =IFERROR(MATCH($C$2&"|"&(ROW()-4),Tasks!$K$4:$K$403,0)+3,"") -> 102 | B20: =IF($A20="","",IF(INDEX(Tasks!$A:$A,$A20)="","",INDEX(Tasks!$A:$A,$A20))) -> DL-5.2 | C20: =IF($A20="","",IF(ISERROR(FIND(".",INDEX(Tasks!$A:$A,$A20))),""," ")&INDEX(Tasks!$C:$C,$A20)) -> Application-Level Testing on WiFi + 5G | D20: =IF($A20="","",IF(INDEX(Tasks!$D:$D,$A20)="","",INDEX(Tasks!$D:$D,$A20))) -> Dual-link owner | E20: =IF($A20="","",IF(INDEX(Tasks!$E:$E,$A20)="","",INDEX(Tasks!$E:$E,$A20))) -> Not Started | F20: =IF($A20="","",IF(INDEX(Tasks!$F:$F,$A20)="","",INDEX(Tasks!$F:$F,$A20))) -> 46209 | G20: =IF($A20="","",IF(INDEX(Tasks!$H:$H,$A20)="","",INDEX(Tasks!$H:$H,$A20))) -> 46213
A21: =IFERROR(MATCH($C$2&"|"&(ROW()-4),Tasks!$K$4:$K$403,0)+3,"") -> 103 | B21: =IF($A21="","",IF(INDEX(Tasks!$A:$A,$A21)="","",INDEX(Tasks!$A:$A,$A21))) -> DL-6 | C21: =IF($A21="","",IF(ISERROR(FIND(".",INDEX(Tasks!$A:$A,$A21))),""," ")&INDEX(Tasks!$C:$C,$A21)) -> Test failover & reliability | D21: =IF($A21="","",IF(INDEX(Tasks!$D:$D,$A21)="","",INDEX(Tasks!$D:$D,$A21))) -> Dual-link owner | E21: =IF($A21="","",IF(INDEX(Tasks!$E:$E,$A21)="","",INDEX(Tasks!$E:$E,$A21))) -> Not Started | F21: =IF($A21="","",IF(INDEX(Tasks!$F:$F,$A21)="","",INDEX(Tasks!$F:$F,$A21))) -> 46216 | G21: =IF($A21="","",IF(INDEX(Tasks!$H:$H,$A21)="","",INDEX(Tasks!$H:$H,$A21))) -> 46220
A22: =IFERROR(MATCH($C$2&"|"&(ROW()-4),Tasks!$K$4:$K$403,0)+3,"") -> 104 | B22: =IF($A22="","",IF(INDEX(Tasks!$A:$A,$A22)="","",INDEX(Tasks!$A:$A,$A22))) -> DL-6.1 | C22: =IF($A22="","",IF(ISERROR(FIND(".",INDEX(Tasks!$A:$A,$A22))),""," ")&INDEX(Tasks!$C:$C,$A22)) -> Failover Test Scenarios | D22: =IF($A22="","",IF(INDEX(Tasks!$D:$D,$A22)="","",INDEX(Tasks!$D:$D,$A22))) -> Dual-link owner | E22: =IF($A22="","",IF(INDEX(Tasks!$E:$E,$A22)="","",INDEX(Tasks!$E:$E,$A22))) -> Not Started | F22: =IF($A22="","",IF(INDEX(Tasks!$F:$F,$A22)="","",INDEX(Tasks!$F:$F,$A22))) -> 46216 | G22: =IF($A22="","",IF(INDEX(Tasks!$H:$H,$A22)="","",INDEX(Tasks!$H:$H,$A22))) -> 46220
A23: =IFERROR(MATCH($C$2&"|"&(ROW()-4),Tasks!$K$4:$K$403,0)+3,"") -> 105 | B23: =IF($A23="","",IF(INDEX(Tasks!$A:$A,$A23)="","",INDEX(Tasks!$A:$A,$A23))) -> DL-6.2 | C23: =IF($A23="","",IF(ISERROR(FIND(".",INDEX(Tasks!$A:$A,$A23))),""," ")&INDEX(Tasks!$C:$C,$A23)) -> Availability / Latency Target Validation | D23: =IF($A23="","",IF(INDEX(Tasks!$D:$D,$A23)="","",INDEX(Tasks!$D:$D,$A23))) -> Dual-link owner | E23: =IF($A23="","",IF(INDEX(Tasks!$E:$E,$A23)="","",INDEX(Tasks!$E:$E,$A23))) -> Not Started | F23: =IF($A23="","",IF(INDEX(Tasks!$F:$F,$A23)="","",INDEX(Tasks!$F:$F,$A23))) -> 46216 | G23: =IF($A23="","",IF(INDEX(Tasks!$H:$H,$A23)="","",INDEX(Tasks!$H:$H,$A23))) -> 46220
A24: =IFERROR(MATCH($C$2&"|"&(ROW()-4),Tasks!$K$4:$K$403,0)+3,"") -> 106 | B24: =IF($A24="","",IF(INDEX(Tasks!$A:$A,$A24)="","",INDEX(Tasks!$A:$A,$A24))) -> DL-7 | C24: =IF($A24="","",IF(ISERROR(FIND(".",INDEX(Tasks!$A:$A,$A24))),""," ")&INDEX(Tasks!$C:$C,$A24)) -> Integrate with digital twin | D24: =IF($A24="","",IF(INDEX(Tasks!$D:$D,$A24)="","",INDEX(Tasks!$D:$D,$A24))) -> Dual-link owner | E24: =IF($A24="","",IF(INDEX(Tasks!$E:$E,$A24)="","",INDEX(Tasks!$E:$E,$A24))) -> Not Started | F24: =IF($A24="","",IF(INDEX(Tasks!$F:$F,$A24)="","",INDEX(Tasks!$F:$F,$A24))) -> 46223 | G24: =IF($A24="","",IF(INDEX(Tasks!$H:$H,$A24)="","",INDEX(Tasks!$H:$H,$A24))) -> 46234
A25: =IFERROR(MATCH($C$2&"|"&(ROW()-4),Tasks!$K$4:$K$403,0)+3,"") -> 107 | B25: =IF($A25="","",IF(INDEX(Tasks!$A:$A,$A25)="","",INDEX(Tasks!$A:$A,$A25))) -> DL-7.1 | C25: =IF($A25="","",IF(ISERROR(FIND(".",INDEX(Tasks!$A:$A,$A25))),""," ")&INDEX(Tasks!$C:$C,$A25)) -> Predictive Handover <-> Twin Tracking Wiring | D25: =IF($A25="","",IF(INDEX(Tasks!$D:$D,$A25)="","",INDEX(Tasks!$D:$D,$A25))) -> Dual-link owner | E25: =IF($A25="","",IF(INDEX(Tasks!$E:$E,$A25)="","",INDEX(Tasks!$E:$E,$A25))) -> Not Started | F25: =IF($A25="","",IF(INDEX(Tasks!$F:$F,$A25)="","",INDEX(Tasks!$F:$F,$A25))) -> 46223 | G25: =IF($A25="","",IF(INDEX(Tasks!$H:$H,$A25)="","",INDEX(Tasks!$H:$H,$A25))) -> 46227
... A124: =IFERROR(MATCH($C$2&"|"&(ROW()-4),Tasks!$K$4:$K$403,0)+3,"") | B124: =IF($A124="","",IF(INDEX(Tasks!$A:$A,$A124)="","",INDEX(Tasks!$A:$A,$A124))) | C124: =IF($A124="","",IF(ISERROR(FIND(".",INDEX(Tasks!$A:$A,$A124))),""," ")&INDEX(Tasks!$C:$C,$A124)) | D124: =IF($A124="","",IF(INDEX(Tasks!$D:$D,$A124)="","",INDEX(Tasks!$D:$D,$A124))) | E124: =IF($A124="","",IF(INDEX(Tasks!$E:$E,$A124)="","",INDEX(Tasks!$E:$E,$A124))) | F124: =IF($A124="","",IF(INDEX(Tasks!$F:$F,$A124)="","",INDEX(Tasks!$F:$F,$A124))) | G124: =IF($A124="","",IF(INDEX(Tasks!$H:$H,$A124)="","",INDEX(Tasks!$H:$H,$A124)))

Sheet Semantic comm
B1: Goal: Semantic Communication
B2: Goal: | C2: Semantic Communication | E2: =COUNTIFS(Tasks!$B$4:$B$403,$C$2,Tasks!$C$4:$C$403,"?*")&" tasks · "&COUNTIFS(Tasks!$B$4:$B$403,$C$2,Tasks!$C$4:$C$403,"?*",Tasks!$E$4:$E$403,"In Progress")&" in progress · "&COUNTIFS(Tasks!$B$4:$B$403,$C$2,Tasks!$C$4:$C$403,"?*",Tasks!$E$4:$E$403,"Blocked")&" blocked · "&COUNTIFS(Tasks!$B$4:$B$403,$C$2,Tasks!$C$4:$C$403,"?*",Tasks!$H$4:$H$403,"<"&TODAY(),Tasks!$E$4:$E$403,"<>Complete")&" overdue" -> 14 tasks · 0 in progress · 0 blocked · 6 overdue
A4: Tasks row | B4: ID | C4: Task | D4: Assigned to | E4: Status | F4: Start | G4: End | H4: =Gantt!$C$3+7*0 -> 46195 | I4: =Gantt!$C$3+7*1 -> 46202 | J4: =Gantt!$C$3+7*2 -> 46209 | K4: =Gantt!$C$3+7*3 -> 46216 | L4: =Gantt!$C$3+7*4 -> 46223 | M4: =Gantt!$C$3+7*5 -> 46230 | N4: =Gantt!$C$3+7*6 -> 46237 | O4: =Gantt!$C$3+7*7 -> 46244 | P4: =Gantt!$C$3+7*8 -> 46251 | Q4: =Gantt!$C$3+7*9 -> 46258 | R4: =Gantt!$C$3+7*10 -> 46265 | S4: =Gantt!$C$3+7*11 -> 46272 | T4: =Gantt!$C$3+7*12 -> 46279 | U4: =Gantt!$C$3+7*13 -> 46286 | V4: =Gantt!$C$3+7*14 -> 46293 | W4: =Gantt!$C$3+7*15 -> 46300 | X4: =Gantt!$C$3+7*16 -> 46307 | Y4: =Gantt!$C$3+7*17 -> 46314 | Z4: =Gantt!$C$3+7*18 -> 46321 | AA4: =Gantt!$C$3+7*19 -> 46328 | AB4: =Gantt!$C$3+7*20 -> 46335 | AC4: =Gantt!$C$3+7*21 -> 46342 | AD4: =Gantt!$C$3+7*22 -> 46349 | AE4: =Gantt!$C$3+7*23 -> 46356 | AF4: =Gantt!$C$3+7*24 -> 46363 | AG4: =Gantt!$C$3+7*25 -> 46370 | AH4: =Gantt!$C$3+7*26 -> 46377 | AI4: =Gantt!$C$3+7*27 -> 46384 | AJ4: =Gantt!$C$3+7*28 -> 46391 | AK4: =Gantt!$C$3+7*29 -> 46398 | AL4: =Gantt!$C$3+7*30 -> 46405 | AM4: =Gantt!$C$3+7*31 -> 46412 | AN4: =Gantt!$C$3+7*32 -> 46419 | AO4: =Gantt!$C$3+7*33 -> 46426 | AP4: =Gantt!$C$3+7*34 -> 46433 | AQ4: =Gantt!$C$3+7*35 -> 46440 | AR4: =Gantt!$C$3+7*36 -> 46447 | AS4: =Gantt!$C$3+7*37 -> 46454 | AT4: =Gantt!$C$3+7*38 -> 46461 | AU4: =Gantt!$C$3+7*39 -> 46468 | AV4: =Gantt!$C$3+7*40 -> 46475 | AW4: =Gantt!$C$3+7*41 -> 46482 | AX4: =Gantt!$C$3+7*42 -> 46489 | AY4: =Gantt!$C$3+7*43 -> 46496 | BB4: Legend
A5: =IFERROR(MATCH($C$2&"|"&(ROW()-4),Tasks!$K$4:$K$403,0)+3,"") -> 109 | B5: =IF($A5="","",IF(INDEX(Tasks!$A:$A,$A5)="","",INDEX(Tasks!$A:$A,$A5))) -> SC-1 | C5: =IF($A5="","",IF(ISERROR(FIND(".",INDEX(Tasks!$A:$A,$A5))),""," ")&INDEX(Tasks!$C:$C,$A5)) -> Object Recognition (Camera Encoder/Decoder) | D5: =IF($A5="","",IF(INDEX(Tasks!$D:$D,$A5)="","",INDEX(Tasks!$D:$D,$A5))) -> Semantic comm owner | E5: =IF($A5="","",IF(INDEX(Tasks!$E:$E,$A5)="","",INDEX(Tasks!$E:$E,$A5))) -> Not Started | F5: =IF($A5="","",IF(INDEX(Tasks!$F:$F,$A5)="","",INDEX(Tasks!$F:$F,$A5))) -> 46195 | G5: =IF($A5="","",IF(INDEX(Tasks!$H:$H,$A5)="","",INDEX(Tasks!$H:$H,$A5))) -> 46206 | BB5: Complete
A6: =IFERROR(MATCH($C$2&"|"&(ROW()-4),Tasks!$K$4:$K$403,0)+3,"") -> 110 | B6: =IF($A6="","",IF(INDEX(Tasks!$A:$A,$A6)="","",INDEX(Tasks!$A:$A,$A6))) -> SC-1.1 | C6: =IF($A6="","",IF(ISERROR(FIND(".",INDEX(Tasks!$A:$A,$A6))),""," ")&INDEX(Tasks!$C:$C,$A6)) -> Encoder + Decoder | D6: =IF($A6="","",IF(INDEX(Tasks!$D:$D,$A6)="","",INDEX(Tasks!$D:$D,$A6))) -> Semantic comm owner | E6: =IF($A6="","",IF(INDEX(Tasks!$E:$E,$A6)="","",INDEX(Tasks!$E:$E,$A6))) -> Not Started | F6: =IF($A6="","",IF(INDEX(Tasks!$F:$F,$A6)="","",INDEX(Tasks!$F:$F,$A6))) -> 46195 | G6: =IF($A6="","",IF(INDEX(Tasks!$H:$H,$A6)="","",INDEX(Tasks!$H:$H,$A6))) -> 46206 | BB6: In Progress
A7: =IFERROR(MATCH($C$2&"|"&(ROW()-4),Tasks!$K$4:$K$403,0)+3,"") -> 111 | B7: =IF($A7="","",IF(INDEX(Tasks!$A:$A,$A7)="","",INDEX(Tasks!$A:$A,$A7))) -> SC-1.2 | C7: =IF($A7="","",IF(ISERROR(FIND(".",INDEX(Tasks!$A:$A,$A7))),""," ")&INDEX(Tasks!$C:$C,$A7)) -> Accuracy Validation | D7: =IF($A7="","",IF(INDEX(Tasks!$D:$D,$A7)="","",INDEX(Tasks!$D:$D,$A7))) -> Semantic comm owner | E7: =IF($A7="","",IF(INDEX(Tasks!$E:$E,$A7)="","",INDEX(Tasks!$E:$E,$A7))) -> Not Started | F7: =IF($A7="","",IF(INDEX(Tasks!$F:$F,$A7)="","",INDEX(Tasks!$F:$F,$A7))) -> 46202 | G7: =IF($A7="","",IF(INDEX(Tasks!$H:$H,$A7)="","",INDEX(Tasks!$H:$H,$A7))) -> 46206 | BB7: Partially Completed
A8: =IFERROR(MATCH($C$2&"|"&(ROW()-4),Tasks!$K$4:$K$403,0)+3,"") -> 112 | B8: =IF($A8="","",IF(INDEX(Tasks!$A:$A,$A8)="","",INDEX(Tasks!$A:$A,$A8))) -> SC-2 | C8: =IF($A8="","",IF(ISERROR(FIND(".",INDEX(Tasks!$A:$A,$A8))),""," ")&INDEX(Tasks!$C:$C,$A8)) -> Build Core Framework | D8: =IF($A8="","",IF(INDEX(Tasks!$D:$D,$A8)="","",INDEX(Tasks!$D:$D,$A8))) -> Semantic comm owner | E8: =IF($A8="","",IF(INDEX(Tasks!$E:$E,$A8)="","",INDEX(Tasks!$E:$E,$A8))) -> Not Started | F8: =IF($A8="","",IF(INDEX(Tasks!$F:$F,$A8)="","",INDEX(Tasks!$F:$F,$A8))) -> 46209 | G8: =IF($A8="","",IF(INDEX(Tasks!$H:$H,$A8)="","",INDEX(Tasks!$H:$H,$A8))) -> 46220 | BB8: Blocked
A9: =IFERROR(MATCH($C$2&"|"&(ROW()-4),Tasks!$K$4:$K$403,0)+3,"") -> 113 | B9: =IF($A9="","",IF(INDEX(Tasks!$A:$A,$A9)="","",INDEX(Tasks!$A:$A,$A9))) -> SC-2.1 | C9: =IF($A9="","",IF(ISERROR(FIND(".",INDEX(Tasks!$A:$A,$A9))),""," ")&INDEX(Tasks!$C:$C,$A9)) -> Baseline 3-Stage Framework | D9: =IF($A9="","",IF(INDEX(Tasks!$D:$D,$A9)="","",INDEX(Tasks!$D:$D,$A9))) -> Semantic comm owner | E9: =IF($A9="","",IF(INDEX(Tasks!$E:$E,$A9)="","",INDEX(Tasks!$E:$E,$A9))) -> Not Started | F9: =IF($A9="","",IF(INDEX(Tasks!$F:$F,$A9)="","",INDEX(Tasks!$F:$F,$A9))) -> 46209 | G9: =IF($A9="","",IF(INDEX(Tasks!$H:$H,$A9)="","",INDEX(Tasks!$H:$H,$A9))) -> 46220 | BB9: Not Started
A10: =IFERROR(MATCH($C$2&"|"&(ROW()-4),Tasks!$K$4:$K$403,0)+3,"") -> 114 | B10: =IF($A10="","",IF(INDEX(Tasks!$A:$A,$A10)="","",INDEX(Tasks!$A:$A,$A10))) -> SC-2.2 | C10: =IF($A10="","",IF(ISERROR(FIND(".",INDEX(Tasks!$A:$A,$A10))),""," ")&INDEX(Tasks!$C:$C,$A10)) -> Realistic Channel Model | D10: =IF($A10="","",IF(INDEX(Tasks!$D:$D,$A10)="","",INDEX(Tasks!$D:$D,$A10))) -> Semantic comm owner | E10: =IF($A10="","",IF(INDEX(Tasks!$E:$E,$A10)="","",INDEX(Tasks!$E:$E,$A10))) -> Not Started | F10: =IF($A10="","",IF(INDEX(Tasks!$F:$F,$A10)="","",INDEX(Tasks!$F:$F,$A10))) -> 46216 | G10: =IF($A10="","",IF(INDEX(Tasks!$H:$H,$A10)="","",INDEX(Tasks!$H:$H,$A10))) -> 46220 | BB10: Milestone
A11: =IFERROR(MATCH($C$2&"|"&(ROW()-4),Tasks!$K$4:$K$403,0)+3,"") -> 115 | B11: =IF($A11="","",IF(INDEX(Tasks!$A:$A,$A11)="","",INDEX(Tasks!$A:$A,$A11))) -> SC-3 | C11: =IF($A11="","",IF(ISERROR(FIND(".",INDEX(Tasks!$A:$A,$A11))),""," ")&INDEX(Tasks!$C:$C,$A11)) -> Dynamic Bandwidth Management | D11: =IF($A11="","",IF(INDEX(Tasks!$D:$D,$A11)="","",INDEX(Tasks!$D:$D,$A11))) -> Semantic comm owner | E11: =IF($A11="","",IF(INDEX(Tasks!$E:$E,$A11)="","",INDEX(Tasks!$E:$E,$A11))) -> Not Started | F11: =IF($A11="","",IF(INDEX(Tasks!$F:$F,$A11)="","",INDEX(Tasks!$F:$F,$A11))) | G11: =IF($A11="","",IF(INDEX(Tasks!$H:$H,$A11)="","",INDEX(Tasks!$H:$H,$A11))) | BB11: Today's week
A12: =IFERROR(MATCH($C$2&"|"&(ROW()-4),Tasks!$K$4:$K$403,0)+3,"") -> 116 | B12: =IF($A12="","",IF(INDEX(Tasks!$A:$A,$A12)="","",INDEX(Tasks!$A:$A,$A12))) -> SC-3.1 | C12: =IF($A12="","",IF(ISERROR(FIND(".",INDEX(Tasks!$A:$A,$A12))),""," ")&INDEX(Tasks!$C:$C,$A12)) -> Semantic Allocation | D12: =IF($A12="","",IF(INDEX(Tasks!$D:$D,$A12)="","",INDEX(Tasks!$D:$D,$A12))) -> Semantic comm owner | E12: =IF($A12="","",IF(INDEX(Tasks!$E:$E,$A12)="","",INDEX(Tasks!$E:$E,$A12))) -> Not Started | F12: =IF($A12="","",IF(INDEX(Tasks!$F:$F,$A12)="","",INDEX(Tasks!$F:$F,$A12))) | G12: =IF($A12="","",IF(INDEX(Tasks!$H:$H,$A12)="","",INDEX(Tasks!$H:$H,$A12)))
A13: =IFERROR(MATCH($C$2&"|"&(ROW()-4),Tasks!$K$4:$K$403,0)+3,"") -> 117 | B13: =IF($A13="","",IF(INDEX(Tasks!$A:$A,$A13)="","",INDEX(Tasks!$A:$A,$A13))) -> SC-3.2 | C13: =IF($A13="","",IF(ISERROR(FIND(".",INDEX(Tasks!$A:$A,$A13))),""," ")&INDEX(Tasks!$C:$C,$A13)) -> Physical Constraint Bounds | D13: =IF($A13="","",IF(INDEX(Tasks!$D:$D,$A13)="","",INDEX(Tasks!$D:$D,$A13))) -> Semantic comm owner | E13: =IF($A13="","",IF(INDEX(Tasks!$E:$E,$A13)="","",INDEX(Tasks!$E:$E,$A13))) -> Not Started | F13: =IF($A13="","",IF(INDEX(Tasks!$F:$F,$A13)="","",INDEX(Tasks!$F:$F,$A13))) | G13: =IF($A13="","",IF(INDEX(Tasks!$H:$H,$A13)="","",INDEX(Tasks!$H:$H,$A13))) | BB13: Red End = overdue
A14: =IFERROR(MATCH($C$2&"|"&(ROW()-4),Tasks!$K$4:$K$403,0)+3,"") -> 118 | B14: =IF($A14="","",IF(INDEX(Tasks!$A:$A,$A14)="","",INDEX(Tasks!$A:$A,$A14))) -> SC-3.3 | C14: =IF($A14="","",IF(ISERROR(FIND(".",INDEX(Tasks!$A:$A,$A14))),""," ")&INDEX(Tasks!$C:$C,$A14)) -> Per-Modality Truncation | D14: =IF($A14="","",IF(INDEX(Tasks!$D:$D,$A14)="","",INDEX(Tasks!$D:$D,$A14))) -> Semantic comm owner | E14: =IF($A14="","",IF(INDEX(Tasks!$E:$E,$A14)="","",INDEX(Tasks!$E:$E,$A14))) -> Not Started | F14: =IF($A14="","",IF(INDEX(Tasks!$F:$F,$A14)="","",INDEX(Tasks!$F:$F,$A14))) | G14: =IF($A14="","",IF(INDEX(Tasks!$H:$H,$A14)="","",INDEX(Tasks!$H:$H,$A14)))
A15: =IFERROR(MATCH($C$2&"|"&(ROW()-4),Tasks!$K$4:$K$403,0)+3,"") -> 119 | B15: =IF($A15="","",IF(INDEX(Tasks!$A:$A,$A15)="","",INDEX(Tasks!$A:$A,$A15))) -> SC-3.4 | C15: =IF($A15="","",IF(ISERROR(FIND(".",INDEX(Tasks!$A:$A,$A15))),""," ")&INDEX(Tasks!$C:$C,$A15)) -> Cost-Aware Feedback Loop | D15: =IF($A15="","",IF(INDEX(Tasks!$D:$D,$A15)="","",INDEX(Tasks!$D:$D,$A15))) -> Semantic comm owner | E15: =IF($A15="","",IF(INDEX(Tasks!$E:$E,$A15)="","",INDEX(Tasks!$E:$E,$A15))) -> Not Started | F15: =IF($A15="","",IF(INDEX(Tasks!$F:$F,$A15)="","",INDEX(Tasks!$F:$F,$A15))) | G15: =IF($A15="","",IF(INDEX(Tasks!$H:$H,$A15)="","",INDEX(Tasks!$H:$H,$A15)))
A16: =IFERROR(MATCH($C$2&"|"&(ROW()-4),Tasks!$K$4:$K$403,0)+3,"") -> 120 | B16: =IF($A16="","",IF(INDEX(Tasks!$A:$A,$A16)="","",INDEX(Tasks!$A:$A,$A16))) -> SC-4 | C16: =IF($A16="","",IF(ISERROR(FIND(".",INDEX(Tasks!$A:$A,$A16))),""," ")&INDEX(Tasks!$C:$C,$A16)) -> Multi-Task Transmission | D16: =IF($A16="","",IF(INDEX(Tasks!$D:$D,$A16)="","",INDEX(Tasks!$D:$D,$A16))) -> Semantic comm owner | E16: =IF($A16="","",IF(INDEX(Tasks!$E:$E,$A16)="","",INDEX(Tasks!$E:$E,$A16))) -> Not Started | F16: =IF($A16="","",IF(INDEX(Tasks!$F:$F,$A16)="","",INDEX(Tasks!$F:$F,$A16))) | G16: =IF($A16="","",IF(INDEX(Tasks!$H:$H,$A16)="","",INDEX(Tasks!$H:$H,$A16)))
A17: =IFERROR(MATCH($C$2&"|"&(ROW()-4),Tasks!$K$4:$K$403,0)+3,"") -> 121 | B17: =IF($A17="","",IF(INDEX(Tasks!$A:$A,$A17)="","",INDEX(Tasks!$A:$A,$A17))) -> SC-5 | C17: =IF($A17="","",IF(ISERROR(FIND(".",INDEX(Tasks!$A:$A,$A17))),""," ")&INDEX(Tasks!$C:$C,$A17)) -> Train & Evaluate on Dataset | D17: =IF($A17="","",IF(INDEX(Tasks!$D:$D,$A17)="","",INDEX(Tasks!$D:$D,$A17))) -> Semantic comm owner | E17: =IF($A17="","",IF(INDEX(Tasks!$E:$E,$A17)="","",INDEX(Tasks!$E:$E,$A17))) -> Not Started | F17: =IF($A17="","",IF(INDEX(Tasks!$F:$F,$A17)="","",INDEX(Tasks!$F:$F,$A17))) | G17: =IF($A17="","",IF(INDEX(Tasks!$H:$H,$A17)="","",INDEX(Tasks!$H:$H,$A17)))
A18: =IFERROR(MATCH($C$2&"|"&(ROW()-4),Tasks!$K$4:$K$403,0)+3,"") -> 122 | B18: =IF($A18="","",IF(INDEX(Tasks!$A:$A,$A18)="","",INDEX(Tasks!$A:$A,$A18))) -> SC-6 | C18: =IF($A18="","",IF(ISERROR(FIND(".",INDEX(Tasks!$A:$A,$A18))),""," ")&INDEX(Tasks!$C:$C,$A18)) -> Integrate with Dual-Link | D18: =IF($A18="","",IF(INDEX(Tasks!$D:$D,$A18)="","",INDEX(Tasks!$D:$D,$A18))) -> Semantic comm owner | E18: =IF($A18="","",IF(INDEX(Tasks!$E:$E,$A18)="","",INDEX(Tasks!$E:$E,$A18))) -> Not Started | F18: =IF($A18="","",IF(INDEX(Tasks!$F:$F,$A18)="","",INDEX(Tasks!$F:$F,$A18))) | G18: =IF($A18="","",IF(INDEX(Tasks!$H:$H,$A18)="","",INDEX(Tasks!$H:$H,$A18)))
A19: =IFERROR(MATCH($C$2&"|"&(ROW()-4),Tasks!$K$4:$K$403,0)+3,"") | B19: =IF($A19="","",IF(INDEX(Tasks!$A:$A,$A19)="","",INDEX(Tasks!$A:$A,$A19))) | C19: =IF($A19="","",IF(ISERROR(FIND(".",INDEX(Tasks!$A:$A,$A19))),""," ")&INDEX(Tasks!$C:$C,$A19)) | D19: =IF($A19="","",IF(INDEX(Tasks!$D:$D,$A19)="","",INDEX(Tasks!$D:$D,$A19))) | E19: =IF($A19="","",IF(INDEX(Tasks!$E:$E,$A19)="","",INDEX(Tasks!$E:$E,$A19))) | F19: =IF($A19="","",IF(INDEX(Tasks!$F:$F,$A19)="","",INDEX(Tasks!$F:$F,$A19))) | G19: =IF($A19="","",IF(INDEX(Tasks!$H:$H,$A19)="","",INDEX(Tasks!$H:$H,$A19)))
A20: =IFERROR(MATCH($C$2&"|"&(ROW()-4),Tasks!$K$4:$K$403,0)+3,"") | B20: =IF($A20="","",IF(INDEX(Tasks!$A:$A,$A20)="","",INDEX(Tasks!$A:$A,$A20))) | C20: =IF($A20="","",IF(ISERROR(FIND(".",INDEX(Tasks!$A:$A,$A20))),""," ")&INDEX(Tasks!$C:$C,$A20)) | D20: =IF($A20="","",IF(INDEX(Tasks!$D:$D,$A20)="","",INDEX(Tasks!$D:$D,$A20))) | E20: =IF($A20="","",IF(INDEX(Tasks!$E:$E,$A20)="","",INDEX(Tasks!$E:$E,$A20))) | F20: =IF($A20="","",IF(INDEX(Tasks!$F:$F,$A20)="","",INDEX(Tasks!$F:$F,$A20))) | G20: =IF($A20="","",IF(INDEX(Tasks!$H:$H,$A20)="","",INDEX(Tasks!$H:$H,$A20)))
A21: =IFERROR(MATCH($C$2&"|"&(ROW()-4),Tasks!$K$4:$K$403,0)+3,"") | B21: =IF($A21="","",IF(INDEX(Tasks!$A:$A,$A21)="","",INDEX(Tasks!$A:$A,$A21))) | C21: =IF($A21="","",IF(ISERROR(FIND(".",INDEX(Tasks!$A:$A,$A21))),""," ")&INDEX(Tasks!$C:$C,$A21)) | D21: =IF($A21="","",IF(INDEX(Tasks!$D:$D,$A21)="","",INDEX(Tasks!$D:$D,$A21))) | E21: =IF($A21="","",IF(INDEX(Tasks!$E:$E,$A21)="","",INDEX(Tasks!$E:$E,$A21))) | F21: =IF($A21="","",IF(INDEX(Tasks!$F:$F,$A21)="","",INDEX(Tasks!$F:$F,$A21))) | G21: =IF($A21="","",IF(INDEX(Tasks!$H:$H,$A21)="","",INDEX(Tasks!$H:$H,$A21)))
A22: =IFERROR(MATCH($C$2&"|"&(ROW()-4),Tasks!$K$4:$K$403,0)+3,"") | B22: =IF($A22="","",IF(INDEX(Tasks!$A:$A,$A22)="","",INDEX(Tasks!$A:$A,$A22))) | C22: =IF($A22="","",IF(ISERROR(FIND(".",INDEX(Tasks!$A:$A,$A22))),""," ")&INDEX(Tasks!$C:$C,$A22)) | D22: =IF($A22="","",IF(INDEX(Tasks!$D:$D,$A22)="","",INDEX(Tasks!$D:$D,$A22))) | E22: =IF($A22="","",IF(INDEX(Tasks!$E:$E,$A22)="","",INDEX(Tasks!$E:$E,$A22))) | F22: =IF($A22="","",IF(INDEX(Tasks!$F:$F,$A22)="","",INDEX(Tasks!$F:$F,$A22))) | G22: =IF($A22="","",IF(INDEX(Tasks!$H:$H,$A22)="","",INDEX(Tasks!$H:$H,$A22)))
A23: =IFERROR(MATCH($C$2&"|"&(ROW()-4),Tasks!$K$4:$K$403,0)+3,"") | B23: =IF($A23="","",IF(INDEX(Tasks!$A:$A,$A23)="","",INDEX(Tasks!$A:$A,$A23))) | C23: =IF($A23="","",IF(ISERROR(FIND(".",INDEX(Tasks!$A:$A,$A23))),""," ")&INDEX(Tasks!$C:$C,$A23)) | D23: =IF($A23="","",IF(INDEX(Tasks!$D:$D,$A23)="","",INDEX(Tasks!$D:$D,$A23))) | E23: =IF($A23="","",IF(INDEX(Tasks!$E:$E,$A23)="","",INDEX(Tasks!$E:$E,$A23))) | F23: =IF($A23="","",IF(INDEX(Tasks!$F:$F,$A23)="","",INDEX(Tasks!$F:$F,$A23))) | G23: =IF($A23="","",IF(INDEX(Tasks!$H:$H,$A23)="","",INDEX(Tasks!$H:$H,$A23)))
A24: =IFERROR(MATCH($C$2&"|"&(ROW()-4),Tasks!$K$4:$K$403,0)+3,"") | B24: =IF($A24="","",IF(INDEX(Tasks!$A:$A,$A24)="","",INDEX(Tasks!$A:$A,$A24))) | C24: =IF($A24="","",IF(ISERROR(FIND(".",INDEX(Tasks!$A:$A,$A24))),""," ")&INDEX(Tasks!$C:$C,$A24)) | D24: =IF($A24="","",IF(INDEX(Tasks!$D:$D,$A24)="","",INDEX(Tasks!$D:$D,$A24))) | E24: =IF($A24="","",IF(INDEX(Tasks!$E:$E,$A24)="","",INDEX(Tasks!$E:$E,$A24))) | F24: =IF($A24="","",IF(INDEX(Tasks!$F:$F,$A24)="","",INDEX(Tasks!$F:$F,$A24))) | G24: =IF($A24="","",IF(INDEX(Tasks!$H:$H,$A24)="","",INDEX(Tasks!$H:$H,$A24)))
A25: =IFERROR(MATCH($C$2&"|"&(ROW()-4),Tasks!$K$4:$K$403,0)+3,"") | B25: =IF($A25="","",IF(INDEX(Tasks!$A:$A,$A25)="","",INDEX(Tasks!$A:$A,$A25))) | C25: =IF($A25="","",IF(ISERROR(FIND(".",INDEX(Tasks!$A:$A,$A25))),""," ")&INDEX(Tasks!$C:$C,$A25)) | D25: =IF($A25="","",IF(INDEX(Tasks!$D:$D,$A25)="","",INDEX(Tasks!$D:$D,$A25))) | E25: =IF($A25="","",IF(INDEX(Tasks!$E:$E,$A25)="","",INDEX(Tasks!$E:$E,$A25))) | F25: =IF($A25="","",IF(INDEX(Tasks!$F:$F,$A25)="","",INDEX(Tasks!$F:$F,$A25))) | G25: =IF($A25="","",IF(INDEX(Tasks!$H:$H,$A25)="","",INDEX(Tasks!$H:$H,$A25)))
... A124: =IFERROR(MATCH($C$2&"|"&(ROW()-4),Tasks!$K$4:$K$403,0)+3,"") | B124: =IF($A124="","",IF(INDEX(Tasks!$A:$A,$A124)="","",INDEX(Tasks!$A:$A,$A124))) | C124: =IF($A124="","",IF(ISERROR(FIND(".",INDEX(Tasks!$A:$A,$A124))),""," ")&INDEX(Tasks!$C:$C,$A124)) | D124: =IF($A124="","",IF(INDEX(Tasks!$D:$D,$A124)="","",INDEX(Tasks!$D:$D,$A124))) | E124: =IF($A124="","",IF(INDEX(Tasks!$E:$E,$A124)="","",INDEX(Tasks!$E:$E,$A124))) | F124: =IF($A124="","",IF(INDEX(Tasks!$F:$F,$A124)="","",INDEX(Tasks!$F:$F,$A124))) | G124: =IF($A124="","",IF(INDEX(Tasks!$H:$H,$A124)="","",INDEX(Tasks!$H:$H,$A124)))

Sheet GS-SLAM owner
B1: Person
B2: Name: | C2: =People!$A$4 -> GS-SLAM owner | E2: =COUNTIFS(Tasks!$D$4:$D$403,$C$2,Tasks!$C$4:$C$403,"?*")&" tasks · "&COUNTIFS(Tasks!$D$4:$D$403,$C$2,Tasks!$C$4:$C$403,"?*",Tasks!$E$4:$E$403,"In Progress")&" in progress · "&COUNTIFS(Tasks!$D$4:$D$403,$C$2,Tasks!$C$4:$C$403,"?*",Tasks!$E$4:$E$403,"Blocked")&" blocked · "&COUNTIFS(Tasks!$D$4:$D$403,$C$2,Tasks!$C$4:$C$403,"?*",Tasks!$H$4:$H$403,"<"&TODAY(),Tasks!$E$4:$E$403,"<>Complete")&" overdue" -> 8 tasks · 0 in progress · 0 blocked · 2 overdue
A4: Tasks row | B4: ID | C4: Task | D4: Goal | E4: Status | F4: Start | G4: End | H4: =Gantt!$C$3+7*0 -> 46195 | I4: =Gantt!$C$3+7*1 -> 46202 | J4: =Gantt!$C$3+7*2 -> 46209 | K4: =Gantt!$C$3+7*3 -> 46216 | L4: =Gantt!$C$3+7*4 -> 46223 | M4: =Gantt!$C$3+7*5 -> 46230 | N4: =Gantt!$C$3+7*6 -> 46237 | O4: =Gantt!$C$3+7*7 -> 46244 | P4: =Gantt!$C$3+7*8 -> 46251 | Q4: =Gantt!$C$3+7*9 -> 46258 | R4: =Gantt!$C$3+7*10 -> 46265 | S4: =Gantt!$C$3+7*11 -> 46272 | T4: =Gantt!$C$3+7*12 -> 46279 | U4: =Gantt!$C$3+7*13 -> 46286 | V4: =Gantt!$C$3+7*14 -> 46293 | W4: =Gantt!$C$3+7*15 -> 46300 | X4: =Gantt!$C$3+7*16 -> 46307 | Y4: =Gantt!$C$3+7*17 -> 46314 | Z4: =Gantt!$C$3+7*18 -> 46321 | AA4: =Gantt!$C$3+7*19 -> 46328 | AB4: =Gantt!$C$3+7*20 -> 46335 | AC4: =Gantt!$C$3+7*21 -> 46342 | AD4: =Gantt!$C$3+7*22 -> 46349 | AE4: =Gantt!$C$3+7*23 -> 46356 | AF4: =Gantt!$C$3+7*24 -> 46363 | AG4: =Gantt!$C$3+7*25 -> 46370 | AH4: =Gantt!$C$3+7*26 -> 46377 | AI4: =Gantt!$C$3+7*27 -> 46384 | AJ4: =Gantt!$C$3+7*28 -> 46391 | AK4: =Gantt!$C$3+7*29 -> 46398 | AL4: =Gantt!$C$3+7*30 -> 46405 | AM4: =Gantt!$C$3+7*31 -> 46412 | AN4: =Gantt!$C$3+7*32 -> 46419 | AO4: =Gantt!$C$3+7*33 -> 46426 | AP4: =Gantt!$C$3+7*34 -> 46433 | AQ4: =Gantt!$C$3+7*35 -> 46440 | AR4: =Gantt!$C$3+7*36 -> 46447 | AS4: =Gantt!$C$3+7*37 -> 46454 | AT4: =Gantt!$C$3+7*38 -> 46461 | AU4: =Gantt!$C$3+7*39 -> 46468 | AV4: =Gantt!$C$3+7*40 -> 46475 | AW4: =Gantt!$C$3+7*41 -> 46482 | AX4: =Gantt!$C$3+7*42 -> 46489 | AY4: =Gantt!$C$3+7*43 -> 46496 | BB4: Legend
A5: =IFERROR(MATCH($C$2&"|"&(ROW()-4),Tasks!$J$4:$J$403,0)+3,"") -> 50 | B5: =IF($A5="","",IF(INDEX(Tasks!$A:$A,$A5)="","",INDEX(Tasks!$A:$A,$A5))) -> G1-GS-1 | C5: =IF($A5="","",IF(ISERROR(FIND(".",INDEX(Tasks!$A:$A,$A5))),""," ")&INDEX(Tasks!$C:$C,$A5)) -> Metric prior | D5: =IF($A5="","",IF(INDEX(Tasks!$B:$B,$A5)="","",INDEX(Tasks!$B:$B,$A5))) -> G1 ED305 live digital twin | E5: =IF($A5="","",IF(INDEX(Tasks!$E:$E,$A5)="","",INDEX(Tasks!$E:$E,$A5))) -> Not Started | F5: =IF($A5="","",IF(INDEX(Tasks!$F:$F,$A5)="","",INDEX(Tasks!$F:$F,$A5))) -> 46307 | G5: =IF($A5="","",IF(INDEX(Tasks!$H:$H,$A5)="","",INDEX(Tasks!$H:$H,$A5))) -> 46318 | BB5: Complete
A6: =IFERROR(MATCH($C$2&"|"&(ROW()-4),Tasks!$J$4:$J$403,0)+3,"") -> 51 | B6: =IF($A6="","",IF(INDEX(Tasks!$A:$A,$A6)="","",INDEX(Tasks!$A:$A,$A6))) -> G1-GS-2 | C6: =IF($A6="","",IF(ISERROR(FIND(".",INDEX(Tasks!$A:$A,$A6))),""," ")&INDEX(Tasks!$C:$C,$A6)) -> Tracking + keyframe gate | D6: =IF($A6="","",IF(INDEX(Tasks!$B:$B,$A6)="","",INDEX(Tasks!$B:$B,$A6))) -> G1 ED305 live digital twin | E6: =IF($A6="","",IF(INDEX(Tasks!$E:$E,$A6)="","",INDEX(Tasks!$E:$E,$A6))) -> Not Started | F6: =IF($A6="","",IF(INDEX(Tasks!$F:$F,$A6)="","",INDEX(Tasks!$F:$F,$A6))) -> 46314 | G6: =IF($A6="","",IF(INDEX(Tasks!$H:$H,$A6)="","",INDEX(Tasks!$H:$H,$A6))) -> 46339 | BB6: In Progress
A7: =IFERROR(MATCH($C$2&"|"&(ROW()-4),Tasks!$J$4:$J$403,0)+3,"") -> 52 | B7: =IF($A7="","",IF(INDEX(Tasks!$A:$A,$A7)="","",INDEX(Tasks!$A:$A,$A7))) -> G1-GS-3 | C7: =IF($A7="","",IF(ISERROR(FIND(".",INDEX(Tasks!$A:$A,$A7))),""," ")&INDEX(Tasks!$C:$C,$A7)) -> Mapping + loop closure | D7: =IF($A7="","",IF(INDEX(Tasks!$B:$B,$A7)="","",INDEX(Tasks!$B:$B,$A7))) -> G1 ED305 live digital twin | E7: =IF($A7="","",IF(INDEX(Tasks!$E:$E,$A7)="","",INDEX(Tasks!$E:$E,$A7))) -> Not Started | F7: =IF($A7="","",IF(INDEX(Tasks!$F:$F,$A7)="","",INDEX(Tasks!$F:$F,$A7))) -> 46328 | G7: =IF($A7="","",IF(INDEX(Tasks!$H:$H,$A7)="","",INDEX(Tasks!$H:$H,$A7))) -> 46353 | BB7: Partially Completed
A8: =IFERROR(MATCH($C$2&"|"&(ROW()-4),Tasks!$J$4:$J$403,0)+3,"") -> 53 | B8: =IF($A8="","",IF(INDEX(Tasks!$A:$A,$A8)="","",INDEX(Tasks!$A:$A,$A8))) -> G1-GS-3.1 | C8: =IF($A8="","",IF(ISERROR(FIND(".",INDEX(Tasks!$A:$A,$A8))),""," ")&INDEX(Tasks!$C:$C,$A8)) -> Dynamic-Object Filter (Pre-Registration) | D8: =IF($A8="","",IF(INDEX(Tasks!$B:$B,$A8)="","",INDEX(Tasks!$B:$B,$A8))) -> G1 ED305 live digital twin | E8: =IF($A8="","",IF(INDEX(Tasks!$E:$E,$A8)="","",INDEX(Tasks!$E:$E,$A8))) -> Not Started | F8: =IF($A8="","",IF(INDEX(Tasks!$F:$F,$A8)="","",INDEX(Tasks!$F:$F,$A8))) -> 46202 | G8: =IF($A8="","",IF(INDEX(Tasks!$H:$H,$A8)="","",INDEX(Tasks!$H:$H,$A8))) -> 46206 | BB8: Blocked
A9: =IFERROR(MATCH($C$2&"|"&(ROW()-4),Tasks!$J$4:$J$403,0)+3,"") -> 54 | B9: =IF($A9="","",IF(INDEX(Tasks!$A:$A,$A9)="","",INDEX(Tasks!$A:$A,$A9))) -> G1-GS-3.2 | C9: =IF($A9="","",IF(ISERROR(FIND(".",INDEX(Tasks!$A:$A,$A9))),""," ")&INDEX(Tasks!$C:$C,$A9)) -> Static Point Cloud Registration | D9: =IF($A9="","",IF(INDEX(Tasks!$B:$B,$A9)="","",INDEX(Tasks!$B:$B,$A9))) -> G1 ED305 live digital twin | E9: =IF($A9="","",IF(INDEX(Tasks!$E:$E,$A9)="","",INDEX(Tasks!$E:$E,$A9))) -> Not Started | F9: =IF($A9="","",IF(INDEX(Tasks!$F:$F,$A9)="","",INDEX(Tasks!$F:$F,$A9))) -> 46202 | G9: =IF($A9="","",IF(INDEX(Tasks!$H:$H,$A9)="","",INDEX(Tasks!$H:$H,$A9))) -> 46206 | BB9: Not Started
A10: =IFERROR(MATCH($C$2&"|"&(ROW()-4),Tasks!$J$4:$J$403,0)+3,"") -> 55 | B10: =IF($A10="","",IF(INDEX(Tasks!$A:$A,$A10)="","",INDEX(Tasks!$A:$A,$A10))) -> G1-GS-4 | C10: =IF($A10="","",IF(ISERROR(FIND(".",INDEX(Tasks!$A:$A,$A10))),""," ")&INDEX(Tasks!$C:$C,$A10)) -> Real-time budget | D10: =IF($A10="","",IF(INDEX(Tasks!$B:$B,$A10)="","",INDEX(Tasks!$B:$B,$A10))) -> G1 ED305 live digital twin | E10: =IF($A10="","",IF(INDEX(Tasks!$E:$E,$A10)="","",INDEX(Tasks!$E:$E,$A10))) -> Not Started | F10: =IF($A10="","",IF(INDEX(Tasks!$F:$F,$A10)="","",INDEX(Tasks!$F:$F,$A10))) -> 46349 | G10: =IF($A10="","",IF(INDEX(Tasks!$H:$H,$A10)="","",INDEX(Tasks!$H:$H,$A10))) -> 46360 | BB10: Milestone
A11: =IFERROR(MATCH($C$2&"|"&(ROW()-4),Tasks!$J$4:$J$403,0)+3,"") -> 56 | B11: =IF($A11="","",IF(INDEX(Tasks!$A:$A,$A11)="","",INDEX(Tasks!$A:$A,$A11))) -> G1-GS-5 | C11: =IF($A11="","",IF(ISERROR(FIND(".",INDEX(Tasks!$A:$A,$A11))),""," ")&INDEX(Tasks!$C:$C,$A11)) -> Map fusion (multi-robot) | D11: =IF($A11="","",IF(INDEX(Tasks!$B:$B,$A11)="","",INDEX(Tasks!$B:$B,$A11))) -> G1 ED305 live digital twin | E11: =IF($A11="","",IF(INDEX(Tasks!$E:$E,$A11)="","",INDEX(Tasks!$E:$E,$A11))) -> Not Started | F11: =IF($A11="","",IF(INDEX(Tasks!$F:$F,$A11)="","",INDEX(Tasks!$F:$F,$A11))) -> 46356 | G11: =IF($A11="","",IF(INDEX(Tasks!$H:$H,$A11)="","",INDEX(Tasks!$H:$H,$A11))) -> 46381 | BB11: Today's week
A12: =IFERROR(MATCH($C$2&"|"&(ROW()-4),Tasks!$J$4:$J$403,0)+3,"") -> 57 | B12: =IF($A12="","",IF(INDEX(Tasks!$A:$A,$A12)="","",INDEX(Tasks!$A:$A,$A12))) -> G1-GS-6 | C12: =IF($A12="","",IF(ISERROR(FIND(".",INDEX(Tasks!$A:$A,$A12))),""," ")&INDEX(Tasks!$C:$C,$A12)) -> Evaluation | D12: =IF($A12="","",IF(INDEX(Tasks!$B:$B,$A12)="","",INDEX(Tasks!$B:$B,$A12))) -> G1 ED305 live digital twin | E12: =IF($A12="","",IF(INDEX(Tasks!$E:$E,$A12)="","",INDEX(Tasks!$E:$E,$A12))) -> Not Started | F12: =IF($A12="","",IF(INDEX(Tasks!$F:$F,$A12)="","",INDEX(Tasks!$F:$F,$A12))) -> 46377 | G12: =IF($A12="","",IF(INDEX(Tasks!$H:$H,$A12)="","",INDEX(Tasks!$H:$H,$A12))) -> 46388
A13: =IFERROR(MATCH($C$2&"|"&(ROW()-4),Tasks!$J$4:$J$403,0)+3,"") | B13: =IF($A13="","",IF(INDEX(Tasks!$A:$A,$A13)="","",INDEX(Tasks!$A:$A,$A13))) | C13: =IF($A13="","",IF(ISERROR(FIND(".",INDEX(Tasks!$A:$A,$A13))),""," ")&INDEX(Tasks!$C:$C,$A13)) | D13: =IF($A13="","",IF(INDEX(Tasks!$B:$B,$A13)="","",INDEX(Tasks!$B:$B,$A13))) | E13: =IF($A13="","",IF(INDEX(Tasks!$E:$E,$A13)="","",INDEX(Tasks!$E:$E,$A13))) | F13: =IF($A13="","",IF(INDEX(Tasks!$F:$F,$A13)="","",INDEX(Tasks!$F:$F,$A13))) | G13: =IF($A13="","",IF(INDEX(Tasks!$H:$H,$A13)="","",INDEX(Tasks!$H:$H,$A13))) | BB13: Red End = overdue
A14: =IFERROR(MATCH($C$2&"|"&(ROW()-4),Tasks!$J$4:$J$403,0)+3,"") | B14: =IF($A14="","",IF(INDEX(Tasks!$A:$A,$A14)="","",INDEX(Tasks!$A:$A,$A14))) | C14: =IF($A14="","",IF(ISERROR(FIND(".",INDEX(Tasks!$A:$A,$A14))),""," ")&INDEX(Tasks!$C:$C,$A14)) | D14: =IF($A14="","",IF(INDEX(Tasks!$B:$B,$A14)="","",INDEX(Tasks!$B:$B,$A14))) | E14: =IF($A14="","",IF(INDEX(Tasks!$E:$E,$A14)="","",INDEX(Tasks!$E:$E,$A14))) | F14: =IF($A14="","",IF(INDEX(Tasks!$F:$F,$A14)="","",INDEX(Tasks!$F:$F,$A14))) | G14: =IF($A14="","",IF(INDEX(Tasks!$H:$H,$A14)="","",INDEX(Tasks!$H:$H,$A14)))
A15: =IFERROR(MATCH($C$2&"|"&(ROW()-4),Tasks!$J$4:$J$403,0)+3,"") | B15: =IF($A15="","",IF(INDEX(Tasks!$A:$A,$A15)="","",INDEX(Tasks!$A:$A,$A15))) | C15: =IF($A15="","",IF(ISERROR(FIND(".",INDEX(Tasks!$A:$A,$A15))),""," ")&INDEX(Tasks!$C:$C,$A15)) | D15: =IF($A15="","",IF(INDEX(Tasks!$B:$B,$A15)="","",INDEX(Tasks!$B:$B,$A15))) | E15: =IF($A15="","",IF(INDEX(Tasks!$E:$E,$A15)="","",INDEX(Tasks!$E:$E,$A15))) | F15: =IF($A15="","",IF(INDEX(Tasks!$F:$F,$A15)="","",INDEX(Tasks!$F:$F,$A15))) | G15: =IF($A15="","",IF(INDEX(Tasks!$H:$H,$A15)="","",INDEX(Tasks!$H:$H,$A15)))
A16: =IFERROR(MATCH($C$2&"|"&(ROW()-4),Tasks!$J$4:$J$403,0)+3,"") | B16: =IF($A16="","",IF(INDEX(Tasks!$A:$A,$A16)="","",INDEX(Tasks!$A:$A,$A16))) | C16: =IF($A16="","",IF(ISERROR(FIND(".",INDEX(Tasks!$A:$A,$A16))),""," ")&INDEX(Tasks!$C:$C,$A16)) | D16: =IF($A16="","",IF(INDEX(Tasks!$B:$B,$A16)="","",INDEX(Tasks!$B:$B,$A16))) | E16: =IF($A16="","",IF(INDEX(Tasks!$E:$E,$A16)="","",INDEX(Tasks!$E:$E,$A16))) | F16: =IF($A16="","",IF(INDEX(Tasks!$F:$F,$A16)="","",INDEX(Tasks!$F:$F,$A16))) | G16: =IF($A16="","",IF(INDEX(Tasks!$H:$H,$A16)="","",INDEX(Tasks!$H:$H,$A16)))
A17: =IFERROR(MATCH($C$2&"|"&(ROW()-4),Tasks!$J$4:$J$403,0)+3,"") | B17: =IF($A17="","",IF(INDEX(Tasks!$A:$A,$A17)="","",INDEX(Tasks!$A:$A,$A17))) | C17: =IF($A17="","",IF(ISERROR(FIND(".",INDEX(Tasks!$A:$A,$A17))),""," ")&INDEX(Tasks!$C:$C,$A17)) | D17: =IF($A17="","",IF(INDEX(Tasks!$B:$B,$A17)="","",INDEX(Tasks!$B:$B,$A17))) | E17: =IF($A17="","",IF(INDEX(Tasks!$E:$E,$A17)="","",INDEX(Tasks!$E:$E,$A17))) | F17: =IF($A17="","",IF(INDEX(Tasks!$F:$F,$A17)="","",INDEX(Tasks!$F:$F,$A17))) | G17: =IF($A17="","",IF(INDEX(Tasks!$H:$H,$A17)="","",INDEX(Tasks!$H:$H,$A17)))
A18: =IFERROR(MATCH($C$2&"|"&(ROW()-4),Tasks!$J$4:$J$403,0)+3,"") | B18: =IF($A18="","",IF(INDEX(Tasks!$A:$A,$A18)="","",INDEX(Tasks!$A:$A,$A18))) | C18: =IF($A18="","",IF(ISERROR(FIND(".",INDEX(Tasks!$A:$A,$A18))),""," ")&INDEX(Tasks!$C:$C,$A18)) | D18: =IF($A18="","",IF(INDEX(Tasks!$B:$B,$A18)="","",INDEX(Tasks!$B:$B,$A18))) | E18: =IF($A18="","",IF(INDEX(Tasks!$E:$E,$A18)="","",INDEX(Tasks!$E:$E,$A18))) | F18: =IF($A18="","",IF(INDEX(Tasks!$F:$F,$A18)="","",INDEX(Tasks!$F:$F,$A18))) | G18: =IF($A18="","",IF(INDEX(Tasks!$H:$H,$A18)="","",INDEX(Tasks!$H:$H,$A18)))
A19: =IFERROR(MATCH($C$2&"|"&(ROW()-4),Tasks!$J$4:$J$403,0)+3,"") | B19: =IF($A19="","",IF(INDEX(Tasks!$A:$A,$A19)="","",INDEX(Tasks!$A:$A,$A19))) | C19: =IF($A19="","",IF(ISERROR(FIND(".",INDEX(Tasks!$A:$A,$A19))),""," ")&INDEX(Tasks!$C:$C,$A19)) | D19: =IF($A19="","",IF(INDEX(Tasks!$B:$B,$A19)="","",INDEX(Tasks!$B:$B,$A19))) | E19: =IF($A19="","",IF(INDEX(Tasks!$E:$E,$A19)="","",INDEX(Tasks!$E:$E,$A19))) | F19: =IF($A19="","",IF(INDEX(Tasks!$F:$F,$A19)="","",INDEX(Tasks!$F:$F,$A19))) | G19: =IF($A19="","",IF(INDEX(Tasks!$H:$H,$A19)="","",INDEX(Tasks!$H:$H,$A19)))
A20: =IFERROR(MATCH($C$2&"|"&(ROW()-4),Tasks!$J$4:$J$403,0)+3,"") | B20: =IF($A20="","",IF(INDEX(Tasks!$A:$A,$A20)="","",INDEX(Tasks!$A:$A,$A20))) | C20: =IF($A20="","",IF(ISERROR(FIND(".",INDEX(Tasks!$A:$A,$A20))),""," ")&INDEX(Tasks!$C:$C,$A20)) | D20: =IF($A20="","",IF(INDEX(Tasks!$B:$B,$A20)="","",INDEX(Tasks!$B:$B,$A20))) | E20: =IF($A20="","",IF(INDEX(Tasks!$E:$E,$A20)="","",INDEX(Tasks!$E:$E,$A20))) | F20: =IF($A20="","",IF(INDEX(Tasks!$F:$F,$A20)="","",INDEX(Tasks!$F:$F,$A20))) | G20: =IF($A20="","",IF(INDEX(Tasks!$H:$H,$A20)="","",INDEX(Tasks!$H:$H,$A20)))
A21: =IFERROR(MATCH($C$2&"|"&(ROW()-4),Tasks!$J$4:$J$403,0)+3,"") | B21: =IF($A21="","",IF(INDEX(Tasks!$A:$A,$A21)="","",INDEX(Tasks!$A:$A,$A21))) | C21: =IF($A21="","",IF(ISERROR(FIND(".",INDEX(Tasks!$A:$A,$A21))),""," ")&INDEX(Tasks!$C:$C,$A21)) | D21: =IF($A21="","",IF(INDEX(Tasks!$B:$B,$A21)="","",INDEX(Tasks!$B:$B,$A21))) | E21: =IF($A21="","",IF(INDEX(Tasks!$E:$E,$A21)="","",INDEX(Tasks!$E:$E,$A21))) | F21: =IF($A21="","",IF(INDEX(Tasks!$F:$F,$A21)="","",INDEX(Tasks!$F:$F,$A21))) | G21: =IF($A21="","",IF(INDEX(Tasks!$H:$H,$A21)="","",INDEX(Tasks!$H:$H,$A21)))
A22: =IFERROR(MATCH($C$2&"|"&(ROW()-4),Tasks!$J$4:$J$403,0)+3,"") | B22: =IF($A22="","",IF(INDEX(Tasks!$A:$A,$A22)="","",INDEX(Tasks!$A:$A,$A22))) | C22: =IF($A22="","",IF(ISERROR(FIND(".",INDEX(Tasks!$A:$A,$A22))),""," ")&INDEX(Tasks!$C:$C,$A22)) | D22: =IF($A22="","",IF(INDEX(Tasks!$B:$B,$A22)="","",INDEX(Tasks!$B:$B,$A22))) | E22: =IF($A22="","",IF(INDEX(Tasks!$E:$E,$A22)="","",INDEX(Tasks!$E:$E,$A22))) | F22: =IF($A22="","",IF(INDEX(Tasks!$F:$F,$A22)="","",INDEX(Tasks!$F:$F,$A22))) | G22: =IF($A22="","",IF(INDEX(Tasks!$H:$H,$A22)="","",INDEX(Tasks!$H:$H,$A22)))
A23: =IFERROR(MATCH($C$2&"|"&(ROW()-4),Tasks!$J$4:$J$403,0)+3,"") | B23: =IF($A23="","",IF(INDEX(Tasks!$A:$A,$A23)="","",INDEX(Tasks!$A:$A,$A23))) | C23: =IF($A23="","",IF(ISERROR(FIND(".",INDEX(Tasks!$A:$A,$A23))),""," ")&INDEX(Tasks!$C:$C,$A23)) | D23: =IF($A23="","",IF(INDEX(Tasks!$B:$B,$A23)="","",INDEX(Tasks!$B:$B,$A23))) | E23: =IF($A23="","",IF(INDEX(Tasks!$E:$E,$A23)="","",INDEX(Tasks!$E:$E,$A23))) | F23: =IF($A23="","",IF(INDEX(Tasks!$F:$F,$A23)="","",INDEX(Tasks!$F:$F,$A23))) | G23: =IF($A23="","",IF(INDEX(Tasks!$H:$H,$A23)="","",INDEX(Tasks!$H:$H,$A23)))
A24: =IFERROR(MATCH($C$2&"|"&(ROW()-4),Tasks!$J$4:$J$403,0)+3,"") | B24: =IF($A24="","",IF(INDEX(Tasks!$A:$A,$A24)="","",INDEX(Tasks!$A:$A,$A24))) | C24: =IF($A24="","",IF(ISERROR(FIND(".",INDEX(Tasks!$A:$A,$A24))),""," ")&INDEX(Tasks!$C:$C,$A24)) | D24: =IF($A24="","",IF(INDEX(Tasks!$B:$B,$A24)="","",INDEX(Tasks!$B:$B,$A24))) | E24: =IF($A24="","",IF(INDEX(Tasks!$E:$E,$A24)="","",INDEX(Tasks!$E:$E,$A24))) | F24: =IF($A24="","",IF(INDEX(Tasks!$F:$F,$A24)="","",INDEX(Tasks!$F:$F,$A24))) | G24: =IF($A24="","",IF(INDEX(Tasks!$H:$H,$A24)="","",INDEX(Tasks!$H:$H,$A24)))
A25: =IFERROR(MATCH($C$2&"|"&(ROW()-4),Tasks!$J$4:$J$403,0)+3,"") | B25: =IF($A25="","",IF(INDEX(Tasks!$A:$A,$A25)="","",INDEX(Tasks!$A:$A,$A25))) | C25: =IF($A25="","",IF(ISERROR(FIND(".",INDEX(Tasks!$A:$A,$A25))),""," ")&INDEX(Tasks!$C:$C,$A25)) | D25: =IF($A25="","",IF(INDEX(Tasks!$B:$B,$A25)="","",INDEX(Tasks!$B:$B,$A25))) | E25: =IF($A25="","",IF(INDEX(Tasks!$E:$E,$A25)="","",INDEX(Tasks!$E:$E,$A25))) | F25: =IF($A25="","",IF(INDEX(Tasks!$F:$F,$A25)="","",INDEX(Tasks!$F:$F,$A25))) | G25: =IF($A25="","",IF(INDEX(Tasks!$H:$H,$A25)="","",INDEX(Tasks!$H:$H,$A25)))
... A124: =IFERROR(MATCH($C$2&"|"&(ROW()-4),Tasks!$J$4:$J$403,0)+3,"") | B124: =IF($A124="","",IF(INDEX(Tasks!$A:$A,$A124)="","",INDEX(Tasks!$A:$A,$A124))) | C124: =IF($A124="","",IF(ISERROR(FIND(".",INDEX(Tasks!$A:$A,$A124))),""," ")&INDEX(Tasks!$C:$C,$A124)) | D124: =IF($A124="","",IF(INDEX(Tasks!$B:$B,$A124)="","",INDEX(Tasks!$B:$B,$A124))) | E124: =IF($A124="","",IF(INDEX(Tasks!$E:$E,$A124)="","",INDEX(Tasks!$E:$E,$A124))) | F124: =IF($A124="","",IF(INDEX(Tasks!$F:$F,$A124)="","",INDEX(Tasks!$F:$F,$A124))) | G124: =IF($A124="","",IF(INDEX(Tasks!$H:$H,$A124)="","",INDEX(Tasks!$H:$H,$A124)))

Sheet Isaac Sim owner
B1: Person
B2: Name: | C2: =People!$A$5 -> Isaac Sim owner | E2: =COUNTIFS(Tasks!$D$4:$D$403,$C$2,Tasks!$C$4:$C$403,"?*")&" tasks · "&COUNTIFS(Tasks!$D$4:$D$403,$C$2,Tasks!$C$4:$C$403,"?*",Tasks!$E$4:$E$403,"In Progress")&" in progress · "&COUNTIFS(Tasks!$D$4:$D$403,$C$2,Tasks!$C$4:$C$403,"?*",Tasks!$E$4:$E$403,"Blocked")&" blocked · "&COUNTIFS(Tasks!$D$4:$D$403,$C$2,Tasks!$C$4:$C$403,"?*",Tasks!$H$4:$H$403,"<"&TODAY(),Tasks!$E$4:$E$403,"<>Complete")&" overdue" -> 8 tasks · 0 in progress · 0 blocked · 0 overdue
A4: Tasks row | B4: ID | C4: Task | D4: Goal | E4: Status | F4: Start | G4: End | H4: =Gantt!$C$3+7*0 -> 46195 | I4: =Gantt!$C$3+7*1 -> 46202 | J4: =Gantt!$C$3+7*2 -> 46209 | K4: =Gantt!$C$3+7*3 -> 46216 | L4: =Gantt!$C$3+7*4 -> 46223 | M4: =Gantt!$C$3+7*5 -> 46230 | N4: =Gantt!$C$3+7*6 -> 46237 | O4: =Gantt!$C$3+7*7 -> 46244 | P4: =Gantt!$C$3+7*8 -> 46251 | Q4: =Gantt!$C$3+7*9 -> 46258 | R4: =Gantt!$C$3+7*10 -> 46265 | S4: =Gantt!$C$3+7*11 -> 46272 | T4: =Gantt!$C$3+7*12 -> 46279 | U4: =Gantt!$C$3+7*13 -> 46286 | V4: =Gantt!$C$3+7*14 -> 46293 | W4: =Gantt!$C$3+7*15 -> 46300 | X4: =Gantt!$C$3+7*16 -> 46307 | Y4: =Gantt!$C$3+7*17 -> 46314 | Z4: =Gantt!$C$3+7*18 -> 46321 | AA4: =Gantt!$C$3+7*19 -> 46328 | AB4: =Gantt!$C$3+7*20 -> 46335 | AC4: =Gantt!$C$3+7*21 -> 46342 | AD4: =Gantt!$C$3+7*22 -> 46349 | AE4: =Gantt!$C$3+7*23 -> 46356 | AF4: =Gantt!$C$3+7*24 -> 46363 | AG4: =Gantt!$C$3+7*25 -> 46370 | AH4: =Gantt!$C$3+7*26 -> 46377 | AI4: =Gantt!$C$3+7*27 -> 46384 | AJ4: =Gantt!$C$3+7*28 -> 46391 | AK4: =Gantt!$C$3+7*29 -> 46398 | AL4: =Gantt!$C$3+7*30 -> 46405 | AM4: =Gantt!$C$3+7*31 -> 46412 | AN4: =Gantt!$C$3+7*32 -> 46419 | AO4: =Gantt!$C$3+7*33 -> 46426 | AP4: =Gantt!$C$3+7*34 -> 46433 | AQ4: =Gantt!$C$3+7*35 -> 46440 | AR4: =Gantt!$C$3+7*36 -> 46447 | AS4: =Gantt!$C$3+7*37 -> 46454 | AT4: =Gantt!$C$3+7*38 -> 46461 | AU4: =Gantt!$C$3+7*39 -> 46468 | AV4: =Gantt!$C$3+7*40 -> 46475 | AW4: =Gantt!$C$3+7*41 -> 46482 | AX4: =Gantt!$C$3+7*42 -> 46489 | AY4: =Gantt!$C$3+7*43 -> 46496 | BB4: Legend
A5: =IFERROR(MATCH($C$2&"|"&(ROW()-4),Tasks!$J$4:$J$403,0)+3,"") -> 69 | B5: =IF($A5="","",IF(INDEX(Tasks!$A:$A,$A5)="","",INDEX(Tasks!$A:$A,$A5))) -> G1-IS-1 | C5: =IF($A5="","",IF(ISERROR(FIND(".",INDEX(Tasks!$A:$A,$A5))),""," ")&INDEX(Tasks!$C:$C,$A5)) -> ED305 USD stage in the room frame | D5: =IF($A5="","",IF(INDEX(Tasks!$B:$B,$A5)="","",INDEX(Tasks!$B:$B,$A5))) -> G1 ED305 live digital twin | E5: =IF($A5="","",IF(INDEX(Tasks!$E:$E,$A5)="","",INDEX(Tasks!$E:$E,$A5))) -> Not Started | F5: =IF($A5="","",IF(INDEX(Tasks!$F:$F,$A5)="","",INDEX(Tasks!$F:$F,$A5))) -> 46307 | G5: =IF($A5="","",IF(INDEX(Tasks!$H:$H,$A5)="","",INDEX(Tasks!$H:$H,$A5))) -> 46325 | BB5: Complete
A6: =IFERROR(MATCH($C$2&"|"&(ROW()-4),Tasks!$J$4:$J$403,0)+3,"") -> 70 | B6: =IF($A6="","",IF(INDEX(Tasks!$A:$A,$A6)="","",INDEX(Tasks!$A:$A,$A6))) -> G1-IS-2 | C6: =IF($A6="","",IF(ISERROR(FIND(".",INDEX(Tasks!$A:$A,$A6))),""," ")&INDEX(Tasks!$C:$C,$A6)) -> Robot + antenna prims, live pose | D6: =IF($A6="","",IF(INDEX(Tasks!$B:$B,$A6)="","",INDEX(Tasks!$B:$B,$A6))) -> G1 ED305 live digital twin | E6: =IF($A6="","",IF(INDEX(Tasks!$E:$E,$A6)="","",INDEX(Tasks!$E:$E,$A6))) -> Not Started | F6: =IF($A6="","",IF(INDEX(Tasks!$F:$F,$A6)="","",INDEX(Tasks!$F:$F,$A6))) -> 46321 | G6: =IF($A6="","",IF(INDEX(Tasks!$H:$H,$A6)="","",INDEX(Tasks!$H:$H,$A6))) -> 46339 | BB6: In Progress
A7: =IFERROR(MATCH($C$2&"|"&(ROW()-4),Tasks!$J$4:$J$403,0)+3,"") -> 71 | B7: =IF($A7="","",IF(INDEX(Tasks!$A:$A,$A7)="","",INDEX(Tasks!$A:$A,$A7))) -> G1-IS-3 | C7: =IF($A7="","",IF(ISERROR(FIND(".",INDEX(Tasks!$A:$A,$A7))),""," ")&INDEX(Tasks!$C:$C,$A7)) -> Gaussian layer | D7: =IF($A7="","",IF(INDEX(Tasks!$B:$B,$A7)="","",INDEX(Tasks!$B:$B,$A7))) -> G1 ED305 live digital twin | E7: =IF($A7="","",IF(INDEX(Tasks!$E:$E,$A7)="","",INDEX(Tasks!$E:$E,$A7))) -> Not Started | F7: =IF($A7="","",IF(INDEX(Tasks!$F:$F,$A7)="","",INDEX(Tasks!$F:$F,$A7))) -> 46335 | G7: =IF($A7="","",IF(INDEX(Tasks!$H:$H,$A7)="","",INDEX(Tasks!$H:$H,$A7))) -> 46353 | BB7: Partially Completed
A8: =IFERROR(MATCH($C$2&"|"&(ROW()-4),Tasks!$J$4:$J$403,0)+3,"") -> 72 | B8: =IF($A8="","",IF(INDEX(Tasks!$A:$A,$A8)="","",INDEX(Tasks!$A:$A,$A8))) -> G1-IS-4 | C8: =IF($A8="","",IF(ISERROR(FIND(".",INDEX(Tasks!$A:$A,$A8))),""," ")&INDEX(Tasks!$C:$C,$A8)) -> Mesh layer | D8: =IF($A8="","",IF(INDEX(Tasks!$B:$B,$A8)="","",INDEX(Tasks!$B:$B,$A8))) -> G1 ED305 live digital twin | E8: =IF($A8="","",IF(INDEX(Tasks!$E:$E,$A8)="","",INDEX(Tasks!$E:$E,$A8))) -> Not Started | F8: =IF($A8="","",IF(INDEX(Tasks!$F:$F,$A8)="","",INDEX(Tasks!$F:$F,$A8))) -> 46328 | G8: =IF($A8="","",IF(INDEX(Tasks!$H:$H,$A8)="","",INDEX(Tasks!$H:$H,$A8))) -> 46346 | BB8: Blocked
A9: =IFERROR(MATCH($C$2&"|"&(ROW()-4),Tasks!$J$4:$J$403,0)+3,"") -> 73 | B9: =IF($A9="","",IF(INDEX(Tasks!$A:$A,$A9)="","",INDEX(Tasks!$A:$A,$A9))) -> G1-IS-5 | C9: =IF($A9="","",IF(ISERROR(FIND(".",INDEX(Tasks!$A:$A,$A9))),""," ")&INDEX(Tasks!$C:$C,$A9)) -> Expected-view render | D9: =IF($A9="","",IF(INDEX(Tasks!$B:$B,$A9)="","",INDEX(Tasks!$B:$B,$A9))) -> G1 ED305 live digital twin | E9: =IF($A9="","",IF(INDEX(Tasks!$E:$E,$A9)="","",INDEX(Tasks!$E:$E,$A9))) -> Not Started | F9: =IF($A9="","",IF(INDEX(Tasks!$F:$F,$A9)="","",INDEX(Tasks!$F:$F,$A9))) -> 46349 | G9: =IF($A9="","",IF(INDEX(Tasks!$H:$H,$A9)="","",INDEX(Tasks!$H:$H,$A9))) -> 46367 | BB9: Not Started
A10: =IFERROR(MATCH($C$2&"|"&(ROW()-4),Tasks!$J$4:$J$403,0)+3,"") -> 74 | B10: =IF($A10="","",IF(INDEX(Tasks!$A:$A,$A10)="","",INDEX(Tasks!$A:$A,$A10))) -> G1-IS-6 | C10: =IF($A10="","",IF(ISERROR(FIND(".",INDEX(Tasks!$A:$A,$A10))),""," ")&INDEX(Tasks!$C:$C,$A10)) -> Apply live USD edits | D10: =IF($A10="","",IF(INDEX(Tasks!$B:$B,$A10)="","",INDEX(Tasks!$B:$B,$A10))) -> G1 ED305 live digital twin | E10: =IF($A10="","",IF(INDEX(Tasks!$E:$E,$A10)="","",INDEX(Tasks!$E:$E,$A10))) -> Not Started | F10: =IF($A10="","",IF(INDEX(Tasks!$F:$F,$A10)="","",INDEX(Tasks!$F:$F,$A10))) -> 46370 | G10: =IF($A10="","",IF(INDEX(Tasks!$H:$H,$A10)="","",INDEX(Tasks!$H:$H,$A10))) -> 46388 | BB10: Milestone
A11: =IFERROR(MATCH($C$2&"|"&(ROW()-4),Tasks!$J$4:$J$403,0)+3,"") -> 75 | B11: =IF($A11="","",IF(INDEX(Tasks!$A:$A,$A11)="","",INDEX(Tasks!$A:$A,$A11))) -> G1-IS-7 | C11: =IF($A11="","",IF(ISERROR(FIND(".",INDEX(Tasks!$A:$A,$A11))),""," ")&INDEX(Tasks!$C:$C,$A11)) -> Control commands to robots | D11: =IF($A11="","",IF(INDEX(Tasks!$B:$B,$A11)="","",INDEX(Tasks!$B:$B,$A11))) -> G1 ED305 live digital twin | E11: =IF($A11="","",IF(INDEX(Tasks!$E:$E,$A11)="","",INDEX(Tasks!$E:$E,$A11))) -> Not Started | F11: =IF($A11="","",IF(INDEX(Tasks!$F:$F,$A11)="","",INDEX(Tasks!$F:$F,$A11))) -> 46391 | G11: =IF($A11="","",IF(INDEX(Tasks!$H:$H,$A11)="","",INDEX(Tasks!$H:$H,$A11))) -> 46402 | BB11: Today's week
A12: =IFERROR(MATCH($C$2&"|"&(ROW()-4),Tasks!$J$4:$J$403,0)+3,"") -> 76 | B12: =IF($A12="","",IF(INDEX(Tasks!$A:$A,$A12)="","",INDEX(Tasks!$A:$A,$A12))) -> G1-IS-8 | C12: =IF($A12="","",IF(ISERROR(FIND(".",INDEX(Tasks!$A:$A,$A12))),""," ")&INDEX(Tasks!$C:$C,$A12)) -> Export to Sionna | D12: =IF($A12="","",IF(INDEX(Tasks!$B:$B,$A12)="","",INDEX(Tasks!$B:$B,$A12))) -> G1 ED305 live digital twin | E12: =IF($A12="","",IF(INDEX(Tasks!$E:$E,$A12)="","",INDEX(Tasks!$E:$E,$A12))) -> Not Started | F12: =IF($A12="","",IF(INDEX(Tasks!$F:$F,$A12)="","",INDEX(Tasks!$F:$F,$A12))) -> 46356 | G12: =IF($A12="","",IF(INDEX(Tasks!$H:$H,$A12)="","",INDEX(Tasks!$H:$H,$A12))) -> 46367
A13: =IFERROR(MATCH($C$2&"|"&(ROW()-4),Tasks!$J$4:$J$403,0)+3,"") | B13: =IF($A13="","",IF(INDEX(Tasks!$A:$A,$A13)="","",INDEX(Tasks!$A:$A,$A13))) | C13: =IF($A13="","",IF(ISERROR(FIND(".",INDEX(Tasks!$A:$A,$A13))),""," ")&INDEX(Tasks!$C:$C,$A13)) | D13: =IF($A13="","",IF(INDEX(Tasks!$B:$B,$A13)="","",INDEX(Tasks!$B:$B,$A13))) | E13: =IF($A13="","",IF(INDEX(Tasks!$E:$E,$A13)="","",INDEX(Tasks!$E:$E,$A13))) | F13: =IF($A13="","",IF(INDEX(Tasks!$F:$F,$A13)="","",INDEX(Tasks!$F:$F,$A13))) | G13: =IF($A13="","",IF(INDEX(Tasks!$H:$H,$A13)="","",INDEX(Tasks!$H:$H,$A13))) | BB13: Red End = overdue
A14: =IFERROR(MATCH($C$2&"|"&(ROW()-4),Tasks!$J$4:$J$403,0)+3,"") | B14: =IF($A14="","",IF(INDEX(Tasks!$A:$A,$A14)="","",INDEX(Tasks!$A:$A,$A14))) | C14: =IF($A14="","",IF(ISERROR(FIND(".",INDEX(Tasks!$A:$A,$A14))),""," ")&INDEX(Tasks!$C:$C,$A14)) | D14: =IF($A14="","",IF(INDEX(Tasks!$B:$B,$A14)="","",INDEX(Tasks!$B:$B,$A14))) | E14: =IF($A14="","",IF(INDEX(Tasks!$E:$E,$A14)="","",INDEX(Tasks!$E:$E,$A14))) | F14: =IF($A14="","",IF(INDEX(Tasks!$F:$F,$A14)="","",INDEX(Tasks!$F:$F,$A14))) | G14: =IF($A14="","",IF(INDEX(Tasks!$H:$H,$A14)="","",INDEX(Tasks!$H:$H,$A14)))
A15: =IFERROR(MATCH($C$2&"|"&(ROW()-4),Tasks!$J$4:$J$403,0)+3,"") | B15: =IF($A15="","",IF(INDEX(Tasks!$A:$A,$A15)="","",INDEX(Tasks!$A:$A,$A15))) | C15: =IF($A15="","",IF(ISERROR(FIND(".",INDEX(Tasks!$A:$A,$A15))),""," ")&INDEX(Tasks!$C:$C,$A15)) | D15: =IF($A15="","",IF(INDEX(Tasks!$B:$B,$A15)="","",INDEX(Tasks!$B:$B,$A15))) | E15: =IF($A15="","",IF(INDEX(Tasks!$E:$E,$A15)="","",INDEX(Tasks!$E:$E,$A15))) | F15: =IF($A15="","",IF(INDEX(Tasks!$F:$F,$A15)="","",INDEX(Tasks!$F:$F,$A15))) | G15: =IF($A15="","",IF(INDEX(Tasks!$H:$H,$A15)="","",INDEX(Tasks!$H:$H,$A15)))
A16: =IFERROR(MATCH($C$2&"|"&(ROW()-4),Tasks!$J$4:$J$403,0)+3,"") | B16: =IF($A16="","",IF(INDEX(Tasks!$A:$A,$A16)="","",INDEX(Tasks!$A:$A,$A16))) | C16: =IF($A16="","",IF(ISERROR(FIND(".",INDEX(Tasks!$A:$A,$A16))),""," ")&INDEX(Tasks!$C:$C,$A16)) | D16: =IF($A16="","",IF(INDEX(Tasks!$B:$B,$A16)="","",INDEX(Tasks!$B:$B,$A16))) | E16: =IF($A16="","",IF(INDEX(Tasks!$E:$E,$A16)="","",INDEX(Tasks!$E:$E,$A16))) | F16: =IF($A16="","",IF(INDEX(Tasks!$F:$F,$A16)="","",INDEX(Tasks!$F:$F,$A16))) | G16: =IF($A16="","",IF(INDEX(Tasks!$H:$H,$A16)="","",INDEX(Tasks!$H:$H,$A16)))
A17: =IFERROR(MATCH($C$2&"|"&(ROW()-4),Tasks!$J$4:$J$403,0)+3,"") | B17: =IF($A17="","",IF(INDEX(Tasks!$A:$A,$A17)="","",INDEX(Tasks!$A:$A,$A17))) | C17: =IF($A17="","",IF(ISERROR(FIND(".",INDEX(Tasks!$A:$A,$A17))),""," ")&INDEX(Tasks!$C:$C,$A17)) | D17: =IF($A17="","",IF(INDEX(Tasks!$B:$B,$A17)="","",INDEX(Tasks!$B:$B,$A17))) | E17: =IF($A17="","",IF(INDEX(Tasks!$E:$E,$A17)="","",INDEX(Tasks!$E:$E,$A17))) | F17: =IF($A17="","",IF(INDEX(Tasks!$F:$F,$A17)="","",INDEX(Tasks!$F:$F,$A17))) | G17: =IF($A17="","",IF(INDEX(Tasks!$H:$H,$A17)="","",INDEX(Tasks!$H:$H,$A17)))
A18: =IFERROR(MATCH($C$2&"|"&(ROW()-4),Tasks!$J$4:$J$403,0)+3,"") | B18: =IF($A18="","",IF(INDEX(Tasks!$A:$A,$A18)="","",INDEX(Tasks!$A:$A,$A18))) | C18: =IF($A18="","",IF(ISERROR(FIND(".",INDEX(Tasks!$A:$A,$A18))),""," ")&INDEX(Tasks!$C:$C,$A18)) | D18: =IF($A18="","",IF(INDEX(Tasks!$B:$B,$A18)="","",INDEX(Tasks!$B:$B,$A18))) | E18: =IF($A18="","",IF(INDEX(Tasks!$E:$E,$A18)="","",INDEX(Tasks!$E:$E,$A18))) | F18: =IF($A18="","",IF(INDEX(Tasks!$F:$F,$A18)="","",INDEX(Tasks!$F:$F,$A18))) | G18: =IF($A18="","",IF(INDEX(Tasks!$H:$H,$A18)="","",INDEX(Tasks!$H:$H,$A18)))
A19: =IFERROR(MATCH($C$2&"|"&(ROW()-4),Tasks!$J$4:$J$403,0)+3,"") | B19: =IF($A19="","",IF(INDEX(Tasks!$A:$A,$A19)="","",INDEX(Tasks!$A:$A,$A19))) | C19: =IF($A19="","",IF(ISERROR(FIND(".",INDEX(Tasks!$A:$A,$A19))),""," ")&INDEX(Tasks!$C:$C,$A19)) | D19: =IF($A19="","",IF(INDEX(Tasks!$B:$B,$A19)="","",INDEX(Tasks!$B:$B,$A19))) | E19: =IF($A19="","",IF(INDEX(Tasks!$E:$E,$A19)="","",INDEX(Tasks!$E:$E,$A19))) | F19: =IF($A19="","",IF(INDEX(Tasks!$F:$F,$A19)="","",INDEX(Tasks!$F:$F,$A19))) | G19: =IF($A19="","",IF(INDEX(Tasks!$H:$H,$A19)="","",INDEX(Tasks!$H:$H,$A19)))
A20: =IFERROR(MATCH($C$2&"|"&(ROW()-4),Tasks!$J$4:$J$403,0)+3,"") | B20: =IF($A20="","",IF(INDEX(Tasks!$A:$A,$A20)="","",INDEX(Tasks!$A:$A,$A20))) | C20: =IF($A20="","",IF(ISERROR(FIND(".",INDEX(Tasks!$A:$A,$A20))),""," ")&INDEX(Tasks!$C:$C,$A20)) | D20: =IF($A20="","",IF(INDEX(Tasks!$B:$B,$A20)="","",INDEX(Tasks!$B:$B,$A20))) | E20: =IF($A20="","",IF(INDEX(Tasks!$E:$E,$A20)="","",INDEX(Tasks!$E:$E,$A20))) | F20: =IF($A20="","",IF(INDEX(Tasks!$F:$F,$A20)="","",INDEX(Tasks!$F:$F,$A20))) | G20: =IF($A20="","",IF(INDEX(Tasks!$H:$H,$A20)="","",INDEX(Tasks!$H:$H,$A20)))
A21: =IFERROR(MATCH($C$2&"|"&(ROW()-4),Tasks!$J$4:$J$403,0)+3,"") | B21: =IF($A21="","",IF(INDEX(Tasks!$A:$A,$A21)="","",INDEX(Tasks!$A:$A,$A21))) | C21: =IF($A21="","",IF(ISERROR(FIND(".",INDEX(Tasks!$A:$A,$A21))),""," ")&INDEX(Tasks!$C:$C,$A21)) | D21: =IF($A21="","",IF(INDEX(Tasks!$B:$B,$A21)="","",INDEX(Tasks!$B:$B,$A21))) | E21: =IF($A21="","",IF(INDEX(Tasks!$E:$E,$A21)="","",INDEX(Tasks!$E:$E,$A21))) | F21: =IF($A21="","",IF(INDEX(Tasks!$F:$F,$A21)="","",INDEX(Tasks!$F:$F,$A21))) | G21: =IF($A21="","",IF(INDEX(Tasks!$H:$H,$A21)="","",INDEX(Tasks!$H:$H,$A21)))
A22: =IFERROR(MATCH($C$2&"|"&(ROW()-4),Tasks!$J$4:$J$403,0)+3,"") | B22: =IF($A22="","",IF(INDEX(Tasks!$A:$A,$A22)="","",INDEX(Tasks!$A:$A,$A22))) | C22: =IF($A22="","",IF(ISERROR(FIND(".",INDEX(Tasks!$A:$A,$A22))),""," ")&INDEX(Tasks!$C:$C,$A22)) | D22: =IF($A22="","",IF(INDEX(Tasks!$B:$B,$A22)="","",INDEX(Tasks!$B:$B,$A22))) | E22: =IF($A22="","",IF(INDEX(Tasks!$E:$E,$A22)="","",INDEX(Tasks!$E:$E,$A22))) | F22: =IF($A22="","",IF(INDEX(Tasks!$F:$F,$A22)="","",INDEX(Tasks!$F:$F,$A22))) | G22: =IF($A22="","",IF(INDEX(Tasks!$H:$H,$A22)="","",INDEX(Tasks!$H:$H,$A22)))
A23: =IFERROR(MATCH($C$2&"|"&(ROW()-4),Tasks!$J$4:$J$403,0)+3,"") | B23: =IF($A23="","",IF(INDEX(Tasks!$A:$A,$A23)="","",INDEX(Tasks!$A:$A,$A23))) | C23: =IF($A23="","",IF(ISERROR(FIND(".",INDEX(Tasks!$A:$A,$A23))),""," ")&INDEX(Tasks!$C:$C,$A23)) | D23: =IF($A23="","",IF(INDEX(Tasks!$B:$B,$A23)="","",INDEX(Tasks!$B:$B,$A23))) | E23: =IF($A23="","",IF(INDEX(Tasks!$E:$E,$A23)="","",INDEX(Tasks!$E:$E,$A23))) | F23: =IF($A23="","",IF(INDEX(Tasks!$F:$F,$A23)="","",INDEX(Tasks!$F:$F,$A23))) | G23: =IF($A23="","",IF(INDEX(Tasks!$H:$H,$A23)="","",INDEX(Tasks!$H:$H,$A23)))
A24: =IFERROR(MATCH($C$2&"|"&(ROW()-4),Tasks!$J$4:$J$403,0)+3,"") | B24: =IF($A24="","",IF(INDEX(Tasks!$A:$A,$A24)="","",INDEX(Tasks!$A:$A,$A24))) | C24: =IF($A24="","",IF(ISERROR(FIND(".",INDEX(Tasks!$A:$A,$A24))),""," ")&INDEX(Tasks!$C:$C,$A24)) | D24: =IF($A24="","",IF(INDEX(Tasks!$B:$B,$A24)="","",INDEX(Tasks!$B:$B,$A24))) | E24: =IF($A24="","",IF(INDEX(Tasks!$E:$E,$A24)="","",INDEX(Tasks!$E:$E,$A24))) | F24: =IF($A24="","",IF(INDEX(Tasks!$F:$F,$A24)="","",INDEX(Tasks!$F:$F,$A24))) | G24: =IF($A24="","",IF(INDEX(Tasks!$H:$H,$A24)="","",INDEX(Tasks!$H:$H,$A24)))
A25: =IFERROR(MATCH($C$2&"|"&(ROW()-4),Tasks!$J$4:$J$403,0)+3,"") | B25: =IF($A25="","",IF(INDEX(Tasks!$A:$A,$A25)="","",INDEX(Tasks!$A:$A,$A25))) | C25: =IF($A25="","",IF(ISERROR(FIND(".",INDEX(Tasks!$A:$A,$A25))),""," ")&INDEX(Tasks!$C:$C,$A25)) | D25: =IF($A25="","",IF(INDEX(Tasks!$B:$B,$A25)="","",INDEX(Tasks!$B:$B,$A25))) | E25: =IF($A25="","",IF(INDEX(Tasks!$E:$E,$A25)="","",INDEX(Tasks!$E:$E,$A25))) | F25: =IF($A25="","",IF(INDEX(Tasks!$F:$F,$A25)="","",INDEX(Tasks!$F:$F,$A25))) | G25: =IF($A25="","",IF(INDEX(Tasks!$H:$H,$A25)="","",INDEX(Tasks!$H:$H,$A25)))
... A124: =IFERROR(MATCH($C$2&"|"&(ROW()-4),Tasks!$J$4:$J$403,0)+3,"") | B124: =IF($A124="","",IF(INDEX(Tasks!$A:$A,$A124)="","",INDEX(Tasks!$A:$A,$A124))) | C124: =IF($A124="","",IF(ISERROR(FIND(".",INDEX(Tasks!$A:$A,$A124))),""," ")&INDEX(Tasks!$C:$C,$A124)) | D124: =IF($A124="","",IF(INDEX(Tasks!$B:$B,$A124)="","",INDEX(Tasks!$B:$B,$A124))) | E124: =IF($A124="","",IF(INDEX(Tasks!$E:$E,$A124)="","",INDEX(Tasks!$E:$E,$A124))) | F124: =IF($A124="","",IF(INDEX(Tasks!$F:$F,$A124)="","",INDEX(Tasks!$F:$F,$A124))) | G124: =IF($A124="","",IF(INDEX(Tasks!$H:$H,$A124)="","",INDEX(Tasks!$H:$H,$A124)))

Sheet Sensors owner
B1: Person
B2: Name: | C2: =People!$A$6 -> Sensors & platform owner | E2: =COUNTIFS(Tasks!$D$4:$D$403,$C$2,Tasks!$C$4:$C$403,"?*")&" tasks · "&COUNTIFS(Tasks!$D$4:$D$403,$C$2,Tasks!$C$4:$C$403,"?*",Tasks!$E$4:$E$403,"In Progress")&" in progress · "&COUNTIFS(Tasks!$D$4:$D$403,$C$2,Tasks!$C$4:$C$403,"?*",Tasks!$E$4:$E$403,"Blocked")&" blocked · "&COUNTIFS(Tasks!$D$4:$D$403,$C$2,Tasks!$C$4:$C$403,"?*",Tasks!$H$4:$H$403,"<"&TODAY(),Tasks!$E$4:$E$403,"<>Complete")&" overdue" -> 17 tasks · 5 in progress · 1 blocked · 3 overdue
A4: Tasks row | B4: ID | C4: Task | D4: Goal | E4: Status | F4: Start | G4: End | H4: =Gantt!$C$3+7*0 -> 46195 | I4: =Gantt!$C$3+7*1 -> 46202 | J4: =Gantt!$C$3+7*2 -> 46209 | K4: =Gantt!$C$3+7*3 -> 46216 | L4: =Gantt!$C$3+7*4 -> 46223 | M4: =Gantt!$C$3+7*5 -> 46230 | N4: =Gantt!$C$3+7*6 -> 46237 | O4: =Gantt!$C$3+7*7 -> 46244 | P4: =Gantt!$C$3+7*8 -> 46251 | Q4: =Gantt!$C$3+7*9 -> 46258 | R4: =Gantt!$C$3+7*10 -> 46265 | S4: =Gantt!$C$3+7*11 -> 46272 | T4: =Gantt!$C$3+7*12 -> 46279 | U4: =Gantt!$C$3+7*13 -> 46286 | V4: =Gantt!$C$3+7*14 -> 46293 | W4: =Gantt!$C$3+7*15 -> 46300 | X4: =Gantt!$C$3+7*16 -> 46307 | Y4: =Gantt!$C$3+7*17 -> 46314 | Z4: =Gantt!$C$3+7*18 -> 46321 | AA4: =Gantt!$C$3+7*19 -> 46328 | AB4: =Gantt!$C$3+7*20 -> 46335 | AC4: =Gantt!$C$3+7*21 -> 46342 | AD4: =Gantt!$C$3+7*22 -> 46349 | AE4: =Gantt!$C$3+7*23 -> 46356 | AF4: =Gantt!$C$3+7*24 -> 46363 | AG4: =Gantt!$C$3+7*25 -> 46370 | AH4: =Gantt!$C$3+7*26 -> 46377 | AI4: =Gantt!$C$3+7*27 -> 46384 | AJ4: =Gantt!$C$3+7*28 -> 46391 | AK4: =Gantt!$C$3+7*29 -> 46398 | AL4: =Gantt!$C$3+7*30 -> 46405 | AM4: =Gantt!$C$3+7*31 -> 46412 | AN4: =Gantt!$C$3+7*32 -> 46419 | AO4: =Gantt!$C$3+7*33 -> 46426 | AP4: =Gantt!$C$3+7*34 -> 46433 | AQ4: =Gantt!$C$3+7*35 -> 46440 | AR4: =Gantt!$C$3+7*36 -> 46447 | AS4: =Gantt!$C$3+7*37 -> 46454 | AT4: =Gantt!$C$3+7*38 -> 46461 | AU4: =Gantt!$C$3+7*39 -> 46468 | AV4: =Gantt!$C$3+7*40 -> 46475 | AW4: =Gantt!$C$3+7*41 -> 46482 | AX4: =Gantt!$C$3+7*42 -> 46489 | AY4: =Gantt!$C$3+7*43 -> 46496 | BB4: Legend
A5: =IFERROR(MATCH($C$2&"|"&(ROW()-4),Tasks!$J$4:$J$403,0)+3,"") -> 4 | B5: =IF($A5="","",IF(INDEX(Tasks!$A:$A,$A5)="","",INDEX(Tasks!$A:$A,$A5))) -> TB-1 | C5: =IF($A5="","",IF(ISERROR(FIND(".",INDEX(Tasks!$A:$A,$A5))),""," ")&INDEX(Tasks!$C:$C,$A5)) -> Hardware inventory & specs | D5: =IF($A5="","",IF(INDEX(Tasks!$B:$B,$A5)="","",INDEX(Tasks!$B:$B,$A5))) -> Shared SCooP testbed | E5: =IF($A5="","",IF(INDEX(Tasks!$E:$E,$A5)="","",INDEX(Tasks!$E:$E,$A5))) -> Not Started | F5: =IF($A5="","",IF(INDEX(Tasks!$F:$F,$A5)="","",INDEX(Tasks!$F:$F,$A5))) -> 46307 | G5: =IF($A5="","",IF(INDEX(Tasks!$H:$H,$A5)="","",INDEX(Tasks!$H:$H,$A5))) -> 46318 | BB5: Complete
A6: =IFERROR(MATCH($C$2&"|"&(ROW()-4),Tasks!$J$4:$J$403,0)+3,"") -> 5 | B6: =IF($A6="","",IF(INDEX(Tasks!$A:$A,$A6)="","",INDEX(Tasks!$A:$A,$A6))) -> TB-2 | C6: =IF($A6="","",IF(ISERROR(FIND(".",INDEX(Tasks!$A:$A,$A6))),""," ")&INDEX(Tasks!$C:$C,$A6)) -> Sensor calibration (all units) | D6: =IF($A6="","",IF(INDEX(Tasks!$B:$B,$A6)="","",INDEX(Tasks!$B:$B,$A6))) -> Shared SCooP testbed | E6: =IF($A6="","",IF(INDEX(Tasks!$E:$E,$A6)="","",INDEX(Tasks!$E:$E,$A6))) -> In Progress | F6: =IF($A6="","",IF(INDEX(Tasks!$F:$F,$A6)="","",INDEX(Tasks!$F:$F,$A6))) -> 46195 | G6: =IF($A6="","",IF(INDEX(Tasks!$H:$H,$A6)="","",INDEX(Tasks!$H:$H,$A6))) -> 46206 | BB6: In Progress
A7: =IFERROR(MATCH($C$2&"|"&(ROW()-4),Tasks!$J$4:$J$403,0)+3,"") -> 6 | B7: =IF($A7="","",IF(INDEX(Tasks!$A:$A,$A7)="","",INDEX(Tasks!$A:$A,$A7))) -> TB-2.1 | C7: =IF($A7="","",IF(ISERROR(FIND(".",INDEX(Tasks!$A:$A,$A7))),""," ")&INDEX(Tasks!$C:$C,$A7)) -> Sensor Calibration (LiDAR-Camera, LiDAR-IMU, Camera-Radar, Intrinsics, Realsense-Zed, Mobile-Infra Extrinsics) | D7: =IF($A7="","",IF(INDEX(Tasks!$B:$B,$A7)="","",INDEX(Tasks!$B:$B,$A7))) -> Shared SCooP testbed | E7: =IF($A7="","",IF(INDEX(Tasks!$E:$E,$A7)="","",INDEX(Tasks!$E:$E,$A7))) -> In Progress | F7: =IF($A7="","",IF(INDEX(Tasks!$F:$F,$A7)="","",INDEX(Tasks!$F:$F,$A7))) -> 46195 | G7: =IF($A7="","",IF(INDEX(Tasks!$H:$H,$A7)="","",INDEX(Tasks!$H:$H,$A7))) -> 46206 | BB7: Partially Completed
A8: =IFERROR(MATCH($C$2&"|"&(ROW()-4),Tasks!$J$4:$J$403,0)+3,"") -> 7 | B8: =IF($A8="","",IF(INDEX(Tasks!$A:$A,$A8)="","",INDEX(Tasks!$A:$A,$A8))) -> TB-2.2 | C8: =IF($A8="","",IF(ISERROR(FIND(".",INDEX(Tasks!$A:$A,$A8))),""," ")&INDEX(Tasks!$C:$C,$A8)) -> Calibration: LiDAR - Camera | D8: =IF($A8="","",IF(INDEX(Tasks!$B:$B,$A8)="","",INDEX(Tasks!$B:$B,$A8))) -> Shared SCooP testbed | E8: =IF($A8="","",IF(INDEX(Tasks!$E:$E,$A8)="","",INDEX(Tasks!$E:$E,$A8))) | F8: =IF($A8="","",IF(INDEX(Tasks!$F:$F,$A8)="","",INDEX(Tasks!$F:$F,$A8))) | G8: =IF($A8="","",IF(INDEX(Tasks!$H:$H,$A8)="","",INDEX(Tasks!$H:$H,$A8))) | BB8: Blocked
A9: =IFERROR(MATCH($C$2&"|"&(ROW()-4),Tasks!$J$4:$J$403,0)+3,"") -> 8 | B9: =IF($A9="","",IF(INDEX(Tasks!$A:$A,$A9)="","",INDEX(Tasks!$A:$A,$A9))) -> TB-2.3 | C9: =IF($A9="","",IF(ISERROR(FIND(".",INDEX(Tasks!$A:$A,$A9))),""," ")&INDEX(Tasks!$C:$C,$A9)) -> Calibration: LiDAR - IMU | D9: =IF($A9="","",IF(INDEX(Tasks!$B:$B,$A9)="","",INDEX(Tasks!$B:$B,$A9))) -> Shared SCooP testbed | E9: =IF($A9="","",IF(INDEX(Tasks!$E:$E,$A9)="","",INDEX(Tasks!$E:$E,$A9))) | F9: =IF($A9="","",IF(INDEX(Tasks!$F:$F,$A9)="","",INDEX(Tasks!$F:$F,$A9))) | G9: =IF($A9="","",IF(INDEX(Tasks!$H:$H,$A9)="","",INDEX(Tasks!$H:$H,$A9))) | BB9: Not Started
A10: =IFERROR(MATCH($C$2&"|"&(ROW()-4),Tasks!$J$4:$J$403,0)+3,"") -> 9 | B10: =IF($A10="","",IF(INDEX(Tasks!$A:$A,$A10)="","",INDEX(Tasks!$A:$A,$A10))) -> TB-2.4 | C10: =IF($A10="","",IF(ISERROR(FIND(".",INDEX(Tasks!$A:$A,$A10))),""," ")&INDEX(Tasks!$C:$C,$A10)) -> Calibration: RealSense - ZED | D10: =IF($A10="","",IF(INDEX(Tasks!$B:$B,$A10)="","",INDEX(Tasks!$B:$B,$A10))) -> Shared SCooP testbed | E10: =IF($A10="","",IF(INDEX(Tasks!$E:$E,$A10)="","",INDEX(Tasks!$E:$E,$A10))) | F10: =IF($A10="","",IF(INDEX(Tasks!$F:$F,$A10)="","",INDEX(Tasks!$F:$F,$A10))) | G10: =IF($A10="","",IF(INDEX(Tasks!$H:$H,$A10)="","",INDEX(Tasks!$H:$H,$A10))) | BB10: Milestone
A11: =IFERROR(MATCH($C$2&"|"&(ROW()-4),Tasks!$J$4:$J$403,0)+3,"") -> 10 | B11: =IF($A11="","",IF(INDEX(Tasks!$A:$A,$A11)="","",INDEX(Tasks!$A:$A,$A11))) -> TB-2.5 | C11: =IF($A11="","",IF(ISERROR(FIND(".",INDEX(Tasks!$A:$A,$A11))),""," ")&INDEX(Tasks!$C:$C,$A11)) -> Calibration: ZED - Arducam | D11: =IF($A11="","",IF(INDEX(Tasks!$B:$B,$A11)="","",INDEX(Tasks!$B:$B,$A11))) -> Shared SCooP testbed | E11: =IF($A11="","",IF(INDEX(Tasks!$E:$E,$A11)="","",INDEX(Tasks!$E:$E,$A11))) | F11: =IF($A11="","",IF(INDEX(Tasks!$F:$F,$A11)="","",INDEX(Tasks!$F:$F,$A11))) | G11: =IF($A11="","",IF(INDEX(Tasks!$H:$H,$A11)="","",INDEX(Tasks!$H:$H,$A11))) | BB11: Today's week
A12: =IFERROR(MATCH($C$2&"|"&(ROW()-4),Tasks!$J$4:$J$403,0)+3,"") -> 11 | B12: =IF($A12="","",IF(INDEX(Tasks!$A:$A,$A12)="","",INDEX(Tasks!$A:$A,$A12))) -> TB-2.6 | C12: =IF($A12="","",IF(ISERROR(FIND(".",INDEX(Tasks!$A:$A,$A12))),""," ")&INDEX(Tasks!$C:$C,$A12)) -> Calibration: Radars - ZED | D12: =IF($A12="","",IF(INDEX(Tasks!$B:$B,$A12)="","",INDEX(Tasks!$B:$B,$A12))) -> Shared SCooP testbed | E12: =IF($A12="","",IF(INDEX(Tasks!$E:$E,$A12)="","",INDEX(Tasks!$E:$E,$A12))) | F12: =IF($A12="","",IF(INDEX(Tasks!$F:$F,$A12)="","",INDEX(Tasks!$F:$F,$A12))) | G12: =IF($A12="","",IF(INDEX(Tasks!$H:$H,$A12)="","",INDEX(Tasks!$H:$H,$A12)))
A13: =IFERROR(MATCH($C$2&"|"&(ROW()-4),Tasks!$J$4:$J$403,0)+3,"") -> 12 | B13: =IF($A13="","",IF(INDEX(Tasks!$A:$A,$A13)="","",INDEX(Tasks!$A:$A,$A13))) -> TB-3 | C13: =IF($A13="","",IF(ISERROR(FIND(".",INDEX(Tasks!$A:$A,$A13))),""," ")&INDEX(Tasks!$C:$C,$A13)) -> Time sync & TF chain | D13: =IF($A13="","",IF(INDEX(Tasks!$B:$B,$A13)="","",INDEX(Tasks!$B:$B,$A13))) -> Shared SCooP testbed | E13: =IF($A13="","",IF(INDEX(Tasks!$E:$E,$A13)="","",INDEX(Tasks!$E:$E,$A13))) -> In Progress | F13: =IF($A13="","",IF(INDEX(Tasks!$F:$F,$A13)="","",INDEX(Tasks!$F:$F,$A13))) -> 46202 | G13: =IF($A13="","",IF(INDEX(Tasks!$H:$H,$A13)="","",INDEX(Tasks!$H:$H,$A13))) -> 46206 | BB13: Red End = overdue
A14: =IFERROR(MATCH($C$2&"|"&(ROW()-4),Tasks!$J$4:$J$403,0)+3,"") -> 13 | B14: =IF($A14="","",IF(INDEX(Tasks!$A:$A,$A14)="","",INDEX(Tasks!$A:$A,$A14))) -> TB-4 | C14: =IF($A14="","",IF(ISERROR(FIND(".",INDEX(Tasks!$A:$A,$A14))),""," ")&INDEX(Tasks!$C:$C,$A14)) -> Wi-Fi & comms logging | D14: =IF($A14="","",IF(INDEX(Tasks!$B:$B,$A14)="","",INDEX(Tasks!$B:$B,$A14))) -> Shared SCooP testbed | E14: =IF($A14="","",IF(INDEX(Tasks!$E:$E,$A14)="","",INDEX(Tasks!$E:$E,$A14))) -> In Progress | F14: =IF($A14="","",IF(INDEX(Tasks!$F:$F,$A14)="","",INDEX(Tasks!$F:$F,$A14))) -> 46307 | G14: =IF($A14="","",IF(INDEX(Tasks!$H:$H,$A14)="","",INDEX(Tasks!$H:$H,$A14))) -> 46318
A15: =IFERROR(MATCH($C$2&"|"&(ROW()-4),Tasks!$J$4:$J$403,0)+3,"") -> 14 | B15: =IF($A15="","",IF(INDEX(Tasks!$A:$A,$A15)="","",INDEX(Tasks!$A:$A,$A15))) -> TB-5 | C15: =IF($A15="","",IF(ISERROR(FIND(".",INDEX(Tasks!$A:$A,$A15))),""," ")&INDEX(Tasks!$C:$C,$A15)) -> Recording tooling fixes | D15: =IF($A15="","",IF(INDEX(Tasks!$B:$B,$A15)="","",INDEX(Tasks!$B:$B,$A15))) -> Shared SCooP testbed | E15: =IF($A15="","",IF(INDEX(Tasks!$E:$E,$A15)="","",INDEX(Tasks!$E:$E,$A15))) -> Not Started | F15: =IF($A15="","",IF(INDEX(Tasks!$F:$F,$A15)="","",INDEX(Tasks!$F:$F,$A15))) -> 46307 | G15: =IF($A15="","",IF(INDEX(Tasks!$H:$H,$A15)="","",INDEX(Tasks!$H:$H,$A15))) -> 46318
A16: =IFERROR(MATCH($C$2&"|"&(ROW()-4),Tasks!$J$4:$J$403,0)+3,"") -> 44 | B16: =IF($A16="","",IF(INDEX(Tasks!$A:$A,$A16)="","",INDEX(Tasks!$A:$A,$A16))) -> G1-SP-1 | C16: =IF($A16="","",IF(ISERROR(FIND(".",INDEX(Tasks!$A:$A,$A16))),""," ")&INDEX(Tasks!$C:$C,$A16)) -> Sensor rig & TF tree per robot | D16: =IF($A16="","",IF(INDEX(Tasks!$B:$B,$A16)="","",INDEX(Tasks!$B:$B,$A16))) -> G1 ED305 live digital twin | E16: =IF($A16="","",IF(INDEX(Tasks!$E:$E,$A16)="","",INDEX(Tasks!$E:$E,$A16))) -> Not Started | F16: =IF($A16="","",IF(INDEX(Tasks!$F:$F,$A16)="","",INDEX(Tasks!$F:$F,$A16))) -> 46307 | G16: =IF($A16="","",IF(INDEX(Tasks!$H:$H,$A16)="","",INDEX(Tasks!$H:$H,$A16))) -> 46318
A17: =IFERROR(MATCH($C$2&"|"&(ROW()-4),Tasks!$J$4:$J$403,0)+3,"") -> 45 | B17: =IF($A17="","",IF(INDEX(Tasks!$A:$A,$A17)="","",INDEX(Tasks!$A:$A,$A17))) -> G1-SP-2 | C17: =IF($A17="","",IF(ISERROR(FIND(".",INDEX(Tasks!$A:$A,$A17))),""," ")&INDEX(Tasks!$C:$C,$A17)) -> Odometry: front end + fusion filter | D17: =IF($A17="","",IF(INDEX(Tasks!$B:$B,$A17)="","",INDEX(Tasks!$B:$B,$A17))) -> G1 ED305 live digital twin | E17: =IF($A17="","",IF(INDEX(Tasks!$E:$E,$A17)="","",INDEX(Tasks!$E:$E,$A17))) -> Not Started | F17: =IF($A17="","",IF(INDEX(Tasks!$F:$F,$A17)="","",INDEX(Tasks!$F:$F,$A17))) -> 46314 | G17: =IF($A17="","",IF(INDEX(Tasks!$H:$H,$A17)="","",INDEX(Tasks!$H:$H,$A17))) -> 46339
A18: =IFERROR(MATCH($C$2&"|"&(ROW()-4),Tasks!$J$4:$J$403,0)+3,"") -> 46 | B18: =IF($A18="","",IF(INDEX(Tasks!$A:$A,$A18)="","",INDEX(Tasks!$A:$A,$A18))) -> G1-SP-3 | C18: =IF($A18="","",IF(ISERROR(FIND(".",INDEX(Tasks!$A:$A,$A18))),""," ")&INDEX(Tasks!$C:$C,$A18)) -> ED305 camera calibration in the room frame | D18: =IF($A18="","",IF(INDEX(Tasks!$B:$B,$A18)="","",INDEX(Tasks!$B:$B,$A18))) -> G1 ED305 live digital twin | E18: =IF($A18="","",IF(INDEX(Tasks!$E:$E,$A18)="","",INDEX(Tasks!$E:$E,$A18))) -> Blocked | F18: =IF($A18="","",IF(INDEX(Tasks!$F:$F,$A18)="","",INDEX(Tasks!$F:$F,$A18))) -> 46307 | G18: =IF($A18="","",IF(INDEX(Tasks!$H:$H,$A18)="","",INDEX(Tasks!$H:$H,$A18))) -> 46318
A19: =IFERROR(MATCH($C$2&"|"&(ROW()-4),Tasks!$J$4:$J$403,0)+3,"") -> 47 | B19: =IF($A19="","",IF(INDEX(Tasks!$A:$A,$A19)="","",INDEX(Tasks!$A:$A,$A19))) -> G1-SP-4 | C19: =IF($A19="","",IF(ISERROR(FIND(".",INDEX(Tasks!$A:$A,$A19))),""," ")&INDEX(Tasks!$C:$C,$A19)) -> ED305 coverage & camera placement | D19: =IF($A19="","",IF(INDEX(Tasks!$B:$B,$A19)="","",INDEX(Tasks!$B:$B,$A19))) -> G1 ED305 live digital twin | E19: =IF($A19="","",IF(INDEX(Tasks!$E:$E,$A19)="","",INDEX(Tasks!$E:$E,$A19))) -> In Progress | F19: =IF($A19="","",IF(INDEX(Tasks!$F:$F,$A19)="","",INDEX(Tasks!$F:$F,$A19))) -> 46321 | G19: =IF($A19="","",IF(INDEX(Tasks!$H:$H,$A19)="","",INDEX(Tasks!$H:$H,$A19))) -> 46339
A20: =IFERROR(MATCH($C$2&"|"&(ROW()-4),Tasks!$J$4:$J$403,0)+3,"") -> 48 | B20: =IF($A20="","",IF(INDEX(Tasks!$A:$A,$A20)="","",INDEX(Tasks!$A:$A,$A20))) -> G1-SP-5 | C20: =IF($A20="","",IF(ISERROR(FIND(".",INDEX(Tasks!$A:$A,$A20))),""," ")&INDEX(Tasks!$C:$C,$A20)) -> Printed pan-tilt heads | D20: =IF($A20="","",IF(INDEX(Tasks!$B:$B,$A20)="","",INDEX(Tasks!$B:$B,$A20))) -> G1 ED305 live digital twin | E20: =IF($A20="","",IF(INDEX(Tasks!$E:$E,$A20)="","",INDEX(Tasks!$E:$E,$A20))) -> Not Started | F20: =IF($A20="","",IF(INDEX(Tasks!$F:$F,$A20)="","",INDEX(Tasks!$F:$F,$A20))) -> 46314 | G20: =IF($A20="","",IF(INDEX(Tasks!$H:$H,$A20)="","",INDEX(Tasks!$H:$H,$A20))) -> 46332
A21: =IFERROR(MATCH($C$2&"|"&(ROW()-4),Tasks!$J$4:$J$403,0)+3,"") -> 49 | B21: =IF($A21="","",IF(INDEX(Tasks!$A:$A,$A21)="","",INDEX(Tasks!$A:$A,$A21))) -> G1-SP-6 | C21: =IF($A21="","",IF(ISERROR(FIND(".",INDEX(Tasks!$A:$A,$A21))),""," ")&INDEX(Tasks!$C:$C,$A21)) -> ED305 camera time sync | D21: =IF($A21="","",IF(INDEX(Tasks!$B:$B,$A21)="","",INDEX(Tasks!$B:$B,$A21))) -> G1 ED305 live digital twin | E21: =IF($A21="","",IF(INDEX(Tasks!$E:$E,$A21)="","",INDEX(Tasks!$E:$E,$A21))) -> Not Started | F21: =IF($A21="","",IF(INDEX(Tasks!$F:$F,$A21)="","",INDEX(Tasks!$F:$F,$A21))) -> 46321 | G21: =IF($A21="","",IF(INDEX(Tasks!$H:$H,$A21)="","",INDEX(Tasks!$H:$H,$A21))) -> 46332
A22: =IFERROR(MATCH($C$2&"|"&(ROW()-4),Tasks!$J$4:$J$403,0)+3,"") | B22: =IF($A22="","",IF(INDEX(Tasks!$A:$A,$A22)="","",INDEX(Tasks!$A:$A,$A22))) | C22: =IF($A22="","",IF(ISERROR(FIND(".",INDEX(Tasks!$A:$A,$A22))),""," ")&INDEX(Tasks!$C:$C,$A22)) | D22: =IF($A22="","",IF(INDEX(Tasks!$B:$B,$A22)="","",INDEX(Tasks!$B:$B,$A22))) | E22: =IF($A22="","",IF(INDEX(Tasks!$E:$E,$A22)="","",INDEX(Tasks!$E:$E,$A22))) | F22: =IF($A22="","",IF(INDEX(Tasks!$F:$F,$A22)="","",INDEX(Tasks!$F:$F,$A22))) | G22: =IF($A22="","",IF(INDEX(Tasks!$H:$H,$A22)="","",INDEX(Tasks!$H:$H,$A22)))
A23: =IFERROR(MATCH($C$2&"|"&(ROW()-4),Tasks!$J$4:$J$403,0)+3,"") | B23: =IF($A23="","",IF(INDEX(Tasks!$A:$A,$A23)="","",INDEX(Tasks!$A:$A,$A23))) | C23: =IF($A23="","",IF(ISERROR(FIND(".",INDEX(Tasks!$A:$A,$A23))),""," ")&INDEX(Tasks!$C:$C,$A23)) | D23: =IF($A23="","",IF(INDEX(Tasks!$B:$B,$A23)="","",INDEX(Tasks!$B:$B,$A23))) | E23: =IF($A23="","",IF(INDEX(Tasks!$E:$E,$A23)="","",INDEX(Tasks!$E:$E,$A23))) | F23: =IF($A23="","",IF(INDEX(Tasks!$F:$F,$A23)="","",INDEX(Tasks!$F:$F,$A23))) | G23: =IF($A23="","",IF(INDEX(Tasks!$H:$H,$A23)="","",INDEX(Tasks!$H:$H,$A23)))
A24: =IFERROR(MATCH($C$2&"|"&(ROW()-4),Tasks!$J$4:$J$403,0)+3,"") | B24: =IF($A24="","",IF(INDEX(Tasks!$A:$A,$A24)="","",INDEX(Tasks!$A:$A,$A24))) | C24: =IF($A24="","",IF(ISERROR(FIND(".",INDEX(Tasks!$A:$A,$A24))),""," ")&INDEX(Tasks!$C:$C,$A24)) | D24: =IF($A24="","",IF(INDEX(Tasks!$B:$B,$A24)="","",INDEX(Tasks!$B:$B,$A24))) | E24: =IF($A24="","",IF(INDEX(Tasks!$E:$E,$A24)="","",INDEX(Tasks!$E:$E,$A24))) | F24: =IF($A24="","",IF(INDEX(Tasks!$F:$F,$A24)="","",INDEX(Tasks!$F:$F,$A24))) | G24: =IF($A24="","",IF(INDEX(Tasks!$H:$H,$A24)="","",INDEX(Tasks!$H:$H,$A24)))
A25: =IFERROR(MATCH($C$2&"|"&(ROW()-4),Tasks!$J$4:$J$403,0)+3,"") | B25: =IF($A25="","",IF(INDEX(Tasks!$A:$A,$A25)="","",INDEX(Tasks!$A:$A,$A25))) | C25: =IF($A25="","",IF(ISERROR(FIND(".",INDEX(Tasks!$A:$A,$A25))),""," ")&INDEX(Tasks!$C:$C,$A25)) | D25: =IF($A25="","",IF(INDEX(Tasks!$B:$B,$A25)="","",INDEX(Tasks!$B:$B,$A25))) | E25: =IF($A25="","",IF(INDEX(Tasks!$E:$E,$A25)="","",INDEX(Tasks!$E:$E,$A25))) | F25: =IF($A25="","",IF(INDEX(Tasks!$F:$F,$A25)="","",INDEX(Tasks!$F:$F,$A25))) | G25: =IF($A25="","",IF(INDEX(Tasks!$H:$H,$A25)="","",INDEX(Tasks!$H:$H,$A25)))
... A124: =IFERROR(MATCH($C$2&"|"&(ROW()-4),Tasks!$J$4:$J$403,0)+3,"") | B124: =IF($A124="","",IF(INDEX(Tasks!$A:$A,$A124)="","",INDEX(Tasks!$A:$A,$A124))) | C124: =IF($A124="","",IF(ISERROR(FIND(".",INDEX(Tasks!$A:$A,$A124))),""," ")&INDEX(Tasks!$C:$C,$A124)) | D124: =IF($A124="","",IF(INDEX(Tasks!$B:$B,$A124)="","",INDEX(Tasks!$B:$B,$A124))) | E124: =IF($A124="","",IF(INDEX(Tasks!$E:$E,$A124)="","",INDEX(Tasks!$E:$E,$A124))) | F124: =IF($A124="","",IF(INDEX(Tasks!$F:$F,$A124)="","",INDEX(Tasks!$F:$F,$A124))) | G124: =IF($A124="","",IF(INDEX(Tasks!$H:$H,$A124)="","",INDEX(Tasks!$H:$H,$A124)))

Sheet Scene detection owner
B1: Person
B2: Name: | C2: =People!$A$7 -> Scene detection owner | E2: =COUNTIFS(Tasks!$D$4:$D$403,$C$2,Tasks!$C$4:$C$403,"?*")&" tasks · "&COUNTIFS(Tasks!$D$4:$D$403,$C$2,Tasks!$C$4:$C$403,"?*",Tasks!$E$4:$E$403,"In Progress")&" in progress · "&COUNTIFS(Tasks!$D$4:$D$403,$C$2,Tasks!$C$4:$C$403,"?*",Tasks!$E$4:$E$403,"Blocked")&" blocked · "&COUNTIFS(Tasks!$D$4:$D$403,$C$2,Tasks!$C$4:$C$403,"?*",Tasks!$H$4:$H$403,"<"&TODAY(),Tasks!$E$4:$E$403,"<>Complete")&" overdue" -> 11 tasks · 0 in progress · 0 blocked · 4 overdue
A4: Tasks row | B4: ID | C4: Task | D4: Goal | E4: Status | F4: Start | G4: End | H4: =Gantt!$C$3+7*0 -> 46195 | I4: =Gantt!$C$3+7*1 -> 46202 | J4: =Gantt!$C$3+7*2 -> 46209 | K4: =Gantt!$C$3+7*3 -> 46216 | L4: =Gantt!$C$3+7*4 -> 46223 | M4: =Gantt!$C$3+7*5 -> 46230 | N4: =Gantt!$C$3+7*6 -> 46237 | O4: =Gantt!$C$3+7*7 -> 46244 | P4: =Gantt!$C$3+7*8 -> 46251 | Q4: =Gantt!$C$3+7*9 -> 46258 | R4: =Gantt!$C$3+7*10 -> 46265 | S4: =Gantt!$C$3+7*11 -> 46272 | T4: =Gantt!$C$3+7*12 -> 46279 | U4: =Gantt!$C$3+7*13 -> 46286 | V4: =Gantt!$C$3+7*14 -> 46293 | W4: =Gantt!$C$3+7*15 -> 46300 | X4: =Gantt!$C$3+7*16 -> 46307 | Y4: =Gantt!$C$3+7*17 -> 46314 | Z4: =Gantt!$C$3+7*18 -> 46321 | AA4: =Gantt!$C$3+7*19 -> 46328 | AB4: =Gantt!$C$3+7*20 -> 46335 | AC4: =Gantt!$C$3+7*21 -> 46342 | AD4: =Gantt!$C$3+7*22 -> 46349 | AE4: =Gantt!$C$3+7*23 -> 46356 | AF4: =Gantt!$C$3+7*24 -> 46363 | AG4: =Gantt!$C$3+7*25 -> 46370 | AH4: =Gantt!$C$3+7*26 -> 46377 | AI4: =Gantt!$C$3+7*27 -> 46384 | AJ4: =Gantt!$C$3+7*28 -> 46391 | AK4: =Gantt!$C$3+7*29 -> 46398 | AL4: =Gantt!$C$3+7*30 -> 46405 | AM4: =Gantt!$C$3+7*31 -> 46412 | AN4: =Gantt!$C$3+7*32 -> 46419 | AO4: =Gantt!$C$3+7*33 -> 46426 | AP4: =Gantt!$C$3+7*34 -> 46433 | AQ4: =Gantt!$C$3+7*35 -> 46440 | AR4: =Gantt!$C$3+7*36 -> 46447 | AS4: =Gantt!$C$3+7*37 -> 46454 | AT4: =Gantt!$C$3+7*38 -> 46461 | AU4: =Gantt!$C$3+7*39 -> 46468 | AV4: =Gantt!$C$3+7*40 -> 46475 | AW4: =Gantt!$C$3+7*41 -> 46482 | AX4: =Gantt!$C$3+7*42 -> 46489 | AY4: =Gantt!$C$3+7*43 -> 46496 | BB4: Legend
A5: =IFERROR(MATCH($C$2&"|"&(ROW()-4),Tasks!$J$4:$J$403,0)+3,"") -> 58 | B5: =IF($A5="","",IF(INDEX(Tasks!$A:$A,$A5)="","",INDEX(Tasks!$A:$A,$A5))) -> G1-SD-1 | C5: =IF($A5="","",IF(ISERROR(FIND(".",INDEX(Tasks!$A:$A,$A5))),""," ")&INDEX(Tasks!$C:$C,$A5)) -> Object asset library | D5: =IF($A5="","",IF(INDEX(Tasks!$B:$B,$A5)="","",INDEX(Tasks!$B:$B,$A5))) -> G1 ED305 live digital twin | E5: =IF($A5="","",IF(INDEX(Tasks!$E:$E,$A5)="","",INDEX(Tasks!$E:$E,$A5))) -> Not Started | F5: =IF($A5="","",IF(INDEX(Tasks!$F:$F,$A5)="","",INDEX(Tasks!$F:$F,$A5))) -> 46307 | G5: =IF($A5="","",IF(INDEX(Tasks!$H:$H,$A5)="","",INDEX(Tasks!$H:$H,$A5))) -> 46325 | BB5: Complete
A6: =IFERROR(MATCH($C$2&"|"&(ROW()-4),Tasks!$J$4:$J$403,0)+3,"") -> 59 | B6: =IF($A6="","",IF(INDEX(Tasks!$A:$A,$A6)="","",INDEX(Tasks!$A:$A,$A6))) -> G1-SD-2 | C6: =IF($A6="","",IF(ISERROR(FIND(".",INDEX(Tasks!$A:$A,$A6))),""," ")&INDEX(Tasks!$C:$C,$A6)) -> Object retrieval from G* | D6: =IF($A6="","",IF(INDEX(Tasks!$B:$B,$A6)="","",INDEX(Tasks!$B:$B,$A6))) -> G1 ED305 live digital twin | E6: =IF($A6="","",IF(INDEX(Tasks!$E:$E,$A6)="","",INDEX(Tasks!$E:$E,$A6))) -> Not Started | F6: =IF($A6="","",IF(INDEX(Tasks!$F:$F,$A6)="","",INDEX(Tasks!$F:$F,$A6))) -> 46328 | G6: =IF($A6="","",IF(INDEX(Tasks!$H:$H,$A6)="","",INDEX(Tasks!$H:$H,$A6))) -> 46353 | BB6: In Progress
A7: =IFERROR(MATCH($C$2&"|"&(ROW()-4),Tasks!$J$4:$J$403,0)+3,"") -> 60 | B7: =IF($A7="","",IF(INDEX(Tasks!$A:$A,$A7)="","",INDEX(Tasks!$A:$A,$A7))) -> G1-SD-2.1 | C7: =IF($A7="","",IF(ISERROR(FIND(".",INDEX(Tasks!$A:$A,$A7))),""," ")&INDEX(Tasks!$C:$C,$A7)) -> Object Detection & Instance Identification (RGB / RGBD / LiDAR / Radar) | D7: =IF($A7="","",IF(INDEX(Tasks!$B:$B,$A7)="","",INDEX(Tasks!$B:$B,$A7))) -> G1 ED305 live digital twin | E7: =IF($A7="","",IF(INDEX(Tasks!$E:$E,$A7)="","",INDEX(Tasks!$E:$E,$A7))) -> Not Started | F7: =IF($A7="","",IF(INDEX(Tasks!$F:$F,$A7)="","",INDEX(Tasks!$F:$F,$A7))) -> 46209 | G7: =IF($A7="","",IF(INDEX(Tasks!$H:$H,$A7)="","",INDEX(Tasks!$H:$H,$A7))) -> 46220 | BB7: Partially Completed
