Workbook

Sheet README
A1: Project tracker: ED305 digital twin, SCooP, dual-link, semantic comm
A2: Built from Project_Tracker.xlsx; old tasks kept with their text, status and weeks.
A4: Sheets
A5: Tasks | B5: Every task, one row each. Edit freely, add rows anywhere inside the table. ID: a row whose ID has no '.' is a parent (shown bold).
A6: Gantt | B6: Automatic: bars come from Tasks Start + Weeks, coloured by Status. Change the Gantt start date in Gantt!C2. Nothing to edit by hand.
A7: Problems | B7: Anything that blocks work for more than a day. Link it to the task it blocks (Task ID) and set that task's Status to Blocked.
A8: Interfaces | B8: One row per hand-off between owners (arrows in the system diagram). Move State from Not defined -> Defined -> Implemented -> Tested.
A9: Weekly Log | B9: Every Friday, one row per person: Done / Next / Blockers (problem IDs).
A10: Runs | B10: One row per pipeline run on the server: run ID, data, git commit, key numbers. The server writes the logs; this sheet indexes them.
A11: Dashboard | B11: Counts by goal, owner and status; overdue tasks; open problems; interface states. All formulas.
A12: Lists | B12: Owner names (fill these in) and the dropdown lists.
A14: What to edit
A15: Yellow cells | B15: Settings and owner names: Gantt!C2 (Gantt start), Lists!B (person per role).
A16: Tasks: Start, Weeks | B16: Start = Monday the task starts; Weeks = length. End is computed (Friday of the last week). Leave both empty if not scheduled.
A17: Grey italic columns | B17: Formulas (Person, End). Do not type over them.
A19: Assumptions
A20: Old weeks | B20: Old W1 = Mon 22 Jun 2026. Coloured week cells became Start + Weeks. Rows coloured red across all ten weeks were read as 'not scheduled' (note on each row).
A21: New plan | B21: New tasks start W17 = Mon 12 Oct 2026 (assumed start; shift Start dates as needed).
A22: Statuses | B22: Old statuses kept as they were; new tasks set from the state of the code (e.g. SCooP site 1 processed).
A23: Owners | B23: Owner = role. Put each person's name against the role in Lists; Tasks and Gantt show it.
A25: Google Sheets
A26: Open it | B26: Upload the .xlsx to Google Drive -> open it -> File > Save as Google Sheets. Share the Google Sheet (Editor) with the team; use only that copy.
A27: Rule | B27: Nobody downloads, edits offline and re-uploads: that overwrites everyone else's changes. File > Version history shows who changed what.
A28: Dropdown values | B28: Stored in each column's rule (Data > Data validation). To add a status/role/goal: add it there; also add a new role to Lists so Person can be looked up.

Sheet Dashboard
A1: Dashboard
A2: All numbers are formulas over Tasks, Problems and Interfaces.
A4: Goal | B4: Not Started | C4: In Progress | D4: Blocked | E4: Complete | F4: Partially Completed | G4: No status | H4: Total | I4: Overdue | J4: Not scheduled
A5: G1 ED305 live digital twin | B5: =COUNTIFS(Tasks!$B$4:$B$403,$A5,Tasks!$H$4:$H$403,"Not Started") -> 41 | C5: =COUNTIFS(Tasks!$B$4:$B$403,$A5,Tasks!$H$4:$H$403,"In Progress") -> 1 | D5: =COUNTIFS(Tasks!$B$4:$B$403,$A5,Tasks!$H$4:$H$403,"Blocked") -> 1 | E5: =COUNTIFS(Tasks!$B$4:$B$403,$A5,Tasks!$H$4:$H$403,"Complete") -> 0 | F5: =COUNTIFS(Tasks!$B$4:$B$403,$A5,Tasks!$H$4:$H$403,"Partially Completed") -> 0 | G5: =COUNTIFS(Tasks!$B$4:$B$403,$A5,Tasks!$H$4:$H$403,"") -> 0 | H5: =SUM(B5:G5) -> 43 | I5: =COUNTIFS(Tasks!$B$4:$B$403,$A5,Tasks!$K$4:$K$403,"<"&TODAY(),Tasks!$H$4:$H$403,"<>Complete") -> 6 | J5: =COUNTIFS(Tasks!$B$4:$B$403,$A5,Tasks!$I$4:$I$403,"") -> 0
A6: G2 SCooP dataset & paper | B6: =COUNTIFS(Tasks!$B$4:$B$403,$A6,Tasks!$H$4:$H$403,"Not Started") -> 21 | C6: =COUNTIFS(Tasks!$B$4:$B$403,$A6,Tasks!$H$4:$H$403,"In Progress") -> 4 | D6: =COUNTIFS(Tasks!$B$4:$B$403,$A6,Tasks!$H$4:$H$403,"Blocked") -> 0 | E6: =COUNTIFS(Tasks!$B$4:$B$403,$A6,Tasks!$H$4:$H$403,"Complete") -> 0 | F6: =COUNTIFS(Tasks!$B$4:$B$403,$A6,Tasks!$H$4:$H$403,"Partially Completed") -> 2 | G6: =COUNTIFS(Tasks!$B$4:$B$403,$A6,Tasks!$H$4:$H$403,"") -> 2 | H6: =SUM(B6:G6) -> 29 | I6: =COUNTIFS(Tasks!$B$4:$B$403,$A6,Tasks!$K$4:$K$403,"<"&TODAY(),Tasks!$H$4:$H$403,"<>Complete") -> 5 | J6: =COUNTIFS(Tasks!$B$4:$B$403,$A6,Tasks!$I$4:$I$403,"") -> 3
A7: Shared SCooP testbed | B7: =COUNTIFS(Tasks!$B$4:$B$403,$A7,Tasks!$H$4:$H$403,"Not Started") -> 2 | C7: =COUNTIFS(Tasks!$B$4:$B$403,$A7,Tasks!$H$4:$H$403,"In Progress") -> 4 | D7: =COUNTIFS(Tasks!$B$4:$B$403,$A7,Tasks!$H$4:$H$403,"Blocked") -> 0 | E7: =COUNTIFS(Tasks!$B$4:$B$403,$A7,Tasks!$H$4:$H$403,"Complete") -> 0 | F7: =COUNTIFS(Tasks!$B$4:$B$403,$A7,Tasks!$H$4:$H$403,"Partially Completed") -> 0 | G7: =COUNTIFS(Tasks!$B$4:$B$403,$A7,Tasks!$H$4:$H$403,"") -> 5 | H7: =SUM(B7:G7) -> 11 | I7: =COUNTIFS(Tasks!$B$4:$B$403,$A7,Tasks!$K$4:$K$403,"<"&TODAY(),Tasks!$H$4:$H$403,"<>Complete") -> 3 | J7: =COUNTIFS(Tasks!$B$4:$B$403,$A7,Tasks!$I$4:$I$403,"") -> 5
A8: Dual-Link Communication | B8: =COUNTIFS(Tasks!$B$4:$B$403,$A8,Tasks!$H$4:$H$403,"Not Started") -> 13 | C8: =COUNTIFS(Tasks!$B$4:$B$403,$A8,Tasks!$H$4:$H$403,"In Progress") -> 2 | D8: =COUNTIFS(Tasks!$B$4:$B$403,$A8,Tasks!$H$4:$H$403,"Blocked") -> 0 | E8: =COUNTIFS(Tasks!$B$4:$B$403,$A8,Tasks!$H$4:$H$403,"Complete") -> 0 | F8: =COUNTIFS(Tasks!$B$4:$B$403,$A8,Tasks!$H$4:$H$403,"Partially Completed") -> 7 | G8: =COUNTIFS(Tasks!$B$4:$B$403,$A8,Tasks!$H$4:$H$403,"") -> 0 | H8: =SUM(B8:G8) -> 22 | I8: =COUNTIFS(Tasks!$B$4:$B$403,$A8,Tasks!$K$4:$K$403,"<"&TODAY(),Tasks!$H$4:$H$403,"<>Complete") -> 22 | J8: =COUNTIFS(Tasks!$B$4:$B$403,$A8,Tasks!$I$4:$I$403,"") -> 0
A9: Semantic Communication | B9: =COUNTIFS(Tasks!$B$4:$B$403,$A9,Tasks!$H$4:$H$403,"Not Started") -> 14 | C9: =COUNTIFS(Tasks!$B$4:$B$403,$A9,Tasks!$H$4:$H$403,"In Progress") -> 0 | D9: =COUNTIFS(Tasks!$B$4:$B$403,$A9,Tasks!$H$4:$H$403,"Blocked") -> 0 | E9: =COUNTIFS(Tasks!$B$4:$B$403,$A9,Tasks!$H$4:$H$403,"Complete") -> 0 | F9: =COUNTIFS(Tasks!$B$4:$B$403,$A9,Tasks!$H$4:$H$403,"Partially Completed") -> 0 | G9: =COUNTIFS(Tasks!$B$4:$B$403,$A9,Tasks!$H$4:$H$403,"") -> 0 | H9: =SUM(B9:G9) -> 14 | I9: =COUNTIFS(Tasks!$B$4:$B$403,$A9,Tasks!$K$4:$K$403,"<"&TODAY(),Tasks!$H$4:$H$403,"<>Complete") -> 6 | J9: =COUNTIFS(Tasks!$B$4:$B$403,$A9,Tasks!$I$4:$I$403,"") -> 8
A10: Total | B10: =SUM(B5:B9) -> 91 | C10: =SUM(C5:C9) -> 11 | D10: =SUM(D5:D9) -> 1 | E10: =SUM(E5:E9) -> 0 | F10: =SUM(F5:F9) -> 9 | G10: =SUM(G5:G9) -> 7 | H10: =SUM(H5:H9) -> 119 | I10: =SUM(I5:I9) -> 42 | J10: =SUM(J5:J9) -> 16
A13: Owner (role) | B13: Person | C13: Not Started | D13: In Progress | E13: Blocked | F13: Complete | G13: Partially Completed | H13: No status | I13: Total | J13: Overdue | K13: Not scheduled
A14: Sensors & platform | B14: =IFERROR(INDEX(Lists!$B$4:$B$12,MATCH($A14,Lists!$A$4:$A$12,0)),"") -> TBD | C14: =COUNTIFS(Tasks!$F$4:$F$403,$A14,Tasks!$H$4:$H$403,"Not Started") -> 6 | D14: =COUNTIFS(Tasks!$F$4:$F$403,$A14,Tasks!$H$4:$H$403,"In Progress") -> 5 | E14: =COUNTIFS(Tasks!$F$4:$F$403,$A14,Tasks!$H$4:$H$403,"Blocked") -> 1 | F14: =COUNTIFS(Tasks!$F$4:$F$403,$A14,Tasks!$H$4:$H$403,"Complete") -> 0 | G14: =COUNTIFS(Tasks!$F$4:$F$403,$A14,Tasks!$H$4:$H$403,"Partially Completed") -> 0 | H14: =COUNTIFS(Tasks!$F$4:$F$403,$A14,Tasks!$H$4:$H$403,"") -> 5 | I14: =SUM(C14:H14) -> 17 | J14: =COUNTIFS(Tasks!$F$4:$F$403,$A14,Tasks!$K$4:$K$403,"<"&TODAY(),Tasks!$H$4:$H$403,"<>Complete") -> 3 | K14: =COUNTIFS(Tasks!$F$4:$F$403,$A14,Tasks!$I$4:$I$403,"") -> 5
A15: GS-SLAM | B15: =IFERROR(INDEX(Lists!$B$4:$B$12,MATCH($A15,Lists!$A$4:$A$12,0)),"") -> TBD | C15: =COUNTIFS(Tasks!$F$4:$F$403,$A15,Tasks!$H$4:$H$403,"Not Started") -> 8 | D15: =COUNTIFS(Tasks!$F$4:$F$403,$A15,Tasks!$H$4:$H$403,"In Progress") -> 0 | E15: =COUNTIFS(Tasks!$F$4:$F$403,$A15,Tasks!$H$4:$H$403,"Blocked") -> 0 | F15: =COUNTIFS(Tasks!$F$4:$F$403,$A15,Tasks!$H$4:$H$403,"Complete") -> 0 | G15: =COUNTIFS(Tasks!$F$4:$F$403,$A15,Tasks!$H$4:$H$403,"Partially Completed") -> 0 | H15: =COUNTIFS(Tasks!$F$4:$F$403,$A15,Tasks!$H$4:$H$403,"") -> 0 | I15: =SUM(C15:H15) -> 8 | J15: =COUNTIFS(Tasks!$F$4:$F$403,$A15,Tasks!$K$4:$K$403,"<"&TODAY(),Tasks!$H$4:$H$403,"<>Complete") -> 2 | K15: =COUNTIFS(Tasks!$F$4:$F$403,$A15,Tasks!$I$4:$I$403,"") -> 0
A16: Scene detection | B16: =IFERROR(INDEX(Lists!$B$4:$B$12,MATCH($A16,Lists!$A$4:$A$12,0)),"") -> TBD | C16: =COUNTIFS(Tasks!$F$4:$F$403,$A16,Tasks!$H$4:$H$403,"Not Started") -> 11 | D16: =COUNTIFS(Tasks!$F$4:$F$403,$A16,Tasks!$H$4:$H$403,"In Progress") -> 0 | E16: =COUNTIFS(Tasks!$F$4:$F$403,$A16,Tasks!$H$4:$H$403,"Blocked") -> 0 | F16: =COUNTIFS(Tasks!$F$4:$F$403,$A16,Tasks!$H$4:$H$403,"Complete") -> 0 | G16: =COUNTIFS(Tasks!$F$4:$F$403,$A16,Tasks!$H$4:$H$403,"Partially Completed") -> 0 | H16: =COUNTIFS(Tasks!$F$4:$F$403,$A16,Tasks!$H$4:$H$403,"") -> 0 | I16: =SUM(C16:H16) -> 11 | J16: =COUNTIFS(Tasks!$F$4:$F$403,$A16,Tasks!$K$4:$K$403,"<"&TODAY(),Tasks!$H$4:$H$403,"<>Complete") -> 4 | K16: =COUNTIFS(Tasks!$F$4:$F$403,$A16,Tasks!$I$4:$I$403,"") -> 0
A17: Isaac Sim | B17: =IFERROR(INDEX(Lists!$B$4:$B$12,MATCH($A17,Lists!$A$4:$A$12,0)),"") -> TBD | C17: =COUNTIFS(Tasks!$F$4:$F$403,$A17,Tasks!$H$4:$H$403,"Not Started") -> 8 | D17: =COUNTIFS(Tasks!$F$4:$F$403,$A17,Tasks!$H$4:$H$403,"In Progress") -> 0 | E17: =COUNTIFS(Tasks!$F$4:$F$403,$A17,Tasks!$H$4:$H$403,"Blocked") -> 0 | F17: =COUNTIFS(Tasks!$F$4:$F$403,$A17,Tasks!$H$4:$H$403,"Complete") -> 0 | G17: =COUNTIFS(Tasks!$F$4:$F$403,$A17,Tasks!$H$4:$H$403,"Partially Completed") -> 0 | H17: =COUNTIFS(Tasks!$F$4:$F$403,$A17,Tasks!$H$4:$H$403,"") -> 0 | I17: =SUM(C17:H17) -> 8 | J17: =COUNTIFS(Tasks!$F$4:$F$403,$A17,Tasks!$K$4:$K$403,"<"&TODAY(),Tasks!$H$4:$H$403,"<>Complete") -> 0 | K17: =COUNTIFS(Tasks!$F$4:$F$403,$A17,Tasks!$I$4:$I$403,"") -> 0
A18: Sionna RT | B18: =IFERROR(INDEX(Lists!$B$4:$B$12,MATCH($A18,Lists!$A$4:$A$12,0)),"") -> TBD | C18: =COUNTIFS(Tasks!$F$4:$F$403,$A18,Tasks!$H$4:$H$403,"Not Started") -> 4 | D18: =COUNTIFS(Tasks!$F$4:$F$403,$A18,Tasks!$H$4:$H$403,"In Progress") -> 0 | E18: =COUNTIFS(Tasks!$F$4:$F$403,$A18,Tasks!$H$4:$H$403,"Blocked") -> 0 | F18: =COUNTIFS(Tasks!$F$4:$F$403,$A18,Tasks!$H$4:$H$403,"Complete") -> 0 | G18: =COUNTIFS(Tasks!$F$4:$F$403,$A18,Tasks!$H$4:$H$403,"Partially Completed") -> 0 | H18: =COUNTIFS(Tasks!$F$4:$F$403,$A18,Tasks!$H$4:$H$403,"") -> 0 | I18: =SUM(C18:H18) -> 4 | J18: =COUNTIFS(Tasks!$F$4:$F$403,$A18,Tasks!$K$4:$K$403,"<"&TODAY(),Tasks!$H$4:$H$403,"<>Complete") -> 0 | K18: =COUNTIFS(Tasks!$F$4:$F$403,$A18,Tasks!$I$4:$I$403,"") -> 0
A19: SCooP dataset | B19: =IFERROR(INDEX(Lists!$B$4:$B$12,MATCH($A19,Lists!$A$4:$A$12,0)),"") -> TBD | C19: =COUNTIFS(Tasks!$F$4:$F$403,$A19,Tasks!$H$4:$H$403,"Not Started") -> 21 | D19: =COUNTIFS(Tasks!$F$4:$F$403,$A19,Tasks!$H$4:$H$403,"In Progress") -> 4 | E19: =COUNTIFS(Tasks!$F$4:$F$403,$A19,Tasks!$H$4:$H$403,"Blocked") -> 0 | F19: =COUNTIFS(Tasks!$F$4:$F$403,$A19,Tasks!$H$4:$H$403,"Complete") -> 0 | G19: =COUNTIFS(Tasks!$F$4:$F$403,$A19,Tasks!$H$4:$H$403,"Partially Completed") -> 2 | H19: =COUNTIFS(Tasks!$F$4:$F$403,$A19,Tasks!$H$4:$H$403,"") -> 2 | I19: =SUM(C19:H19) -> 29 | J19: =COUNTIFS(Tasks!$F$4:$F$403,$A19,Tasks!$K$4:$K$403,"<"&TODAY(),Tasks!$H$4:$H$403,"<>Complete") -> 5 | K19: =COUNTIFS(Tasks!$F$4:$F$403,$A19,Tasks!$I$4:$I$403,"") -> 3
A20: Dual-link comms | B20: =IFERROR(INDEX(Lists!$B$4:$B$12,MATCH($A20,Lists!$A$4:$A$12,0)),"") -> TBD | C20: =COUNTIFS(Tasks!$F$4:$F$403,$A20,Tasks!$H$4:$H$403,"Not Started") -> 13 | D20: =COUNTIFS(Tasks!$F$4:$F$403,$A20,Tasks!$H$4:$H$403,"In Progress") -> 2 | E20: =COUNTIFS(Tasks!$F$4:$F$403,$A20,Tasks!$H$4:$H$403,"Blocked") -> 0 | F20: =COUNTIFS(Tasks!$F$4:$F$403,$A20,Tasks!$H$4:$H$403,"Complete") -> 0 | G20: =COUNTIFS(Tasks!$F$4:$F$403,$A20,Tasks!$H$4:$H$403,"Partially Completed") -> 7 | H20: =COUNTIFS(Tasks!$F$4:$F$403,$A20,Tasks!$H$4:$H$403,"") -> 0 | I20: =SUM(C20:H20) -> 22 | J20: =COUNTIFS(Tasks!$F$4:$F$403,$A20,Tasks!$K$4:$K$403,"<"&TODAY(),Tasks!$H$4:$H$403,"<>Complete") -> 22 | K20: =COUNTIFS(Tasks!$F$4:$F$403,$A20,Tasks!$I$4:$I$403,"") -> 0
A21: Semantic comms | B21: =IFERROR(INDEX(Lists!$B$4:$B$12,MATCH($A21,Lists!$A$4:$A$12,0)),"") -> TBD | C21: =COUNTIFS(Tasks!$F$4:$F$403,$A21,Tasks!$H$4:$H$403,"Not Started") -> 14 | D21: =COUNTIFS(Tasks!$F$4:$F$403,$A21,Tasks!$H$4:$H$403,"In Progress") -> 0 | E21: =COUNTIFS(Tasks!$F$4:$F$403,$A21,Tasks!$H$4:$H$403,"Blocked") -> 0 | F21: =COUNTIFS(Tasks!$F$4:$F$403,$A21,Tasks!$H$4:$H$403,"Complete") -> 0 | G21: =COUNTIFS(Tasks!$F$4:$F$403,$A21,Tasks!$H$4:$H$403,"Partially Completed") -> 0 | H21: =COUNTIFS(Tasks!$F$4:$F$403,$A21,Tasks!$H$4:$H$403,"") -> 0 | I21: =SUM(C21:H21) -> 14 | J21: =COUNTIFS(Tasks!$F$4:$F$403,$A21,Tasks!$K$4:$K$403,"<"&TODAY(),Tasks!$H$4:$H$403,"<>Complete") -> 6 | K21: =COUNTIFS(Tasks!$F$4:$F$403,$A21,Tasks!$I$4:$I$403,"") -> 8
A22: All (integration) | B22: =IFERROR(INDEX(Lists!$B$4:$B$12,MATCH($A22,Lists!$A$4:$A$12,0)),"") -> TBD | C22: =COUNTIFS(Tasks!$F$4:$F$403,$A22,Tasks!$H$4:$H$403,"Not Started") -> 6 | D22: =COUNTIFS(Tasks!$F$4:$F$403,$A22,Tasks!$H$4:$H$403,"In Progress") -> 0 | E22: =COUNTIFS(Tasks!$F$4:$F$403,$A22,Tasks!$H$4:$H$403,"Blocked") -> 0 | F22: =COUNTIFS(Tasks!$F$4:$F$403,$A22,Tasks!$H$4:$H$403,"Complete") -> 0 | G22: =COUNTIFS(Tasks!$F$4:$F$403,$A22,Tasks!$H$4:$H$403,"Partially Completed") -> 0 | H22: =COUNTIFS(Tasks!$F$4:$F$403,$A22,Tasks!$H$4:$H$403,"") -> 0 | I22: =SUM(C22:H22) -> 6 | J22: =COUNTIFS(Tasks!$F$4:$F$403,$A22,Tasks!$K$4:$K$403,"<"&TODAY(),Tasks!$H$4:$H$403,"<>Complete") -> 0 | K22: =COUNTIFS(Tasks!$F$4:$F$403,$A22,Tasks!$I$4:$I$403,"") -> 0
A23: Total | C23: =SUM(C14:C22) -> 91 | D23: =SUM(D14:D22) -> 11 | E23: =SUM(E14:E22) -> 1 | F23: =SUM(F14:F22) -> 0 | G23: =SUM(G14:G22) -> 9 | H23: =SUM(H14:H22) -> 7 | I23: =SUM(I14:I22) -> 119 | J23: =SUM(J14:J22) -> 42 | K23: =SUM(K14:K22) -> 16
A26: Problems | B26: Open | C26: Investigating | D26: Resolved | E26: Won't fix | F26: Still open
A27: Blocker | B27: =COUNTIFS(Problems!$F$4:$F$203,$A27,Problems!$G$4:$G$203,"Open") -> 1 | C27: =COUNTIFS(Problems!$F$4:$F$203,$A27,Problems!$G$4:$G$203,"Investigating") -> 0 | D27: =COUNTIFS(Problems!$F$4:$F$203,$A27,Problems!$G$4:$G$203,"Resolved") -> 0 | E27: =COUNTIFS(Problems!$F$4:$F$203,$A27,Problems!$G$4:$G$203,"Won't fix") -> 0 | F27: =B27+C27 -> 1
A28: Major | B28: =COUNTIFS(Problems!$F$4:$F$203,$A28,Problems!$G$4:$G$203,"Open") -> 2 | C28: =COUNTIFS(Problems!$F$4:$F$203,$A28,Problems!$G$4:$G$203,"Investigating") -> 3 | D28: =COUNTIFS(Problems!$F$4:$F$203,$A28,Problems!$G$4:$G$203,"Resolved") -> 0 | E28: =COUNTIFS(Problems!$F$4:$F$203,$A28,Problems!$G$4:$G$203,"Won't fix") -> 0 | F28: =B28+C28 -> 5
A29: Minor | B29: =COUNTIFS(Problems!$F$4:$F$203,$A29,Problems!$G$4:$G$203,"Open") -> 4 | C29: =COUNTIFS(Problems!$F$4:$F$203,$A29,Problems!$G$4:$G$203,"Investigating") -> 0 | D29: =COUNTIFS(Problems!$F$4:$F$203,$A29,Problems!$G$4:$G$203,"Resolved") -> 0 | E29: =COUNTIFS(Problems!$F$4:$F$203,$A29,Problems!$G$4:$G$203,"Won't fix") -> 0 | F29: =B29+C29 -> 4
A32: Interfaces | B32: Count
A33: Not defined | B33: =COUNTIF(Interfaces!$J$4:$J$103,$A33) -> 14
A34: Defined | B34: =COUNTIF(Interfaces!$J$4:$J$103,$A34) -> 0
A35: Implemented | B35: =COUNTIF(Interfaces!$J$4:$J$103,$A35) -> 0
A36: Tested | B36: =COUNTIF(Interfaces!$J$4:$J$103,$A36) -> 0

Sheet Tasks
A1: Tasks
A2: One row per task. Start + Weeks drive the Gantt sheet. Grey italic columns are formulas.
A3: ID | B3: Goal | C3: Component | D3: Task | E3: Detail | F3: Owner (role) | G3: Person | H3: Status | I3: Start | J3: Weeks | K3: End | L3: Depends on | M3: Done when | N3: Link | O3: Notes | P3: Old tracker ref
A4: TB-1 | B4: Shared SCooP testbed | C4: Testbed | D4: Hardware inventory & specs | E4: mobile_1, mobile_2, infra masts, sniffer: what is mounted where. | F4: Sensors & platform | G4: =IF($F4="","",IFERROR(INDEX(Lists!$B$4:$B$12,MATCH($F4,Lists!$A$4:$A$12,0)),"")) -> TBD | H4: Not Started | I4: 46307 | J4: 2 | K4: =IF(OR($I4="",$J4=""),"",$I4+7*$J4-3) -> 46318 | M4: Number of infra masts fixed; cascade radar and mobile_2 radar/Wi-Fi specs confirmed (paper sensors table complete)
A5: TB-2 | B5: Shared SCooP testbed | C5: Testbed | D5: Sensor calibration (all units) | E5: Spatial and temporal calibration across all sensors; verify the TF chain (map -> odom -> zed_camera_center). | F5: Sensors & platform | G5: =IF($F5="","",IFERROR(INDEX(Lists!$B$4:$B$12,MATCH($F5,Lists!$A$4:$A$12,0)),"")) -> TBD | H5: In Progress | I5: 46195 | J5: 2 | K5: =IF(OR($I5="",$J5=""),"",$I5+7*$J5-3) -> 46206 | M5: Calibration table in the paper filled; residual per sensor pair recorded | P5: Dataset Collection 1
A6: TB-2.1 | B6: Shared SCooP testbed | C6: Testbed | D6: Sensor Calibration (LiDAR-Camera, LiDAR-IMU, Camera-Radar, Intrinsics, Realsense-Zed, Mobile-Infra Extrinsics) | E6: Spatial calibration across all sensor pairs. | F6: Sensors & platform | G6: =IF($F6="","",IFERROR(INDEX(Lists!$B$4:$B$12,MATCH($F6,Lists!$A$4:$A$12,0)),"")) -> TBD | H6: In Progress | I6: 46195 | J6: 2 | K6: =IF(OR($I6="",$J6=""),"",$I6+7*$J6-3) -> 46206 | P6: Dataset Collection 1.1
A7: TB-2.2 | B7: Shared SCooP testbed | C7: Testbed | D7: Calibration: LiDAR - Camera | E7: From the old tracker's Sheet1 calibration list. | F7: Sensors & platform | G7: =IF($F7="","",IFERROR(INDEX(Lists!$B$4:$B$12,MATCH($F7,Lists!$A$4:$A$12,0)),"")) -> TBD | K7: =IF(OR($I7="",$J7=""),"",$I7+7*$J7-3) | O7: Status not recorded in the old file | P7: Old Sheet1 'calibration'
A8: TB-2.3 | B8: Shared SCooP testbed | C8: Testbed | D8: Calibration: LiDAR - IMU | E8: From the old tracker's Sheet1 calibration list. | F8: Sensors & platform | G8: =IF($F8="","",IFERROR(INDEX(Lists!$B$4:$B$12,MATCH($F8,Lists!$A$4:$A$12,0)),"")) -> TBD | K8: =IF(OR($I8="",$J8=""),"",$I8+7*$J8-3) | O8: Status not recorded in the old file | P8: Old Sheet1 'calibration'
A9: TB-2.4 | B9: Shared SCooP testbed | C9: Testbed | D9: Calibration: RealSense - ZED | E9: From the old tracker's Sheet1 calibration list. | F9: Sensors & platform | G9: =IF($F9="","",IFERROR(INDEX(Lists!$B$4:$B$12,MATCH($F9,Lists!$A$4:$A$12,0)),"")) -> TBD | K9: =IF(OR($I9="",$J9=""),"",$I9+7*$J9-3) | O9: Status not recorded in the old file | P9: Old Sheet1 'calibration'
A10: TB-2.5 | B10: Shared SCooP testbed | C10: Testbed | D10: Calibration: ZED - Arducam | E10: From the old tracker's Sheet1 calibration list. | F10: Sensors & platform | G10: =IF($F10="","",IFERROR(INDEX(Lists!$B$4:$B$12,MATCH($F10,Lists!$A$4:$A$12,0)),"")) -> TBD | K10: =IF(OR($I10="",$J10=""),"",$I10+7*$J10-3) | O10: Status not recorded in the old file | P10: Old Sheet1 'calibration'
A11: TB-2.6 | B11: Shared SCooP testbed | C11: Testbed | D11: Calibration: Radars - ZED | E11: From the old tracker's Sheet1 calibration list. | F11: Sensors & platform | G11: =IF($F11="","",IFERROR(INDEX(Lists!$B$4:$B$12,MATCH($F11,Lists!$A$4:$A$12,0)),"")) -> TBD | K11: =IF(OR($I11="",$J11=""),"",$I11+7*$J11-3) | O11: Status not recorded in the old file | P11: Old Sheet1 'calibration'
A12: TB-3 | B12: Shared SCooP testbed | C12: Testbed | D12: Time sync & TF chain | E12: Confirm TF chain resolves; sync clocks via UTC pivot. | F12: Sensors & platform | G12: =IF($F12="","",IFERROR(INDEX(Lists!$B$4:$B$12,MATCH($F12,Lists!$A$4:$A$12,0)),"")) -> TBD | H12: In Progress | I12: 46202 | J12: 1 | K12: =IF(OR($I12="",$J12=""),"",$I12+7*$J12-3) -> 46206 | M12: Sniffer NTP bias measured; NTP checked over >= 3 passes; per-sensor transport latency measured; TF chain resolves | P12: Dataset Collection 1.2
A13: TB-4 | B13: Shared SCooP testbed | C13: Testbed | D13: Wi-Fi & comms logging | E13: AP ch149 VHT-80, wifi/status, iperf3, ping, chrony, Nexmon CSI. | F13: Sensors & platform | G13: =IF($F13="","",IFERROR(INDEX(Lists!$B$4:$B$12,MATCH($F13,Lists!$A$4:$A$12,0)),"")) -> TBD | H13: In Progress | I13: 46307 | J13: 2 | K13: =IF(OR($I13="",$J13=""),"",$I13+7*$J13-3) -> 46318 | M13: Pre-recording check passes on every node
A14: TB-5 | B14: Shared SCooP testbed | C14: Testbed | D14: Recording tooling fixes | E14: Record mobile_2's on-board VSLAM; record mobile_2 depth/IMU/IR in survey mode. | F14: Sensors & platform | G14: =IF($F14="","",IFERROR(INDEX(Lists!$B$4:$B$12,MATCH($F14,Lists!$A$4:$A$12,0)),"")) -> TBD | H14: Not Started | I14: 46307 | J14: 2 | K14: =IF(OR($I14="",$J14=""),"",$I14+7*$J14-3) -> 46318 | L14: TB-4 | M14: A test pass records every topic listed in record.yaml
A15: G2-DS-1 | B15: G2 SCooP dataset & paper | C15: SCooP dataset | D15: Recording campaign | E15: All sites x pass types (mapping, survey, coop, contention). Site 1 (MIRC) recorded 2026-09-24. | F15: SCooP dataset | G15: =IF($F15="","",IFERROR(INDEX(Lists!$B$4:$B$12,MATCH($F15,Lists!$A$4:$A$12,0)),"")) -> TBD | H15: Partially Completed | I15: 46314 | J15: 6 | K15: =IF(OR($I15="",$J15=""),"",$I15+7*$J15-3) -> 46353 | L15: TB-2, TB-3, TB-5 | M15: Sites 2 and 3 recorded, all four pass types per site | O15: Only Cameras and LiDAR mainly for calibration accuracy validation | P15: Dataset Collection 2 | tag Dataset #1
A16: G2-DS-1.1 | B16: G2 SCooP dataset & paper | C16: SCooP dataset | D16: Indoor Trajectory Sessions | E16: Planned indoor routes and formations across both robots. | F16: SCooP dataset | G16: =IF($F16="","",IFERROR(INDEX(Lists!$B$4:$B$12,MATCH($F16,Lists!$A$4:$A$12,0)),"")) -> TBD | H16: Partially Completed | I16: 46202 | J16: 1 | K16: =IF(OR($I16="",$J16=""),"",$I16+7*$J16-3) -> 46206 | O16: 2 different datasets → detect change (in validation) | P16: Dataset Collection 2.1
A17: G2-DS-1.2 | B17: G2 SCooP dataset & paper | C17: SCooP dataset | D17: Outdoor Trajectory Sessions | E17: Planned outdoor routes, including GPS-denied test zones. | F17: SCooP dataset | G17: =IF($F17="","",IFERROR(INDEX(Lists!$B$4:$B$12,MATCH($F17,Lists!$A$4:$A$12,0)),"")) -> TBD | H17: Not Started | K17: =IF(OR($I17="",$J17=""),"",$I17+7*$J17-3) | O17: Old tracker: red across W1-W10 (read as not scheduled) | P17: Dataset Collection 2.2
A18: G2-DS-1.3 | B18: G2 SCooP dataset & paper | C18: SCooP dataset | D18: Record sites 2 and 3 | E18: Mapping, survey, coop, contention passes per site. | F18: SCooP dataset | G18: =IF($F18="","",IFERROR(INDEX(Lists!$B$4:$B$12,MATCH($F18,Lists!$A$4:$A$12,0)),"")) -> TBD | H18: Not Started | I18: 46321 | J18: 4 | K18: =IF(OR($I18="",$J18=""),"",$I18+7*$J18-3) -> 46346 | L18: TB-5
A19: G2-DS-1.4 | B19: G2 SCooP dataset & paper | C19: SCooP dataset | D19: Calibration rosbag | E19: Stop at several points where camera and LiDAR see the same scene (LiDAR, radar, ZED; Arducam; RealSense). | F19: SCooP dataset | G19: =IF($F19="","",IFERROR(INDEX(Lists!$B$4:$B$12,MATCH($F19,Lists!$A$4:$A$12,0)),"")) -> TBD | I19: 46314 | J19: 1 | K19: =IF(OR($I19="",$J19=""),"",$I19+7*$J19-3) -> 46318 | O19: Status not recorded in the old file | P19: Old Sheet1 'To record' 2
A20: G2-DS-1.5 | B20: G2 SCooP dataset & paper | C20: SCooP dataset | D20: Short test recordings | E20: Distance from object, occlusion, object at image edge (LiDAR, radar, ZED; Arducam; RealSense). | F20: SCooP dataset | G20: =IF($F20="","",IFERROR(INDEX(Lists!$B$4:$B$12,MATCH($F20,Lists!$A$4:$A$12,0)),"")) -> TBD | I20: 46314 | J20: 1 | K20: =IF(OR($I20="",$J20=""),"",$I20+7*$J20-3) -> 46318 | O20: Status not recorded in the old file | P20: Old Sheet1 'To record' 2
A21: G2-DS-2 | B21: G2 SCooP dataset & paper | C21: SCooP dataset | D21: Per-pass processing | E21: Decode Ouster, retime, GLIM, ZED SVO->bag, offline cuVSLAM for mobile_2, merge + check against record.yaml. | F21: SCooP dataset | G21: =IF($F21="","",IFERROR(INDEX(Lists!$B$4:$B$12,MATCH($F21,Lists!$A$4:$A$12,0)),"")) -> TBD | H21: In Progress | I21: 46307 | J21: 10 | K21: =IF(OR($I21="",$J21=""),"",$I21+7*$J21-3) -> 46374 | M21: Every recorded pass processed and merged; bag_check clean | O21: Done for the 2026-09-24 passes; rerun per new pass | P21: Dataset Collection 3 | tag Dataset #2
A22: G2-DS-2.1 | B22: G2 SCooP dataset & paper | C22: SCooP dataset | D22: Merging Sensor Data | E22: Merge all recorded sensor data and transforms | F22: SCooP dataset | G22: =IF($F22="","",IFERROR(INDEX(Lists!$B$4:$B$12,MATCH($F22,Lists!$A$4:$A$12,0)),"")) -> TBD | H22: In Progress | I22: 46202 | J22: 1 | K22: =IF(OR($I22="",$J22=""),"",$I22+7*$J22-3) -> 46206 | P22: Dataset Collection 2.3
A23: G2-DS-2.2 | B23: G2 SCooP dataset & paper | C23: SCooP dataset | D23: Timestamp Alignment Post-Processing | E23: Align all recorded streams to the UTC pivot reference. | F23: SCooP dataset | G23: =IF($F23="","",IFERROR(INDEX(Lists!$B$4:$B$12,MATCH($F23,Lists!$A$4:$A$12,0)),"")) -> TBD | H23: Not Started | I23: 46202 | J23: 1 | K23: =IF(OR($I23="",$J23=""),"",$I23+7*$J23-3) -> 46206 | P23: Dataset Collection 3.1
A24: G2-DS-3 | B24: G2 SCooP dataset & paper | C24: SCooP dataset | D24: Reference maps & board networks per site | E24: Map stages 01-02; ChArUco board network. | F24: SCooP dataset | G24: =IF($F24="","",IFERROR(INDEX(Lists!$B$4:$B$12,MATCH($F24,Lists!$A$4:$A$12,0)),"")) -> TBD | H24: In Progress | I24: 46307 | J24: 8 | K24: =IF(OR($I24="",$J24=""),"",$I24+7*$J24-3) -> 46360 | M24: Map + boards per site; wall/floor thickness reported | O24: Done for site 1 mapping_A (7.4 / 2.6 cm)
A25: G2-DS-3.1 | B25: G2 SCooP dataset & paper | C25: SCooP dataset | D25: Localization and Mapping | E25: Pointcloud Mapping using LiDAR (LiDAR-SLAM) and Camera (V-SLAM) | F25: SCooP dataset | G25: =IF($F25="","",IFERROR(INDEX(Lists!$B$4:$B$12,MATCH($F25,Lists!$A$4:$A$12,0)),"")) -> TBD | H25: Not Started | I25: 46202 | J25: 1 | K25: =IF(OR($I25="",$J25=""),"",$I25+7*$J25-3) -> 46206 | P25: Dataset Collection 3.2
A26: G2-DS-3.2 | B26: G2 SCooP dataset & paper | C26: SCooP dataset | D26: Mesh Conversion | E26: Converting pointcloud data to watertight mesh/cuboids | F26: SCooP dataset | G26: =IF($F26="","",IFERROR(INDEX(Lists!$B$4:$B$12,MATCH($F26,Lists!$A$4:$A$12,0)),"")) -> TBD | H26: Not Started | I26: 46209 | J26: 2 | K26: =IF(OR($I26="",$J26=""),"",$I26+7*$J26-3) -> 46220 | O26: Varying object resolution → zoom in, zoom out | P26: Dataset Collection 3.3
A27: G2-DS-4 | B27: G2 SCooP dataset & paper | C27: SCooP dataset | D27: Reference poses (map stages 03-10) | E27: Boards init, reference trajectory (LiDAR ICP; depth_track/PGO for mobile_2), anchor, cut, cameras, TFs, cloud, poses. | F27: SCooP dataset | G27: =IF($F27="","",IFERROR(INDEX(Lists!$B$4:$B$12,MATCH($F27,Lists!$A$4:$A$12,0)),"")) -> TBD | H27: In Progress | I27: 46307 | J27: 6 | K27: =IF(OR($I27="",$J27=""),"",$I27+7*$J27-3) -> 46346 | L27: G2-DS-3 | M27: Every robot in every sequence has a reference trajectory | O27: Current: coop_2 mobile_2 track (P-001)
A28: G2-DS-5 | B28: G2 SCooP dataset & paper | C28: SCooP dataset | D28: Ground-truth validation | E28: Control distances, held-out boards, cross-robot, cross-session. | F28: SCooP dataset | G28: =IF($F28="","",IFERROR(INDEX(Lists!$B$4:$B$12,MATCH($F28,Lists!$A$4:$A$12,0)),"")) -> TBD | H28: Not Started | I28: 46342 | J28: 3 | K28: =IF(OR($I28="",$J28=""),"",$I28+7*$J28-3) -> 46360 | L28: G2-DS-4 | M28: Paper GT table has no '--' cells
A29: G2-DS-6 | B29: G2 SCooP dataset & paper | C29: SCooP dataset | D29: Annotations | E29: Boxes, per-point labels, masks; decide the keyframe rate. No pipeline code yet. | F29: SCooP dataset | G29: =IF($F29="","",IFERROR(INDEX(Lists!$B$4:$B$12,MATCH($F29,Lists!$A$4:$A$12,0)),"")) -> TBD | H29: Not Started | I29: 46335 | J29: 7 | K29: =IF(OR($I29="",$J29=""),"",$I29+7*$J29-3) -> 46381 | L29: G2-DS-4 | M29: Annotation set + statistics for every sequence | P29: Dataset Collection 3.4
A30: G2-DS-6.1 | B30: G2 SCooP dataset & paper | C30: SCooP dataset | D30: Label QA (Coverage & Class Balance) | E30: Spot-check annotation quality and scenario/class coverage. | F30: SCooP dataset | G30: =IF($F30="","",IFERROR(INDEX(Lists!$B$4:$B$12,MATCH($F30,Lists!$A$4:$A$12,0)),"")) -> TBD | H30: Not Started | K30: =IF(OR($I30="",$J30=""),"",$I30+7*$J30-3) | O30: Old tracker: red across W1-W10 (read as not scheduled) | P30: Dataset Collection 4.1
A31: G2-DS-7 | B31: G2 SCooP dataset & paper | C31: SCooP dataset | D31: Collaboration geometry & comm ground truth | E31: Overlap, visibility, beta, C, Fresnel clearance; comms tables; channel replay. | F31: SCooP dataset | G31: =IF($F31="","",IFERROR(INDEX(Lists!$B$4:$B$12,MATCH($F31,Lists!$A$4:$A$12,0)),"")) -> TBD | H31: Not Started | I31: 46349 | J31: 5 | K31: =IF(OR($I31="",$J31=""),"",$I31+7*$J31-3) -> 46381 | L31: G2-DS-4, TB-4 | M31: Per-frame geometry + link files for every coop sequence
A32: G2-DS-8 | B32: G2 SCooP dataset & paper | C32: SCooP dataset | D32: Release | E32: Raw MCAP layout, OPV2V-style extracted format, devkit, license/DOI/hosting. | F32: SCooP dataset | G32: =IF($F32="","",IFERROR(INDEX(Lists!$B$4:$B$12,MATCH($F32,Lists!$A$4:$A$12,0)),"")) -> TBD | H32: Not Started | I32: 46384 | J32: 5 | K32: =IF(OR($I32="",$J32=""),"",$I32+7*$J32-3) -> 46416 | L32: G2-DS-5, G2-DS-6, G2-DS-7 | M32: Versioned release online with DOI; devkit examples run | O32: Old tracker: red across W1-W10 (read as not scheduled) | P32: Dataset Collection 4 | tag Dataset #3
A33: G2-DS-8.1 | B33: G2 SCooP dataset & paper | C33: SCooP dataset | D33: Dataset Packaging & Documentation | E33: Assemble the final versioned dataset release. | F33: SCooP dataset | G33: =IF($F33="","",IFERROR(INDEX(Lists!$B$4:$B$12,MATCH($F33,Lists!$A$4:$A$12,0)),"")) -> TBD | H33: Not Started | K33: =IF(OR($I33="",$J33=""),"",$I33+7*$J33-3) | O33: Old tracker: red across W1-W10 (read as not scheduled) | P33: Dataset Collection 4.2
A34: G2-DS-8.2 | B34: G2 SCooP dataset & paper | C34: SCooP dataset | D34: Devkit | E34: Readers, calib/clock API, projection, geometry, channel replay, evaluation. | F34: SCooP dataset | G34: =IF($F34="","",IFERROR(INDEX(Lists!$B$4:$B$12,MATCH($F34,Lists!$A$4:$A$12,0)),"")) -> TBD | H34: Not Started | I34: 46384 | J34: 4 | K34: =IF(OR($I34="",$J34=""),"",$I34+7*$J34-3) -> 46409
A35: G2-DS-8.3 | B35: G2 SCooP dataset & paper | C35: SCooP dataset | D35: License, DOI, hosting | F35: SCooP dataset | G35: =IF($F35="","",IFERROR(INDEX(Lists!$B$4:$B$12,MATCH($F35,Lists!$A$4:$A$12,0)),"")) -> TBD | H35: Not Started | I35: 46398 | J35: 2 | K35: =IF(OR($I35="",$J35=""),"",$I35+7*$J35-3) -> 46409
A36: G2-BP-A | B36: G2 SCooP dataset & paper | C36: SCooP paper & benchmarks | D36: Ground-truth numbers (RESULTS_PLAN A0) | E36: Control distances, held-out board residuals, box-fit fraction, sniffer bias. | F36: SCooP dataset | G36: =IF($F36="","",IFERROR(INDEX(Lists!$B$4:$B$12,MATCH($F36,Lists!$A$4:$A$12,0)),"")) -> TBD | H36: Not Started | I36: 46314 | J36: 3 | K36: =IF(OR($I36="",$J36=""),"",$I36+7*$J36-3) -> 46332 | L36: G2-DS-4
A37: G2-BP-B | B37: G2 SCooP dataset & paper | C37: SCooP paper & benchmarks | D37: Inventory & statistics tables (B) | E37: Sessions and sequence tables, annotation statistics. | F37: SCooP dataset | G37: =IF($F37="","",IFERROR(INDEX(Lists!$B$4:$B$12,MATCH($F37,Lists!$A$4:$A$12,0)),"")) -> TBD | H37: Not Started | I37: 46342 | J37: 3 | K37: =IF(OR($I37="",$J37=""),"",$I37+7*$J37-3) -> 46360 | L37: G2-DS-1
A38: G2-BP-C | B38: G2 SCooP dataset & paper | C38: SCooP paper & benchmarks | D38: Geometry validation (C) | E38: Clearance vs RSSI, co-visibility vs evidence. | F38: SCooP dataset | G38: =IF($F38="","",IFERROR(INDEX(Lists!$B$4:$B$12,MATCH($F38,Lists!$A$4:$A$12,0)),"")) -> TBD | H38: Not Started | I38: 46363 | J38: 3 | K38: =IF(OR($I38="",$J38=""),"",$I38+7*$J38-3) -> 46381 | L38: G2-DS-7
A39: G2-BP-D | B39: G2 SCooP dataset & paper | C39: SCooP paper & benchmarks | D39: T2 collaborative perception under 3 channels (D) | E39: Port the OpenCOOD harness; early, late, Where2comm minimum. | F39: SCooP dataset | G39: =IF($F39="","",IFERROR(INDEX(Lists!$B$4:$B$12,MATCH($F39,Lists!$A$4:$A$12,0)),"")) -> TBD | H39: Not Started | I39: 46363 | J39: 5 | K39: =IF(OR($I39="",$J39=""),"",$I39+7*$J39-3) -> 46395 | L39: G2-DS-6, G2-DS-7
A40: G2-BP-E | B40: G2 SCooP dataset & paper | C40: SCooP paper & benchmarks | D40: T1 collaborative SLAM (E) | E40: Swarm-SLAM minimum; DiSCo, COVINS-G, Kimera/Hydra-Multi stretch. | F40: SCooP dataset | G40: =IF($F40="","",IFERROR(INDEX(Lists!$B$4:$B$12,MATCH($F40,Lists!$A$4:$A$12,0)),"")) -> TBD | H40: Not Started | I40: 46363 | J40: 5 | K40: =IF(OR($I40="",$J40=""),"",$I40+7*$J40-3) -> 46395 | L40: G2-DS-4
A41: G2-BP-F | B41: G2 SCooP dataset & paper | C41: SCooP paper & benchmarks | D41: Q2 regression (F) | E41: LightGBM, leave-one-site-out. | F41: SCooP dataset | G41: =IF($F41="","",IFERROR(INDEX(Lists!$B$4:$B$12,MATCH($F41,Lists!$A$4:$A$12,0)),"")) -> TBD | H41: Not Started | I41: 46398 | J41: 2 | K41: =IF(OR($I41="",$J41=""),"",$I41+7*$J41-3) -> 46409 | L41: G2-BP-D, G2-BP-C
A42: G2-BP-G | B42: G2 SCooP dataset & paper | C42: SCooP paper & benchmarks | D42: Write-up (G) | E42: Replace 6 dummy-data figures, add 5 missing figures, results, abstract. | F42: SCooP dataset | G42: =IF($F42="","",IFERROR(INDEX(Lists!$B$4:$B$12,MATCH($F42,Lists!$A$4:$A$12,0)),"")) -> TBD | H42: Not Started | I42: 46398 | J42: 4 | K42: =IF(OR($I42="",$J42=""),"",$I42+7*$J42-3) -> 46423 | L42: G2-BP-F
A43: G2-M1 | B43: G2 SCooP dataset & paper | C43: Milestone | D43: Paper submitted (IJRR) | F43: SCooP dataset | G43: =IF($F43="","",IFERROR(INDEX(Lists!$B$4:$B$12,MATCH($F43,Lists!$A$4:$A$12,0)),"")) -> TBD | H43: Not Started | I43: 46426 | J43: 1 | K43: =IF(OR($I43="",$J43=""),"",$I43+7*$J43-3) -> 46430 | L43: G2-BP-G, G2-DS-8
A44: G1-SP-1 | B44: G1 ED305 live digital twin | C44: Sensors & platform | D44: Sensor rig & TF tree per robot | E44: RGB-D, IMU, wheel encoders, radio antenna; URDF/TF. | F44: Sensors & platform | G44: =IF($F44="","",IFERROR(INDEX(Lists!$B$4:$B$12,MATCH($F44,Lists!$A$4:$A$12,0)),"")) -> TBD | H44: Not Started | I44: 46307 | J44: 2 | K44: =IF(OR($I44="",$J44=""),"",$I44+7*$J44-3) -> 46318 | L44: TB-1
A45: G1-SP-2 | B45: G1 ED305 live digital twin | C45: Sensors & platform | D45: Odometry: front end + fusion filter | E45: Feature tracking + IMU + wheel ticks -> pose prior T_k with covariance. | F45: Sensors & platform | G45: =IF($F45="","",IFERROR(INDEX(Lists!$B$4:$B$12,MATCH($F45,Lists!$A$4:$A$12,0)),"")) -> TBD | H45: Not Started | I45: 46314 | J45: 4 | K45: =IF(OR($I45="",$J45=""),"",$I45+7*$J45-3) -> 46339 | L45: TB-2, TB-3 | M45: >= 30 Hz pose prior with covariance; drift measured on a closed loop
A46: G1-SP-3 | B46: G1 ED305 live digital twin | C46: Sensors & platform | D46: ED305 camera calibration in the room frame | E46: Convert the ED305-cameras calibration into cameras.yaml; pose check against the red dot. | F46: Sensors & platform | G46: =IF($F46="","",IFERROR(INDEX(Lists!$B$4:$B$12,MATCH($F46,Lists!$A$4:$A$12,0)),"")) -> TBD | H46: Blocked | I46: 46307 | J46: 2 | K46: =IF(OR($I46="",$J46=""),"",$I46+7*$J46-3) -> 46318 | M46: configs/cameras.yaml from measurements; reprojection check passes | O46: Blocked by P-009
A47: G1-SP-4 | B47: G1 ED305 live digital twin | C47: Sensors & platform | D47: ED305 coverage & camera placement | E47: coverage_map -> measure mounts -> optimize_cameras -> re-aim -> re-calibrate (WORKFLOW.md). | F47: Sensors & platform | G47: =IF($F47="","",IFERROR(INDEX(Lists!$B$4:$B$12,MATCH($F47,Lists!$A$4:$A$12,0)),"")) -> TBD | H47: In Progress | I47: 46321 | J47: 3 | K47: =IF(OR($I47="",$J47=""),"",$I47+7*$J47-3) -> 46339 | L47: G1-SP-3 | M47: No blind spots at k = 2 in the target volume | N47: ed305_digital_twin/WORKFLOW.md
A48: G1-SP-5 | B48: G1 ED305 live digital twin | C48: Sensors & platform | D48: Printed pan-tilt heads | E48: Check camera holes vs Basler drawing, print one, fit-check, then the flagged cameras. | F48: Sensors & platform | G48: =IF($F48="","",IFERROR(INDEX(Lists!$B$4:$B$12,MATCH($F48,Lists!$A$4:$A$12,0)),"")) -> TBD | H48: Not Started | I48: 46314 | J48: 3 | K48: =IF(OR($I48="",$J48=""),"",$I48+7*$J48-3) -> 46332 | M48: Flagged cameras on printed heads, set from moves.md readings | N48: ed305_digital_twin/hardware/pan_tilt
A49: G1-SP-6 | B49: G1 ED305 live digital twin | C49: Sensors & platform | D49: ED305 camera time sync | E49: PTP between the two camera hosts; measure offset with a common event. | F49: Sensors & platform | G49: =IF($F49="","",IFERROR(INDEX(Lists!$B$4:$B$12,MATCH($F49,Lists!$A$4:$A$12,0)),"")) -> TBD | H49: Not Started | I49: 46321 | J49: 2 | K49: =IF(OR($I49="",$J49=""),"",$I49+7*$J49-3) -> 46332 | M49: Measured offset between any two cameras < 5 ms
A50: G1-GS-1 | B50: G1 ED305 live digital twin | C50: GS-SLAM | D50: Metric prior | E50: Back-project depth with K and the odometry pose into world points. | F50: GS-SLAM | G50: =IF($F50="","",IFERROR(INDEX(Lists!$B$4:$B$12,MATCH($F50,Lists!$A$4:$A$12,0)),"")) -> TBD | H50: Not Started | I50: 46307 | J50: 2 | K50: =IF(OR($I50="",$J50=""),"",$I50+7*$J50-3) -> 46318 | L50: G1-SP-2
A51: G1-GS-2 | B51: G1 ED305 live digital twin | C51: GS-SLAM | D51: Tracking + keyframe gate | E51: Colour + depth residual pose solve; keyframe gate on overlap/motion. | F51: GS-SLAM | G51: =IF($F51="","",IFERROR(INDEX(Lists!$B$4:$B$12,MATCH($F51,Lists!$A$4:$A$12,0)),"")) -> TBD | H51: Not Started | I51: 46314 | J51: 4 | K51: =IF(OR($I51="",$J51=""),"",$I51+7*$J51-3) -> 46339 | L51: G1-GS-1
A52: G1-GS-3 | B52: G1 ED305 live digital twin | C52: GS-SLAM | D52: Mapping + loop closure | E52: Densify, optimize, prune; local pose graph loop closure; keep moving objects out of the static map. | F52: GS-SLAM | G52: =IF($F52="","",IFERROR(INDEX(Lists!$B$4:$B$12,MATCH($F52,Lists!$A$4:$A$12,0)),"")) -> TBD | H52: Not Started | I52: 46328 | J52: 4 | K52: =IF(OR($I52="",$J52=""),"",$I52+7*$J52-3) -> 46353 | L52: G1-GS-2 | P52: Dynamic Digital Twin 1 | tag Dataset #2; Dataset #3
A53: G1-GS-3.1 | B53: G1 ED305 live digital twin | C53: GS-SLAM | D53: Dynamic-Object Filter (Pre-Registration) | E53: Strip moving objects out of the point cloud before registration. | F53: GS-SLAM | G53: =IF($F53="","",IFERROR(INDEX(Lists!$B$4:$B$12,MATCH($F53,Lists!$A$4:$A$12,0)),"")) -> TBD | H53: Not Started | I53: 46202 | J53: 1 | K53: =IF(OR($I53="",$J53=""),"",$I53+7*$J53-3) -> 46206 | P53: Dynamic Digital Twin 1.1
A54: G1-GS-3.2 | B54: G1 ED305 live digital twin | C54: GS-SLAM | D54: Static Point Cloud Registration | E54: Register the filtered static points into the base map. | F54: GS-SLAM | G54: =IF($F54="","",IFERROR(INDEX(Lists!$B$4:$B$12,MATCH($F54,Lists!$A$4:$A$12,0)),"")) -> TBD | H54: Not Started | I54: 46202 | J54: 1 | K54: =IF(OR($I54="",$J54=""),"",$I54+7*$J54-3) -> 46206 | P54: Dynamic Digital Twin 1.2
A55: G1-GS-4 | B55: G1 ED305 live digital twin | C55: GS-SLAM | D55: Real-time budget | E55: FPS and memory on the target machine. | F55: GS-SLAM | G55: =IF($F55="","",IFERROR(INDEX(Lists!$B$4:$B$12,MATCH($F55,Lists!$A$4:$A$12,0)),"")) -> TBD | H55: Not Started | I55: 46349 | J55: 2 | K55: =IF(OR($I55="",$J55=""),"",$I55+7*$J55-3) -> 46360 | L55: G1-GS-3 | M55: Tracking at camera rate; numbers in Runs
A56: G1-GS-5 | B56: G1 ED305 live digital twin | C56: GS-SLAM | D56: Map fusion (multi-robot) | E56: Inter-robot loop closure, alignment to the ED305 room frame, shared map store -> global map G*. | F56: GS-SLAM | G56: =IF($F56="","",IFERROR(INDEX(Lists!$B$4:$B$12,MATCH($F56,Lists!$A$4:$A$12,0)),"")) -> TBD | H56: Not Started | I56: 46356 | J56: 4 | K56: =IF(OR($I56="",$J56=""),"",$I56+7*$J56-3) -> 46381 | L56: G1-GS-3, G1-SP-3
A57: G1-GS-6 | B57: G1 ED305 live digital twin | C57: GS-SLAM | D57: Evaluation | E57: ATE/RPE; rendered PSNR/SSIM and depth L1 on held-out views (SCooP sequences as test data). | F57: GS-SLAM | G57: =IF($F57="","",IFERROR(INDEX(Lists!$B$4:$B$12,MATCH($F57,Lists!$A$4:$A$12,0)),"")) -> TBD | H57: Not Started | I57: 46377 | J57: 2 | K57: =IF(OR($I57="",$J57=""),"",$I57+7*$J57-3) -> 46388 | L57: G1-GS-5, G2-DS-4
A58: G1-SD-1 | B58: G1 ED305 live digital twin | C58: Scene detection | D58: Object asset library | E58: USD assets of the lab's objects (chairs, tables, robots). | F58: Scene detection | G58: =IF($F58="","",IFERROR(INDEX(Lists!$B$4:$B$12,MATCH($F58,Lists!$A$4:$A$12,0)),"")) -> TBD | H58: Not Started | I58: 46307 | J58: 3 | K58: =IF(OR($I58="",$J58=""),"",$I58+7*$J58-3) -> 46325
A59: G1-SD-2 | B59: G1 ED305 live digital twin | C59: Scene detection | D59: Object retrieval from G* | E59: Which library object, where (pose, point cloud); persistent instance IDs. | F59: Scene detection | G59: =IF($F59="","",IFERROR(INDEX(Lists!$B$4:$B$12,MATCH($F59,Lists!$A$4:$A$12,0)),"")) -> TBD | H59: Not Started | I59: 46328 | J59: 4 | K59: =IF(OR($I59="",$J59=""),"",$I59+7*$J59-3) -> 46353 | L59: G1-SD-1, G1-GS-5 | O59: Split up the metric map into objects | P59: Dynamic Digital Twin 2 | tag Dataset #2; Dataset #3
A60: G1-SD-2.1 | B60: G1 ED305 live digital twin | C60: Scene detection | D60: Object Detection & Instance Identification (RGB / RGBD / LiDAR / Radar) | E60: Detect and assign persistent instance IDs to every object on the map, reusing the detection/segmentation methods proven in the dataset pipeline (Dataset Task 9). | F60: Scene detection | G60: =IF($F60="","",IFERROR(INDEX(Lists!$B$4:$B$12,MATCH($F60,Lists!$A$4:$A$12,0)),"")) -> TBD | H60: Not Started | I60: 46209 | J60: 2 | K60: =IF(OR($I60="",$J60=""),"",$I60+7*$J60-3) -> 46220 | P60: Dynamic Digital Twin 2.1
A61: G1-SD-2.2 | B61: G1 ED305 live digital twin | C61: Scene detection | D61: Radar + Panoptic Fusion Tracking | E61: Combine radar motion data with segmentation labels for tracked objects. | F61: Scene detection | G61: =IF($F61="","",IFERROR(INDEX(Lists!$B$4:$B$12,MATCH($F61,Lists!$A$4:$A$12,0)),"")) -> TBD | H61: Not Started | I61: 46209 | J61: 2 | K61: =IF(OR($I61="",$J61=""),"",$I61+7*$J61-3) -> 46220 | P61: Dynamic Digital Twin 2.2
A62: G1-SD-3 | B62: G1 ED305 live digital twin | C62: Scene detection | D62: Decomposition: segments & materials | E62: Segment the Gaussian map; material labels (needed by Sionna). | F62: Scene detection | G62: =IF($F62="","",IFERROR(INDEX(Lists!$B$4:$B$12,MATCH($F62,Lists!$A$4:$A$12,0)),"")) -> TBD | H62: Not Started | I62: 46335 | J62: 4 | K62: =IF(OR($I62="",$J62=""),"",$I62+7*$J62-3) -> 46360 | L62: G1-SD-2
A63: G1-SD-4 | B63: G1 ED305 live digital twin | C63: Scene detection | D63: Change detection | E63: Twin's expected view vs live map, plus live targets from the ED305 cameras. | F63: Scene detection | G63: =IF($F63="","",IFERROR(INDEX(Lists!$B$4:$B$12,MATCH($F63,Lists!$A$4:$A$12,0)),"")) -> TBD | H63: Not Started | I63: 46356 | J63: 4 | K63: =IF(OR($I63="",$J63=""),"",$I63+7*$J63-3) -> 46381 | L63: G1-IS-5, G1-SD-2 | P63: Dynamic Digital Twin 3 | tag Twin #1; Twin #2
A64: G1-SD-4.1 | B64: G1 ED305 live digital twin | C64: Scene detection | D64: Change Detection (Object Moved / Appeared / Disappeared) | E64: Compare current scene-graph state against the existing map to flag what changed. | F64: Scene detection | G64: =IF($F64="","",IFERROR(INDEX(Lists!$B$4:$B$12,MATCH($F64,Lists!$A$4:$A$12,0)),"")) -> TBD | H64: Not Started | I64: 46223 | J64: 1 | K64: =IF(OR($I64="",$J64=""),"",$I64+7*$J64-3) -> 46227 | P64: Dynamic Digital Twin 3.1
A65: G1-SD-5 | B65: G1 ED305 live digital twin | C65: Scene detection | D65: Maintenance with change history | E65: Prune, reuse; timestamped history instead of overwriting. | F65: Scene detection | G65: =IF($F65="","",IFERROR(INDEX(Lists!$B$4:$B$12,MATCH($F65,Lists!$A$4:$A$12,0)),"")) -> TBD | H65: Not Started | I65: 46370 | J65: 3 | K65: =IF(OR($I65="",$J65=""),"",$I65+7*$J65-3) -> 46388 | L65: G1-SD-4
A66: G1-SD-5.1 | B66: G1 ED305 live digital twin | C66: Scene detection | D66: Scene Graph & Map Update on Change (with Change History) | E66: Apply the detected change to both the map and scene graph, keeping a timestamped history rather than just the latest state. | F66: Scene detection | G66: =IF($F66="","",IFERROR(INDEX(Lists!$B$4:$B$12,MATCH($F66,Lists!$A$4:$A$12,0)),"")) -> TBD | H66: Not Started | I66: 46223 | J66: 2 | K66: =IF(OR($I66="",$J66=""),"",$I66+7*$J66-3) -> 46234 | P66: Dynamic Digital Twin 3.2
A67: G1-SD-6 | B67: G1 ED305 live digital twin | C67: Scene detection | D67: USD edits to Isaac | E67: Add / move / remove operations sent to the stage. | F67: Scene detection | G67: =IF($F67="","",IFERROR(INDEX(Lists!$B$4:$B$12,MATCH($F67,Lists!$A$4:$A$12,0)),"")) -> TBD | H67: Not Started | I67: 46370 | J67: 3 | K67: =IF(OR($I67="",$J67=""),"",$I67+7*$J67-3) -> 46388 | L67: G1-SD-4, G1-IS-6
A68: G1-SD-7 | B68: G1 ED305 live digital twin | C68: Scene detection | D68: Live targets from the ED305 cameras | E68: Multi-view detection of people/robots -> positions in the room frame. | F68: Scene detection | G68: =IF($F68="","",IFERROR(INDEX(Lists!$B$4:$B$12,MATCH($F68,Lists!$A$4:$A$12,0)),"")) -> TBD | H68: Not Started | I68: 46349 | J68: 4 | K68: =IF(OR($I68="",$J68=""),"",$I68+7*$J68-3) -> 46374 | L68: G1-SP-3, G1-SP-6 | M68: Targets at >= 10 Hz in the room frame, error measured
A69: G1-IS-1 | B69: G1 ED305 live digital twin | C69: Isaac Sim | D69: ED305 USD stage in the room frame | E69: Static room model, units, frame = ED305 room frame. | F69: Isaac Sim | G69: =IF($F69="","",IFERROR(INDEX(Lists!$B$4:$B$12,MATCH($F69,Lists!$A$4:$A$12,0)),"")) -> TBD | H69: Not Started | I69: 46307 | J69: 3 | K69: =IF(OR($I69="",$J69=""),"",$I69+7*$J69-3) -> 46325 | L69: G1-SP-3
A70: G1-IS-2 | B70: G1 ED305 live digital twin | C70: Isaac Sim | D70: Robot + antenna prims, live pose | E70: One per robot, world-frame pose every frame. | F70: Isaac Sim | G70: =IF($F70="","",IFERROR(INDEX(Lists!$B$4:$B$12,MATCH($F70,Lists!$A$4:$A$12,0)),"")) -> TBD | H70: Not Started | I70: 46321 | J70: 3 | K70: =IF(OR($I70="",$J70=""),"",$I70+7*$J70-3) -> 46339 | L70: G1-IS-1
A71: G1-IS-3 | B71: G1 ED305 live digital twin | C71: Isaac Sim | D71: Gaussian layer | E71: Render G* splats (RTX). | F71: Isaac Sim | G71: =IF($F71="","",IFERROR(INDEX(Lists!$B$4:$B$12,MATCH($F71,Lists!$A$4:$A$12,0)),"")) -> TBD | H71: Not Started | I71: 46335 | J71: 3 | K71: =IF(OR($I71="",$J71=""),"",$I71+7*$J71-3) -> 46353 | L71: G1-GS-5
A72: G1-IS-4 | B72: G1 ED305 live digital twin | C72: Isaac Sim | D72: Mesh layer | E72: Physics and radio materials. | F72: Isaac Sim | G72: =IF($F72="","",IFERROR(INDEX(Lists!$B$4:$B$12,MATCH($F72,Lists!$A$4:$A$12,0)),"")) -> TBD | H72: Not Started | I72: 46328 | J72: 3 | K72: =IF(OR($I72="",$J72=""),"",$I72+7*$J72-3) -> 46346 | L72: G1-IS-1, G1-SD-3
A73: G1-IS-5 | B73: G1 ED305 live digital twin | C73: Isaac Sim | D73: Expected-view render | E73: Render the twin from a robot/camera pose for change detection. | F73: Isaac Sim | G73: =IF($F73="","",IFERROR(INDEX(Lists!$B$4:$B$12,MATCH($F73,Lists!$A$4:$A$12,0)),"")) -> TBD | H73: Not Started | I73: 46349 | J73: 3 | K73: =IF(OR($I73="",$J73=""),"",$I73+7*$J73-3) -> 46367 | L73: G1-IS-3
A74: G1-IS-6 | B74: G1 ED305 live digital twin | C74: Isaac Sim | D74: Apply live USD edits | E74: Add / move / remove within a latency budget. | F74: Isaac Sim | G74: =IF($F74="","",IFERROR(INDEX(Lists!$B$4:$B$12,MATCH($F74,Lists!$A$4:$A$12,0)),"")) -> TBD | H74: Not Started | I74: 46370 | J74: 3 | K74: =IF(OR($I74="",$J74=""),"",$I74+7*$J74-3) -> 46388 | L74: G1-IS-1
A75: G1-IS-7 | B75: G1 ED305 live digital twin | C75: Isaac Sim | D75: Control commands to robots | E75: Twin -> robot command path. | F75: Isaac Sim | G75: =IF($F75="","",IFERROR(INDEX(Lists!$B$4:$B$12,MATCH($F75,Lists!$A$4:$A$12,0)),"")) -> TBD | H75: Not Started | I75: 46391 | J75: 2 | K75: =IF(OR($I75="",$J75=""),"",$I75+7*$J75-3) -> 46402 | L75: G1-IS-2
A76: G1-IS-8 | B76: G1 ED305 live digital twin | C76: Isaac Sim | D76: Export to Sionna | E76: Meshes, materials, all Tx/Rx poses. | F76: Isaac Sim | G76: =IF($F76="","",IFERROR(INDEX(Lists!$B$4:$B$12,MATCH($F76,Lists!$A$4:$A$12,0)),"")) -> TBD | H76: Not Started | I76: 46356 | J76: 2 | K76: =IF(OR($I76="",$J76=""),"",$I76+7*$J76-3) -> 46367 | L76: G1-IS-4
A77: G1-SR-1 | B77: G1 ED305 live digital twin | C77: Sionna RT | D77: Scene export USD -> Mitsuba | F77: Sionna RT | G77: =IF($F77="","",IFERROR(INDEX(Lists!$B$4:$B$12,MATCH($F77,Lists!$A$4:$A$12,0)),"")) -> TBD | H77: Not Started | I77: 46363 | J77: 2 | K77: =IF(OR($I77="",$J77=""),"",$I77+7*$J77-3) -> 46374 | L77: G1-IS-8
A78: G1-SR-2 | B78: G1 ED305 live digital twin | C78: Sionna RT | D78: Path solver, all Tx/Rx links | F78: Sionna RT | G78: =IF($F78="","",IFERROR(INDEX(Lists!$B$4:$B$12,MATCH($F78,Lists!$A$4:$A$12,0)),"")) -> TBD | H78: Not Started | I78: 46370 | J78: 3 | K78: =IF(OR($I78="",$J78=""),"",$I78+7*$J78-3) -> 46388 | L78: G1-SR-1
A79: G1-SR-3 | B79: G1 ED305 live digital twin | C79: Sionna RT | D79: Channel output | E79: CIR per link, radio map. | F79: Sionna RT | G79: =IF($F79="","",IFERROR(INDEX(Lists!$B$4:$B$12,MATCH($F79,Lists!$A$4:$A$12,0)),"")) -> TBD | H79: Not Started | I79: 46384 | J79: 2 | K79: =IF(OR($I79="",$J79=""),"",$I79+7*$J79-3) -> 46395 | L79: G1-SR-2
A80: G1-SR-4 | B80: G1 ED305 live digital twin | C80: Sionna RT | D80: Validate against measured channels | E80: Compare with SCooP CSI/RSSI logs. | F80: Sionna RT | G80: =IF($F80="","",IFERROR(INDEX(Lists!$B$4:$B$12,MATCH($F80,Lists!$A$4:$A$12,0)),"")) -> TBD | H80: Not Started | I80: 46391 | J80: 3 | K80: =IF(OR($I80="",$J80=""),"",$I80+7*$J80-3) -> 46409 | L80: G1-SR-3, TB-4
A81: G1-M1 | B81: G1 ED305 live digital twin | C81: Milestone | D81: M1 Offline map in Isaac | E81: One recording -> GS map in the room frame -> loaded in Isaac (static). | F81: All (integration) | G81: =IF($F81="","",IFERROR(INDEX(Lists!$B$4:$B$12,MATCH($F81,Lists!$A$4:$A$12,0)),"")) -> TBD | H81: Not Started | I81: 46349 | J81: 1 | K81: =IF(OR($I81="",$J81=""),"",$I81+7*$J81-3) -> 46353 | L81: G1-GS-3, G1-IS-3
A82: G1-M2 | B82: G1 ED305 live digital twin | C82: Milestone | D82: M2 Live robot pose in Isaac | E82: One robot's live pose moves its prim; latency measured. | F82: All (integration) | G82: =IF($F82="","",IFERROR(INDEX(Lists!$B$4:$B$12,MATCH($F82,Lists!$A$4:$A$12,0)),"")) -> TBD | H82: Not Started | I82: 46363 | J82: 1 | K82: =IF(OR($I82="",$J82=""),"",$I82+7*$J82-3) -> 46367 | L82: G1-IS-2, G1-GS-2
A83: G1-M3 | B83: G1 ED305 live digital twin | C83: Milestone | D83: M3 Change loop | E83: Move a chair -> change detected -> twin updated within the target time. | F83: All (integration) | G83: =IF($F83="","",IFERROR(INDEX(Lists!$B$4:$B$12,MATCH($F83,Lists!$A$4:$A$12,0)),"")) -> TBD | H83: Not Started | I83: 46391 | J83: 1 | K83: =IF(OR($I83="",$J83=""),"",$I83+7*$J83-3) -> 46395 | L83: G1-SD-6
A84: G1-M4 | B84: G1 ED305 live digital twin | C84: Milestone | D84: M4 Two robots, fused map | E84: Both robots live on G*. | F84: All (integration) | G84: =IF($F84="","",IFERROR(INDEX(Lists!$B$4:$B$12,MATCH($F84,Lists!$A$4:$A$12,0)),"")) -> TBD | H84: Not Started | I84: 46391 | J84: 1 | K84: =IF(OR($I84="",$J84=""),"",$I84+7*$J84-3) -> 46395 | L84: G1-GS-5
A85: G1-M5 | B85: G1 ED305 live digital twin | C85: Milestone | D85: M5 ED305 targets live in the twin | E85: People/robots from the room cameras appear live. | F85: All (integration) | G85: =IF($F85="","",IFERROR(INDEX(Lists!$B$4:$B$12,MATCH($F85,Lists!$A$4:$A$12,0)),"")) -> TBD | H85: Not Started | I85: 46398 | J85: 1 | K85: =IF(OR($I85="",$J85=""),"",$I85+7*$J85-3) -> 46402 | L85: G1-SD-7
A86: G1-M6 | B86: G1 ED305 live digital twin | C86: Milestone | D86: M6 Radio channels from the live twin | E86: Sionna channel per link from the live scene. | F86: All (integration) | G86: =IF($F86="","",IFERROR(INDEX(Lists!$B$4:$B$12,MATCH($F86,Lists!$A$4:$A$12,0)),"")) -> TBD | H86: Not Started | I86: 46405 | J86: 1 | K86: =IF(OR($I86="",$J86=""),"",$I86+7*$J86-3) -> 46409 | L86: G1-SR-3
A87: DL-1 | B87: Dual-Link Communication | C87: Dual-link | D87: Define dual-link architecture | E87: Define the dual-link architecture (e.g. WiFi + WiFi) and QoS-tiered traffic-steering policy. | F87: Dual-link comms | G87: =IF($F87="","",IFERROR(INDEX(Lists!$B$4:$B$12,MATCH($F87,Lists!$A$4:$A$12,0)),"")) -> TBD | H87: Partially Completed | I87: 46195 | J87: 1 | K87: =IF(OR($I87="",$J87=""),"",$I87+7*$J87-3) -> 46199 | P87: Dual-Link 1 | tag -
A88: DL-1.1 | B88: Dual-Link Communication | C88: Dual-link | D88: Link Pairing Selection (WiFi + WiFi) | E88: Confirm the two physical links actually used and steered between. | F88: Dual-link comms | G88: =IF($F88="","",IFERROR(INDEX(Lists!$B$4:$B$12,MATCH($F88,Lists!$A$4:$A$12,0)),"")) -> TBD | H88: Partially Completed | I88: 46195 | J88: 1 | K88: =IF(OR($I88="",$J88=""),"",$I88+7*$J88-3) -> 46199 | P88: Dual-Link 1.1
A89: DL-1.2 | B89: Dual-Link Communication | C89: Dual-link | D89: QoS-Tiered Traffic-Steering Policy | E89: Which data classes (critical vs. map) route over which link. | F89: Dual-link comms | G89: =IF($F89="","",IFERROR(INDEX(Lists!$B$4:$B$12,MATCH($F89,Lists!$A$4:$A$12,0)),"")) -> TBD | H89: Partially Completed | I89: 46195 | J89: 1 | K89: =IF(OR($I89="",$J89=""),"",$I89+7*$J89-3) -> 46199 | P89: Dual-Link 1.2
A90: DL-2 | B90: Dual-Link Communication | C90: Dual-link | D90: Build link monitor | E90: Build the link monitor: track PER/MTU, throughput/RTT, SNR and queue health on both links. | F90: Dual-link comms | G90: =IF($F90="","",IFERROR(INDEX(Lists!$B$4:$B$12,MATCH($F90,Lists!$A$4:$A$12,0)),"")) -> TBD | H90: Partially Completed | I90: 46195 | J90: 1 | K90: =IF(OR($I90="",$J90=""),"",$I90+7*$J90-3) -> 46199 | P90: Dual-Link 2
A91: DL-2.1 | B91: Dual-Link Communication | C91: Dual-link | D91: PER / MTU Tracking | E91: Packet error rate and MTU behavior per link in real time. | F91: Dual-link comms | G91: =IF($F91="","",IFERROR(INDEX(Lists!$B$4:$B$12,MATCH($F91,Lists!$A$4:$A$12,0)),"")) -> TBD | H91: Partially Completed | I91: 46195 | J91: 1 | K91: =IF(OR($I91="",$J91=""),"",$I91+7*$J91-3) -> 46199 | P91: Dual-Link 2.1
A92: DL-2.2 | B92: Dual-Link Communication | C92: Dual-link | D92: Throughput / RTT / Queue-Health Tracking | E92: Throughput, round-trip time, and queue/buffer health per link. | F92: Dual-link comms | G92: =IF($F92="","",IFERROR(INDEX(Lists!$B$4:$B$12,MATCH($F92,Lists!$A$4:$A$12,0)),"")) -> TBD | H92: Partially Completed | I92: 46195 | J92: 1 | K92: =IF(OR($I92="",$J92=""),"",$I92+7*$J92-3) -> 46199 | P92: Dual-Link 2.2
A93: DL-3 | B93: Dual-Link Communication | C93: Dual-link | D93: Implement link compression | E93: Implement link-aware dynamic compression that reacts to link-monitor signals in real time. | F93: Dual-link comms | G93: =IF($F93="","",IFERROR(INDEX(Lists!$B$4:$B$12,MATCH($F93,Lists!$A$4:$A$12,0)),"")) -> TBD | H93: In Progress | I93: 46195 | J93: 1 | K93: =IF(OR($I93="",$J93=""),"",$I93+7*$J93-3) -> 46199 | P93: Dual-Link 3 | tag Link #2
A94: DL-3.1 | B94: Dual-Link Communication | C94: Dual-link | D94: Compression Module (Link-Monitor Reactive) | E94: Wire PER/RTT/queue-health output into a live compression-rate decision. | F94: Dual-link comms | G94: =IF($F94="","",IFERROR(INDEX(Lists!$B$4:$B$12,MATCH($F94,Lists!$A$4:$A$12,0)),"")) -> TBD | H94: Partially Completed | I94: 46195 | J94: 1 | K94: =IF(OR($I94="",$J94=""),"",$I94+7*$J94-3) -> 46199 | P94: Dual-Link 3.1
A95: DL-3.2 | B95: Dual-Link Communication | C95: Dual-link | D95: Compression Threshold Tuning | E95: Calibrate thresholds so compression triggers early enough to avoid loss. | F95: Dual-link comms | G95: =IF($F95="","",IFERROR(INDEX(Lists!$B$4:$B$12,MATCH($F95,Lists!$A$4:$A$12,0)),"")) -> TBD | H95: In Progress | I95: 46195 | J95: 1 | K95: =IF(OR($I95="",$J95=""),"",$I95+7*$J95-3) -> 46199 | P95: Dual-Link 3.2
A96: DL-4 | B96: Dual-Link Communication | C96: Dual-link | D96: Validate Switching Strategies — WiFi1 + WiFi2 | E96: Compare three approaches on the WiFi1+WiFi2 pair to determine which actually performs best before committing to one. | F96: Dual-link comms | G96: =IF($F96="","",IFERROR(INDEX(Lists!$B$4:$B$12,MATCH($F96,Lists!$A$4:$A$12,0)),"")) -> TBD | H96: Not Started | I96: 46195 | J96: 1 | K96: =IF(OR($I96="",$J96=""),"",$I96+7*$J96-3) -> 46199 | P96: Dual-Link 4 | tag Link #1;Link #2; Link #3;
A97: DL-4.1 | B97: Dual-Link Communication | C97: Dual-link | D97: Single-Link Baseline | E97: Run all traffic over one WiFi link only — the no-switching baseline. | F97: Dual-link comms | G97: =IF($F97="","",IFERROR(INDEX(Lists!$B$4:$B$12,MATCH($F97,Lists!$A$4:$A$12,0)),"")) -> TBD | H97: Not Started | I97: 46195 | J97: 1 | K97: =IF(OR($I97="",$J97=""),"",$I97+7*$J97-3) -> 46199 | P97: Dual-Link 4.1
A98: DL-4.2 | B98: Dual-Link Communication | C98: Dual-link | D98: Full Topic Switchover | E98: All topics move together to the other link on failover — coarse, all-or-nothing switching. | F98: Dual-link comms | G98: =IF($F98="","",IFERROR(INDEX(Lists!$B$4:$B$12,MATCH($F98,Lists!$A$4:$A$12,0)),"")) -> TBD | H98: Not Started | I98: 46195 | J98: 1 | K98: =IF(OR($I98="",$J98=""),"",$I98+7*$J98-3) -> 46199 | P98: Dual-Link 4.2
... A114: SC-2.2 | B114: Semantic Communication | C114: Semantic comm | D114: Realistic Channel Model | E114: Replace flat-fading/AWGN assumption, validate it. | F114: Semantic comms | G114: =IF($F114="","",IFERROR(INDEX(Lists!$B$4:$B$12,MATCH($F114,Lists!$A$4:$A$12,0)),"")) -> TBD | H114: Not Started | I114: 46216 | J114: 1 | K114: =IF(OR($I114="",$J114=""),"",$I114+7*$J114-3) -> 46220 | P114: Semantic Comm 2.2
A115: SC-3 | B115: Semantic Communication | C115: Semantic comm | D115: Dynamic Bandwidth Management | E115: Network-aware allocation, physical limits, per-modality truncation, and outage-aware feedback. | F115: Semantic comms | G115: =IF($F115="","",IFERROR(INDEX(Lists!$B$4:$B$12,MATCH($F115,Lists!$A$4:$A$12,0)),"")) -> TBD | H115: Not Started | K115: =IF(OR($I115="",$J115=""),"",$I115+7*$J115-3) | O115: Old tracker: red across W1-W10 (read as not scheduled) | P115: Semantic Comm 3 | tag Sem #2; Link #1
...

Sheet Gantt
A1: Gantt
A2: Gantt starts (Monday): | C2: 46195 | E2: Today: | F2: =TODAY() -> 46302
A4: ID | B4: Task | C4: Owner | D4: Status | E4: Start | F4: End | G4: =$C$2+7*0 -> 46195 | H4: =$C$2+7*1 -> 46202 | I4: =$C$2+7*2 -> 46209 | J4: =$C$2+7*3 -> 46216 | K4: =$C$2+7*4 -> 46223 | L4: =$C$2+7*5 -> 46230 | M4: =$C$2+7*6 -> 46237 | N4: =$C$2+7*7 -> 46244 | O4: =$C$2+7*8 -> 46251 | P4: =$C$2+7*9 -> 46258 | Q4: =$C$2+7*10 -> 46265 | R4: =$C$2+7*11 -> 46272 | S4: =$C$2+7*12 -> 46279 | T4: =$C$2+7*13 -> 46286 | U4: =$C$2+7*14 -> 46293 | V4: =$C$2+7*15 -> 46300 | W4: =$C$2+7*16 -> 46307 | X4: =$C$2+7*17 -> 46314 | Y4: =$C$2+7*18 -> 46321 | Z4: =$C$2+7*19 -> 46328 | AA4: =$C$2+7*20 -> 46335 | AB4: =$C$2+7*21 -> 46342 | AC4: =$C$2+7*22 -> 46349 | AD4: =$C$2+7*23 -> 46356 | AE4: =$C$2+7*24 -> 46363 | AF4: =$C$2+7*25 -> 46370 | AG4: =$C$2+7*26 -> 46377 | AH4: =$C$2+7*27 -> 46384 | AI4: =$C$2+7*28 -> 46391 | AJ4: =$C$2+7*29 -> 46398 | AK4: =$C$2+7*30 -> 46405 | AL4: =$C$2+7*31 -> 46412 | AM4: =$C$2+7*32 -> 46419 | AN4: =$C$2+7*33 -> 46426 | AO4: =$C$2+7*34 -> 46433 | AP4: =$C$2+7*35 -> 46440 | AQ4: =$C$2+7*36 -> 46447 | AR4: =$C$2+7*37 -> 46454 | AS4: =$C$2+7*38 -> 46461 | AT4: =$C$2+7*39 -> 46468 | AU4: =$C$2+7*40 -> 46475 | AV4: =$C$2+7*41 -> 46482 | AW4: =$C$2+7*42 -> 46489 | AX4: =$C$2+7*43 -> 46496 | BA4: Legend
A5: =IF(INDEX(Tasks!$A:$A,ROW()-1)="","",INDEX(Tasks!$A:$A,ROW()-1)) -> TB-1 | B5: =IF(INDEX(Tasks!$A:$A,ROW()-1)="","",IF(ISERROR(FIND(".",INDEX(Tasks!$A:$A,ROW()-1))),""," ")&INDEX(Tasks!$D:$D,ROW()-1)) -> Hardware inventory & specs | C5: =IF(INDEX(Tasks!$G:$G,ROW()-1)="","",INDEX(Tasks!$G:$G,ROW()-1)) -> TBD | D5: =IF(INDEX(Tasks!$H:$H,ROW()-1)="","",INDEX(Tasks!$H:$H,ROW()-1)) -> Not Started | E5: =IF(INDEX(Tasks!$I:$I,ROW()-1)="","",INDEX(Tasks!$I:$I,ROW()-1)) -> 46307 | F5: =IF(INDEX(Tasks!$K:$K,ROW()-1)="","",INDEX(Tasks!$K:$K,ROW()-1)) -> 46318 | BA5: Complete
A6: =IF(INDEX(Tasks!$A:$A,ROW()-1)="","",INDEX(Tasks!$A:$A,ROW()-1)) -> TB-2 | B6: =IF(INDEX(Tasks!$A:$A,ROW()-1)="","",IF(ISERROR(FIND(".",INDEX(Tasks!$A:$A,ROW()-1))),""," ")&INDEX(Tasks!$D:$D,ROW()-1)) -> Sensor calibration (all units) | C6: =IF(INDEX(Tasks!$G:$G,ROW()-1)="","",INDEX(Tasks!$G:$G,ROW()-1)) -> TBD | D6: =IF(INDEX(Tasks!$H:$H,ROW()-1)="","",INDEX(Tasks!$H:$H,ROW()-1)) -> In Progress | E6: =IF(INDEX(Tasks!$I:$I,ROW()-1)="","",INDEX(Tasks!$I:$I,ROW()-1)) -> 46195 | F6: =IF(INDEX(Tasks!$K:$K,ROW()-1)="","",INDEX(Tasks!$K:$K,ROW()-1)) -> 46206 | BA6: In Progress
A7: =IF(INDEX(Tasks!$A:$A,ROW()-1)="","",INDEX(Tasks!$A:$A,ROW()-1)) -> TB-2.1 | B7: =IF(INDEX(Tasks!$A:$A,ROW()-1)="","",IF(ISERROR(FIND(".",INDEX(Tasks!$A:$A,ROW()-1))),""," ")&INDEX(Tasks!$D:$D,ROW()-1)) -> Sensor Calibration (LiDAR-Camera, LiDAR-IMU, Camera-Radar, Intrinsics, Realsense-Zed, Mobile-Infra Extrinsics) | C7: =IF(INDEX(Tasks!$G:$G,ROW()-1)="","",INDEX(Tasks!$G:$G,ROW()-1)) -> TBD | D7: =IF(INDEX(Tasks!$H:$H,ROW()-1)="","",INDEX(Tasks!$H:$H,ROW()-1)) -> In Progress | E7: =IF(INDEX(Tasks!$I:$I,ROW()-1)="","",INDEX(Tasks!$I:$I,ROW()-1)) -> 46195 | F7: =IF(INDEX(Tasks!$K:$K,ROW()-1)="","",INDEX(Tasks!$K:$K,ROW()-1)) -> 46206 | BA7: Partially Completed
A8: =IF(INDEX(Tasks!$A:$A,ROW()-1)="","",INDEX(Tasks!$A:$A,ROW()-1)) -> TB-2.2 | B8: =IF(INDEX(Tasks!$A:$A,ROW()-1)="","",IF(ISERROR(FIND(".",INDEX(Tasks!$A:$A,ROW()-1))),""," ")&INDEX(Tasks!$D:$D,ROW()-1)) -> Calibration: LiDAR - Camera | C8: =IF(INDEX(Tasks!$G:$G,ROW()-1)="","",INDEX(Tasks!$G:$G,ROW()-1)) -> TBD | D8: =IF(INDEX(Tasks!$H:$H,ROW()-1)="","",INDEX(Tasks!$H:$H,ROW()-1)) | E8: =IF(INDEX(Tasks!$I:$I,ROW()-1)="","",INDEX(Tasks!$I:$I,ROW()-1)) | F8: =IF(INDEX(Tasks!$K:$K,ROW()-1)="","",INDEX(Tasks!$K:$K,ROW()-1)) | BA8: Blocked
A9: =IF(INDEX(Tasks!$A:$A,ROW()-1)="","",INDEX(Tasks!$A:$A,ROW()-1)) -> TB-2.3 | B9: =IF(INDEX(Tasks!$A:$A,ROW()-1)="","",IF(ISERROR(FIND(".",INDEX(Tasks!$A:$A,ROW()-1))),""," ")&INDEX(Tasks!$D:$D,ROW()-1)) -> Calibration: LiDAR - IMU | C9: =IF(INDEX(Tasks!$G:$G,ROW()-1)="","",INDEX(Tasks!$G:$G,ROW()-1)) -> TBD | D9: =IF(INDEX(Tasks!$H:$H,ROW()-1)="","",INDEX(Tasks!$H:$H,ROW()-1)) | E9: =IF(INDEX(Tasks!$I:$I,ROW()-1)="","",INDEX(Tasks!$I:$I,ROW()-1)) | F9: =IF(INDEX(Tasks!$K:$K,ROW()-1)="","",INDEX(Tasks!$K:$K,ROW()-1)) | BA9: Not Started
A10: =IF(INDEX(Tasks!$A:$A,ROW()-1)="","",INDEX(Tasks!$A:$A,ROW()-1)) -> TB-2.4 | B10: =IF(INDEX(Tasks!$A:$A,ROW()-1)="","",IF(ISERROR(FIND(".",INDEX(Tasks!$A:$A,ROW()-1))),""," ")&INDEX(Tasks!$D:$D,ROW()-1)) -> Calibration: RealSense - ZED | C10: =IF(INDEX(Tasks!$G:$G,ROW()-1)="","",INDEX(Tasks!$G:$G,ROW()-1)) -> TBD | D10: =IF(INDEX(Tasks!$H:$H,ROW()-1)="","",INDEX(Tasks!$H:$H,ROW()-1)) | E10: =IF(INDEX(Tasks!$I:$I,ROW()-1)="","",INDEX(Tasks!$I:$I,ROW()-1)) | F10: =IF(INDEX(Tasks!$K:$K,ROW()-1)="","",INDEX(Tasks!$K:$K,ROW()-1)) | BA10: Milestone
A11: =IF(INDEX(Tasks!$A:$A,ROW()-1)="","",INDEX(Tasks!$A:$A,ROW()-1)) -> TB-2.5 | B11: =IF(INDEX(Tasks!$A:$A,ROW()-1)="","",IF(ISERROR(FIND(".",INDEX(Tasks!$A:$A,ROW()-1))),""," ")&INDEX(Tasks!$D:$D,ROW()-1)) -> Calibration: ZED - Arducam | C11: =IF(INDEX(Tasks!$G:$G,ROW()-1)="","",INDEX(Tasks!$G:$G,ROW()-1)) -> TBD | D11: =IF(INDEX(Tasks!$H:$H,ROW()-1)="","",INDEX(Tasks!$H:$H,ROW()-1)) | E11: =IF(INDEX(Tasks!$I:$I,ROW()-1)="","",INDEX(Tasks!$I:$I,ROW()-1)) | F11: =IF(INDEX(Tasks!$K:$K,ROW()-1)="","",INDEX(Tasks!$K:$K,ROW()-1)) | BA11: Today's week
A12: =IF(INDEX(Tasks!$A:$A,ROW()-1)="","",INDEX(Tasks!$A:$A,ROW()-1)) -> TB-2.6 | B12: =IF(INDEX(Tasks!$A:$A,ROW()-1)="","",IF(ISERROR(FIND(".",INDEX(Tasks!$A:$A,ROW()-1))),""," ")&INDEX(Tasks!$D:$D,ROW()-1)) -> Calibration: Radars - ZED | C12: =IF(INDEX(Tasks!$G:$G,ROW()-1)="","",INDEX(Tasks!$G:$G,ROW()-1)) -> TBD | D12: =IF(INDEX(Tasks!$H:$H,ROW()-1)="","",INDEX(Tasks!$H:$H,ROW()-1)) | E12: =IF(INDEX(Tasks!$I:$I,ROW()-1)="","",INDEX(Tasks!$I:$I,ROW()-1)) | F12: =IF(INDEX(Tasks!$K:$K,ROW()-1)="","",INDEX(Tasks!$K:$K,ROW()-1))
A13: =IF(INDEX(Tasks!$A:$A,ROW()-1)="","",INDEX(Tasks!$A:$A,ROW()-1)) -> TB-3 | B13: =IF(INDEX(Tasks!$A:$A,ROW()-1)="","",IF(ISERROR(FIND(".",INDEX(Tasks!$A:$A,ROW()-1))),""," ")&INDEX(Tasks!$D:$D,ROW()-1)) -> Time sync & TF chain | C13: =IF(INDEX(Tasks!$G:$G,ROW()-1)="","",INDEX(Tasks!$G:$G,ROW()-1)) -> TBD | D13: =IF(INDEX(Tasks!$H:$H,ROW()-1)="","",INDEX(Tasks!$H:$H,ROW()-1)) -> In Progress | E13: =IF(INDEX(Tasks!$I:$I,ROW()-1)="","",INDEX(Tasks!$I:$I,ROW()-1)) -> 46202 | F13: =IF(INDEX(Tasks!$K:$K,ROW()-1)="","",INDEX(Tasks!$K:$K,ROW()-1)) -> 46206 | BA13: Red End date = overdue
A14: =IF(INDEX(Tasks!$A:$A,ROW()-1)="","",INDEX(Tasks!$A:$A,ROW()-1)) -> TB-4 | B14: =IF(INDEX(Tasks!$A:$A,ROW()-1)="","",IF(ISERROR(FIND(".",INDEX(Tasks!$A:$A,ROW()-1))),""," ")&INDEX(Tasks!$D:$D,ROW()-1)) -> Wi-Fi & comms logging | C14: =IF(INDEX(Tasks!$G:$G,ROW()-1)="","",INDEX(Tasks!$G:$G,ROW()-1)) -> TBD | D14: =IF(INDEX(Tasks!$H:$H,ROW()-1)="","",INDEX(Tasks!$H:$H,ROW()-1)) -> In Progress | E14: =IF(INDEX(Tasks!$I:$I,ROW()-1)="","",INDEX(Tasks!$I:$I,ROW()-1)) -> 46307 | F14: =IF(INDEX(Tasks!$K:$K,ROW()-1)="","",INDEX(Tasks!$K:$K,ROW()-1)) -> 46318
A15: =IF(INDEX(Tasks!$A:$A,ROW()-1)="","",INDEX(Tasks!$A:$A,ROW()-1)) -> TB-5 | B15: =IF(INDEX(Tasks!$A:$A,ROW()-1)="","",IF(ISERROR(FIND(".",INDEX(Tasks!$A:$A,ROW()-1))),""," ")&INDEX(Tasks!$D:$D,ROW()-1)) -> Recording tooling fixes | C15: =IF(INDEX(Tasks!$G:$G,ROW()-1)="","",INDEX(Tasks!$G:$G,ROW()-1)) -> TBD | D15: =IF(INDEX(Tasks!$H:$H,ROW()-1)="","",INDEX(Tasks!$H:$H,ROW()-1)) -> Not Started | E15: =IF(INDEX(Tasks!$I:$I,ROW()-1)="","",INDEX(Tasks!$I:$I,ROW()-1)) -> 46307 | F15: =IF(INDEX(Tasks!$K:$K,ROW()-1)="","",INDEX(Tasks!$K:$K,ROW()-1)) -> 46318
A16: =IF(INDEX(Tasks!$A:$A,ROW()-1)="","",INDEX(Tasks!$A:$A,ROW()-1)) -> G2-DS-1 | B16: =IF(INDEX(Tasks!$A:$A,ROW()-1)="","",IF(ISERROR(FIND(".",INDEX(Tasks!$A:$A,ROW()-1))),""," ")&INDEX(Tasks!$D:$D,ROW()-1)) -> Recording campaign | C16: =IF(INDEX(Tasks!$G:$G,ROW()-1)="","",INDEX(Tasks!$G:$G,ROW()-1)) -> TBD | D16: =IF(INDEX(Tasks!$H:$H,ROW()-1)="","",INDEX(Tasks!$H:$H,ROW()-1)) -> Partially Completed | E16: =IF(INDEX(Tasks!$I:$I,ROW()-1)="","",INDEX(Tasks!$I:$I,ROW()-1)) -> 46314 | F16: =IF(INDEX(Tasks!$K:$K,ROW()-1)="","",INDEX(Tasks!$K:$K,ROW()-1)) -> 46353
A17: =IF(INDEX(Tasks!$A:$A,ROW()-1)="","",INDEX(Tasks!$A:$A,ROW()-1)) -> G2-DS-1.1 | B17: =IF(INDEX(Tasks!$A:$A,ROW()-1)="","",IF(ISERROR(FIND(".",INDEX(Tasks!$A:$A,ROW()-1))),""," ")&INDEX(Tasks!$D:$D,ROW()-1)) -> Indoor Trajectory Sessions | C17: =IF(INDEX(Tasks!$G:$G,ROW()-1)="","",INDEX(Tasks!$G:$G,ROW()-1)) -> TBD | D17: =IF(INDEX(Tasks!$H:$H,ROW()-1)="","",INDEX(Tasks!$H:$H,ROW()-1)) -> Partially Completed | E17: =IF(INDEX(Tasks!$I:$I,ROW()-1)="","",INDEX(Tasks!$I:$I,ROW()-1)) -> 46202 | F17: =IF(INDEX(Tasks!$K:$K,ROW()-1)="","",INDEX(Tasks!$K:$K,ROW()-1)) -> 46206
A18: =IF(INDEX(Tasks!$A:$A,ROW()-1)="","",INDEX(Tasks!$A:$A,ROW()-1)) -> G2-DS-1.2 | B18: =IF(INDEX(Tasks!$A:$A,ROW()-1)="","",IF(ISERROR(FIND(".",INDEX(Tasks!$A:$A,ROW()-1))),""," ")&INDEX(Tasks!$D:$D,ROW()-1)) -> Outdoor Trajectory Sessions | C18: =IF(INDEX(Tasks!$G:$G,ROW()-1)="","",INDEX(Tasks!$G:$G,ROW()-1)) -> TBD | D18: =IF(INDEX(Tasks!$H:$H,ROW()-1)="","",INDEX(Tasks!$H:$H,ROW()-1)) -> Not Started | E18: =IF(INDEX(Tasks!$I:$I,ROW()-1)="","",INDEX(Tasks!$I:$I,ROW()-1)) | F18: =IF(INDEX(Tasks!$K:$K,ROW()-1)="","",INDEX(Tasks!$K:$K,ROW()-1))
A19: =IF(INDEX(Tasks!$A:$A,ROW()-1)="","",INDEX(Tasks!$A:$A,ROW()-1)) -> G2-DS-1.3 | B19: =IF(INDEX(Tasks!$A:$A,ROW()-1)="","",IF(ISERROR(FIND(".",INDEX(Tasks!$A:$A,ROW()-1))),""," ")&INDEX(Tasks!$D:$D,ROW()-1)) -> Record sites 2 and 3 | C19: =IF(INDEX(Tasks!$G:$G,ROW()-1)="","",INDEX(Tasks!$G:$G,ROW()-1)) -> TBD | D19: =IF(INDEX(Tasks!$H:$H,ROW()-1)="","",INDEX(Tasks!$H:$H,ROW()-1)) -> Not Started | E19: =IF(INDEX(Tasks!$I:$I,ROW()-1)="","",INDEX(Tasks!$I:$I,ROW()-1)) -> 46321 | F19: =IF(INDEX(Tasks!$K:$K,ROW()-1)="","",INDEX(Tasks!$K:$K,ROW()-1)) -> 46346
A20: =IF(INDEX(Tasks!$A:$A,ROW()-1)="","",INDEX(Tasks!$A:$A,ROW()-1)) -> G2-DS-1.4 | B20: =IF(INDEX(Tasks!$A:$A,ROW()-1)="","",IF(ISERROR(FIND(".",INDEX(Tasks!$A:$A,ROW()-1))),""," ")&INDEX(Tasks!$D:$D,ROW()-1)) -> Calibration rosbag | C20: =IF(INDEX(Tasks!$G:$G,ROW()-1)="","",INDEX(Tasks!$G:$G,ROW()-1)) -> TBD | D20: =IF(INDEX(Tasks!$H:$H,ROW()-1)="","",INDEX(Tasks!$H:$H,ROW()-1)) | E20: =IF(INDEX(Tasks!$I:$I,ROW()-1)="","",INDEX(Tasks!$I:$I,ROW()-1)) -> 46314 | F20: =IF(INDEX(Tasks!$K:$K,ROW()-1)="","",INDEX(Tasks!$K:$K,ROW()-1)) -> 46318
A21: =IF(INDEX(Tasks!$A:$A,ROW()-1)="","",INDEX(Tasks!$A:$A,ROW()-1)) -> G2-DS-1.5 | B21: =IF(INDEX(Tasks!$A:$A,ROW()-1)="","",IF(ISERROR(FIND(".",INDEX(Tasks!$A:$A,ROW()-1))),""," ")&INDEX(Tasks!$D:$D,ROW()-1)) -> Short test recordings | C21: =IF(INDEX(Tasks!$G:$G,ROW()-1)="","",INDEX(Tasks!$G:$G,ROW()-1)) -> TBD | D21: =IF(INDEX(Tasks!$H:$H,ROW()-1)="","",INDEX(Tasks!$H:$H,ROW()-1)) | E21: =IF(INDEX(Tasks!$I:$I,ROW()-1)="","",INDEX(Tasks!$I:$I,ROW()-1)) -> 46314 | F21: =IF(INDEX(Tasks!$K:$K,ROW()-1)="","",INDEX(Tasks!$K:$K,ROW()-1)) -> 46318
A22: =IF(INDEX(Tasks!$A:$A,ROW()-1)="","",INDEX(Tasks!$A:$A,ROW()-1)) -> G2-DS-2 | B22: =IF(INDEX(Tasks!$A:$A,ROW()-1)="","",IF(ISERROR(FIND(".",INDEX(Tasks!$A:$A,ROW()-1))),""," ")&INDEX(Tasks!$D:$D,ROW()-1)) -> Per-pass processing | C22: =IF(INDEX(Tasks!$G:$G,ROW()-1)="","",INDEX(Tasks!$G:$G,ROW()-1)) -> TBD | D22: =IF(INDEX(Tasks!$H:$H,ROW()-1)="","",INDEX(Tasks!$H:$H,ROW()-1)) -> In Progress | E22: =IF(INDEX(Tasks!$I:$I,ROW()-1)="","",INDEX(Tasks!$I:$I,ROW()-1)) -> 46307 | F22: =IF(INDEX(Tasks!$K:$K,ROW()-1)="","",INDEX(Tasks!$K:$K,ROW()-1)) -> 46374
A23: =IF(INDEX(Tasks!$A:$A,ROW()-1)="","",INDEX(Tasks!$A:$A,ROW()-1)) -> G2-DS-2.1 | B23: =IF(INDEX(Tasks!$A:$A,ROW()-1)="","",IF(ISERROR(FIND(".",INDEX(Tasks!$A:$A,ROW()-1))),""," ")&INDEX(Tasks!$D:$D,ROW()-1)) -> Merging Sensor Data | C23: =IF(INDEX(Tasks!$G:$G,ROW()-1)="","",INDEX(Tasks!$G:$G,ROW()-1)) -> TBD | D23: =IF(INDEX(Tasks!$H:$H,ROW()-1)="","",INDEX(Tasks!$H:$H,ROW()-1)) -> In Progress | E23: =IF(INDEX(Tasks!$I:$I,ROW()-1)="","",INDEX(Tasks!$I:$I,ROW()-1)) -> 46202 | F23: =IF(INDEX(Tasks!$K:$K,ROW()-1)="","",INDEX(Tasks!$K:$K,ROW()-1)) -> 46206
A24: =IF(INDEX(Tasks!$A:$A,ROW()-1)="","",INDEX(Tasks!$A:$A,ROW()-1)) -> G2-DS-2.2 | B24: =IF(INDEX(Tasks!$A:$A,ROW()-1)="","",IF(ISERROR(FIND(".",INDEX(Tasks!$A:$A,ROW()-1))),""," ")&INDEX(Tasks!$D:$D,ROW()-1)) -> Timestamp Alignment Post-Processing | C24: =IF(INDEX(Tasks!$G:$G,ROW()-1)="","",INDEX(Tasks!$G:$G,ROW()-1)) -> TBD | D24: =IF(INDEX(Tasks!$H:$H,ROW()-1)="","",INDEX(Tasks!$H:$H,ROW()-1)) -> Not Started | E24: =IF(INDEX(Tasks!$I:$I,ROW()-1)="","",INDEX(Tasks!$I:$I,ROW()-1)) -> 46202 | F24: =IF(INDEX(Tasks!$K:$K,ROW()-1)="","",INDEX(Tasks!$K:$K,ROW()-1)) -> 46206
A25: =IF(INDEX(Tasks!$A:$A,ROW()-1)="","",INDEX(Tasks!$A:$A,ROW()-1)) -> G2-DS-3 | B25: =IF(INDEX(Tasks!$A:$A,ROW()-1)="","",IF(ISERROR(FIND(".",INDEX(Tasks!$A:$A,ROW()-1))),""," ")&INDEX(Tasks!$D:$D,ROW()-1)) -> Reference maps & board networks per site | C25: =IF(INDEX(Tasks!$G:$G,ROW()-1)="","",INDEX(Tasks!$G:$G,ROW()-1)) -> TBD | D25: =IF(INDEX(Tasks!$H:$H,ROW()-1)="","",INDEX(Tasks!$H:$H,ROW()-1)) -> In Progress | E25: =IF(INDEX(Tasks!$I:$I,ROW()-1)="","",INDEX(Tasks!$I:$I,ROW()-1)) -> 46307 | F25: =IF(INDEX(Tasks!$K:$K,ROW()-1)="","",INDEX(Tasks!$K:$K,ROW()-1)) -> 46360
... A404: =IF(INDEX(Tasks!$A:$A,ROW()-1)="","",INDEX(Tasks!$A:$A,ROW()-1)) | B404: =IF(INDEX(Tasks!$A:$A,ROW()-1)="","",IF(ISERROR(FIND(".",INDEX(Tasks!$A:$A,ROW()-1))),""," ")&INDEX(Tasks!$D:$D,ROW()-1)) | C404: =IF(INDEX(Tasks!$G:$G,ROW()-1)="","",INDEX(Tasks!$G:$G,ROW()-1)) | D404: =IF(INDEX(Tasks!$H:$H,ROW()-1)="","",INDEX(Tasks!$H:$H,ROW()-1)) | E404: =IF(INDEX(Tasks!$I:$I,ROW()-1)="","",INDEX(Tasks!$I:$I,ROW()-1)) | F404: =IF(INDEX(Tasks!$K:$K,ROW()-1)="","",INDEX(Tasks!$K:$K,ROW()-1))

Sheet Problems
A1: Problems
A2: Log anything that blocks work for more than a day. Link the task it blocks. | E2: Date opened for seeded rows = when they were logged here (7 Oct 2026); found in the SCooP code/paper and this project's work.
A3: P-ID | B3: Opened | C3: Goal | D3: Task ID | E3: Owner (role) | F3: Severity | G3: Status | H3: What happened | I3: Blocks / impact | J3: Root cause | K3: Fix / workaround | L3: Closed | M3: Notes
A4: P-001 | B4: 46302 | C4: G2 SCooP dataset & paper | D4: G2-DS-4 | E4: SCooP dataset | F4: Major | G4: Investigating | H4: coop_2: mobile_2's on-board VSLAM was not recorded; its camera has dropouts. | I4: mobile_2 reference track for coop_2 | J4: On-board VSLAM topic not in the recording | K4: Offline cuVSLAM + depth tracking/PGO with board and LiDAR fixes; stages 05/07/08 off, boards and Arducam borrowed from survey_1
A5: P-002 | B5: 46302 | C5: Shared SCooP testbed | D5: TB-5 | E5: Sensors & platform | F5: Major | G5: Open | H5: Survey mode: mobile_2 parked; its depth, IMU and IR not recorded, no trajectory. | I5: mobile_2 data in survey passes | J5: record.yaml survey profile | K5: Add the topics to the survey profile (TB-5)
A6: P-003 | B6: 46302 | C6: G2 SCooP dataset & paper | D6: G2-DS-4 | E6: SCooP dataset | F6: Major | G6: Investigating | H6: ZED's own tracking drifts; infra-camera ChArUco extrinsics in map_zed carry that drift. | I6: Infra camera placement; map_zed | J6: ZED odometry not trusted | K6: map_zed placed at mobile_1's start, odom_zed dropped
A7: P-004 | B7: 46302 | C7: Shared SCooP testbed | D7: TB-3 | E7: Sensors & platform | F7: Major | G7: Open | H7: Sniffer NTP asymmetry bias (up to 7.8 ms) not measured; NTP numbers from one pass only. | I7: Clock table in the paper; CSI timing
A8: P-005 | B8: 46302 | C8: G2 SCooP dataset & paper | D8: G2-DS-3 | E8: SCooP dataset | F8: Minor | G8: Open | H8: Seq B walls thicker than seq A (single-visit corridors). | I8: Map quality numbers | J8: Corridors visited once
A9: P-006 | B9: 46302 | C9: Shared SCooP testbed | D9: TB-1 | E9: Sensors & platform | F9: Minor | G9: Open | H9: Cascade radar spec and mobile_2 radar/Wi-Fi parts unconfirmed. | I9: Paper sensors table
A10: P-007 | B10: 46302 | C10: G2 SCooP dataset & paper | D10: G2-DS-7 | E10: SCooP dataset | F10: Minor | G10: Open | H10: CSI resolves relative speeds only up to about 1.2 m/s. | I10: Channel analysis at higher speeds | J10: CSI sample rate | K10: State as a limitation
A11: P-008 | B11: 46302 | C11: G2 SCooP dataset & paper | D11: G2-BP-A | E11: SCooP dataset | F11: Minor | G11: Open | H11: RESULTS_PLAN.md cites old stage paths (03_anchor, 08_reference_traj -> now 05_anchor, 04_reference_traj). | I11: Following the results plan | J11: Stages renumbered | K11: Update the paths
A12: P-009 | B12: 46302 | C12: G1 ED305 live digital twin | D12: G1-SP-3 | E12: Sensors & platform | F12: Blocker | G12: Open | H12: No access to the HCIS-Lab/ED305-cameras repo (calibration files). | I12: Camera calibration -> coverage -> placement | J12: Repo not shared with the GitHub app | K12: Share the calibration/ files or grant repo access
A13: P-010 | B13: 46302 | C13: G1 ED305 live digital twin | D13: G1-SP-4 | E13: Sensors & platform | F13: Major | G13: Investigating | H13: Each camera mount's range of movement is unknown. | I13: Camera placement optimization | J13: Not documented | K13: Assumed ranges for now; measure from video (measure_rotation.py) or fit printed pan-tilt heads

Sheet Interfaces
A1: Interfaces
A2: One row per hand-off between owners (arrows in the system diagram). Fill format/rate/frame when agreed.
A3: I-ID | B3: From (component) | C3: To (component) | D3: What is passed | E3: Topic / format | F3: Rate | G3: Frame & timestamps | H3: From owner | I3: To owner | J3: State | K3: Notes
A4: I-01 | B4: Sensors | C4: Odometry | D4: RGB-D, IMU, wheel ticks | E4: TBD | F4: TBD | G4: TBD | H4: Sensors & platform | I4: Sensors & platform | J4: Not defined
A5: I-02 | B5: Odometry | C5: Metric prior / Tracking | D5: Pose prior T_k with covariance | E5: TBD | F5: TBD | G5: TBD | H5: Sensors & platform | I5: GS-SLAM | J5: Not defined
A6: I-03 | B6: Sensors | C6: Metric prior | D6: Depth image + intrinsics K | E6: TBD | F6: TBD | G6: TBD | H6: Sensors & platform | I6: GS-SLAM | J6: Not defined
A7: I-04 | B7: Mobile robots (sensor rig) | C7: GS-SLAM front end | D7: Current frame: colour I_k, depth D_k | E7: TBD | F7: TBD | G7: TBD | H7: Sensors & platform | I7: GS-SLAM | J7: Not defined
A8: I-05 | B8: GS-SLAM tracking | C8: Isaac Sim robot prims | D8: Each robot's pose T_k (every frame) | E8: TBD | F8: TBD | G8: TBD | H8: GS-SLAM | I8: Isaac Sim | J8: Not defined
A9: I-06 | B9: GS-SLAM back end | C9: Map fusion | D9: Submaps / keyframes per robot | E9: TBD | F9: TBD | G9: TBD | H9: GS-SLAM | I9: GS-SLAM | J9: Not defined
A10: I-07 | B10: Map fusion | C10: Scene update (object retrieval) | D10: Global map G* | E10: TBD | F10: TBD | G10: TBD | H10: GS-SLAM | I10: Scene detection | J10: Not defined
A11: I-08 | B11: Isaac Sim | C11: Scene update (change detection) | D11: Expected view (render of the twin) | E11: TBD | F11: TBD | G11: TBD | H11: Isaac Sim | I11: Scene detection | J11: Not defined
A12: I-09 | B12: Scene update (maintenance) | C12: Isaac Sim USD stage | D12: USD edits: add, move, remove | E12: TBD | F12: TBD | G12: TBD | H12: Scene detection | I12: Isaac Sim | J12: Not defined
A13: I-10 | B13: Isaac Sim | C13: Mobile robots | D13: Control commands | E13: TBD | F13: TBD | G13: TBD | H13: Isaac Sim | I13: Sensors & platform | J13: Not defined
A14: I-11 | B14: Isaac Sim | C14: Sionna RT | D14: Meshes, materials, all Tx/Rx poses | E14: TBD | F14: TBD | G14: TBD | H14: Isaac Sim | I14: Sionna RT | J14: Not defined
A15: I-12 | B15: ED305 cameras | C15: Scene update | D15: Live target positions (people, robots) in the room frame | E15: TBD | F15: TBD | G15: TBD | H15: Sensors & platform | I15: Scene detection | J15: Not defined
... A17: I-14 | B17: SCooP testbed logs | C17: Sionna RT validation | D17: Measured CSI / RSSI per link | E17: TBD | F17: TBD | G17: TBD | H17: SCooP dataset | I17: Sionna RT | J17: Not defined

Sheet Weekly Log
A1: Weekly Log
A2: Every Friday, one row per person. Blockers = problem IDs from Problems. Row 4 is an example: overwrite it.
A3: Week (Monday) | B3: Person | C3: Done | D3: Next | E3: Blockers (P-IDs) | F3: Notes
A4: 46300 | B4: (example) | C4: Coverage + placement tools; printed pan-tilt head design | D4: Get ED305 calibration files; print one head | E4: P-009 | F4: Example row

Sheet Runs
A1: Runs
A2: One row per pipeline run on the server. The server keeps the logs/bags; this sheet points to them. Row 4 is an example.
A3: Run ID | B3: Date | C3: Goal | D3: Task ID | E3: Data (pass / bag) | F3: Git commit | G3: Components | H3: Key numbers | I3: Result / notes | J3: Log location
A4: (example) R-0001 | B4: 46301 | C4: G2 SCooP dataset & paper | D4: G2-DS-4 | E4: 20260924/coop_2 | F4: (commit) | G4: map stages 03-04 | H4: mobile_2 track: board residual ... cm | I4: Track fixed except camera dropouts | J4: server:/data/processed/20260924/coop_2

Sheet Lists
A1: Lists
A2: Owner names and dropdown values.
A3: Role | B3: Person | C3: Owns | E3: Status | F3: Goal | G3: Severity | H3: Problem status | I3: Interface state
A4: Sensors & platform | B4: TBD | C4: Robots, sensors, odometry, calibration, time sync, ED305 cameras, SCooP testbed | E4: Not Started | F4: G1 ED305 live digital twin | G4: Blocker | H4: Open | I4: Not defined
A5: GS-SLAM | B5: TBD | C5: Metric prior, GS-SLAM front/back end, map fusion | E5: In Progress | F5: G2 SCooP dataset & paper | G5: Major | H5: Investigating | I5: Defined
A6: Scene detection | B6: TBD | C6: Scene update: asset library, retrieval, decomposition, change detection, maintenance | E6: Blocked | F6: Shared SCooP testbed | G6: Minor | H6: Resolved | I6: Implemented
A7: Isaac Sim | B7: TBD | C7: USD stage, robot prims, Gaussian/mesh layers, live edits, control, Sionna export | E7: Complete | F7: Dual-Link Communication | H7: Won't fix | I7: Tested
A8: Sionna RT | B8: TBD | C8: Scene export, path solver, channel output | E8: Partially Completed | F8: Semantic Communication
A9: SCooP dataset | B9: TBD | C9: SCooP recording campaign, reference poses, annotations, release, paper
A10: Dual-link comms | B10: TBD | C10: Dual-link communication workstream
A11: Semantic comms | B11: TBD | C11: Semantic communication workstream
A12: All (integration) | B12: TBD | C12: Cross-owner integration milestones
